Workbook

Sheet flows
D1: EU | E1: EU | F1: EU | G1: EU | H1: EU | I1: EU | J1: EU | K1: EU | L1: EU | M1: EU | N1: EU | O1: EU | P1: EU | Q1: EU | R1: EU | S1: EU | T1: EU | U1: EU | V1: EU | W1: EU | X1: EU | Y1: EU | Z1: EU | AA1: EU | AB1: EU | AC1: EU | AD1: EU | AE1: EU | AF1: EU | AG1: EU | AH1: EU | AI1: EU | AJ1: EU | AK1: EU | AL1: EU | AM1: EU | AN1: EU | AO1: EU | AP1: EU | AQ1: EU | AR1: EU | AS1: EU | AT1: EU | AU1: EU | AV1: EU | AW1: EU | AX1: EU | AY1: EU | AZ1: EU | BA1: EU | BB1: EU | BC1: EU | BD1: EU | BE1: EU | BF1: RoW | BG1: RoW | BH1: RoW | BI1: RoW | BJ1: RoW | BK1: RoW | BL1: RoW | BM1: RoW | BN1: RoW | BO1: RoW | BP1: RoW | BQ1: RoW | BR1: RoW | BS1: RoW | BT1: RoW | BU1: RoW | BV1: RoW | BW1: RoW | BX1: RoW | BY1: RoW | BZ1: RoW | CA1: RoW | CB1: RoW | CC1: RoW | CD1: RoW | CE1: RoW | CF1: RoW | CG1: RoW | CH1: RoW | CI1: RoW | CJ1: RoW | CK1: RoW | CL1: RoW | CM1: RoW | CN1: RoW | CO1: RoW | CP1: RoW | CQ1: RoW | CR1: RoW | CS1: RoW | CT1: RoW | CU1: RoW | CV1: RoW | CW1: RoW | CX1: RoW | CY1: RoW | CZ1: RoW | DA1: RoW | DB1: RoW | DC1: RoW | DD1: RoW | DE1: RoW | DF1: RoW | DG1: RoW | DH1: EU | DI1: EU | DJ1: EU | DK1: EU | DL1: RoW | DM1: RoW | DN1: RoW | DO1: RoW
D2: Sector | E2: Sector | F2: Sector | G2: Sector | H2: Sector | I2: Sector | J2: Sector | K2: Sector | L2: Sector | M2: Sector | N2: Sector | O2: Sector | P2: Sector | Q2: Sector | R2: Sector | S2: Sector | T2: Sector | U2: Sector | V2: Sector | W2: Sector | X2: Sector | Y2: Sector | Z2: Sector | AA2: Sector | AB2: Sector | AC2: Sector | AD2: Sector | AE2: Sector | AF2: Sector | AG2: Sector | AH2: Sector | AI2: Sector | AJ2: Sector | AK2: Sector | AL2: Sector | AM2: Sector | AN2: Sector | AO2: Sector | AP2: Sector | AQ2: Sector | AR2: Sector | AS2: Sector | AT2: Sector | AU2: Sector | AV2: Sector | AW2: Sector | AX2: Sector | AY2: Sector | AZ2: Sector | BA2: Sector | BB2: Sector | BC2: Sector | BD2: Sector | BE2: Sector | BF2: Sector | BG2: Sector | BH2: Sector | BI2: Sector | BJ2: Sector | BK2: Sector | BL2: Sector | BM2: Sector | BN2: Sector | BO2: Sector | BP2: Sector | BQ2: Sector | BR2: Sector | BS2: Sector | BT2: Sector | BU2: Sector | BV2: Sector | BW2: Sector | BX2: Sector | BY2: Sector | BZ2: Sector | CA2: Sector | CB2: Sector | CC2: Sector | CD2: Sector | CE2: Sector | CF2: Sector | CG2: Sector | CH2: Sector | CI2: Sector | CJ2: Sector | CK2: Sector | CL2: Sector | CM2: Sector | CN2: Sector | CO2: Sector | CP2: Sector | CQ2: Sector | CR2: Sector | CS2: Sector | CT2: Sector | CU2: Sector | CV2: Sector | CW2: Sector | CX2: Sector | CY2: Sector | CZ2: Sector | DA2: Sector | DB2: Sector | DC2: Sector | DD2: Sector | DE2: Sector | DF2: Sector | DG2: Sector | DH2: Consumption category | DI2: Consumption category | DJ2: Consumption category | DK2: Consumption category | DL2: Consumption category | DM2: Consumption category | DN2: Consumption category | DO2: Consumption category
D3: Agriculture | E3: Animal Farming | F3: Forestry, logging and related service activities (02) | G3: Fishing, operating of fish hatcheries and fish farms; service activities incidental to fishing (05) | H3: Extraction of Fossil-Fuels | I3: Mining & Quarrying of raw materials | J3: Processing of meat | K3: Processing of other food&beverage | L3: Manufacture of tobacco products (16) | M3: Manufacture of textiles | N3: Manufacture of wood and of products of wood and cork, except furniture; manufacture of articles of straw and plaiting materials (20) | O3: Re-processing of secondary wood material into new wood material | P3: Pulp | Q3: Re-processing of secondary paper into new pulp | R3: Paper | S3: Processing of Fossil Fuels | T3: Plastics, basic | U3: Re-processing of secondary plastic into new plastic | V3: Manufacture of Chemicals | W3: Manufacture of rubber and plastic products (25) | X3: Manufacture of glass and glass products | Y3: Re-processing of secondary glass into new glass | Z3: Manufacture of other non-metallic mineral products | AA3: Manufacture of cement, lime and plaster | AB3: Re-processing of ash into clinker | AC3: Manufacture of Metals | AD3: Re-processing of Metals | AE3: Manufacture of durable goods | AF3: Manufacture of furniture; manufacturing n.e.c. (36) | AG3: Recycling | AH3: Production of electricity by fossil fuels | AI3: Production of electricity by renewable energy | AJ3: Transmission & Distribution | AK3: Manufacture of gas; distribution of gaseous fuels through mains | AL3: Water | AM3: Construction (45) | AN3: Re-processing of secondary construction material into aggregates | AO3: Sale, maintenance, repair of motor vehicles, motor vehicles parts, motorcycles, motor cycles parts and accessoiries | AP3: Retail sale of automotive fuel | AQ3: Retail & Wholesale trade | AR3: Leisure Services | AS3: Transport | AT3: KIBS | AU3: Real estate activities (70) | AV3: Renting of machinery and equipment without operator and of personal and household goods (71) | AW3: Research and development (73) | AX3: Public administration and defence; compulsory social security (75) | AY3: Education (80) | AZ3: Health and social work (85) | BA3: Incineration of Waste | BB3: Biogas & Composting | BC3: Waste water | BD3: Landfill of Waste | BE3: Other Services | BF3: Agriculture | BG3: Animal Farming | BH3: Forestry, logging and related service activities (02) | BI3: Fishing, operating of fish hatcheries and fish farms; service activities incidental to fishing (05) | BJ3: Extraction of Fossil-Fuels | BK3: Mining & Quarrying of raw materials | BL3: Processing of meat | BM3: Processing of other food&beverage | BN3: Manufacture of tobacco products (16) | BO3: Manufacture of textiles | BP3: Manufacture of wood and of products of wood and cork, except furniture; manufacture of articles of straw and plaiting materials (20) | BQ3: Re-processing of secondary wood material into new wood material | BR3: Pulp | BS3: Re-processing of secondary paper into new pulp | BT3: Paper | BU3: Processing of Fossil Fuels | BV3: Plastics, basic | BW3: Re-processing of secondary plastic into new plastic | BX3: Manufacture of Chemicals | BY3: Manufacture of rubber and plastic products (25) | BZ3: Manufacture of glass and glass products | CA3: Re-processing of secondary glass into new glass | CB3: Manufacture of other non-metallic mineral products | CC3: Manufacture of cement, lime and plaster | CD3: Re-processing of ash into clinker | CE3: Manufacture of Metals | CF3: Re-processing of Metals | CG3: Manufacture of durable goods | CH3: Manufacture of furniture; manufacturing n.e.c. (36) | CI3: Recycling | CJ3: Production of electricity by fossil fuels | CK3: Production of electricity by renewable energy | CL3: Transmission & Distribution | CM3: Manufacture of gas; distribution of gaseous fuels through mains | CN3: Water | CO3: Construction (45) | CP3: Re-processing of secondary construction material into aggregates | CQ3: Sale, maintenance, repair of motor vehicles, motor vehicles parts, motorcycles, motor cycles parts and accessoiries | CR3: Retail sale of automotive fuel | CS3: Retail & Wholesale trade | CT3: Leisure Services | CU3: Transport | CV3: KIBS | CW3: Real estate activities (70) | CX3: Renting of machinery and equipment without operator and of personal and household goods (71) | CY3: Research and development (73) | CZ3: Public administration and defence; compulsory social security (75) | DA3: Education (80) | DB3: Health and social work (85) | DC3: Incineration of Waste | DD3: Biogas & Composting | DE3: Waste water | DF3: Landfill of Waste | DG3: Other Services | DH3: Consumption | DI3: Final consumption expenditure by government | DJ3: GFCF | DK3: Exports: Total (fob) | DL3: Consumption | DM3: Final consumption expenditure by government | DN3: GFCF | DO3: Exports: Total (fob) | DQ3: Final Demand | DR3: Sector Share in Total Final Demand
A4: EU | B4: Sector | C4: Agriculture | D4: 8803.6991 | E4: 16240.262 | F4: 360.83742 | G4: 25.311202 | H4: 13.129934 | I4: 20.441096 | J4: 11248.607 | K4: 50197.749 | L4: 555.0464 | M4: 573.00978 | N4: 44.470807 | O4: 18.993006 | P4: 7.5353694 | Q4: 13.55555 | R4: 71.622524 | S4: 82.84664 | T4: 579.01984 | U4: 183.68161 | V4: 324.90242 | W4: 42.13407 | X4: 1.3361302 | Y4: 0.57214146 | Z4: 11.433018 | AA4: 7.4762978 | AB4: 1.9506785 | AC4: 20.132222 | AD4: 11.58373 | AE4: 234.37868 | AF4: 24.056063 | AG4: 4.7169939 | AH4: 21.157032 | AI4: 48.754638 | AJ4: 22.960809 | AK4: 10.871347 | AL4: 18.598645 | AM4: 357.71997 | AN4: 1.0825321 | AO4: 14.082722 | AP4: 9.7755484 | AQ4: 1292.4246 | AR4: 6765.0953 | AS4: 286.9124 | AT4: 1531.1713 | AU4: 108.42601 | AV4: 69.029443 | AW4: 73.580716 | AX4: 1057.9237 | AY4: 294.98862 | AZ4: 1413.7604 | BA4: 41.957275 | BB4: 6.9276913 | BC4: 7.6941768 | BD4: 14.983323 | BE4: 178.78636 | BF4: 965.2175 | BG4: 692.84923 | BH4: 88.03311 | BI4: 10.027684 | BJ4: 106.29395 | BK4: 56.264184 | BL4: 333.59113 | BM4: 2368.4797 | BN4: 527.08792 | BO4: 533.44196 | BP4: 42.839671 | BQ4: 0.44490747 | BR4: 9.971673 | BS4: 0.47262363 | BT4: 53.828867 | BU4: 78.205172 | BV4: 6.4553879 | BW4: 0.59234732 | BX4: 2381.9896 | BY4: 2.7466132 | BZ4: 5.393543 | CA4: 0.029553505 | CB4: 11.139308 | CC4: 5.3166818 | CD4: 0.045894036 | CE4: 213.84242 | CF4: 0.54887531 | CG4: 114.69785 | CH4: 16.129967 | CI4: 9.9723009 | CJ4: 124.28609 | CK4: 27.794842 | CL4: 74.950895 | CM4: 123.40404 | CN4: 2.9415742 | CO4: 223.32075 | CP4: 0.00054050234 | CQ4: 40.514858 | CR4: 28.301149 | CS4: 131.90605 | CT4: 868.60511 | CU4: 126.0903 | CV4: 581.15382 | CW4: 366.62994 | CX4: 165.65554 | CY4: 43.541988 | CZ4: 93.481002 | DA4: 232.95168 | DB4: 396.15983 | DC4: 0.16436782 | DD4: 0.070122378 | DE4: 0.52296247 | DF4: 96.476838 | DG4: 233.29362 | DH4: 86708.162 | DI4: 772.08459 | DJ4: 4035.6257 | DK4: 0 | DL4: 11170.928 | DM4: 3.9765862 | DN4: 205.64305 | DO4: 0 | DQ4: =SUM(DL4:DN4) -> 11380.548 | DR4: =DQ4/SUM(DQ$4:DQ$57) -> 0.011073165
A5: EU | B5: Sector | C5: Animal Farming | D5: 21.516292 | E5: 1410.103 | F5: 6.295688 | G5: 2.3099831 | H5: 12.90772 | I5: 6.5145027 | J5: 83314.272 | K5: 29544.863 | L5: 40.421047 | M5: 372.19566 | N5: 13.283675 | O5: 3.6478333 | P5: 1.624197 | Q5: 4.4196655 | R5: 28.307719 | S5: 17.801515 | T5: 35.081518 | U5: 14.23652 | V5: 15.886971 | W5: 13.143119 | X5: 0.76574425 | Y5: 0.32176234 | Z5: 4.6070878 | AA5: 6.0913636 | AB5: 1.3559557 | AC5: 16.440439 | AD5: 5.2847002 | AE5: 187.69476 | AF5: 14.384862 | AG5: 2.387502 | AH5: 23.283812 | AI5: 4.4548176 | AJ5: 42.583807 | AK5: 10.999867 | AL5: 5.6027332 | AM5: 100.26945 | AN5: 1.4128073 | AO5: 9.9079229 | AP5: 5.308718 | AQ5: 744.27893 | AR5: 1461.0087 | AS5: 185.26292 | AT5: 552.76062 | AU5: 46.716625 | AV5: 59.407725 | AW5: 25.547914 | AX5: 221.33746 | AY5: 74.157706 | AZ5: 277.63048 | BA5: 41.253359 | BB5: 5.8148076 | BC5: 3.1439891 | BD5: 4.3001306 | BE5: 168.24091 | BF5: 31.060319 | BG5: 49.230982 | BH5: 1.0458534 | BI5: 0.95107341 | BJ5: 19.86017 | BK5: 18.008154 | BL5: 156.27782 | BM5: 138.60114 | BN5: 0.30296561 | BO5: 90.725894 | BP5: 1.310645 | BQ5: 0.44996364 | BR5: 0.18598812 | BS5: 0.10919755 | BT5: 2.7263039 | BU5: 238.68922 | BV5: 0.78615175 | BW5: 0.092025501 | BX5: 391.66317 | BY5: 8.27457 | BZ5: 0.63210044 | CA5: 0.012600311 | CB5: 0.72790853 | CC5: 0.43123645 | CD5: 0.019888476 | CE5: 109.19383 | CF5: 0.15386147 | CG5: 19.741343 | CH5: 11.012061 | CI5: 1.0565367 | CJ5: 0.96438033 | CK5: 1.6354781 | CL5: 0.37273646 | CM5: 5.7113697 | CN5: 0.13815267 | CO5: 13.273804 | CP5: 0.00050490223 | CQ5: 2.7435637 | CR5: 0.21960793 | CS5: 13.191303 | CT5: 105.08456 | CU5: 9.4502403 | CV5: 44.405097 | CW5: 32.239863 | CX5: 21.393939 | CY5: 8.2711632 | CZ5: 14.801017 | DA5: 54.790409 | DB5: 50.865629 | DC5: 0.1751225 | DD5: 0.096714204 | DE5: 0.61516198 | DF5: 0.65271707 | DG5: 48.677188 | DH5: 31069.75 | DI5: 338.35783 | DJ5: 10212.043 | DK5: 0 | DL5: 740.59621 | DM5: 34.270392 | DN5: 640.05016 | DO5: 0 | DQ5: =SUM(DL5:DN5) -> 1414.9168 | DR5: =DQ5/SUM(DQ$4:DQ$57) -> 0.0013767005
A6: EU | B6: Sector | C6: Forestry, logging and related service activities (02) | D6: 89.57997 | E6: 289.71842 | F6: 8819.7701 | G6: 4.4464753 | H6: 55.948028 | I6: 46.959943 | J6: 69.119391 | K6: 322.69468 | L6: 55.499172 | M6: 73.983448 | N6: 11774.783 | O6: 88.823391 | P6: 763.57891 | Q6: 8.6042431 | R6: 2224.1065 | S6: 6.3571942 | T6: 45.363287 | U6: 14.832391 | V6: 45.929935 | W6: 100.48155 | X6: 6.914999 | Y6: 1.4944305 | Z6: 18.815196 | AA6: 15.412492 | AB6: 3.0757718 | AC6: 21.838022 | AD6: 6.76502 | AE6: 146.81855 | AF6: 464.44293 | AG6: 6.0429745 | AH6: 15.852174 | AI6: 162.63867 | AJ6: 15.66696 | AK6: 4.3639313 | AL6: 14.566218 | AM6: 1014.2768 | AN6: 0.032996608 | AO6: 10.195033 | AP6: 1.755637 | AQ6: 121.23766 | AR6: 126.6466 | AS6: 70.861333 | AT6: 185.78118 | AU6: 65.027106 | AV6: 3.2025325 | AW6: 7.1310122 | AX6: 138.38523 | AY6: 23.869501 | AZ6: 30.322802 | BA6: 4.6411499 | BB6: 1.3993722 | BC6: 1.2102875 | BD6: 2.8859218 | BE6: 39.116463 | BF6: 8.8127152 | BG6: 13.729107 | BH6: 72.13864 | BI6: 0.24548987 | BJ6: 12.133331 | BK6: 1.0724971 | BL6: 1.2658671 | BM6: 27.35311 | BN6: 9.9496398 | BO6: 19.413531 | BP6: 245.01455 | BQ6: 3.5332062 | BR6: 7.8631387 | BS6: 0.022884189 | BT6: 139.46367 | BU6: 1.0020514 | BV6: 0.70259084 | BW6: 0.073392036 | BX6: 168.58203 | BY6: 72.857993 | BZ6: 0.41698603 | CA6: 0.02283068 | CB6: 0.80617596 | CC6: 0.30200749 | CD6: 0.010531091 | CE6: 9.2425871 | CF6: 0.023435224 | CG6: 8.7100393 | CH6: 38.867712 | CI6: 0.75641906 | CJ6: 0.17030768 | CK6: 0.17687698 | CL6: 0.17643505 | CM6: 0.3416055 | CN6: 0.069872123 | CO6: 111.76247 | CP6: 4.7273205e-05 | CQ6: 0.60852597 | CR6: 0.12300299 | CS6: 7.3869222 | CT6: 10.577153 | CU6: 16.246134 | CV6: 6.4365494 | CW6: 8.7620665 | CX6: 1.3839587 | CY6: 3.5946734 | CZ6: 5.3642951 | DA6: 2.8306211 | DB6: 5.6786091 | DC6: 0.13131392 | DD6: 0.030640128 | DE6: 0.055511251 | DF6: 0.12407026 | DG6: 1.6140561 | DH6: 6546.6653 | DI6: 345.76523 | DJ6: 4631.7332 | DK6: 0 | DL6: 321.66744 | DM6: 3.4734653 | DN6: 35.834991 | DO6: 0 | DQ6: =SUM(DL6:DN6) -> 360.97589 | DR6: =DQ6/SUM(DQ$4:DQ$57) -> 0.0003512261
A7: EU | B7: Sector | C7: Fishing, operating of fish hatcheries and fish farms; service activities incidental to fishing (05) | D7: 1.1935058 | E7: 63.336381 | F7: 15.462937 | G7: 442.40274 | H7: 0.29474942 | I7: 0.30574242 | J7: 797.08059 | K7: 1138.6526 | L7: 18.180075 | M7: 21.601083 | N7: 1.6828152 | O7: 0.13382889 | P7: 0.20092095 | Q7: 0.23202509 | R7: 2.8277997 | S7: 1.0512411 | T7: 52.967871 | U7: 14.872061 | V7: 6.1699391 | W7: 14.705098 | X7: 0.18983727 | Y7: 0.08398566 | Z7: 0.27910818 | AA7: 0.38975227 | AB7: 0.11129984 | AC7: 0.49649432 | AD7: 0.45480829 | AE7: 8.5136366 | AF7: 0.80390806 | AG7: 0.65062055 | AH7: 9.1552696 | AI7: 3.7910555 | AJ7: 4.6680886 | AK7: 7.0737141 | AL7: 9.0143175 | AM7: 4.4252201 | AN7: 87.853237 | AO7: 4.3095728 | AP7: 3.3220867 | AQ7: 22.504829 | AR7: 1016.797 | AS7: 77.89723 | AT7: 32.302143 | AU7: 3.2530291 | AV7: 0.95595871 | AW7: 2.1014594 | AX7: 33.725472 | AY7: 19.768622 | AZ7: 88.115206 | BA7: 1.4518367 | BB7: 0.30347838 | BC7: 0.26327414 | BD7: 1.2605387 | BE7: 20.444427 | BF7: 0.61787243 | BG7: 1.4115068 | BH7: 0.04847588 | BI7: 66.132301 | BJ7: 0.40886281 | BK7: 0.38943538 | BL7: 285.17185 | BM7: 69.569587 | BN7: 0.056899713 | BO7: 0.93919915 | BP7: 0.09018245 | BQ7: 0.018658586 | BR7: 0.027870126 | BS7: 0.012619982 | BT7: 0.23746988 | BU7: 1.5193682 | BV7: 0.13697376 | BW7: 0.0063188725 | BX7: 69.205375 | BY7: 0.1392341 | BZ7: 0.045556426 | CA7: 0.00088111356 | CB7: 0.12170564 | CC7: 0.059537975 | CD7: 0.0016212622 | CE7: 0.37536731 | CF7: 0.016546925 | CG7: 2.1513659 | CH7: 0.18643101 | CI7: 0.072237582 | CJ7: 0.1785108 | CK7: 0.038196783 | CL7: 0.089403264 | CM7: 0.087307882 | CN7: 0.025804673 | CO7: 1.8521021 | CP7: 4.4060931e-05 | CQ7: 0.16384997 | CR7: 0.31206286 | CS7: 2.2777897 | CT7: 38.935992 | CU7: 9.0904408 | CV7: 4.465411 | CW7: 0.79988689 | CX7: 0.2500641 | CY7: 0.5621106 | CZ7: 4.8381069 | DA7: 3.2393843 | DB7: 19.526558 | DC7: 0.015642556 | DD7: 0.0058069869 | DE7: 0.023898679 | DF7: 0.096913235 | DG7: 3.5577435 | DH7: 9300.7622 | DI7: 6.6649199 | DJ7: 95.659851 | DK7: 0 | DL7: 450.69839 | DM7: 0.12423353 | DN7: 3.8911598 | DO7: 0 | DQ7: =SUM(DL7:DN7) -> 454.71378 | DR7: =DQ7/SUM(DQ$4:DQ$57) -> 0.00044243217
A8: EU | B8: Sector | C8: Extraction of Fossil-Fuels | D8: 213.56477 | E8: 153.0602 | F8: 20.540615 | G8: 3.4629964 | H8: 1841.0068 | I8: 165.22296 | J8: 177.50445 | K8: 248.82059 | L8: 16.261391 | M8: 567.34811 | N8: 286.26005 | O8: 61.344885 | P8: 98.861554 | Q8: 54.020036 | R8: 98.180084 | S8: 11867.415 | T8: 575.02026 | U8: 41.13826 | V8: 763.14349 | W8: 136.53935 | X8: 52.88625 | Y8: 45.03402 | Z8: 216.83546 | AA8: 312.92884 | AB8: 64.425131 | AC8: 1948.7127 | AD8: 278.98938 | AE8: 603.58281 | AF8: 308.16191 | AG8: 29.347179 | AH8: 15270.787 | AI8: 65.661219 | AJ8: 302.83693 | AK8: 2545.0497 | AL8: 1793.2118 | AM8: 510.88466 | AN8: 0.14582771 | AO8: 40.778683 | AP8: 26.772952 | AQ8: 281.26441 | AR8: 162.74962 | AS8: 490.06228 | AT8: 698.80377 | AU8: 249.22008 | AV8: 44.928811 | AW8: 69.491978 | AX8: 439.17428 | AY8: 97.252992 | AZ8: 143.21472 | BA8: 24.864159 | BB8: 10.276423 | BC8: 8.03165 | BD8: 14.143652 | BE8: 254.9043 | BF8: 17.043234 | BG8: 6.5733322 | BH8: 0.90046739 | BI8: 0.86606329 | BJ8: 196.92474 | BK8: 21.163117 | BL8: 10.56754 | BM8: 14.606403 | BN8: 0.62027478 | BO8: 22.375288 | BP8: 512.26574 | BQ8: 0.7572404 | BR8: 8.967718 | BS8: 0.22659783 | BT8: 8.1064575 | BU8: 1776.7115 | BV8: 44.077106 | BW8: 0.18674364 | BX8: 136.33049 | BY8: 8.995227 | BZ8: 6.018248 | CA8: 0.51030165 | CB8: 15.93318 | CC8: 21.11591 | CD8: 0.94162236 | CE8: 62.210594 | CF8: 1.552043 | CG8: 47.905854 | CH8: 401.62386 | CI8: 0.46554732 | CJ8: 554.54075 | CK8: 7.4413355 | CL8: 6.0553599 | CM8: 319.05987 | CN8: 17.080984 | CO8: 46.446416 | CP8: 0.025183018 | CQ8: 2.8754536 | CR8: 0.52568438 | CS8: 18.941549 | CT8: 14.99909 | CU8: 42.734143 | CV8: 60.095026 | CW8: 18.48284 | CX8: 3.4862807 | CY8: 3.5241192 | CZ8: 43.136503 | DA8: 9.9397097 | DB8: 14.931148 | DC8: 0.3561592 | DD8: 0.15900909 | DE8: 0.97433489 | DF8: 1.4485137 | DG8: 6.9285451 | DH8: 5227.7755 | DI8: 445.42273 | DJ8: 5953.6768 | DK8: 0 | DL8: 141.53321 | DM8: 7.139189 | DN8: 87.740654 | DO8: 0 | DQ8: =SUM(DL8:DN8) -> 236.41305 | DR8: =DQ8/SUM(DQ$4:DQ$57) -> 0.00023002764
A9: EU | B9: Sector | C9: Mining & Quarrying of raw materials | D9: 250.34178 | E9: 179.99094 | F9: 15.633115 | G9: 58.73029 | H9: 49.880604 | I9: 3734.3365 | J9: 204.8189 | K9: 630.29165 | L9: 2.6743811 | M9: 79.811095 | N9: 39.462919 | O9: 17.014555 | P9: 115.56906 | Q9: 307.82808 | R9: 344.94947 | S9: 99.257143 | T9: 415.80809 | U9: 149.09865 | V9: 1413.713 | W9: 295.28909 | X9: 1139.9364 | Y9: 24.6696 | Z9: 3715.6973 | AA9: 6271.028 | AB9: 1587.931 | AC9: 6731.704 | AD9: 361.01916 | AE9: 2545.6808 | AF9: 195.52211 | AG9: 58.305495 | AH9: 138.87726 | AI9: 21.46758 | AJ9: 156.14668 | AK9: 357.57985 | AL9: 126.84477 | AM9: 15689.708 | AN9: 0.15188906 | AO9: 34.336889 | AP9: 33.046904 | AQ9: 695.45494 | AR9: 197.21307 | AS9: 607.19654 | AT9: 700.65161 | AU9: 270.42586 | AV9: 50.034857 | AW9: 51.787679 | AX9: 953.99528 | AY9: 42.774848 | AZ9: 121.54988 | BA9: 90.090041 | BB9: 41.022572 | BC9: 31.11142 | BD9: 68.621457 | BE9: 69.225751 | BF9: 25.820393 | BG9: 12.829301 | BH9: 4.2590738 | BI9: 17.762812 | BJ9: 47.037 | BK9: 219.34005 | BL9: 29.62026 | BM9: 31.335019 | BN9: 1.7766631 | BO9: 32.69568 | BP9: 3.7950264 | BQ9: 0.2366714 | BR9: 3.1562956 | BS9: 1.025123 | BT9: 16.667719 | BU9: 54.084865 | BV9: 27.645828 | BW9: 1.6776132 | BX9: 727.86213 | BY9: 22.97252 | BZ9: 120.50074 | CA9: 0.12191388 | CB9: 205.01338 | CC9: 124.36726 | CD9: 4.2476948 | CE9: 808.12575 | CF9: 7.5279926 | CG9: 336.53464 | CH9: 124.41524 | CI9: 2.5326863 | CJ9: 6.8946001 | CK9: 13.905337 | CL9: 2.4017948 | CM9: 5.5061331 | CN9: 1.9318749 | CO9: 612.16352 | CP9: 0.00039235857 | CQ9: 6.3350299 | CR9: 1.0640407 | CS9: 19.203544 | CT9: 34.759035 | CU9: 28.206573 | CV9: 80.922111 | CW9: 55.420003 | CX9: 18.089259 | CY9: 4.505931 | CZ9: 26.41693 | DA9: 67.054742 | DB9: 97.133831 | DC9: 0.63365617 | DD9: 0.25200119 | DE9: 1.4372561 | DF9: 5.1982267 | DG9: 21.61133 | DH9: 1586.9032 | DI9: 114.54862 | DJ9: 3317.4548 | DK9: 0 | DL9: 238.55977 | DM9: 5.3827142 | DN9: 271.64934 | DO9: 0 | DQ9: =SUM(DL9:DN9) -> 515.59183 | DR9: =DQ9/SUM(DQ$4:DQ$57) -> 0.00050166593
A10: EU | B10: Sector | C10: Processing of meat | D10: 58.805964 | E10: 9946.4529 | F10: 28.827743 | G10: 169.57015 | H10: 22.582744 | I10: 101.91465 | J10: 25945.669 | K10: 25075.896 | L10: 39.319898 | M10: 528.22914 | N10: 40.59153 | O10: 15.03719 | P10: 12.430162 | Q10: 29.807955 | R10: 177.47816 | S10: 102.76103 | T10: 626.36658 | U10: 214.74827 | V10: 313.70574 | W10: 251.5576 | X10: 7.9699982 | Y10: 3.1329445 | Z10: 53.286811 | AA10: 26.467305 | AB10: 7.0279191 | AC10: 65.948199 | AD10: 36.499292 | AE10: 674.10749 | AF10: 130.60992 | AG10: 41.51797 | AH10: 90.036854 | AI10: 18.03651 | AJ10: 62.764418 | AK10: 44.678338 | AL10: 37.889747 | AM10: 464.20557 | AN10: 0.098014878 | AO10: 84.458272 | AP10: 80.529575 | AQ10: 1409.9657 | AR10: 23595.967 | AS10: 1120.9493 | AT10: 2188.3743 | AU10: 408.63745 | AV10: 196.00266 | AW10: 334.63302 | AX10: 1402.9292 | AY10: 1513.1631 | AZ10: 5199.1322 | BA10: 22.768952 | BB10: 9.4415421 | BC10: 10.662515 | BD10: 20.162864 | BE10: 361.80708 | BF10: 184.71959 | BG10: 569.12413 | BH10: 5.2233858 | BI10: 105.96036 | BJ10: 42.592822 | BK10: 16.667262 | BL10: 2365.956 | BM10: 2785.3465 | BN10: 5.5053063 | BO10: 179.5585 | BP10: 4.0508118 | BQ10: 0.28692511 | BR10: 1.9666661 | BS10: 3.4792392 | BT10: 31.816169 | BU10: 22.901444 | BV10: 27.779425 | BW10: 3.1415629 | BX10: 961.62151 | BY10: 41.941335 | BZ10: 3.0241912 | CA10: 0.28434039 | CB10: 11.25933 | CC10: 3.3404822 | CD10: 0.42889634 | CE10: 19.201804 | CF10: 4.1956142 | CG10: 202.10311 | CH10: 12.344112 | CI10: 12.081562 | CJ10: 19.41272 | CK10: 4.3346015 | CL10: 6.0295486 | CM10: 5.406553 | CN10: 3.8645703 | CO10: 34.568085 | CP10: 0.0029767855 | CQ10: 9.9907894 | CR10: 6.8499649 | CS10: 113.64539 | CT10: 2977.1509 | CU10: 95.333378 | CV10: 208.32399 | CW10: 28.011597 | CX10: 106.50484 | CY10: 22.749944 | CZ10: 244.34646 | DA10: 144.10386 | DB10: 649.29965 | DC10: 0.87931145 | DD10: 0.72107087 | DE10: 3.1979035 | DF10: 4.4395441 | DG10: 69.765458 | DH10: 231893.02 | DI10: 829.84077 | DJ10: 2721.3509 | DK10: 0 | DL10: 24667.798 | DM10: 27.683211 | DN10: 179.45972 | DO10: 0 | DQ10: =SUM(DL10:DN10) -> 24874.94 | DR10: =DQ10/SUM(DQ$4:DQ$57) -> 0.02420308
A11: EU | B11: Sector | C11: Processing of other food&beverage | D11: 35.091975 | E11: 21828.082 | F11: 46.488174 | G11: 191.18499 | H11: 27.384445 | I11: 114.43386 | J11: 21193.129 | K11: 37420.895 | L11: 35.85414 | M11: 1561.5123 | N11: 71.060481 | O11: 24.782315 | P11: 18.665851 | Q11: 45.042256 | R11: 418.21659 | S11: 141.28291 | T11: 2158.8044 | U11: 458.66961 | V11: 1239.7135 | W11: 228.32223 | X11: 5.8468107 | Y11: 2.3655345 | Z11: 102.57716 | AA11: 24.748507 | AB11: 5.2629687 | AC11: 116.37395 | AD11: 48.647335 | AE11: 808.38688 | AF11: 195.49401 | AG11: 71.038236 | AH11: 188.52804 | AI11: 22.608165 | AJ11: 65.1205 | AK11: 58.124853 | AL11: 67.966103 | AM11: 923.92899 | AN11: 0.053113967 | AO11: 105.04075 | AP11: 99.445998 | AQ11: 1283.0654 | AR11: 27304.29 | AS11: 1088.0615 | AT11: 2287.8927 | AU11: 380.16878 | AV11: 201.49585 | AW11: 310.40028 | AX11: 1675.9327 | AY11: 1725.767 | AZ11: 6595.9136 | BA11: 28.849842 | BB11: 8.4462802 | BC11: 22.820355 | BD11: 38.875271 | BE11: 395.99104 | BF11: 74.770485 | BG11: 1421.9148 | BH11: 15.363134 | BI11: 97.254468 | BJ11: 44.83621 | BK11: 25.501136 | BL11: 894.27459 | BM11: 4620.7073 | BN11: 7.3126645 | BO11: 180.32862 | BP11: 7.4632118 | BQ11: 0.3765732 | BR11: 2.7256164 | BS11: 4.8295119 | BT11: 46.892794 | BU11: 44.139059 | BV11: 27.202865 | BW11: 3.1679531 | BX11: 720.86317 | BY11: 62.284496 | BZ11: 4.3806688 | CA11: 0.30419467 | CB11: 13.472863 | CC11: 6.1843891 | CD11: 0.48858584 | CE11: 37.805242 | CF11: 5.6127741 | CG11: 225.51506 | CH11: 30.137499 | CI11: 11.79447 | CJ11: 24.478567 | CK11: 7.770822 | CL11: 12.832394 | CM11: 9.3753973 | CN11: 6.3139901 | CO11: 391.08402 | CP11: 0.0027557813 | CQ11: 16.703691 | CR11: 8.4665799 | CS11: 232.82389 | CT11: 5172.621 | CU11: 291.32907 | CV11: 261.31908 | CW11: 31.861019 | CX11: 52.933018 | CY11: 28.200022 | CZ11: 240.79609 | DA11: 176.58927 | DB11: 644.43082 | DC11: 0.88207775 | DD11: 0.58988714 | DE11: 1.4465938 | DF11: 12.015496 | DG11: 84.382827 | DH11: 302148.24 | DI11: 778.89246 | DJ11: 3807.3481 | DK11: 0 | DL11: 41634.874 | DM11: 78.812984 | DN11: 267.34237 | DO11: 0 | DQ11: =SUM(DL11:DN11) -> 41981.029 | DR11: =DQ11/SUM(DQ$4:DQ$57) -> 0.040847141
A12: EU | B12: Sector | C12: Manufacture of tobacco products (16) | D12: 8.1863784 | E12: 19.030173 | F12: 1.5328489 | G12: 0.54117537 | H12: 3.4815553 | I12: 1.4746285 | J12: 32.055095 | K12: 28.224828 | L12: 394.20187 | M12: 14.412492 | N12: 1.3229335 | O12: 2.1622269 | P12: 0.72904948 | Q12: 0.87405367 | R12: 23.390313 | S12: 8.2697352 | T12: 9.735365 | U12: 2.7489574 | V12: 9.8939249 | W12: 8.9380885 | X12: 0.39505872 | Y12: 0.11342645 | Z12: 0.94379619 | AA12: 1.193906 | AB12: 0.38657757 | AC12: 499.85047 | AD12: 52.283513 | AE12: 94.832694 | AF12: 4.7158061 | AG12: 0.66697464 | AH12: 9.4105658 | AI12: 2.083574 | AJ12: 1.8817353 | AK12: 5.8336991 | AL12: 1.2266984 | AM12: 76.115044 | AN12: 0.0046872732 | AO12: 6.6933062 | AP12: 1.0874854 | AQ12: 191.97218 | AR12: 336.97189 | AS12: 57.181167 | AT12: 160.67751 | AU12: 12.918326 | AV12: 12.127279 | AW12: 9.0420482 | AX12: 119.84071 | AY12: 12.103816 | AZ12: 14.281576 | BA12: 2.8442876 | BB12: 0.62930708 | BC12: 2.3938085 | BD12: 3.0787067 | BE12: 65.015436 | BF12: 2.901668 | BG12: 0.85593995 | BH12: 1.2211282 | BI12: 0.25107351 | BJ12: 5.4624211 | BK12: 1.3129006 | BL12: 7.1260583 | BM12: 6.0879446 | BN12: 15.468399 | BO12: 3.9820979 | BP12: 0.56946757 | BQ12: 0.0062007486 | BR12: 0.032074718 | BS12: 0.012286288 | BT12: 2.147714 | BU12: 2.8471883 | BV12: 0.17883754 | BW12: 0.0074399297 | BX12: 60.897567 | BY12: 0.6814061 | BZ12: 0.67123333 | CA12: 0.0036177072 | CB12: 1.6903541 | CC12: 0.72852001 | CD12: 0.0046086029 | CE12: 32.364196 | CF12: 0.62497302 | CG12: 11.393804 | CH12: 2.1582867 | CI12: 0.73450851 | CJ12: 2.939429 | CK12: 0.72638464 | CL12: 0.66911117 | CM12: 3.7814635 | CN12: 0.32007213 | CO12: 4.0240029 | CP12: 0.00019807552 | CQ12: 1.2221965 | CR12: 1.0023078 | CS12: 4.7442714 | CT12: 12.104791 | CU12: 4.7121479 | CV12: 22.164601 | CW12: 4.1054518 | CX12: 4.2501378 | CY12: 1.3647683 | CZ12: 4.8156928 | DA12: 3.8465754 | DB12: 4.4804912 | DC12: 0.045271273 | DD12: 0.013472119 | DE12: 0.20120624 | DF12: 1.829319 | DG12: 4.9430783 | DH12: 12663.349 | DI12: 29.155915 | DJ12: 932.3822 | DK12: 0 | DL12: 3921.8808 | DM12: 0.28552523 | DN12: 10.197401 | DO12: 0 | DQ12: =SUM(DL12:DN12) -> 3932.3637 | DR12: =DQ12/SUM(DQ$4:DQ$57) -> 0.0038261524
A13: EU | B13: Sector | C13: Manufacture of textiles | D13: 371.49919 | E13: 221.32103 | F13: 72.31161 | G13: 230.70512 | H13: 78.36393 | I13: 65.069363 | J13: 182.12319 | K13: 463.1606 | L13: 35.659937 | M13: 49068.039 | N13: 218.01207 | O13: 147.8436 | P13: 37.266879 | Q13: 101.54048 | R13: 1267.9428 | S13: 50.918614 | T13: 350.69854 | U13: 85.18997 | V13: 697.05688 | W13: 1930.1103 | X13: 92.682026 | Y13: 35.486118 | Z13: 146.42225 | AA13: 95.519743 | AB13: 22.202565 | AC13: 285.84196 | AD13: 115.47454 | AE13: 6727.1397 | AF13: 1979.0189 | AG13: 84.805374 | AH13: 143.04041 | AI13: 19.309961 | AJ13: 106.65939 | AK13: 102.97724 | AL13: 69.646438 | AM13: 2424.0763 | AN13: 1.2742648 | AO13: 209.30895 | AP13: 57.520669 | AQ13: 769.32546 | AR13: 2479.5657 | AS13: 776.30519 | AT13: 1683.5293 | AU13: 174.1794 | AV13: 199.793 | AW13: 109.96754 | AX13: 1173.6202 | AY13: 217.48317 | AZ13: 1773.1272 | BA13: 112.77695 | BB13: 44.504999 | BC13: 42.041543 | BD13: 117.02123 | BE13: 683.63787 | BF13: 112.43947 | BG13: 34.172124 | BH13: 11.447789 | BI13: 48.834674 | BJ13: 88.291976 | BK13: 47.031349 | BL13: 30.225666 | BM13: 72.930613 | BN13: 19.871447 | BO13: 8279.7765 | BP13: 29.13419 | BQ13: 0.63665695 | BR13: 3.8923937 | BS13: 1.5680017 | BT13: 242.92135 | BU13: 28.568648 | BV13: 26.825363 | BW13: 1.8463209 | BX13: 3100.1556 | BY13: 290.51742 | BZ13: 15.600197 | CA13: 0.50023436 | CB13: 30.087131 | CC13: 9.8366416 | CD13: 0.18652538 | CE13: 61.239047 | CF13: 1.2909601 | CG13: 947.44941 | CH13: 506.638 | CI13: 13.710141 | CJ13: 22.181791 | CK13: 12.608782 | CL13: 16.447233 | CM13: 11.974498 | CN13: 9.6345734 | CO13: 1137.6255 | CP13: 0.041047299 | CQ13: 40.996489 | CR13: 8.2582067 | CS13: 349.65835 | CT13: 351.22317 | CU13: 176.88717 | CV13: 292.50165 | CW13: 48.409161 | CX13: 40.159466 | CY13: 84.280082 | CZ13: 383.48915 | DA13: 106.88106 | DB13: 472.85777 | DC13: 12.415784 | DD13: 3.7901919 | DE13: 9.3007188 | DF13: 20.344872 | DG13: 175.94743 | DH13: 135292.6 | DI13: 755.84039 | DJ13: 4510.4066 | DK13: 0 | DL13: 34673.503 | DM13: 44.046308 | DN13: 1129.0517 | DO13: 0 | DQ13: =SUM(DL13:DN13) -> 35846.601 | DR13: =DQ13/SUM(DQ$4:DQ$57) -> 0.034878401
A14: EU | B14: Sector | C14: Manufacture of wood and of products of wood and cork, except furniture; manufacture of articles of straw and plaiting materials (20) | D14: 474.76783 | E14: 261.18483 | F14: 197.07972 | G14: 63.972492 | H14: 192.12067 | I14: 183.30699 | J14: 288.22086 | K14: 802.36148 | L14: 25.256434 | M14: 249.87107 | N14: 14272.054 | O14: 4482.2295 | P14: 410.44403 | Q14: 24.080978 | R14: 1323.9192 | S14: 46.977583 | T14: 352.29251 | U14: 84.122181 | V14: 78.742924 | W14: 493.10941 | X14: 129.18915 | Y14: 50.647641 | Z14: 560.12934 | AA14: 103.08586 | AB14: 28.312258 | AC14: 762.14371 | AD14: 366.60625 | AE14: 4955.6325 | AF14: 8890.8995 | AG14: 199.00379 | AH14: 347.89556 | AI14: 187.53144 | AJ14: 531.12974 | AK14: 70.584178 | AL14: 231.92295 | AM14: 23646.72 | AN14: 0.28646851 | AO14: 92.328858 | AP14: 22.907399 | AQ14: 498.00198 | AR14: 1398.239 | AS14: 778.44139 | AT14: 1533.8929 | AU14: 2049.5465 | AV14: 109.24146 | AW14: 72.262706 | AX14: 316.3958 | AY14: 242.84433 | AZ14: 222.72734 | BA14: 101.04183 | BB14: 41.136455 | BC14: 20.623376 | BD14: 35.98606 | BE14: 893.45071 | BF14: 23.826026 | BG14: 7.4897438 | BH14: 8.6205345 | BI14: 7.1919717 | BJ14: 32.442825 | BK14: 11.42499 | BL14: 20.031091 | BM14: 41.485522 | BN14: 7.7093016 | BO14: 25.61705 | BP14: 1359.0607 | BQ14: 329.54374 | BR14: 199.72104 | BS14: 0.69971063 | BT14: 219.27005 | BU14: 10.399118 | BV14: 13.300209 | BW14: 1.9745504 | BX14: 104.97488 | BY14: 38.718728 | BZ14: 17.279709 | CA14: 2.0503282 | CB14: 34.812515 | CC14: 5.0135764 | CD14: 0.79036234 | CE14: 49.513584 | CF14: 1.2211404 | CG14: 438.12504 | CH14: 884.12681 | CI14: 5.4382919 | CJ14: 2.6303668 | CK14: 4.4660448 | CL14: 4.5197122 | CM14: 2.07703 | CN14: 1.9339227 | CO14: 5019.976 | CP14: 0.00066899757 | CQ14: 12.973149 | CR14: 1.9143683 | CS14: 78.050173 | CT14: 95.541118 | CU14: 68.139056 | CV14: 118.1542 | CW14: 276.63998 | CX14: 13.170551 | CY14: 6.5286129 | CZ14: 109.59524 | DA14: 50.329916 | DB14: 42.792421 | DC14: 4.6318643 | DD14: 1.4250472 | DE14: 1.6759654 | DF14: 1.65526 | DG14: 28.703784 | DH14: 10427.412 | DI14: 84.393385 | DJ14: 8824.3183 | DK14: 0 | DL14: 1298.8994 | DM14: 2.217063 | DN14: 1033.4581 | DO14: 0 | DQ14: =SUM(DL14:DN14) -> 2334.5746 | DR14: =DQ14/SUM(DQ$4:DQ$57) -> 0.0022715188
A15: EU | B15: Sector | C15: Re-processing of secondary wood material into new wood material | D15: 204.54395 | E15: 105.47208 | F15: 40.056046 | G15: 23.009819 | H15: 51.961684 | I15: 63.781712 | J15: 124.53545 | K15: 354.26046 | L15: 8.4400313 | M15: 109.89879 | N15: 3900.7583 | O15: 2253.6477 | P15: 65.765141 | Q15: 7.9020116 | R15: 275.68985 | S15: 12.022656 | T15: 131.10101 | U15: 43.337618 | V15: 26.20708 | W15: 209.36727 | X15: 38.965028 | Y15: 21.679378 | Z15: 200.87417 | AA15: 33.556714 | AB15: 9.3013539 | AC15: 152.80323 | AD15: 77.063775 | AE15: 1793.9995 | AF15: 3614.7705 | AG15: 65.829287 | AH15: 44.052379 | AI15: 13.086412 | AJ15: 65.26426 | AK15: 24.610402 | AL15: 22.904805 | AM15: 8451.241 | AN15: 0.059242666 | AO15: 34.108725 | AP15: 8.9582682 | AQ15: 182.59749 | AR15: 507.89005 | AS15: 256.10045 | AT15: 740.27321 | AU15: 458.30898 | AV15: 49.660243 | AW15: 12.088397 | AX15: 110.21048 | AY15: 64.794489 | AZ15: 74.976407 | BA15: 31.471748 | BB15: 13.562269 | BC15: 5.0911612 | BD15: 9.1498173 | BE15: 380.94061 | BF15: 6.2210044 | BG15: 1.448438 | BH15: 2.0366288 | BI15: 1.3296304 | BJ15: 8.2916732 | BK15: 3.2591703 | BL15: 6.0741803 | BM15: 12.262175 | BN15: 2.4317991 | BO15: 8.3379596 | BP15: 291.12399 | BQ15: 65.481491 | BR15: 30.671739 | BS15: 0.19852183 | BT15: 56.510476 | BU15: 1.8017896 | BV15: 2.8540624 | BW15: 0.41585097 | BX15: 30.666094 | BY15: 12.858519 | BZ15: 3.9727872 | CA15: 0.41807311 | CB15: 7.8493149 | CC15: 1.3046386 | CD15: 0.16446713 | CE15: 14.930336 | CF15: 0.31336403 | CG15: 123.73708 | CH15: 204.75117 | CI15: 1.209098 | CJ15: 0.81415775 | CK15: 0.73684078 | CL15: 0.78856426 | CM15: 0.72687004 | CN15: 0.47338956 | CO15: 916.71143 | CP15: 0.00022564739 | CQ15: 3.5636092 | CR15: 0.41266439 | CS15: 19.506345 | CT15: 20.736687 | CU15: 17.98941 | CV15: 31.221379 | CW15: 41.0504 | CX15: 4.0235607 | CY15: 2.1802471 | CZ15: 26.88843 | DA15: 11.570458 | DB15: 10.935117 | DC15: 1.1761464 | DD15: 0.3896534 | DE15: 0.5345988 | DF15: 0.41624913 | DG15: 6.9335944 | DH15: 3737.491 | DI15: 31.353547 | DJ15: 3211.0441 | DK15: 0 | DL15: 343.03997 | DM15: 0.49500641 | DN15: 248.47679 | DO15: 0 | DQ15: =SUM(DL15:DN15) -> 592.01176 | DR15: =DQ15/SUM(DQ$4:DQ$57) -> 0.0005760218
... A57: EU | B57: Sector | C57: Other Services | D57: 1216.5493 | E57: 165.5005 | F57: 427.84517 | G57: 26.767906 | H57: 579.31785 | I57: 315.08928 | J57: 472.69992 | K57: 1685.8197 | L57: 410.08334 | M57: 1218.3911 | N57: 300.00987 | O57: 41.331096 | P57: 39.045318 | Q57: 45.276706 | R57: 702.40543 | S57: 292.21758 | T57: 232.23895 | U57: 68.253084 | V57: 1166.4106 | W57: 254.87064 | X57: 42.561479 | Y57: 11.2911 | Z57: 182.83607 | AA57: 135.06765 | AB57: 43.361847 | AC57: 400.69483 | AD57: 102.43453 | AE57: 3614.1243 | AF57: 387.52206 | AG57: 31.68988 | AH57: 204.37842 | AI57: 68.882316 | AJ57: 129.02702 | AK57: 362.09984 | AL57: 270.61433 | AM57: 968.46392 | AN57: 3.3540029 | AO57: 163.75812 | AP57: 36.213145 | AQ57: 301.98596 | AR57: 2690.7045 | AS57: 1372.6381 | AT57: 6836.2686 | AU57: 1152.3105 | AV57: 581.60328 | AW57: 271.30901 | AX57: 478.54698 | AY57: 464.92999 | AZ57: 3737.8001 | BA57: 321.60241 | BB57: 112.53544 | BC57: 60.871951 | BD57: 60.580274 | BE57: 9037.9422 | BF57: 12.031771 | BG57: 3.0901706 | BH57: 1.2978098 | BI57: 2.8987984 | BJ57: 13.860356 | BK57: 5.7754294 | BL57: 13.82242 | BM57: 39.620544 | BN57: 1.577209 | BO57: 17.228093 | BP57: 5.9455312 | BQ57: 0.97512069 | BR57: 0.9937224 | BS57: 0.067857693 | BT57: 25.792687 | BU57: 4.6832736 | BV57: 1.3940201 | BW57: 0.050285669 | BX57: 49.863617 | BY57: 5.0876467 | BZ57: 2.1895291 | CA57: 0.016306684 | CB57: 7.643125 | CC57: 1.9060239 | CD57: 0.12007093 | CE57: 18.31853 | CF57: 0.8736201 | CG57: 96.325823 | CH57: 7.6201822 | CI57: 4.4822268 | CJ57: 9.4882659 | CK57: 2.9593147 | CL57: 2.1071319 | CM57: 1.7183915 | CN57: 1.620795 | CO57: 37.118334 | CP57: 0.00108283 | CQ57: 9.4561064 | CR57: 0.56500121 | CS57: 27.092587 | CT57: 36.655045 | CU57: 49.145919 | CV57: 113.38611 | CW57: 15.546318 | CX57: 6.9826371 | CY57: 4.6992926 | CZ57: 35.425946 | DA57: 16.591315 | DB57: 32.201038 | DC57: 4.0896015 | DD57: 0.37754447 | DE57: 3.6307949 | DF57: 1.874465 | DG57: 37.992956 | DH57: 306568.43 | DI57: 3732.278 | DJ57: 489.62977 | DK57: 0 | DL57: 40220.69 | DM57: 23.312053 | DN57: 91.67345 | DO57: 0 | DQ57: =SUM(DL57:DN57) -> 40335.675 | DR57: =DQ57/SUM(DQ$4:DQ$57) -> 0.039246227
A58: RoW | B58: Sector | C58: Agriculture | D58: 1072.8292 | E58: 5042.5051 | F58: 421.1424 | G58: 12.790195 | H58: 19.354915 | I58: 15.954901 | J58: 2694.0135 | K58: 11209.655 | L58: 1942.8917 | M58: 1145.6751 | N58: 46.198055 | O58: 23.62128 | P58: 6.8652358 | Q58: 23.76148 | R58: 74.042597 | S58: 216.68842 | T58: 283.50567 | U58: 109.79243 | V58: 116.01161 | W58: 79.381027 | X58: 7.2449682 | Y58: 2.2907201 | Z58: 29.156012 | AA58: 11.727064 | AB58: 3.2767229 | AC58: 143.74429 | AD58: 55.736253 | AE58: 378.32006 | AF58: 38.779616 | AG58: 9.8908593 | AH58: 32.360279 | AI58: 49.865064 | AJ58: 10.905282 | AK58: 15.929343 | AL58: 17.718292 | AM58: 319.36794 | AN58: 0.014272489 | AO58: 15.701879 | AP58: 12.209346 | AQ58: 494.58814 | AR58: 1366.7677 | AS58: 379.2496 | AT58: 380.89176 | AU58: 25.965953 | AV58: 14.113475 | AW58: 25.498768 | AX58: 211.7717 | AY58: 40.812264 | AZ58: 678.8267 | BA58: 17.075118 | BB58: 1.8607167 | BC58: 2.9700217 | BD58: 4.5554931 | BE58: 88.797713 | BF58: 163093.76 | BG58: 75964.53 | BH58: 5360.9307 | BI58: 1037.1516 | BJ58: 4362.1294 | BK58: 1712.9096 | BL58: 71672.125 | BM58: 462651.2 | BN58: 26325.897 | BO58: 42974.445 | BP58: 5394.2838 | BQ58: 12.886878 | BR58: 1636.929 | BS58: 4.5303286 | BT58: 8098.6947 | BU58: 1018.13 | BV58: 14249.195 | BW58: 9.9708276 | BX58: 59804.099 | BY58: 2105.8726 | BZ58: 277.04117 | CA58: 0.61578764 | CB58: 1068.5231 | CC58: 247.00681 | CD58: 0.37339647 | CE58: 2622.419 | CF58: 11.318555 | CG58: 4394.712 | CH58: 1045.4772 | CI58: 470.48626 | CJ58: 1307.8409 | CK58: 355.00698 | CL58: 803.03754 | CM58: 1224.3061 | CN58: 293.05627 | CO58: 25208.231 | CP58: 0.021244303 | CQ58: 636.25481 | CR58: 545.67904 | CS58: 4181.4507 | CT58: 57459.378 | CU58: 4098.9303 | CV58: 7429.5926 | CW58: 5218.5911 | CX58: 1409.9514 | CY58: 1580.7775 | CZ58: 4668.4547 | DA58: 3065.0941 | DB58: 13333.082 | DC58: 47.8598 | DD58: 22.325793 | DE58: 175.30863 | DF58: 1135.4392 | DG58: 7123.0298 | DH58: 33630.685 | DI58: 182.39294 | DJ58: 1595.8359 | DK58: 0 | DL58: 672489.13 | DM58: 11091.222 | DN58: 30464.006 | DO58: 0 | DQ58: =SUM(DH58:DJ58) -> 35408.914 | DR58: =DQ58/SUM(DQ$58:DQ$111) -> 0.053361169
A59: RoW | B59: Sector | C59: Animal Farming | D59: 118.38491 | E59: 144.10895 | F59: 11.952181 | G59: 5.8850376 | H59: 16.755397 | I59: 8.7494162 | J59: 296.96875 | K59: 483.89313 | L59: 33.663542 | M59: 75.248848 | N59: 29.804514 | O59: 14.220332 | P59: 3.9111106 | Q59: 10.210287 | R59: 22.100835 | S59: 201.18014 | T59: 114.61778 | U59: 46.671662 | V59: 67.120725 | W59: 40.531341 | X59: 4.3125878 | Y59: 1.3716758 | Z59: 15.549836 | AA59: 6.7215616 | AB59: 1.9729714 | AC59: 47.690329 | AD59: 14.913138 | AE59: 119.10282 | AF59: 20.718637 | AG59: 4.1669244 | AH59: 25.248495 | AI59: 3.2895097 | AJ59: 6.1072205 | AK59: 16.401012 | AL59: 9.8675667 | AM59: 69.766011 | AN59: 0.012004229 | AO59: 7.3229202 | AP59: 4.7961312 | AQ59: 81.97041 | AR59: 270.74901 | AS59: 80.439521 | AT59: 92.613967 | AU59: 13.527714 | AV59: 6.8233551 | AW59: 14.603172 | AX59: 37.776845 | AY59: 12.92303 | AZ59: 158.2429 | BA59: 6.121757 | BB59: 2.1850104 | BC59: 2.2419528 | BD59: 4.0893561 | BE59: 66.418324 | BF59: 1696.3886 | BG59: 126741.52 | BH59: 878.76905 | BI59: 1120.5451 | BJ59: 2208.1581 | BK59: 1676.6081 | BL59: 317291.24 | BM59: 50937.996 | BN59: 669.67945 | BO59: 17620.531 | BP59: 420.30431 | BQ59: 3.556918 | BR59: 121.0018 | BS59: 1.904114 | BT59: 745.21876 | BU59: 1216.8993 | BV59: 207.53434 | BW59: 2.9048454 | BX59: 16556.606 | BY59: 1811.1291 | BZ59: 245.70133 | CA59: 0.29031026 | CB59: 441.39934 | CC59: 242.22936 | CD59: 0.38137173 | CE59: 1514.1469 | CF59: 5.757041 | CG59: 2686.2389 | CH59: 5692.0684 | CI59: 455.01017 | CJ59: 651.12292 | CK59: 257.97597 | CL59: 470.14618 | CM59: 757.67488 | CN59: 295.55935 | CO59: 4135.6785 | CP59: 0.03226154 | CQ59: 599.33183 | CR59: 348.77517 | CS59: 4424.0755 | CT59: 38159.771 | CU59: 16730.408 | CV59: 4189.7822 | CW59: 1325.029 | CX59: 1108.7294 | CY59: 1662.9123 | CZ59: 5108.7686 | DA59: 2863.6973 | DB59: 3825.2789 | DC59: 99.990465 | DD59: 46.108052 | DE59: 889.01831 | DF59: 833.14191 | DG59: 2519.5509 | DH59: 2240.8765 | DI59: 73.52287 | DJ59: 348.40819 | DK59: 0 | DL59: 199679.12 | DM59: 8086.4068 | DN59: 91918.778 | DO59: 0 | DQ59: =SUM(DH59:DJ59) -> 2662.8075 | DR59: =DQ59/SUM(DQ$58:DQ$111) -> 0.0040128461
A60: RoW | B60: Sector | C60: Forestry, logging and related service activities (02) | D60: 9.3175023 | E60: 11.28869 | F60: 158.52501 | G60: 0.52519395 | H60: 2.4054583 | I60: 2.4247076 | J60: 14.213955 | K60: 47.851875 | L60: 1.0712178 | M60: 5.6596826 | N60: 424.94767 | O60: 9.0196838 | P60: 89.472536 | Q60: 2.2154704 | R60: 262.24835 | S60: 3.2361123 | T60: 13.408167 | U60: 7.4670679 | V60: 13.917919 | W60: 10.718435 | X60: 1.1447482 | Y60: 0.45651489 | Z60: 5.3191244 | AA60: 2.5237254 | AB60: 0.69929383 | AC60: 4.53838 | AD60: 2.0301254 | AE60: 17.474865 | AF60: 35.309755 | AG60: 0.54393279 | AH60: 2.2073322 | AI60: 6.9136945 | AJ60: 0.9099684 | AK60: 0.78672776 | AL60: 1.04686 | AM60: 31.428943 | AN60: 0.0035101443 | AO60: 1.5818679 | AP60: 0.20651902 | AQ60: 11.455941 | AR60: 11.817083 | AS60: 6.5518904 | AT60: 25.685464 | AU60: 3.5971548 | AV60: 0.68022802 | AW60: 1.913318 | AX60: 123.38141 | AY60: 1.5679562 | AZ60: 14.732965 | BA60: 0.74399788 | BB60: 0.27523085 | BC60: 0.33878332 | BD60: 0.73604721 | BE60: 3.646363 | BF60: 1111.0335 | BG60: 325.10732 | BH60: 23245.519 | BI60: 45.942565 | BJ60: 1520.5933 | BK60: 98.868865 | BL60: 773.92837 | BM60: 3360.811 | BN60: 344.66086 | BO60: 2401.8996 | BP60: 56441.333 | BQ60: 29.197048 | BR60: 3010.802 | BS60: 4.8677564 | BT60: 26594.556 | BU60: 55.194812 | BV60: 71.634269 | BW60: 0.86834922 | BX60: 9728.4965 | BY60: 12400.968 | BZ60: 26.407771 | CA60: 2.4670208 | CB60: 100.91137 | CC60: 12.559488 | CD60: 0.078716173 | CE60: 79.777949 | CF60: 0.72755715 | CG60: 350.84843 | CH60: 4606.8003 | CI60: 132.99626 | CJ60: 20.365958 | CK60: 24.664031 | CL60: 16.411947 | CM60: 5.5523312 | CN60: 4.3020802 | CO60: 15349.717 | CP60: 0.0054996105 | CQ60: 23.09655 | CR60: 1.4847328 | CS60: 198.02538 | CT60: 1344.2616 | CU60: 1574.4096 | CV60: 239.26057 | CW60: 81.380056 | CX60: 21.316828 | CY60: 454.10574 | CZ60: 389.37184 | DA60: 79.788395 | DB60: 197.23118 | DC60: 6.1301225 | DD60: 4.1048418 | DE60: 5.5830223 | DF60: 12.572326 | DG60: 93.177106 | DH60: 230.6586 | DI60: 12.298189 | DJ60: 116.18041 | DK60: 0 | DL60: 42348.051 | DM60: 264.55897 | DN60: 7621.564 | DO60: 0 | DQ60: =SUM(DH60:DJ60) -> 359.1372 | DR60: =DQ60/SUM(DQ$58:DQ$111) -> 0.00054121911
A61: RoW | B61: Sector | C61: Fishing, operating of fish hatcheries and fish farms; service activities incidental to fishing (05) | D61: 1.7651894 | E61: 12.499006 | F61: 1.0882657 | G61: 70.151216 | H61: 0.42465527 | I61: 0.39943946 | J61: 692.67944 | K61: 917.877 | L61: 6.3185745 | M61: 5.2342339 | N61: 3.1879761 | O61: 1.7691468 | P61: 0.15817648 | Q61: 0.32015962 | R61: 1.6507322 | S61: 1.349972 | T61: 9.0065027 | U61: 3.8312681 | V61: 5.1583845 | W61: 1.4296329 | X61: 0.1808623 | Y61: 0.10329719 | Z61: 0.5957934 | AA61: 0.29907244 | AB61: 0.13258575 | AC61: 1.5525912 | AD61: 0.45983525 | AE61: 10.272637 | AF61: 1.901156 | AG61: 0.3007671 | AH61: 0.65312533 | AI61: 0.16566113 | AJ61: 0.39694237 | AK61: 0.23370185 | AL61: 0.32267252 | AM61: 6.1367556 | AN61: 0.0010651702 | AO61: 1.469321 | AP61: 0.50525836 | AQ61: 21.642193 | AR61: 358.50099 | AS61: 25.257821 | AT61: 14.54077 | AU61: 2.3668358 | AV61: 1.3210283 | AW61: 1.4504845 | AX61: 6.9683502 | AY61: 5.1938446 | AZ61: 30.927781 | BA61: 0.30549432 | BB61: 0.11463286 | BC61: 0.078700077 | BD61: 0.1931248 | BE61: 2.7325242 | BF61: 769.6079 | BG61: 605.15014 | BH61: 71.443761 | BI61: 6276.9588 | BJ61: 158.42094 | BK61: 153.821 | BL61: 193685.95 | BM61: 3100.3481 | BN61: 58.744864 | BO61: 252.71086 | BP61: 42.668079 | BQ61: 0.61311989 | BR61: 12.843069 | BS61: 0.090210178 | BT61: 71.973269 | BU61: 50.118033 | BV61: 30.27224 | BW61: 0.082161868 | BX61: 2529.6076 | BY61: 13.392119 | BZ61: 18.746219 | CA61: 0.016716867 | CB61: 31.458912 | CC61: 13.358182 | CD61: 0.016930924 | CE61: 102.1182 | CF61: 0.14614009 | CG61: 235.87172 | CH61: 105.33283 | CI61: 30.743123 | CJ61: 119.13929 | CK61: 37.59809 | CL61: 64.160117 | CM61: 90.295439 | CN61: 31.3275 | CO61: 215.31162 | CP61: 0.00094892245 | CQ61: 105.76752 | CR61: 51.606319 | CS61: 613.71944 | CT61: 19765.628 | CU61: 694.01664 | CV61: 481.07322 | CW61: 112.61399 | CX61: 119.17652 | CY61: 96.442031 | CZ61: 252.52644 | DA61: 185.91562 | DB61: 1980.3744 | DC61: 3.0612005 | DD61: 1.8420203 | DE61: 3.7934337 | DF61: 95.286375 | DG61: 543.11361 | DH61: 3144.3506 | DI61: 5.5107608 | DJ61: 31.202717 | DK61: 0 | DL61: 57440.94 | DM61: 117.10438 | DN61: 3059.4967 | DO61: 0 | DQ61: =SUM(DH61:DJ61) -> 3181.0641 | DR61: =DQ61/SUM(DQ$58:DQ$111) -> 0.0047938579
A62: RoW | B62: Sector | C62: Extraction of Fossil-Fuels | D62: 337.54774 | E62: 111.33963 | F62: 14.974365 | G62: 21.126215 | H62: 5579.8109 | I62: 204.51122 | J62: 294.48339 | K62: 460.5324 | L62: 10.686349 | M62: 2286.2201 | N62: 829.24571 | O62: 170.68341 | P62: 131.6051 | Q62: 60.168076 | R62: 227.86376 | S62: 182568.41 | T62: 2935.512 | U62: 283.95627 | V62: 4687.4646 | W62: 1216.5494 | X62: 258.71064 | Y62: 21.18655 | Z62: 531.36928 | AA62: 444.00696 | AB62: 56.931695 | AC62: 2576.6115 | AD62: 245.82626 | AE62: 1696.4561 | AF62: 1727.6936 | AG62: 24.517999 | AH62: 18094.213 | AI62: 345.76255 | AJ62: 261.57634 | AK62: 10089.726 | AL62: 1834.9992 | AM62: 723.91497 | AN62: 0.18272893 | AO62: 68.780442 | AP62: 5.5369489 | AQ62: 538.50156 | AR62: 276.69892 | AS62: 1299.1543 | AT62: 814.73221 | AU62: 348.15053 | AV62: 45.941122 | AW62: 167.01897 | AX62: 935.95908 | AY62: 164.68942 | AZ62: 751.04124 | BA62: 34.140468 | BB62: 11.850654 | BC62: 18.925374 | BD62: 36.274557 | BE62: 192.31795 | BF62: 4354.6912 | BG62: 1069.5465 | BH62: 315.14448 | BI62: 378.38074 | BJ62: 204054.36 | BK62: 9128.1559 | BL62: 1467.3948 | BM62: 2003.3727 | BN62: 268.17723 | BO62: 15947.698 | BP62: 3255.1633 | BQ62: 370.35879 | BR62: 961.45812 | BS62: 34.55317 | BT62: 3889.1197 | BU62: 1069111.4 | BV62: 23278.931 | BW62: 32.439703 | BX62: 97406.459 | BY62: 17873.136 | BZ62: 1456.4817 | CA62: 10.909013 | CB62: 17203.71 | CC62: 25472.69 | CD62: 80.955109 | CE62: 44214.094 | CF62: 172.05752 | CG62: 16668.843 | CH62: 11613.358 | CI62: 161.01491 | CJ62: 163934.19 | CK62: 609.6033 | CL62: 913.44319 | CM62: 29422.076 | CN62: 1844.4153 | CO62: 16091.77 | CP62: 1.8293922 | CQ62: 816.075 | CR62: 174.50419 | CS62: 3604.0535 | CT62: 3317.2017 | CU62: 19852.38 | CV62: 11771.614 | CW62: 2422.265 | CX62: 855.81727 | CY62: 2469.5673 | CZ62: 11045.037 | DA62: 3159.2918 | DB62: 5754.6264 | DC62: 123.63413 | DD62: 89.10402 | DE62: 354.26032 | DF62: 711.44787 | DG62: 3050.9151 | DH62: 2416.9352 | DI62: 392.38548 | DJ62: 21083.117 | DK62: 0 | DL62: 80824.015 | DM62: 2171.3194 | DN62: 227533.73 | DO62: 0 | DQ62: =SUM(DH62:DJ62) -> 23892.438 | DR62: =DQ62/SUM(DQ$58:DQ$111) -> 0.036005861
A63: RoW | B63: Sector | C63: Mining & Quarrying of raw materials | D63: 255.23516 | E63: 150.63525 | F63: 6.0780671 | G63: 19.805559 | H63: 14.641149 | I63: 374.86354 | J63: 384.36764 | K63: 638.43688 | L63: 9.9187965 | M63: 133.74481 | N63: 30.370906 | O63: 17.384193 | P63: 16.745247 | Q63: 55.498256 | R63: 72.596184 | S63: 216.32879 | T63: 663.16848 | U63: 243.58012 | V63: 773.31578 | W63: 130.91026 | X63: 251.69328 | Y63: 13.562524 | Z63: 811.33759 | AA63: 322.23178 | AB63: 139.03162 | AC63: 12190.655 | AD63: 628.68135 | AE63: 824.48928 | AF63: 521.21189 | AG63: 23.488843 | AH63: 73.471502 | AI63: 6.694402 | AJ63: 33.625846 | AK63: 42.016415 | AL63: 28.563595 | AM63: 576.03837 | AN63: 0.037435026 | AO63: 15.846186 | AP63: 7.2063253 | AQ63: 149.76618 | AR63: 411.18292 | AS63: 92.745162 | AT63: 204.31129 | AU63: 24.440729 | AV63: 17.70379 | AW63: 59.032318 | AX63: 112.90529 | AY63: 35.643974 | AZ63: 387.05555 | BA63: 18.307493 | BB63: 6.3883583 | BC63: 7.0284777 | BD63: 11.324675 | BE63: 51.666236 | BF63: 2388.9144 | BG63: 1994.9943 | BH63: 407.24751 | BI63: 511.70613 | BJ63: 6046.942 | BK63: 70981.588 | BL63: 2034.8357 | BM63: 2791.345 | BN63: 291.55073 | BO63: 1593.2293 | BP63: 476.21441 | BQ63: 4.1172267 | BR63: 329.82623 | BS63: 22.379524 | BT63: 2327.781 | BU63: 4347.2818 | BV63: 1406.4368 | BW63: 31.592067 | BX63: 63172.438 | BY63: 8767.8177 | BZ63: 13820.458 | CA63: 5.4764229 | CB63: 32647.69 | CC63: 17272.985 | CD63: 90.654159 | CE63: 314349.91 | CF63: 1151.2586 | CG63: 20852.812 | CH63: 4911.6604 | CI63: 576.32703 | CJ63: 1928.438 | CK63: 516.2537 | CL63: 1062.9517 | CM63: 913.47059 | CN63: 715.17159 | CO63: 105225.83 | CP63: 0.018400076 | CQ63: 534.39844 | CR63: 272.13617 | CS63: 1895.3937 | CT63: 3697.3888 | CU63: 3437.2029 | CV63: 5752.1201 | CW63: 3429.9363 | CX63: 906.41244 | CY63: 876.01262 | CZ63: 6006.0113 | DA63: 1637.0102 | DB63: 3456.19 | DC63: 75.046811 | DD63: 69.648519 | DE63: 470.35923 | DF63: 1323.7862 | DG63: 2043.9272 | DH63: 1524.6505 | DI63: 192.75052 | DJ63: 1311.6432 | DK63: 0 | DL63: 18484.142 | DM63: 1409.1892 | DN63: 47664.793 | DO63: 0 | DQ63: =SUM(DH63:DJ63) -> 3029.0442 | DR63: =DQ63/SUM(DQ$58:DQ$111) -> 0.0045647642
A64: RoW | B64: Sector | C64: Processing of meat | D64: 47.138751 | E64: 661.82649 | F64: 2.2752484 | G64: 27.127185 | H64: 6.2930233 | I64: 24.834531 | J64: 4625.5163 | K64: 7829.0364 | L64: 4.7071007 | M64: 153.10932 | N64: 15.423465 | O64: 8.2851722 | P64: 4.8342366 | Q64: 17.697403 | R64: 46.079318 | S64: 36.71358 | T64: 372.22432 | U64: 122.66721 | V64: 163.38387 | W64: 51.990814 | X64: 10.486281 | Y64: 1.5378766 | Z64: 44.21035 | AA64: 13.542159 | AB64: 4.6572978 | AC64: 43.515355 | AD64: 17.607552 | AE64: 126.41187 | AF64: 50.271835 | AG64: 26.267113 | AH64: 25.3761 | AI64: 3.7077959 | AJ64: 8.5477445 | AK64: 11.705239 | AL64: 13.067222 | AM64: 64.585902 | AN64: 0.0085096326 | AO64: 6.8146137 | AP64: 15.078026 | AQ64: 110.91808 | AR64: 1866.4137 | AS64: 101.65468 | AT64: 179.13812 | AU64: 37.213922 | AV64: 12.469406 | AW64: 52.69488 | AX64: 94.881926 | AY64: 85.178175 | AZ64: 868.07454 | BA64: 4.6154515 | BB64: 2.0877157 | BC64: 1.879695 | BD64: 3.2387449 | BE64: 53.672333 | BF64: 2752.8259 | BG64: 18563.316 | BH64: 196.73697 | BI64: 3322.9526 | BJ64: 983.64102 | BK64: 1615.5086 | BL64: 131761.24 | BM64: 75242.364 | BN64: 233.11976 | BO64: 24024.123 | BP64: 150.93839 | BQ64: 2.8131092 | BR64: 83.161642 | BS64: 17.294508 | BT64: 786.11459 | BU64: 1822.4866 | BV64: 788.10903 | BW64: 24.891944 | BX64: 29540.324 | BY64: 520.67328 | BZ64: 185.0507 | CA64: 2.5370676 | CB64: 1196.2122 | CC64: 136.24624 | CD64: 18.398836 | CE64: 717.20262 | CF64: 15.436877 | CG64: 11228.898 | CH64: 2856.8524 | CI64: 556.37509 | CJ64: 1348.4851 | CK64: 285.97431 | CL64: 170.14598 | CM64: 152.0168 | CN64: 118.18693 | CO64: 1307.0946 | CP64: 0.01806731 | CQ64: 470.3956 | CR64: 195.42862 | CS64: 2228.921 | CT64: 90277.376 | CU64: 4357.7676 | CV64: 4079.8532 | CW64: 1741.2045 | CX64: 2238.6359 | CY64: 958.70314 | CZ64: 14998.255 | DA64: 6437.4072 | DB64: 30955.21 | DC64: 46.682011 | DD64: 29.566984 | DE64: 211.06038 | DF64: 139.90455 | DG64: 4216.1551 | DH64: 8628.2125 | DI64: 107.14125 | DJ64: 335.02608 | DK64: 0 | DL64: 765190.79 | DM64: 4182.6447 | DN64: 21391.893 | DO64: 0 | DQ64: =SUM(DH64:DJ64) -> 9070.3798 | DR64: =DQ64/SUM(DQ$58:DQ$111) -> 0.013669046
A65: RoW | B65: Sector | C65: Processing of other food&beverage | D65: 42.232823 | E65: 794.70687 | F65: 1.9924199 | G65: 13.477579 | H65: 3.6509028 | I65: 47.173895 | J65: 1582.3738 | K65: 3538.3984 | L65: 2.6601575 | M65: 107.30147 | N65: 10.741801 | O65: 5.8644993 | P65: 6.3211306 | Q65: 15.991759 | R65: 52.449494 | S65: 27.732497 | T65: 281.89045 | U65: 95.429525 | V65: 194.86737 | W65: 45.941458 | X65: 22.838745 | Y65: 1.549621 | Z65: 74.306251 | AA65: 37.230429 | AB65: 14.380402 | AC65: 49.480533 | AD65: 13.184034 | AE65: 111.73679 | AF65: 88.789262 | AG65: 15.182439 | AH65: 18.373355 | AI65: 3.165648 | AJ65: 8.0222957 | AK65: 7.5410478 | AL65: 9.5192922 | AM65: 101.02758 | AN65: 0.0099104384 | AO65: 12.025302 | AP65: 11.457452 | AQ65: 123.81029 | AR65: 1835.1817 | AS65: 86.809127 | AT65: 214.19025 | AU65: 24.907388 | AV65: 14.26138 | AW65: 30.988778 | AX65: 124.89266 | AY65: 96.96385 | AZ65: 492.27073 | BA65: 4.2598307 | BB65: 1.6250248 | BC65: 1.8192101 | BD65: 3.0132622 | BE65: 36.084239 | BF65: 1678.5867 | BG65: 119517.49 | BH65: 1062.0282 | BI65: 3522.2308 | BJ65: 1044.1263 | BK65: 3373.6505 | BL65: 31026.805 | BM65: 292576.42 | BN65: 371.1716 | BO65: 5595.1016 | BP65: 154.82906 | BQ65: 11.892159 | BR65: 77.017272 | BS65: 42.243625 | BT65: 2888.4519 | BU65: 656.94357 | BV65: 473.90021 | BW65: 43.322063 | BX65: 17031.022 | BY65: 9993.7526 | BZ65: 462.99833 | CA65: 6.0233248 | CB65: 2294.3262 | CC65: 386.98914 | CD65: 73.342801 | CE65: 2261.4856 | CF65: 28.416989 | CG65: 4175.4661 | CH65: 1460.112 | CI65: 206.81016 | CJ65: 637.9873 | CK65: 193.87265 | CL65: 156.08186 | CM65: 111.44942 | CN65: 70.244306 | CO65: 8291.8832 | CP65: 0.035052565 | CQ65: 396.01866 | CR65: 121.18827 | CS65: 2790.0414 | CT65: 135109.86 | CU65: 4903.3846 | CV65: 3355.9527 | CW65: 731.804 | CX65: 626.07944 | CY65: 2345.5336 | CZ65: 10009.561 | DA65: 3893.5272 | DB65: 26394.13 | DC65: 37.652344 | DD65: 24.748166 | DE65: 115.4545 | DF65: 213.0203 | DG65: 6171.3584 | DH65: 20162.387 | DI65: 72.074348 | DJ65: 365.46672 | DK65: 0 | DL65: 1217362.3 | DM65: 13514.191 | DN65: 31267.179 | DO65: 0 | DQ65: =SUM(DH65:DJ65) -> 20599.928 | DR65: =DQ65/SUM(DQ$58:DQ$111) -> 0.031044054
A66: RoW | B66: Sector | C66: Manufacture of tobacco products (16) | D66: 3.5445299 | E66: 0.97276214 | F66: 0.070394478 | G66: 0.13609261 | H66: 0.44817091 | I66: 0.43765909 | J66: 4.9089388 | K66: 6.0554289 | L66: 23.28206 | M66: 4.7137427 | N66: 0.57112784 | O66: 0.32100346 | P66: 0.23680812 | Q66: 0.56893938 | R66: 2.6130288 | S66: 1.5188621 | T66: 4.9700163 | U66: 2.5763807 | V66: 4.3817615 | W66: 1.9549633 | X66: 0.17917073 | Y66: 0.074480211 | Z66: 0.64848063 | AA66: 0.26632193 | AB66: 0.073508643 | AC66: 91.821944 | AD66: 9.6405257 | AE66: 18.818995 | AF66: 1.0837784 | AG66: 0.14032926 | AH66: 1.8473374 | AI66: 0.37685216 | AJ66: 0.36082718 | AK66: 1.1708365 | AL66: 0.42319557 | AM66: 14.37621 | AN66: 0.00083163962 | AO66: 0.43124307 | AP66: 0.093560628 | AQ66: 24.14127 | AR66: 69.961834 | AS66: 8.6438124 | AT66: 23.174491 | AU66: 1.4028825 | AV66: 2.136546 | AW66: 1.2053922 | AX66: 21.771002 | AY66: 1.1158116 | AZ66: 6.7836454 | BA66: 0.46774133 | BB66: 0.098933111 | BC66: 0.46611935 | BD66: 0.59279997 | BE66: 9.9310914 | BF66: 55.200183 | BG66: 14.347343 | BH66: 9.159687 | BI66: 4.9911947 | BJ66: 48.317642 | BK66: 41.505024 | BL66: 53.532196 | BM66: 56.070068 | BN66: 6118.0854 | BO66: 85.23936 | BP66: 6.3830481 | BQ66: 0.45491483 | BR66: 6.0143654 | BS66: 0.4583368 | BT66: 43.588722 | BU66: 32.183242 | BV66: 10.663162 | BW66: 0.79919431 | BX66: 513.27475 | BY66: 17.326715 | BZ66: 7.223494 | CA66: 0.083154827 | CB66: 17.03799 | CC66: 6.148574 | CD66: 0.097903052 | CE66: 3023.4812 | CF66: 10.688717 | CG66: 449.89303 | CH66: 21.938611 | CI66: 9.8639646 | CJ66: 56.733494 | CK66: 14.61978 | CL66: 9.312666 | CM66: 39.410082 | CN66: 4.4877135 | CO66: 151.607 | CP66: 0.00080522691 | CQ66: 13.550826 | CR66: 4.9965349 | CS66: 185.82955 | CT66: 814.78345 | CU66: 116.3923 | CV66: 568.08737 | CW66: 48.563732 | CX66: 69.669977 | CY66: 14.721087 | CZ66: 457.53834 | DA66: 31.597796 | DB66: 62.279351 | DC66: 3.9033468 | DD66: 1.3830287 | DE66: 7.3614591 | DF66: 16.750437 | DG66: 169.16401 | DH66: 760.14975 | DI66: 3.0884756 | DJ66: 24.450448 | DK66: 0 | DL66: 134348.99 | DM66: 25.40735 | DN66: 1357.6348 | DO66: 0 | DQ66: =SUM(DH66:DJ66) -> 787.68867 | DR66: =DQ66/SUM(DQ$58:DQ$111) -> 0.0011870454
A67: RoW | B67: Sector | C67: Manufacture of textiles | D67: 109.92019 | E67: 77.225567 | F67: 28.366703 | G67: 53.852682 | H67: 22.703705 | I67: 21.710707 | J67: 48.02487 | K67: 181.63568 | L67: 24.073416 | M67: 13494.622 | N67: 48.410409 | O67: 32.840741 | P67: 15.694414 | Q67: 56.206748 | R67: 194.43074 | S67: 26.343095 | T67: 135.074 | U67: 55.456715 | V67: 299.01187 | W67: 636.93163 | X67: 33.475508 | Y67: 12.65012 | Z67: 46.107485 | AA67: 25.29682 | AB67: 5.940101 | AC67: 82.732988 | AD67: 35.856 | AE67: 1899.157 | AF67: 653.20659 | AG67: 9.7918665 | AH67: 33.043327 | AI67: 2.6954188 | AJ67: 15.434759 | AK67: 11.741749 | AL67: 16.384728 | AM67: 670.59229 | AN67: 0.6857873 | AO67: 40.797943 | AP67: 16.23934 | AQ67: 253.58585 | AR67: 424.70571 | AS67: 216.1448 | AT67: 416.51302 | AU67: 30.197745 | AV67: 60.109001 | AW67: 43.415176 | AX67: 385.77466 | AY67: 66.893066 | AZ67: 641.09165 | BA67: 29.894514 | BB67: 14.468348 | BC67: 8.8180717 | BD67: 22.194938 | BE67: 201.07217 | BF67: 2997.534 | BG67: 824.93322 | BH67: 337.0846 | BI67: 1647.3035 | BJ67: 2315.2035 | BK67: 2277.214 | BL67: 750.95778 | BM67: 2850.6094 | BN67: 668.22897 | BO67: 575936.63 | BP67: 1362.7245 | BQ67: 6.7576448 | BR67: 94.152191 | BS67: 9.9961261 | BT67: 14347.487 | BU67: 595.78918 | BV67: 325.25091 | BW67: 6.9553393 | BX67: 20891.597 | BY67: 17964.595 | BZ67: 1369.7471 | CA67: 17.627254 | CB67: 2245.8286 | CC67: 386.51687 | CD67: 3.0733478 | CE67: 3866.3187 | CF67: 25.052845 | CG67: 39472.809 | CH67: 32847.167 | CI67: 417.43918 | CJ67: 1714.6794 | CK67: 716.09235 | CL67: 315.81963 | CM67: 451.51689 | CN67: 219.62963 | CO67: 19020.903 | CP67: 0.15456555 | CQ67: 598.68341 | CR67: 130.64595 | CS67: 3947.1102 | CT67: 8120.7446 | CU67: 8686.9445 | CV67: 14123.075 | CW67: 3916.3635 | CX67: 1523.9837 | CY67: 11630.448 | CZ67: 16762.286 | DA67: 2173.063 | DB67: 17139.871 | DC67: 297.3953 | DD67: 128.16175 | DE67: 982.66621 | DF67: 722.48327 | DG67: 9594.2326 | DH67: 60382.629 | DI67: 88.959889 | DJ67: 991.21781 | DK67: 0 | DL67: 654051.11 | DM67: 2458.9157 | DN67: 37154.3 | DO67: 0 | DQ67: =SUM(DH67:DJ67) -> 61462.806 | DR67: =DQ67/SUM(DQ$58:DQ$111) -> 0.092624338
A68: RoW | B68: Sector | C68: Manufacture of wood and of products of wood and cork, except furniture; manufacture of articles of straw and plaiting materials (20) | D68: 49.866301 | E68: 32.267044 | F68: 5.68216 | G68: 5.3069906 | H68: 12.468834 | I68: 19.843346 | J68: 46.707144 | K68: 114.37381 | L68: 4.5541998 | M68: 23.361556 | N68: 1460.1368 | O68: 667.52434 | P68: 32.131908 | Q68: 2.3550741 | R68: 81.026891 | S68: 8.7401468 | T68: 37.408958 | U68: 15.37883 | V68: 12.372823 | W68: 44.363802 | X68: 12.428452 | Y68: 5.4004402 | Z68: 67.27352 | AA68: 12.769333 | AB68: 6.2584989 | AC68: 70.827285 | AD68: 40.026798 | AE68: 469.21374 | AF68: 806.08817 | AG68: 10.014483 | AH68: 17.541106 | AI68: 7.4730592 | AJ68: 23.121988 | AK68: 5.2563037 | AL68: 12.459904 | AM68: 1729.8413 | AN68: 0.02519016 | AO68: 10.141704 | AP68: 2.0636104 | AQ68: 59.315277 | AR68: 71.911909 | AS68: 55.863588 | AT68: 159.67535 | AU68: 134.74892 | AV68: 11.321846 | AW68: 6.1497995 | AX68: 19.574774 | AY68: 22.657506 | AZ68: 31.343719 | BA68: 5.1353689 | BB68: 2.5769973 | BC68: 1.0349253 | BD68: 2.0002582 | BE68: 55.081524 | BF68: 935.41129 | BG68: 333.61018 | BH68: 462.29943 | BI68: 306.82181 | BJ68: 637.03366 | BK68: 484.95428 | BL68: 888.73704 | BM68: 1760.1708 | BN68: 381.78584 | BO68: 702.58524 | BP68: 38462.277 | BQ68: 2063.2617 | BR68: 4441.8307 | BS68: 16.003421 | BT68: 7451.6775 | BU68: 252.92918 | BV68: 123.48936 | BW68: 3.9981302 | BX68: 2206.3141 | BY68: 1155.2971 | BZ68: 528.82993 | CA68: 13.557744 | CB68: 993.9425 | CC68: 217.03228 | CD68: 3.3884748 | CE68: 1320.6585 | CF68: 15.14689 | CG68: 10819.322 | CH68: 21717.756 | CI68: 126.99178 | CJ68: 88.460969 | CK68: 166.53113 | CL68: 104.81021 | CM68: 360.62343 | CN68: 48.689711 | CO68: 113080.12 | CP68: 0.0044920174 | CQ68: 194.1866 | CR68: 34.97047 | CS68: 1095.5666 | CT68: 3053.2763 | CU68: 2410.0827 | CV68: 2759.7134 | CW68: 4944.3353 | CX68: 1058.9642 | CY68: 291.22364 | CZ68: 4760.658 | DA68: 615.76413 | DB68: 1667.1209 | DC68: 33.921442 | DD68: 30.114932 | DE68: 94.934705 | DF68: 33.81192 | DG68: 801.27103 | DH68: 1071.3363 | DI68: 5.6982404 | DJ68: 437.57396 | DK68: 0 | DL68: 16898.307 | DM68: 101.95747 | DN68: 18956.525 | DO68: 0 | DQ68: =SUM(DH68:DJ68) -> 1514.6085 | DR68: =DQ68/SUM(DQ$58:DQ$111) -> 0.0022825122
A69: RoW | B69: Sector | C69: Re-processing of secondary wood material into new wood material | D69: 1.9938737 | E69: 2.156428 | F69: 0.16230099 | G69: 0.25900004 | H69: 0.32267964 | I69: 0.71398329 | J69: 2.7366525 | K69: 7.7577966 | L69: 0.19413079 | M69: 1.2009836 | N69: 47.417123 | O69: 20.759207 | P69: 1.1446516 | Q69: 0.0886658 | R69: 2.6383722 | S69: 1.7621455 | T69: 1.9816642 | U69: 0.5069394 | V69: 0.86806482 | W69: 2.9853744 | X69: 0.51492127 | Y69: 0.25567245 | Z69: 1.9421676 | AA69: 0.42592923 | AB69: 0.095246065 | AC69: 1.3286191 | AD69: 0.51139972 | AE69: 19.000774 | AF69: 25.078594 | AG69: 0.25041286 | AH69: 0.30135255 | AI69: 0.164334 | AJ69: 0.54946778 | AK69: 0.12945908 | AL69: 0.32229123 | AM69: 85.606921 | AN69: 0.0013751476 | AO69: 0.55524235 | AP69: 0.097055274 | AQ69: 2.1478912 | AR69: 9.6816913 | AS69: 2.5108649 | AT69: 7.1328158 | AU69: 3.8647978 | AV69: 0.78356135 | AW69: 0.37534821 | AX69: 1.0725084 | AY69: 2.3033242 | AZ69: 1.7786153 | BA69: 0.17131884 | BB69: 0.088766526 | BC69: 0.02398306 | BD69: 0.046804186 | BE69: 1.7890471 | BF69: 129.78565 | BG69: 19.170276 | BH69: 22.193829 | BI69: 44.965009 | BJ69: 18.727012 | BK69: 8.3341374 | BL69: 28.043132 | BM69: 80.044355 | BN69: 3.0057622 | BO69: 16.94892 | BP69: 1543.3334 | BQ69: 1220.1138 | BR69: 140.12868 | BS69: 3.7488391 | BT69: 390.39436 | BU69: 5.1045982 | BV69: 9.7746555 | BW69: 1.7020338 | BX69: 186.75133 | BY69: 35.787867 | BZ69: 52.725053 | CA69: 10.700998 | CB69: 221.82756 | CC69: 7.0738366 | CD69: 1.7118681 | CE69: 48.062991 | CF69: 4.0164965 | CG69: 821.25521 | CH69: 2213.6255 | CI69: 2.0035439 | CJ69: 2.8311411 | CK69: 2.6913247 | CL69: 4.4754182 | CM69: 3.0695595 | CN69: 0.27150344 | CO69: 7065.1572 | CP69: 0.0024348646 | CQ69: 9.1775031 | CR69: 1.3509195 | CS69: 94.362785 | CT69: 116.46243 | CU69: 54.715451 | CV69: 132.65293 | CW69: 52.97667 | CX69: 14.989243 | CY69: 4.9171068 | CZ69: 94.255615 | DA69: 108.68788 | DB69: 35.928787 | DC69: 0.36116386 | DD69: 1.1624625 | DE69: 0.40087099 | DF69: 1.5384445 | DG69: 20.13663 | DH69: 61.587696 | DI69: 0.35051794 | DJ69: 18.824416 | DK69: 0 | DL69: 895.57168 | DM69: 0.18731285 | DN69: 494.98368 | DO69: 0 | DQ69: =SUM(DH69:DJ69) -> 80.76263 | DR69: =DQ69/SUM(DQ$58:DQ$111) -> 0.00012170914
... A111: RoW | B111: Sector | C111: Other Services | D111: 6.2820198 | E111: 4.5286756 | F111: 0.45092279 | G111: 0.7842399 | H111: 1.9788993 | I111: 3.1734278 | J111: 18.502115 | K111: 17.863668 | L111: 0.48379502 | M111: 11.205777 | N111: 2.8292769 | O111: 1.2397009 | P111: 0.53508387 | Q111: 1.9584224 | R111: 9.4330265 | S111: 10.45783 | T111: 11.456706 | U111: 4.6145199 | V111: 8.4202916 | W111: 5.3658401 | X111: 0.49477453 | Y111: 0.17923523 | Z111: 2.9959899 | AA111: 2.0198937 | AB111: 0.52382275 | AC111: 245.47755 | AD111: 2.3275403 | AE111: 44.090784 | AF111: 4.5003901 | AG111: 0.64913522 | AH111: 3.5213975 | AI111: 0.63654286 | AJ111: 2.9367524 | AK111: 4.1632369 | AL111: 1.813469 | AM111: 22.534855 | AN111: 0.022845171 | AO111: 3.3026471 | AP111: 0.51064563 | AQ111: 23.628989 | AR111: 37.020674 | AS111: 61.855748 | AT111: 117.73477 | AU111: 71.516147 | AV111: 6.81402 | AW111: 5.1533562 | AX111: 20.48804 | AY111: 9.3884674 | AZ111: 37.043243 | BA111: 4.7929537 | BB111: 2.2566115 | BC111: 0.8693682 | BD111: 1.3091365 | BE111: 211.08673 | BF111: 4342.8038 | BG111: 868.11665 | BH111: 570.42572 | BI111: 643.72028 | BJ111: 4493.3256 | BK111: 1658.6166 | BL111: 1217.5297 | BM111: 4119.9562 | BN111: 394.66018 | BO111: 2929.9925 | BP111: 722.57698 | BQ111: 34.161786 | BR111: 76.055836 | BS111: 9.5809047 | BT111: 2798.3319 | BU111: 1030.4729 | BV111: 146.3456 | BW111: 5.4302855 | BX111: 5162.6091 | BY111: 1815.9052 | BZ111: 356.50702 | CA111: 0.31237768 | CB111: 2318.6939 | CC111: 605.13234 | CD111: 20.108134 | CE111: 5689.3754 | CF111: 138.79827 | CG111: 16503.979 | CH111: 1384.7458 | CI111: 119.69991 | CJ111: 6393.6403 | CK111: 966.46438 | CL111: 500.17976 | CM111: 515.45038 | CN111: 581.46432 | CO111: 12814.769 | CP111: 0.076517194 | CQ111: 1486.7118 | CR111: 100.7535 | CS111: 3314.1739 | CT111: 16946.191 | CU111: 23805.977 | CV111: 43208.089 | CW111: 25686.728 | CX111: 2636.3065 | CY111: 6934.1336 | CZ111: 15555.048 | DA111: 10340.912 | DB111: 28784.353 | DC111: 869.03746 | DD111: 154.68877 | DE111: 1417.4861 | DF111: 534.75365 | DG111: 28646.339 | DH111: 1446.9049 | DI111: 187.11879 | DJ111: 38.851352 | DK111: 0 | DL111: 990690.34 | DM111: 19520.955 | DN111: 8498.4239 | DO111: 0 | DQ111: =SUM(DH111:DJ111) -> 1672.875 | DR111: =DQ111/SUM(DQ$58:DQ$111) -> 0.0025210196
A112: - | B112: Factor of production | C112: Indirect Taxes | D112: 167.11291 | E112: 1893.8717 | F112: 627.50196 | G112: 651.86795 | H112: 347.28212 | I112: 2097.2041 | J112: 11864.694 | K112: 17216.695 | L112: 1353.8296 | M112: 10484.433 | N112: 2217.7244 | O112: 997.08765 | P112: 624.58735 | Q112: 953.98777 | R112: 7494.4807 | S112: 19714.131 | T112: 10928.727 | U112: 1495.7247 | V112: 3186.8874 | W112: 7035.4382 | X112: 578.66615 | Y112: 192.05202 | Z112: 2113.8874 | AA112: 2562.6059 | AB112: 470.05968 | AC112: 5634.9759 | AD112: 2211.7005 | AE112: 49861.544 | AF112: 4401.2113 | AG112: 981.3928 | AH112: 8897.0246 | AI112: 1578.1591 | AJ112: 12287.87 | AK112: 6922.39 | AL112: 4218.1582 | AM112: 36435.651 | AN112: 27.407847 | AO112: 13695.53 | AP112: 2095.3416 | AQ112: 40498.499 | AR112: 50997.786 | AS112: 62426.902 | AT112: 95749.602 | AU112: 92122.696 | AV112: 5560.0842 | AW112: 1491.3652 | AX112: 23892.69 | AY112: 9706.1088 | AZ112: 27186.322 | BA112: 1905.5571 | BB112: 852.08453 | BC112: 541.13923 | BD112: 1103.7113 | BE112: 7801.7046 | BF112: 78815.953 | BG112: 21791.297 | BH112: 14565.756 | BI112: 3398.001 | BJ112: 277923.78 | BK112: 43012.284 | BL112: 44087.544 | BM112: 107576.2 | BN112: 18166.602 | BO112: 95653.297 | BP112: 14765.922 | BQ112: 591.51963 | BR112: 2678.137 | BS112: 250.52841 | BT112: 58237.413 | BU112: 189729.39 | BV112: 9119.7857 | BW112: 196.11725 | BX112: 106519.79 | BY112: 37910.419 | BZ112: 14889.814 | CA112: 71.554098 | CB112: 27131.457 | CC112: 11088.89 | CD112: 95.867876 | CE112: 149146.82 | CF112: 1087.7299 | CG112: 455266.29 | CH112: 42298.441 | CI112: -1790.649 | CJ112: 58907.772 | CK112: 7820.7638 | CL112: 65254.682 | CM112: 10214.065 | CN112: 10861.7 | CO112: 286355.8 | CP112: 4.506481 | CQ112: 90244.515 | CR112: 3010.7014 | CS112: 202027.23 | CT112: 346427.07 | CU112: 245705.69 | CV112: 410871.85 | CW112: 424852.65 | CX112: 28491.477 | CY112: 10499.999 | CZ112: 100165.12 | DA112: 43563.488 | DB112: 103250.76 | DC112: 3209.5717 | DD112: 1185.873 | DE112: 5135.8344 | DF112: 8720.3683 | DG112: 41559.947 | DH112: 0 | DI112: 0 | DJ112: 0 | DK112: 0 | DL112: 0 | DM112: 0 | DN112: 0 | DO112: 0
A113: - | B113: Factor of production | C113: Wages | D113: 26508.465 | E113: 13225.81 | F113: 5901.2171 | G113: 2728.5257 | H113: 13992.432 | I113: 11218.883 | J113: 62088.242 | K113: 64802.492 | L113: 3132.8035 | M113: 64192.586 | N113: 19696.287 | O113: 7838.7731 | P113: 2540.6805 | Q113: 4145.4252 | R113: 70328.826 | S113: 10360.115 | T113: 51152.621 | U113: 10575.506 | V113: 9913.4347 | W113: 48346.796 | X113: 4117.7028 | Y113: 2193.3083 | Z113: 18352.83 | AA113: 19050.638 | AB113: 4753.9906 | AC113: 34487.608 | AD113: 13373.589 | AE113: 619606.69 | AF113: 51380.064 | AG113: 6950.5697 | AH113: 23251.84 | AI113: 3714.2303 | AJ113: 14365.663 | AK113: 28573.843 | AL113: 15638.212 | AM113: 375860.95 | AN113: 936.23946 | AO113: 142803.61 | AP113: 7017.4859 | AQ113: 423625.24 | AR113: 398284.8 | AS113: 431779.8 | AT113: 1000519.3 | AU113: 60445.519 | AV113: 17246.778 | AW113: 56602.92 | AX113: 473407.01 | AY113: 441487.81 | AZ113: 563980.31 | BA113: 14606.78 | BB113: 5898.826 | BC113: 3326.2444 | BD113: 8565.5618 | BE113: 194160.9 | BF113: 593030.99 | BG113: 214460.18 | BH113: 74843.503 | BI113: 193059.3 | BJ113: 275571.33 | BK113: 152795.49 | BL113: 115805.51 | BM113: 228675.87 | BN113: 9977.3986 | BO113: 245740.69 | BP113: 39975.038 | BQ113: 4183.1434 | BR113: 5032.9877 | BS113: 2608.9909 | BT113: 236914.91 | BU113: 67196.683 | BV113: 22371.302 | BW113: 1240.3976 | BX113: 172142.32 | BY113: 220330.22 | BZ113: 28124.292 | CA113: 621.71551 | CB113: 70313.689 | CC113: 32663.479 | CD113: 536.1519 | CE113: 204970.65 | CF113: 5512.9676 | CG113: 1686118.8 | CH113: 144512.04 | CI113: 18512.337 | CJ113: 169876.89 | CK113: 20533.4 | CL113: 68296.133 | CM113: 36128.311 | CN113: 24650.093 | CO113: 1429194.6 | CP113: 191.72338 | CQ113: 686823.46 | CR113: 5396.0814 | CS113: 1416672.4 | CT113: 1498257.5 | CU113: 1236975.5 | CV113: 3710335.6 | CW113: 187182.21 | CX113: 72174.946 | CY113: 262596.96 | CZ113: 2636712.4 | DA113: 1065066.6 | DB113: 1046087.5 | DC113: 26334.812 | DD113: 11180.878 | DE113: 66621.5 | DF113: 107857.06 | DG113: 498715.44 | DH113: 0 | DI113: 0 | DJ113: 0 | DK113: 0 | DL113: 0 | DM113: 0 | DN113: 0 | DO113: 0
A114: - | B114: Factor of production | C114: Operating surplus: Consumption of fixed capital | D114: 29494.37 | E114: 19335.339 | F114: 2679.9773 | G114: 1215.0867 | H114: 6331.936 | I114: 5145.5707 | J114: 10971.868 | K114: 21733.822 | L114: 1374.4317 | M114: 11141.49 | N114: 4709.7481 | O114: 1436.6042 | P114: 1057.8811 | Q114: 3039.4333 | R114: 14784.857 | S114: 6024.7979 | T114: 14458.634 | U114: 3779.6194 | V114: 3555.6904 | W114: 10788.918 | X114: 1530.2277 | Y114: 715.99479 | Z114: 4484.6134 | AA114: 5016.551 | AB114: 1243.984 | AC114: 11180.925 | AD114: 5314.2172 | AE114: 115676.57 | AF114: 8508.1811 | AG114: 971.60812 | AH114: 29392.672 | AI114: 16091.753 | AJ114: 38980.202 | AK114: 8218.9752 | AL114: 16397.822 | AM114: 71684.481 | AN114: 76.291424 | AO114: 21781.837 | AP114: 786.40682 | AQ114: 65308.431 | AR114: 97634.871 | AS114: 158761.6 | AT114: 215416.42 | AU114: 408839.65 | AV114: 72683.364 | AW114: 9577.0074 | AX114: 137193.59 | AY114: 51038.764 | AZ114: 69105.981 | BA114: 12818.068 | BB114: 4306.4995 | BC114: 2305.75 | BD114: 4060.1658 | BE114: 15649.425 | BF114: 132455.51 | BG114: 56278.761 | BH114: 7243.4161 | BI114: 10082.201 | BJ114: 225261.85 | BK114: 74991.581 | BL114: 21668.126 | BM114: 51574.832 | BN114: 21878.511 | BO114: 58482.692 | BP114: 8923.607 | BQ114: 616.05382 | BR114: 2223.8227 | BS114: 470.89792 | BT114: 62553.067 | BU114: 71987.253 | BV114: 11708.95 | BW114: 495.87879 | BX114: 121971.6 | BY114: 49333.239 | BZ114: 13180.238 | CA114: 131.43414 | CB114: 23947.023 | CC114: 11955.47 | CD114: 99.806878 | CE114: 126015.63 | CF114: 4698.3948 | CG114: 523689.63 | CH114: 42354.465 | CI114: 6687.735 | CJ114: 151890.97 | CK114: 80658.313 | CL114: 80700.112 | CM114: 33585.033 | CN114: 37066.082 | CO114: 364930.15 | CP114: 28.328943 | CQ114: 125991.31 | CR114: 1194.8218 | CS114: 276783.26 | CT114: 319298.24 | CU114: 344386.95 | CV114: 1028319.8 | CW114: 1072982.8 | CX114: 221119.59 | CY114: 27042.464 | CZ114: 645769.24 | DA114: 140006.37 | DB114: 210450.26 | DC114: 6728.6522 | DD114: 5680.3378 | DE114: 30392.824 | DF114: 50161.537 | DG114: 60035.426 | DH114: 0 | DI114: 0 | DJ114: 0 | DK114: 0 | DL114: 0 | DM114: 0 | DN114: 0 | DO114: 0
A115: - | B115: Factor of production | C115: Operation Surplus | D115: 76213.429 | E115: 29696.069 | F115: 12581.052 | G115: 3006.7475 | H115: 12227.599 | I115: 9602.7735 | J115: 24507.823 | K115: 49340.014 | L115: 4301.9491 | M115: 18126.228 | N115: 7553.6114 | O115: 2990.6524 | P115: 911.70312 | Q115: 2389.5746 | R115: 36187.05 | S115: 10923.687 | T115: 33887.026 | U115: 11696.301 | V115: 14222.848 | W115: 16424.636 | X115: 1972.6208 | Y115: 1062.5718 | Z115: 5326.5564 | AA115: 5906.3252 | AB115: 1356.6816 | AC115: 6311.1096 | AD115: 4263.5828 | AE115: 203521.26 | AF115: 18276.198 | AG115: 3473.4912 | AH115: 27499.964 | AI115: 7889.8693 | AJ115: 36304.948 | AK115: 18276.218 | AL115: 10583.883 | AM115: 158668.31 | AN115: 596.906 | AO115: 37286.628 | AP115: 8320.4082 | AQ115: 213430.82 | AR115: 220560.06 | AS115: 121326.94 | AT115: 471381.58 | AU115: 589690.79 | AV115: 15519.91 | AW115: 1714.8753 | AX115: 6486.2998 | AY115: 18127.043 | AZ115: 126872.9 | BA115: 3801.5573 | BB115: 1741.9935 | BC115: 1257.4064 | BD115: 3195.3845 | BE115: 60655.099 | BF115: 400341.97 | BG115: 110815.27 | BH115: 55138.242 | BI115: 33537.137 | BJ115: 823318.06 | BK115: 131775.01 | BL115: 71728.46 | BM115: 147417.31 | BN115: 23882.853 | BO115: 72971.837 | BP115: 20307.092 | BQ115: 1815.7462 | BR115: 2219.3024 | BS115: 473.02786 | BT115: 98765.406 | BU115: 65696.376 | BV115: 13783.776 | BW115: 648.72968 | BX115: 174171.62 | BY115: 42692.384 | BZ115: 25582.065 | CA115: 175.69035 | CB115: 32177.924 | CC115: 15390.525 | CD115: 144.45142 | CE115: 118647.12 | CF115: 6113.313 | CG115: 474795.95 | CH115: 102183.58 | CI115: 7233.245 | CJ115: 30271.656 | CK115: 15060.303 | CL115: 42778.277 | CM115: 26141.666 | CN115: 34151.031 | CO115: 300523.75 | CP115: 214.25106 | CQ115: 117750.13 | CR115: 6314.1107 | CS115: 841618.22 | CT115: 495757.22 | CU115: 354577.79 | CV115: 1592867.3 | CW115: 1405565.1 | CX115: 61972.067 | CY115: -4034.5726 | CZ115: 30289.197 | DA115: 19119.907 | DB115: 317888.8 | DC115: 795.97588 | DD115: 3095.2802 | DE115: 12940.81 | DF115: 22380.34 | DG115: 83060.24 | DH115: 0 | DI115: 0 | DJ115: 0 | DK115: 0 | DL115: 0 | DM115: 0 | DN115: 0 | DO115: 0
A116: - | B116: Satellite account | C116: Employment male | D116: 3859.7959 | E116: 1959.0231 | F116: 459.49175 | G116: 329.54227 | H116: 394.86057 | I116: 210.78452 | J116: 1070.7769 | K116: 1204.8749 | L116: 43.28983 | M116: 752.87106 | N116: 632.92192 | O116: 205.70232 | P116: 79.669407 | Q116: 88.590899 | R116: 919.63896 | S116: 150.67812 | T116: 465.72641 | U116: 102.02828 | V116: 733.39733 | W116: 813.75008 | X116: 98.286444 | Y116: 45.676682 | Z116: 399.37631 | AA116: 417.31368 | AB116: 97.616557 | AC116: 686.71429 | AD116: 285.96469 | AE116: 9274.8112 | AF116: 1581.7302 | AG116: 120.53974 | AH116: 346.73714 | AI116: 50.228543 | AJ116: 207.61687 | AK116: 354.3887 | AL116: 345.61002 | AM116: 12284.375 | AN116: 25.358248 | AO116: 2414.9755 | AP116: 310.88233 | AQ116: 11148.577 | AR116: 5343.0177 | AS116: 7025.7317 | AT116: 14754.498 | AU116: 742.4641 | AV116: 236.86691 | AW116: 1259.5908 | AX116: 6968.7934 | AY116: 3712.3199 | AZ116: 4215.8312 | BA116: 332.32612 | BB116: 140.53689 | BC116: 100.31921 | BD116: 247.71083 | BE116: 1849.0871 | BF116: 405324.25 | BG116: 142460.47 | BH116: 30204.521 | BI116: 115955.33 | BJ116: 39489.97 | BK116: 24512.643 | BL116: 10245.513 | BM116: 17635.71 | BN116: 617.67083 | BO116: 24070.247 | BP116: 5483.8821 | BQ116: 253.8083 | BR116: 714.73575 | BS116: 40.896225 | BT116: 18179.531 | BU116: 8982.1011 | BV116: 2334.6206 | BW116: 14.349961 | BX116: 14534.095 | BY116: 27775.54 | BZ116: 3185.0394 | CA116: 26.039081 | CB116: 9760.3054 | CC116: 4008.2343 | CD116: 10.284082 | CE116: 31146.902 | CF116: 182.57404 | CG116: 160413.53 | CH116: 17542.191 | CI116: 1913.9737 | CJ116: 12001.797 | CK116: 2027.3202 | CL116: 4833.8985 | CM116: 4576.6802 | CN116: 3586.1478 | CO116: 144921.63 | CP116: 6.6050119 | CQ116: 26253.23 | CR116: 473.43064 | CS116: 107519.53 | CT116: 61118.974 | CU116: 96020.53 | CV116: 96869.636 | CW116: 5613.3689 | CX116: 1702.7436 | CY116: 13304.911 | CZ116: 91696.796 | DA116: 42727.146 | DB116: 29662.423 | DC116: 545.55874 | DD116: 260.06191 | DE116: 9146.1617 | DF116: 2550.7026 | DG116: 24122.577
A117: - | B117: Satellite account | C117: Employment female | D117: 2350.5542 | E117: 1214.8819 | F117: 254.87158 | G117: 180.21738 | H117: 53.073461 | I117: 29.392453 | J117: 949.6976 | K117: 961.48373 | L117: 38.242087 | M117: 1804.3246 | N117: 155.83102 | O117: 46.926085 | P117: 39.773869 | Q117: 29.168212 | R117: 562.63991 | S117: 57.687061 | T117: 182.55644 | U117: 44.492826 | V117: 405.13503 | W117: 353.80176 | X117: 33.947001 | Y117: 14.608885 | Z117: 121.82804 | AA117: 132.98106 | AB117: 23.718565 | AC117: 115.25561 | AD117: 39.497704 | AE117: 2799.1839 | AF117: 779.21708 | AG117: 48.690658 | AH117: 98.967012 | AI117: 13.873315 | AJ117: 59.893164 | AK117: 100.78999 | AL117: 90.643974 | AM117: 1201.8108 | AN117: 2.9884279 | AO117: 2316.9179 | AP117: 296.4421 | AQ117: 11123.624 | AR117: 6233.6133 | AS117: 1997.3593 | AT117: 13256.915 | AU117: 778.14454 | AV117: 260.28644 | AW117: 1144.4953 | AX117: 5838.5696 | AY117: 9143.3981 | AZ117: 14982.541 | BA117: 79.762599 | BB117: 35.083425 | BC117: 26.494477 | BD117: 62.808729 | BE117: 5670.3319 | BF117: 212254.76 | BG117: 73141.389 | BH117: 16568.124 | BI117: 48225.694 | BJ117: 12971.112 | BK117: 9004.6431 | BL117: 5573.9843 | BM117: 9409.5354 | BN117: 1217.5899 | BO117: 19309.399 | BP117: 1062.8771 | BQ117: 38.70306 | BR117: 212.51209 | BS117: 11.155566 | BT117: 6909.7022 | BU117: 860.40343 | BV117: 803.73124 | BW117: 3.2263363 | BX117: 3717.9482 | BY117: 11236.523 | BZ117: 793.5511 | CA117: 3.8140326 | CB117: 2223.8304 | CC117: 812.67236 | CD117: 2.6025736 | CE117: 2644.9007 | CF117: 21.678803 | CG117: 52477.461 | CH117: 5203.4352 | CI117: 861.69077 | CJ117: 2169.3035 | CK117: 389.79987 | CL117: 729.28051 | CM117: 662.82283 | CN117: 577.63089 | CO117: 16368.574 | CP117: 0.82113012 | CQ117: 21982.177 | CR117: 404.84888 | CS117: 91690.75 | CT117: 57261.131 | CU117: 16128.063 | CV117: 57073.737 | CW117: 3610.1416 | CX117: 1168.7997 | CY117: 8162.6652 | CZ117: 45567.445 | DA117: 49405.535 | DB117: 52148.923 | DC117: 120.73051 | DD117: 60.543093 | DE117: 696.70258 | DF117: 778.89687 | DG117: 28526.741
A118: - | B118: Satellite account | C118: Employment hours male | D118: 7706.1312 | E118: 3924.123 | F118: 934.72469 | G118: 648.46808 | H118: 810.30463 | I118: 417.38779 | J118: 1909.9304 | K118: 2261.4594 | L118: 78.451709 | M118: 1479.3911 | N118: 1220.0339 | O118: 394.234 | P118: 141.41544 | Q118: 166.48806 | R118: 1720.2873 | S118: 296.11662 | T118: 791.75035 | U118: 192.68851 | V118: 1415.8444 | W118: 1418.7734 | X118: 184.84795 | Y118: 85.758933 | Z118: 756.74397 | AA118: 796.80184 | AB118: 186.70125 | AC118: 1252.4948 | AD118: 536.80271 | AE118: 16718.502 | AF118: 2850.4089 | AG118: 213.3054 | AH118: 663.90228 | AI118: 96.587365 | AJ118: 390.34306 | AK118: 642.0143 | AL118: 673.17968 | AM118: 24033.177 | AN118: 46.40849 | AO118: 4435.7362 | AP118: 544.45644 | AQ118: 19891.003 | AR118: 9011.1595 | AS118: 13436.851 | AT118: 25111.653 | AU118: 1187.4622 | AV118: 384.62776 | AW118: 2343.4546 | AX118: 12048.419 | AY118: 5551.3977 | AZ118: 6765.4206 | BA118: 582.80672 | BB118: 254.70129 | BC118: 192.21118 | BD118: 482.95605 | BE118: 3203.4145 | BF118: 833389.93 | BG118: 294575.39 | BH118: 59859.332 | BI118: 228564.33 | BJ118: 91566.796 | BK118: 56489.054 | BL118: 23368.977 | BM118: 40671.264 | BN118: 1408.6286 | BO118: 57709.37 | BP118: 12482.463 | BQ118: 565.937 | BR118: 1566.5651 | BS118: 86.024364 | BT118: 42137.166 | BU118: 21312.385 | BV118: 5074.5262 | BW118: 30.580778 | BX118: 33832.638 | BY118: 65429.795 | BZ118: 7561.1275 | CA118: 57.766421 | CB118: 23192.678 | CC118: 9427.0927 | CD118: 22.089164 | CE118: 73566.191 | CF118: 420.19974 | CG118: 371063.91 | CH118: 39759.97 | CI118: 4592.9921 | CJ118: 26643.091 | CK118: 4605.6498 | CL118: 10645.537 | CM118: 10260.001 | CN118: 8182.7798 | CO118: 335260.41 | CP118: 13.769841 | CQ118: 62128.739 | CR118: 1116.5785 | CS118: 243372.16 | CT118: 141283.47 | CU118: 220411.46 | CV118: 213948.89 | CW118: 11263.447 | CX118: 3686.1548 | CY118: 28202.978 | CZ118: 208439.47 | DA118: 90745.444 | DB118: 65938.426 | DC118: 1164.4275 | DD118: 530.72709 | DE118: 21875.27 | DF118: 5283.9733 | DG118: 53938.22
A119: - | B119: Satellite account | C119: Employment hours female | D119: 4590.4282 | E119: 2375.7317 | F119: 498.68252 | G119: 338.14047 | H119: 108.6348 | I119: 58.040785 | J119: 1670.0977 | K119: 1800.3281 | L119: 70.347392 | M119: 3654.2643 | N119: 302.27044 | O119: 89.640211 | P119: 73.708498 | Q119: 55.601455 | R119: 1046.1697 | S119: 116.05035 | T119: 311.8811 | U119: 85.157466 | V119: 784.45068 | W119: 625.27675 | X119: 64.003046 | Y119: 27.43403 | Z119: 229.42923 | AA119: 255.3013 | AB119: 44.543745 | AC119: 211.50597 | AD119: 72.906216 | AE119: 5125.9674 | AF119: 1415.4429 | AG119: 89.552372 | AH119: 188.05429 | AI119: 26.32797 | AJ119: 111.5923 | AK119: 179.51101 | AL119: 177.05284 | AM119: 2289.5 | AN119: 5.3523885 | AO119: 4229.6114 | AP119: 516.97262 | AQ119: 19797.855 | AR119: 10678.238 | AS119: 3735.5167 | AT119: 22391.341 | AU119: 1241.1815 | AV119: 424.14729 | AW119: 2140.5925 | AX119: 9955.3063 | AY119: 13979.126 | AZ119: 24064.454 | BA119: 139.20185 | BB119: 63.503427 | BC119: 51.196043 | BD119: 123.01343 | BE119: 8775.6015 | BF119: 429546.41 | BG119: 148915.1 | BH119: 32345.353 | BI119: 99528.729 | BJ119: 29907.085 | BK119: 20815.547 | BL119: 12578.615 | BM119: 21443.501 | BN119: 2822.3692 | BO119: 45568.186 | BP119: 2403.6869 | BQ119: 86.280826 | BR119: 474.03124 | BS119: 23.774431 | BT119: 15741.938 | BU119: 1978.4687 | BV119: 1750.55 | BW119: 6.8835183 | BX119: 8394.3409 | BY119: 26440.626 | BZ119: 1878.4371 | CA119: 8.3355683 | CB119: 5267.6541 | CC119: 1881.429 | CD119: 5.6008027 | CE119: 6153.164 | CF119: 50.030116 | CG119: 121816.44 | CH119: 11447.347 | CI119: 2014.9181 | CJ119: 4666.2808 | CK119: 872.44577 | CL119: 1532.6757 | CM119: 1435.1495 | CN119: 1286.5853 | CO119: 38116.695 | CP119: 1.7118527 | CQ119: 51139.751 | CR119: 926.39756 | CS119: 204206.86 | CT119: 127619.48 | CU119: 36165.488 | CV119: 121083.31 | CW119: 6768.4162 | CX119: 2447.178 | CY119: 16824.625 | CZ119: 100984.57 | DA119: 95678.122 | DB119: 108668.4 | DC119: 253.73639 | DD119: 121.15389 | DE119: 1632.2017 | DF119: 1598.7556 | DG119: 58693.841
A120: - | B120: Satellite account | C120: Employment: Vulnerable employment | D120: 4570.8276 | E120: 2432.1644 | F120: 470.45481 | G120: 337.80722 | H120: 7.1953954 | I120: 10.721605 | J120: 134.35847 | K120: 180.97654 | L120: 6.7275619 | M120: 220.22636 | N120: 83.43176 | O120: 24.706173 | P120: 4.4206007 | Q120: 10.14655 | R120: 129.65832 | S120: 15.882063 | T120: 27.118267 | U120: 8.6399464 | V120: 87.302503 | W120: 49.046959 | X120: 9.9392352 | Y120: 5.0844968 | Z120: 44.742432 | AA120: 40.2956 | AB120: 12.073883 | AC120: 41.321132 | AD120: 25.223994 | AE120: 769.12406 | AF120: 216.28125 | AG120: 15.329844 | AH120: 7.150341 | AI120: 1.2871638 | AJ120: 3.5689502 | AK120: 7.5396888 | AL120: 12.53004 | AM120: 3318.7266 | AN120: 6.4023945 | AO120: 1041.6747 | AP120: 133.72182 | AQ120: 4258.8095 | AR120: 2394.719 | AS120: 1026.478 | AT120: 4487.0803 | AU120: 296.61542 | AV120: 93.358584 | AW120: 723.66374 | AX120: 38.4 | AY120: 568.383 | AZ120: 1674.882 | BA120: 15.824206 | BB120: 6.9702323 | BC120: 5.5583183 | BD120: 13.86006 | BE120: 1385.019 | BF120: 440225.33 | BG120: 145491.8 | BH120: 42010.552 | BI120: 133243.86 | BJ120: 16985.883 | BK120: 10826.215 | BL120: 4925.3428 | BM120: 9416.9396 | BN120: 681.13268 | BO120: 21222.873 | BP120: 1937.0521 | BQ120: 51.913475 | BR120: 173.37224 | BS120: 4.7299758 | BT120: 8166.3551 | BU120: 5403.0833 | BV120: 704.20915 | BW120: 1.9727872 | BX120: 10564.425 | BY120: 14951.03 | BZ120: 1717.7273 | CA120: 5.0888596 | CB120: 5651.8729 | CC120: 2240.2953 | CD120: 1.0480789 | CE120: 15834.965 | CF120: 32.47202 | CG120: 77026.713 | CH120: 9612.7535 | CI120: 1288.2042 | CJ120: 3741.6015 | CK120: 618.69821 | CL120: 1437.2792 | CM120: 1474.4381 | CN120: 1256.8383 | CO120: 79680.283 | CP120: 2.9223401 | CQ120: 23402.637 | CR120: 455.10818 | CS120: 86555.358 | CT120: 58461 | CU120: 49520.044 | CV120: 43525.97 | CW120: 2820.9906 | CX120: 719.86935 | CY120: 5185.9602 | CZ120: 47641.378 | DA120: 24451.654 | DB120: 23042.094 | DC120: 114.02283 | DD120: 55.213863 | DE120: 8174.5758 | DF120: 278.85579 | DG120: 18207.604
A121: - | B121: Satellite account | C121: Employment hours: Vulnerable employment | D121: 15062.089 | E121: 8170.367 | F121: 2428.885 | G121: 946.6357 | H121: 16.6054 | I121: 40.8956 | J121: 383.01614 | K121: 596.31817 | L121: 23.028201 | M121: 797.61592 | N121: 236.15103 | O121: 80.77553 | P121: 16.459512 | Q121: 49.810592 | R121: 395.93794 | S121: 62.334938 | T121: 82.063817 | U121: 39.655524 | V121: 288.72231 | W121: 158.55923 | X121: 29.013935 | Y121: 16.620763 | Z121: 135.76914 | AA121: 130.1209 | AB121: 34.719555 | AC121: 144.66422 | AD121: 94.343301 | AE121: 2511.3316 | AF121: 695.02572 | AG121: 43.115997 | AH121: 21.761357 | AI121: 4.3242033 | AJ121: 11.840048 | AK121: 28.391006 | AL121: 30.706613 | AM121: 10519.531 | AN121: 16.580135 | AO121: 3026.1402 | AP121: 389.16709 | AQ121: 14843.598 | AR121: 7936.8087 | AS121: 3400.5864 | AT121: 12662.724 | AU121: 802.30483 | AV121: 266.07533 | AW121: 2647.6152 | AX121: 127.12044 | AY121: 1285.9122 | AZ121: 4601.7133 | BA121: 51.122804 | BB121: 19.050121 | BC121: 18.940491 | BD121: 47.468837 | BE121: 3965.0918 | BF121: 1877993.6 | BG121: 699374.93 | BH121: 107774.25 | BI121: 329698.17 | BJ121: 55384.642 | BK121: 105544.2 | BL121: 40845.692 | BM121: 42582.481 | BN121: 3099.7012 | BO121: 109999.92 | BP121: 8863.654 | BQ121: 349.52856 | BR121: 588.15882 | BS121: 126.68086 | BT121: 37864.393 | BU121: 27435.79 | BV121: 2470.1232 | BW121: 892.21801 | BX121: 51097.162 | BY121: 58186.722 | BZ121: 8349.4376 | CA121: 57.007128 | CB121: 26844.348 | CC121: 9942.9093 | CD121: 459.16445 | CE121: 67102.501 | CF121: 5920.1502 | CG121: 346417.5 | CH121: 45983.664 | CI121: 5957.1843 | CJ121: 12648.568 | CK121: 1943.9567 | CL121: 4456.572 | CM121: 4713.2097 | CN121: 3158.7134 | CO121: 384325.3 | CP121: 87.229173 | CQ121: 123497.45 | CR121: 3730.157 | CS121: 409111.04 | CT121: 291393.85 | CU121: 232390.87 | CV121: 204867.88 | CW121: 11292.339 | CX121: 3545.6146 | CY121: 21928.766 | CZ121: 219947.18 | DA121: 120594.33 | DB121: 104821.09 | DC121: 650.10586 | DD121: 311.57658 | DE121: 40852.798 | DF121: 1460.9132 | DG121: 82398.79
A122: - | B122: Satellite account | C122: Energy Carrier Supply: Total | D122: 38305 | E122: 0 | F122: 480236 | G122: 0 | H122: 13075442 | I122: 0 | J122: 0 | K122: 2301625 | L122: 0 | M122: 0 | N122: 769 | O122: 232624 | P122: 214393 | Q122: 213561 | R122: 0 | S122: 36225098 | T122: 675345 | U122: 0 | V122: 519387 | W122: 0 | X122: 0 | Y122: 0 | Z122: 0 | AA122: 0 | AB122: 0 | AC122: 502061 | AD122: 0 | AE122: 0 | AF122: 0 | AG122: 0 | AH122: 5783588 | AI122: 1994502 | AJ122: 0 | AK122: 463886 | AL122: 4000717 | AM122: 0 | AN122: 0 | AO122: 0 | AP122: 0 | AQ122: 0 | AR122: 0 | AS122: 0 | AT122: 0 | AU122: 0 | AV122: 0 | AW122: 0 | AX122: 0 | AY122: 0 | AZ122: 0 | BA122: 876592 | BB122: 0 | BC122: 0 | BD122: 0 | BE122: 0 | BF122: 11563223 | BG122: 0 | BH122: 3813178 | BI122: 0 | BJ122: 474937835 | BK122: 0 | BL122: 0 | BM122: 25758253 | BN122: 0 | BO122: 0 | BP122: 1383 | BQ122: 506038 | BR122: 813039 | BS122: 451789 | BT122: 0 | BU122: 195206994 | BV122: 753827 | BW122: 0 | BX122: 3878157 | BY122: 0 | BZ122: 0 | CA122: 0 | CB122: 0 | CC122: 0 | CD122: 0 | CE122: 5521662 | CF122: 0 | CG122: 0 | CH122: 0 | CI122: 0 | CJ122: 48618384 | CK122: 12968765 | CL122: 0 | CM122: 2003217 | CN122: 10922938 | CO122: 0 | CP122: 0 | CQ122: 0 | CR122: 0 | CS122: 0 | CT122: 0 | CU122: 0 | CV122: 0 | CW122: 0 | CX122: 0 | CY122: 0 | CZ122: 0 | DA122: 0 | DB122: 0 | DC122: 1459422 | DD122: 0 | DE122: 0 | DF122: 0 | DG122: 0
A123: - | B123: Satellite account | C123: Energy Carrier Use: Total | D123: 667023 | E123: 604595 | F123: 183071 | G123: 57549 | H123: 1695730 | I123: 318877 | J123: 408534 | K123: 690840 | L123: 69989 | M123: 214563 | N123: 304433 | O123: 72331 | P123: 230305 | Q123: 199453 | R123: 1086254 | S123: 39203883 | T123: 4308659 | U123: 577421 | V123: 1119431 | W123: 165056 | X123: 162165 | Y123: 85173 | Z123: 741094 | AA123: 611307 | AB123: 189406 | AC123: 1164081 | AD123: 701450 | AE123: 1523793 | AF123: 333701 | AG123: 517742 | AH123: 16675553 | AI123: 1310334 | AJ123: 314646 | AK123: 1865826 | AL123: 6645669 | AM123: 440030 | AN123: 124872 | AO123: 172494 | AP123: 30781 | AQ123: 309165 | AR123: 842916 | AS123: 6839283 | AT123: 1443991 | AU123: 425407 | AV123: 88839 | AW123: 78221 | AX123: 638462 | AY123: 494710 | AZ123: 934608 | BA123: 284411 | BB123: 28097 | BC123: 17701 | BD123: 21145 | BE123: 420472 | BF123: 6710342 | BG123: 3006487 | BH123: 1850914 | BI123: 269705 | BJ123: 27230702 | BK123: 6086781 | BL123: 3590166 | BM123: 4667175 | BN123: 1963522 | BO123: 6679343 | BP123: 2628992 | BQ123: 217543 | BR123: 732516 | BS123: 410987 | BT123: 6484156 | BU123: 215593421 | BV123: 18352095 | BW123: 4624585 | BX123: 21536024 | BY123: 2596905 | BZ123: 1453667 | CA123: 356659 | CB123: 7358853 | CC123: 6595962 | CD123: 875044 | CE123: 21971222 | CF123: 5298791 | CG123: 12991577 | CH123: 3651056 | CI123: 1505124 | CJ123: 138229577 | CK123: 6666043 | CL123: 633431 | CM123: 16423937 | CN123: 19845289 | CO123: 4665985 | CP123: 687740 | CQ123: 295640 | CR123: 351026 | CS123: 1486574 | CT123: 2358373 | CU123: 26020743 | CV123: 5880874 | CW123: 2851663 | CX123: 435843 | CY123: 777898 | CZ123: 6465562 | DA123: 2152340 | DB123: 3437629 | DC123: 814759 | DD123: 69107 | DE123: 326296 | DF123: 896150 | DG123: 1630756
A124: - | B124: Satellite account | C124: Domestic Extraction Used | D124: 617889.13 | E124: 718291.33 | F124: 262136.62 | G124: 5034.583 | H124: 661236.42 | I124: 2896815.6 | J124: 2012.4984 | K124: 1608.7355 | L124: 1.5561634 | M124: 90.775047 | N124: 2248.8815 | O124: 466.1361 | P124: 154.04536 | Q124: 31.261078 | R124: 619.02651 | S124: 1960.9989 | T124: 34474.454 | U124: 10461.935 | V124: 6808.3152 | W124: 358.71267 | X124: 24370.616 | Y124: 10259.018 | Z124: 77475.297 | AA124: 86070.051 | AB124: 16585.993 | AC124: 14251.762 | AD124: 4806.9436 | AE124: 13283.473 | AF124: 2390.4387 | AG124: 5275.7032 | AH124: 33511.619 | AI124: 1435.3868 | AJ124: 33116.152 | AK124: 25211.651 | AL124: 40548.853 | AM124: 70732.37 | AN124: 192.44991 | AO124: 26.931221 | AP124: 10.585546 | AQ124: 33734.039 | AR124: 921.74013 | AS124: 32125.127 | AT124: 2881.8193 | AU124: 923.25606 | AV124: 503.57458 | AW124: 202.77184 | AX124: 3950.5779 | AY124: 117.26462 | AZ124: 56.07383 | BA124: 333.00834 | BB124: 443.64855 | BC124: 373.54142 | BD124: 1004.3608 | BE124: 394.86046 | BF124: 7713523.9 | BG124: 10257269 | BH124: 2167887.9 | BI124: 94211.86 | BJ124: 13145528 | BK124: 38531752 | BL124: 58332.052 | BM124: 201273.98 | BN124: 77.757519 | BO124: 4785.8611 | BP124: 4370.3997 | BQ124: 449.9754 | BR124: 1441.364 | BS124: 0.012584901 | BT124: 4918.6862 | BU124: 16638.827 | BV124: 4346.524 | BW124: 6.2860443 | BX124: 49677.788 | BY124: 3280.7245 | BZ124: 6340.2473 | CA124: 206.19858 | CB124: 26541.087 | CC124: 32143.488 | CD124: 188.85408 | CE124: 22561.964 | CF124: 2420.5518 | CG124: 21222.848 | CH124: 4786.4708 | CI124: 2343.289 | CJ124: 12804.053 | CK124: 5452.6145 | CL124: 8182.4409 | CM124: 4492.9145 | CN124: 3143.2462 | CO124: 109957.06 | CP124: 0.63283166 | CQ124: 9023.9913 | CR124: 4175.4208 | CS124: 55073.02 | CT124: 4048.4644 | CU124: 63130.887 | CV124: 1601.0028 | CW124: 196.22597 | CX124: 610.71328 | CY124: 2437.6442 | CZ124: 14467.354 | DA124: 1340.4779 | DB124: 870.15079 | DC124: 181.85586 | DD124: 446.40994 | DE124: 28.062282 | DF124: 11131.604 | DG124: 3485.0737
A125: - | B125: Satellite account | C125: Unused Domestic Extraction | D125: 405692.64 | E125: 214220.66 | F125: 47466.936 | G125: 1108.5619 | H125: 3652173.1 | I125: 548668.35 | J125: 413.39352 | K125: 291.6425 | L125: 0.6652723 | M125: 28.613907 | N125: 311.4131 | O125: 54.282143 | P125: 23.925449 | Q125: 4.9201451 | R125: 200.18333 | S125: 171.09751 | T125: 6260.9709 | U125: 1642.9235 | V125: 921.45921 | W125: 76.701119 | X125: 3245.6328 | Y125: 1481.6394 | Z125: 11216.281 | AA125: 11670.577 | AB125: 2432.2688 | AC125: 1880.7586 | AD125: 265.69082 | AE125: 2247.3275 | AF125: 301.088 | AG125: 499.67489 | AH125: 1448.2251 | AI125: 79.826069 | AJ125: 1313.931 | AK125: 951.372 | AL125: 1934.4423 | AM125: 10752.757 | AN125: 44.581609 | AO125: 1.8297061 | AP125: 0.59639786 | AQ125: 6638.4101 | AR125: 182.47447 | AS125: 3711.732 | AT125: 250.39413 | AU125: 1487.1898 | AV125: 12.277751 | AW125: 11.577925 | AX125: 577.16489 | AY125: 18.183804 | AZ125: 9.164098 | BA125: 83.924434 | BB125: 82.206431 | BC125: 65.844957 | BD125: 205.9271 | BE125: 77.751214 | BF125: 4088911.7 | BG125: 384395.64 | BH125: 323873.43 | BI125: 20361.674 | BJ125: 28008630 | BK125: 9607203.5 | BL125: 18536.569 | BM125: 54318.609 | BN125: 25.874053 | BO125: 634.86393 | BP125: 1869.5426 | BQ125: 67.49631 | BR125: 420.86679 | BS125: 0.0017840156 | BT125: 1048.3256 | BU125: 5724.3858 | BV125: 2201.4912 | BW125: 1.5387022 | BX125: 9647.1452 | BY125: 1564.3695 | BZ125: 2722.7305 | CA125: 25.243323 | CB125: 8325.9365 | CC125: 5225.6537 | CD125: 36.469511 | CE125: 26131.721 | CF125: 7197.1042 | CG125: 15196.375 | CH125: 2770.2312 | CI125: 1540.9319 | CJ125: 9721.6892 | CK125: 3146.045 | CL125: 5553.9945 | CM125: 3512.4489 | CN125: 1967.6085 | CO125: 9152.5998 | CP125: 0.006310162 | CQ125: 5178.1744 | CR125: 1551.4997 | CS125: 72955.098 | CT125: 1363.4751 | CU125: 42112.207 | CV125: 995.99189 | CW125: 83.922659 | CX125: 537.21254 | CY125: 1755.7471 | CZ125: 12281.733 | DA125: 1086.5703 | DB125: 510.22767 | DC125: 28.947453 | DD125: 35.797862 | DE125: 21.687069 | DF125: 8258.9947 | DG125: 1630.1447
C127: GO | D127: 218887.74 | E127: 163951.02 | F127: 40586.44 | G127: 14507.49 | H127: 61198.15 | I127: 61245.842 | J127: 376131.61 | K127: 498580.81 | L127: 20139.983 | M127: 273001.1 | N127: 105317 | O127: 35176.609 | P127: 17167 | Q127: 34060.893 | R127: 335172.73 | S127: 336920.99 | T127: 256142.53 | U127: 65576.017 | V127: 127696.28 | W127: 254363.7 | X127: 24056.565 | Y127: 9127.7481 | Z127: 76632.453 | AA127: 95846.67 | AB127: 24357.201 | AC127: 273867.32 | AD127: 110830.72 | AE127: 2678132.3 | AF127: 185338.62 | AG127: 34354.311 | AH127: 220995.49 | AI127: 48109.694 | AJ127: 239550.05 | AK127: 153623.3 | AL127: 98167.471 | AM127: 1595104 | AN127: 1932.6736 | AO127: 286671.14 | AP127: 32057.96 | AQ127: 1059252 | AR127: 1117643 | AS127: 1532830.3 | AT127: 3334041.5 | AU127: 1458481.6 | AV127: 194342.36 | AW127: 132872.94 | AX127: 953974.14 | AY127: 639826.36 | AZ127: 1082605.8 | BA127: 71360.147 | BB127: 27665.631 | BC127: 15789.355 | BD127: 34537.706 | BE127: 396222.42 | BF127: 1877848.3 | BG127: 949837.42 | BH127: 219031.67 | BI127: 300118.59 | BJ127: 2436140.7 | BK127: 814746.77 | BL127: 1294328.7 | BM127: 2002503.5 | BN127: 150424.52 | BO127: 1626895.9 | BP127: 280650.16 | BQ127: 16853.694 | BR127: 47744.405 | BS127: 9105.8011 | BT127: 1224017.5 | BU127: 1797937.4 | BV127: 264315.5 | BW127: 6485.4585 | BX127: 2377557.3 | BY127: 1122528.7 | BZ127: 268472.75 | CA127: 2131.4785 | CB127: 499645.36 | CC127: 227501.75 | CD127: 3438.6573 | CE127: 2471482.5 | CF127: 61732.193 | CG127: 10210114 | CH127: 858984.07 | CI127: 73368.447 | CJ127: 922405.43 | CK127: 182990.21 | CL127: 689026.04 | CM127: 244688.97 | CN127: 193812.92 | CO127: 6042963.6 | CP127: 471.30356 | CQ127: 1204309.9 | CR127: 32091.621 | CS127: 3432603.4 | CT127: 3890335.8 | CU127: 4103364.4 | CV127: 11482504 | CW127: 4234690.9 | CX127: 707994.3 | CY127: 562378.29 | CZ127: 5547963 | DA127: 1760247.8 | DB127: 3586022.4 | DC127: 84878.948 | DD127: 45775.276 | DE127: 197794.78 | DF127: 286083.51 | DG127: 1313829.5
DH128: =SUM(DH4:DH111) -> 6263178.8 | DI128: =SUM(DI4:DI111) -> 2394592.5 | DJ128: =SUM(DJ4:DJ111) -> 2457688.6 | DK128: =SUM(DK4:DK111) -> 0 | DL128: =SUM(DL4:DL111) -> 23707060 | DM128: =SUM(DM4:DM111) -> 6753283.9 | DN128: =SUM(DN4:DN111) -> 11358401 | DO128: =SUM(DO4:DO111) -> 0
C129: Material extraction coeff | D129: =SUM(D124:D125)/D127 -> 4.6762863 | E129: =SUM(E124:E125)/E127 -> 5.6877473 | F129: =SUM(F124:F125)/F127 -> 7.628251 | G129: =SUM(G124:G125)/G127 -> 0.42344645 | H129: =SUM(H124:H125)/H127 -> 70.482678 | I129: =SUM(I124:I125)/I127 -> 56.256618 | J129: =SUM(J124:J125)/J127 -> 0.0064495827 | K129: =SUM(K124:K125)/K127 -> 0.0038115747 | ... DG129: =SUM(DG124:DG125)/DG127 -> 0.0038933654
C130: Energy use coeff | D130: =D123/D127 -> 3.0473291 | E130: =E123/E127 -> 3.6876562 | F130: =F123/F127 -> 4.5106444 | G130: =G123/G127 -> 3.9668476 | H130: =H123/H127 -> 27.708844 | I130: =I123/I127 -> 5.2065086 | J130: =J123/J127 -> 1.0861464 | K130: =K123/K127 -> 1.3856129 | ... DG130: =DG123/DG127 -> 1.2412234
C131: Male employment share | D131: =D116/SUM(D$116:D$117) -> 0.6215102 | E131: =E116/SUM(E$116:E$117) -> 0.61722802 | F131: =F116/SUM(F$116:F$117) -> 0.64321855 | G131: =G116/SUM(G$116:G$117) -> 0.64646598 | H131: =H116/SUM(H$116:H$117) -> 0.88151501 | I131: =I116/SUM(I$116:I$117) -> 0.87762169 | J131: =J116/SUM(J$116:J$117) -> 0.52996309 | K131: =K116/SUM(K$116:K$117) -> 0.55617517 | ... DG131: =DG116/SUM(DG$116:DG$117) -> 0.45817453
C132: Female employment share | D132: =D117/SUM(D$116:D$117) -> 0.3784898 | E132: =E117/SUM(E$116:E$117) -> 0.38277198 | F132: =F117/SUM(F$116:F$117) -> 0.35678145 | G132: =G117/SUM(G$116:G$117) -> 0.35353402 | H132: =H117/SUM(H$116:H$117) -> 0.11848499 | I132: =I117/SUM(I$116:I$117) -> 0.12237831 | J132: =J117/SUM(J$116:J$117) -> 0.47003691 | K132: =K117/SUM(K$116:K$117) -> 0.44382483 | ... DG132: =DG117/SUM(DG$116:DG$117) -> 0.54182547
C133: Wage rate | D133: =D113/SUM(D116:D117) -> 4.2684333 | E133: =E113/SUM(E116:E117) -> 4.1670465 | F133: =F113/SUM(F116:F117) -> 8.2608064 | G133: =G113/SUM(G116:G117) -> 5.3525729 | H133: =H113/SUM(H116:H117) -> 31.237707 | I133: =I113/SUM(I116:I117) -> 46.710901 | J133: =J113/SUM(J116:J117) -> 30.729534 | K133: =K113/SUM(K116:K117) -> 29.913096 | ... DG133: =DG113/SUM(DG116:DG117) -> 9.4724007
D134: =D133/1000 -> 0.0042684333 | E134: =E133/1000 -> 0.0041670465 | F134: =F133/1000 -> 0.0082608064 | G134: =G133/1000 -> 0.0053525729 | H134: =H133/1000 -> 0.031237707 | I134: =I133/1000 -> 0.046710901 | J134: =J133/1000 -> 0.030729534 | K134: =K133/1000 -> 0.029913096 | ... DG134: =DG133/1000 -> 0.0094724007
C135: Productivity | D135: =D127/SUM(D116:D117)/1000 -> 0.035245637 | E135: =E127/SUM(E116:E117)/1000 -> 0.051655934 | F135: =F127/SUM(F116:F117)/1000 -> 0.056814843 | G135: =G127/SUM(G116:G117)/1000 -> 0.02845947 | H135: =H127/SUM(H116:H117)/1000 -> 0.13662313 | I135: =I127/SUM(I116:I117)/1000 -> 0.25500297 | J135: =J127/SUM(J116:J117)/1000 -> 0.18616003 | K135: =K127/SUM(K116:K117)/1000 -> 0.23014694 | ... DG135: =DG127/SUM(DG116:DG117)/1000 -> 0.02495435

Sheet coefficients
D1: EU | E1: EU | F1: EU | G1: EU | H1: EU | I1: EU | J1: EU | K1: EU | L1: EU | M1: EU | N1: EU | O1: EU | P1: EU | Q1: EU | R1: EU | S1: EU | T1: EU | U1: EU | V1: EU | W1: EU | X1: EU | Y1: EU | Z1: EU | AA1: EU | AB1: EU | AC1: EU | AD1: EU | AE1: EU | AF1: EU | AG1: EU | AH1: EU | AI1: EU | AJ1: EU | AK1: EU | AL1: EU | AM1: EU | AN1: EU | AO1: EU | AP1: EU | AQ1: EU | AR1: EU | AS1: EU | AT1: EU | AU1: EU | AV1: EU | AW1: EU | AX1: EU | AY1: EU | AZ1: EU | BA1: EU | BB1: EU | BC1: EU | BD1: EU | BE1: EU | BF1: RoW | BG1: RoW | BH1: RoW | BI1: RoW | BJ1: RoW | BK1: RoW | BL1: RoW | BM1: RoW | BN1: RoW | BO1: RoW | BP1: RoW | BQ1: RoW | BR1: RoW | BS1: RoW | BT1: RoW | BU1: RoW | BV1: RoW | BW1: RoW | BX1: RoW | BY1: RoW | BZ1: RoW | CA1: RoW | CB1: RoW | CC1: RoW | CD1: RoW | CE1: RoW | CF1: RoW | CG1: RoW | CH1: RoW | CI1: RoW | CJ1: RoW | CK1: RoW | CL1: RoW | CM1: RoW | CN1: RoW | CO1: RoW | CP1: RoW | CQ1: RoW | CR1: RoW | CS1: RoW | CT1: RoW | CU1: RoW | CV1: RoW | CW1: RoW | CX1: RoW | CY1: RoW | CZ1: RoW | DA1: RoW | DB1: RoW | DC1: RoW | DD1: RoW | DE1: RoW | DF1: RoW | DG1: RoW | DH1: EU | DI1: EU | DJ1: EU | DK1: EU | DL1: RoW | DM1: RoW | DN1: RoW | DO1: RoW | DP1: Final Demand | DQ1: Final Demand
D2: Sector | E2: Sector | F2: Sector | G2: Sector | H2: Sector | I2: Sector | J2: Sector | K2: Sector | L2: Sector | M2: Sector | N2: Sector | O2: Sector | P2: Sector | Q2: Sector | R2: Sector | S2: Sector | T2: Sector | U2: Sector | V2: Sector | W2: Sector | X2: Sector | Y2: Sector | Z2: Sector | AA2: Sector | AB2: Sector | AC2: Sector | AD2: Sector | AE2: Sector | AF2: Sector | AG2: Sector | AH2: Sector | AI2: Sector | AJ2: Sector | AK2: Sector | AL2: Sector | AM2: Sector | AN2: Sector | AO2: Sector | AP2: Sector | AQ2: Sector | AR2: Sector | AS2: Sector | AT2: Sector | AU2: Sector | AV2: Sector | AW2: Sector | AX2: Sector | AY2: Sector | AZ2: Sector | BA2: Sector | BB2: Sector | BC2: Sector | BD2: Sector | BE2: Sector | BF2: Sector | BG2: Sector | BH2: Sector | BI2: Sector | BJ2: Sector | BK2: Sector | BL2: Sector | BM2: Sector | BN2: Sector | BO2: Sector | BP2: Sector | BQ2: Sector | BR2: Sector | BS2: Sector | BT2: Sector | BU2: Sector | BV2: Sector | BW2: Sector | BX2: Sector | BY2: Sector | BZ2: Sector | CA2: Sector | CB2: Sector | CC2: Sector | CD2: Sector | CE2: Sector | CF2: Sector | CG2: Sector | CH2: Sector | CI2: Sector | CJ2: Sector | CK2: Sector | CL2: Sector | CM2: Sector | CN2: Sector | CO2: Sector | CP2: Sector | CQ2: Sector | CR2: Sector | CS2: Sector | CT2: Sector | CU2: Sector | CV2: Sector | CW2: Sector | CX2: Sector | CY2: Sector | CZ2: Sector | DA2: Sector | DB2: Sector | DC2: Sector | DD2: Sector | DE2: Sector | DF2: Sector | DG2: Sector | DH2: Consumption category | DI2: Consumption category | DJ2: Consumption category | DK2: Consumption category | DL2: Consumption category | DM2: Consumption category | DN2: Consumption category | DO2: Consumption category | DP2: =SUM(DK2:DM2) -> 0 | DQ2: =SUM(DL2:DN2) -> 0
D3: Agriculture | E3: Animal Farming | F3: Forestry, logging and related service activities (02) | G3: Fishing, operating of fish hatcheries and fish farms; service activities incidental to fishing (05) | H3: Extraction of Fossil-Fuels | I3: Mining & Quarrying of raw materials | J3: Processing of meat | K3: Processing of other food&beverage | L3: Manufacture of tobacco products (16) | M3: Manufacture of textiles | N3: Manufacture of wood and of products of wood and cork, except furniture; manufacture of articles of straw and plaiting materials (20) | O3: Re-processing of secondary wood material into new wood material | P3: Pulp | Q3: Re-processing of secondary paper into new pulp | R3: Paper | S3: Processing of Fossil Fuels | T3: Plastics, basic | U3: Re-processing of secondary plastic into new plastic | V3: Manufacture of Chemicals | W3: Manufacture of rubber and plastic products (25) | X3: Manufacture of glass and glass products | Y3: Re-processing of secondary glass into new glass | Z3: Manufacture of other non-metallic mineral products | AA3: Manufacture of cement, lime and plaster | AB3: Re-processing of ash into clinker | AC3: Manufacture of Metals | AD3: Re-processing of Metals | AE3: Manufacture of durable goods | AF3: Manufacture of furniture; manufacturing n.e.c. (36) | AG3: Recycling | AH3: Production of electricity by fossil fuels | AI3: Production of electricity by renewable energy | AJ3: Transmission & Distribution | AK3: Manufacture of gas; distribution of gaseous fuels through mains | AL3: Water | AM3: Construction (45) | AN3: Re-processing of secondary construction material into aggregates | AO3: Sale, maintenance, repair of motor vehicles, motor vehicles parts, motorcycles, motor cycles parts and accessoiries | AP3: Retail sale of automotive fuel | AQ3: Retail & Wholesale trade | AR3: Leisure Services | AS3: Transport | AT3: KIBS | AU3: Real estate activities (70) | AV3: Renting of machinery and equipment without operator and of personal and household goods (71) | AW3: Research and development (73) | AX3: Public administration and defence; compulsory social security (75) | AY3: Education (80) | AZ3: Health and social work (85) | BA3: Incineration of Waste | BB3: Biogas & Composting | BC3: Waste water | BD3: Landfill of Waste | BE3: Other Services | BF3: Agriculture | BG3: Animal Farming | BH3: Forestry, logging and related service activities (02) | BI3: Fishing, operating of fish hatcheries and fish farms; service activities incidental to fishing (05) | BJ3: Extraction of Fossil-Fuels | BK3: Mining & Quarrying of raw materials | BL3: Processing of meat | BM3: Processing of other food&beverage | BN3: Manufacture of tobacco products (16) | BO3: Manufacture of textiles | BP3: Manufacture of wood and of products of wood and cork, except furniture; manufacture of articles of straw and plaiting materials (20) | BQ3: Re-processing of secondary wood material into new wood material | BR3: Pulp | BS3: Re-processing of secondary paper into new pulp | BT3: Paper | BU3: Processing of Fossil Fuels | BV3: Plastics, basic | BW3: Re-processing of secondary plastic into new plastic | BX3: Manufacture of Chemicals | BY3: Manufacture of rubber and plastic products (25) | BZ3: Manufacture of glass and glass products | CA3: Re-processing of secondary glass into new glass | CB3: Manufacture of other non-metallic mineral products | CC3: Manufacture of cement, lime and plaster | CD3: Re-processing of ash into clinker | CE3: Manufacture of Metals | CF3: Re-processing of Metals | CG3: Manufacture of durable goods | CH3: Manufacture of furniture; manufacturing n.e.c. (36) | CI3: Recycling | CJ3: Production of electricity by fossil fuels | CK3: Production of electricity by renewable energy | CL3: Transmission & Distribution | CM3: Manufacture of gas; distribution of gaseous fuels through mains | CN3: Water | CO3: Construction (45) | CP3: Re-processing of secondary construction material into aggregates | CQ3: Sale, maintenance, repair of motor vehicles, motor vehicles parts, motorcycles, motor cycles parts and accessoiries | CR3: Retail sale of automotive fuel | CS3: Retail & Wholesale trade | CT3: Leisure Services | CU3: Transport | CV3: KIBS | CW3: Real estate activities (70) | CX3: Renting of machinery and equipment without operator and of personal and household goods (71) | CY3: Research and development (73) | CZ3: Public administration and defence; compulsory social security (75) | DA3: Education (80) | DB3: Health and social work (85) | DC3: Incineration of Waste | DD3: Biogas & Composting | DE3: Waste water | DF3: Landfill of Waste | DG3: Other Services | DH3: Consumption | DI3: Final consumption expenditure by government | DJ3: GFCF | DK3: Exports: Total (fob) | DL3: Consumption | DM3: Final consumption expenditure by government | DN3: GFCF | DO3: Exports: Total (fob) | DP3: =SUM(DK3:DM3) -> 0 | DQ3: =SUM(DL3:DN3) -> 0
A4: EU | B4: Sector | C4: Agriculture | D4: 0.040220156 | E4: 0.099055571 | F4: 0.0088905906 | G4: 0.0017446989 | H4: 0.00021454789 | I4: 0.00033375483 | J4: 0.02990604 | K4: 0.10068127 | L4: 0.027559426 | M4: 0.0020989284 | N4: 0.00042225668 | O4: 0.00053993283 | P4: 0.00043894504 | Q4: 0.00039797988 | R4: 0.0002136884 | S4: 0.00024589338 | T4: 0.0022605377 | U4: 0.0028010487 | V4: 0.0025443375 | W4: 0.00016564498 | X4: 5.5541188e-05 | Y4: 6.2681557e-05 | Z4: 0.00014919291 | AA4: 7.8002687e-05 | AB4: 8.0086314e-05 | AC4: 7.3510857e-05 | AD4: 0.00010451732 | AE4: 8.751572e-05 | AF4: 0.0001297952 | AG4: 0.00013730428 | AH4: 9.573513e-05 | AI4: 0.0010134057 | AJ4: 9.5849738e-05 | AK4: 7.0766266e-05 | AL4: 0.00018945833 | AM4: 0.00022426122 | AN4: 0.00056012152 | AO4: 4.9125008e-05 | AP4: 0.00030493358 | AQ4: 0.0012201294 | AR4: 0.0060530021 | AS4: 0.00018717819 | AT4: 0.00045925383 | AU4: 7.4341708e-05 | AV4: 0.00035519504 | AW4: 0.00055376749 | AX4: 0.0011089647 | AY4: 0.0004610448 | AZ4: 0.0013058866 | BA4: 0.00058796508 | BB4: 0.00025040786 | BC4: 0.00048730153 | BD4: 0.00043382507 | BE4: 0.00045122728 | BF4: 0.00051400186 | BG4: 0.00072943981 | BH4: 0.00040191954 | BI4: 3.3412405e-05 | BJ4: 4.3632105e-05 | BK4: 6.9057266e-05 | BL4: 0.00025773294 | BM4: 0.0011827594 | BN4: 0.0035040028 | BO4: 0.00032788943 | BP4: 0.00015264439 | BQ4: 2.6398217e-05 | BR4: 0.00020885532 | BS4: 5.1903576e-05 | BT4: 4.3977203e-05 | BU4: 4.3497161e-05 | BV4: 2.442304e-05 | BW4: 9.1334687e-05 | BX4: 0.0010018642 | BY4: 2.4468088e-06 | BZ4: 2.0089723e-05 | CA4: 1.3865261e-05 | CB4: 2.2294429e-05 | CC4: 2.336985e-05 | CD4: 1.3346499e-05 | CE4: 8.6523949e-05 | CF4: 8.8912329e-06 | CG4: 1.1233747e-05 | CH4: 1.8777958e-05 | CI4: 0.00013592084 | CJ4: 0.00013474128 | CK4: 0.00015189251 | CL4: 0.00010877803 | CM4: 0.00050433019 | CN4: 1.5177389e-05 | CO4: 3.6955501e-05 | CP4: 1.1468242e-06 | CQ4: 3.3641555e-05 | CR4: 0.00088188592 | CS4: 3.8427406e-05 | CT4: 0.00022327253 | CU4: 3.0728517e-05 | CV4: 5.0612115e-05 | CW4: 8.6577733e-05 | CX4: 0.00023397863 | CY4: 7.7424732e-05 | CZ4: 1.6849608e-05 | DA4: 0.00013234027 | DB4: 0.00011047333 | DC4: 1.9364969e-06 | DD4: 1.5318832e-06 | DE4: 2.643965e-06 | DF4: 0.00033723313 | DG4: 0.00017756765 | DH4: 86708.162 | DI4: 772.08459 | DJ4: 4035.6257 | DK4: 0 | DL4: 11170.928 | DM4: 3.9765862 | DN4: 205.64305 | DO4: 0 | DP4: =SUM(DK4:DM4) -> 11174.905 | DQ4: =SUM(DL4:DN4) -> 11380.548
A5: EU | B5: Sector | C5: Animal Farming | D5: 9.8298293e-05 | E5: 0.0086007575 | F5: 0.00015511801 | G5: 0.00015922693 | H5: 0.00021091683 | I5: 0.00010636645 | J5: 0.22150298 | K5: 0.059257922 | L5: 0.0020070049 | M5: 0.0013633485 | N5: 0.0001261304 | O5: 0.00010370054 | P5: 9.4611581e-05 | Q5: 0.00012975777 | R5: 8.4457107e-05 | S5: 5.2835873e-05 | T5: 0.00013696093 | U5: 0.00021709949 | V5: 0.00012441217 | W5: 5.1670577e-05 | X5: 3.1830989e-05 | Y5: 3.525101e-05 | Z5: 6.0119279e-05 | AA5: 6.355321e-05 | AB5: 5.56696e-05 | AC5: 6.0030669e-05 | AD5: 4.7682628e-05 | AE5: 7.0084197e-05 | AF5: 7.7613946e-05 | AG5: 6.9496431e-05 | AH5: 0.00010535877 | AI5: 9.2597089e-05 | AJ5: 0.00017776581 | AK5: 7.1602852e-05 | AL5: 5.7073215e-05 | AM5: 6.2860763e-05 | AN5: 0.00073101182 | AO5: 3.4561983e-05 | AP5: 0.0001655975 | AQ5: 0.00070264574 | AR5: 0.0013072231 | AS5: 0.0001208633 | AT5: 0.00016579296 | AU5: 3.2031e-05 | AV5: 0.00030568593 | AW5: 0.00019227326 | AX5: 0.00023201621 | AY5: 0.00011590286 | AZ5: 0.0002564465 | BA5: 0.00057810082 | BB5: 0.00021018164 | BC5: 0.00019912081 | BD5: 0.00012450539 | BE5: 0.0004246123 | BF5: 1.6540377e-05 | BG5: 5.1830957e-05 | BH5: 4.7748956e-06 | BI5: 3.168992e-06 | BJ5: 8.1523081e-06 | BK5: 2.2102762e-05 | BL5: 0.00012074044 | BM5: 6.9213932e-05 | BN5: 2.0140707e-06 | BO5: 5.5766256e-05 | BP5: 4.6700311e-06 | BQ5: 2.669822e-05 | BR5: 3.8954956e-06 | BS5: 1.1992087e-05 | BT5: 2.2273405e-06 | BU5: 0.00013275725 | BV5: 2.9742931e-06 | BW5: 1.4189513e-05 | BX5: 0.00016473343 | BY5: 7.3713659e-06 | BZ5: 2.3544306e-06 | CA5: 5.9115356e-06 | CB5: 1.4568504e-06 | CC5: 1.8955303e-06 | CD5: 5.7837912e-06 | CE5: 4.418151e-05 | CF5: 2.4924024e-06 | CG5: 1.9335085e-06 | CH5: 1.2819866e-05 | CI5: 1.4400424e-05 | CJ5: 1.0455059e-06 | CK5: 8.9375167e-06 | CL5: 5.4096136e-07 | CM5: 2.3341345e-05 | CN5: 7.1281453e-07 | CO5: 2.1965719e-06 | CP5: 1.0712888e-06 | CQ5: 2.278121e-06 | CR5: 6.8431547e-06 | CS5: 3.842944e-06 | CT5: 2.7011694e-05 | CU5: 2.3030468e-06 | CV5: 3.8671963e-06 | CW5: 7.6132743e-06 | CX5: 3.0217672e-05 | CY5: 1.4707473e-05 | CZ5: 2.6678292e-06 | DA5: 3.1126531e-05 | DB5: 1.4184415e-05 | DC5: 2.063203e-06 | DD5: 2.1128044e-06 | DE5: 3.1101022e-06 | DF5: 2.2815613e-06 | DG5: 3.7049851e-05 | DH5: 31069.75 | DI5: 338.35783 | DJ5: 10212.043 | DK5: 0 | DL5: 740.59621 | DM5: 34.270392 | DN5: 640.05016 | DO5: 0 | DP5: =SUM(DK5:DM5) -> 774.8666 | DQ5: =SUM(DL5:DN5) -> 1414.9168
A6: EU | B6: Sector | C6: Forestry, logging and related service activities (02) | D6: 0.00040925073 | E6: 0.0017671034 | F6: 0.21730829 | G6: 0.00030649516 | H6: 0.0009142111 | I6: 0.000766745 | J6: 0.00018376385 | K6: 0.00064722645 | L6: 0.0027556711 | M6: 0.00027100054 | N6: 0.11180325 | O6: 0.0025250698 | P6: 0.044479462 | Q6: 0.00025261355 | R6: 0.0066357023 | S6: 1.8868502e-05 | T6: 0.00017710174 | U6: 0.00022618621 | V6: 0.00035968108 | W6: 0.00039503101 | X6: 0.00028744748 | Y6: 0.0001637239 | Z6: 0.00024552518 | AA6: 0.00016080363 | AB6: 0.00012627772 | AC6: 7.9739423e-05 | AD6: 6.1039211e-05 | AE6: 5.4821244e-05 | AF6: 0.0025059156 | AG6: 0.00017590149 | AH6: 7.1730759e-05 | AI6: 0.0033805799 | AJ6: 6.5401615e-05 | AK6: 2.8406702e-05 | AL6: 0.00014838132 | AM6: 0.00063586879 | AN6: 1.7073037e-05 | AO6: 3.5563516e-05 | AP6: 5.4764465e-05 | AQ6: 0.00011445592 | AR6: 0.0001133158 | AS6: 4.622908e-05 | AT6: 5.5722516e-05 | AU6: 4.4585482e-05 | AV6: 1.6478819e-05 | AW6: 5.3667903e-05 | AX6: 0.00014506183 | AY6: 3.7306216e-05 | AZ6: 2.8009088e-05 | BA6: 6.5038401e-05 | BB6: 5.0581611e-05 | BC6: 7.6652121e-05 | BD6: 8.3558585e-05 | BE6: 9.8723499e-05 | BF6: 4.6929857e-06 | BG6: 1.4454166e-05 | BH6: 0.00032935255 | BI6: 8.1797621e-07 | BJ6: 4.9805543e-06 | BK6: 1.3163564e-06 | BL6: 9.7801051e-07 | BM6: 1.3659457e-05 | BN6: 6.6143738e-05 | BO6: 1.1932866e-05 | BP6: 0.00087302482 | BQ6: 0.00020963987 | BR6: 0.00016469236 | BS6: 2.513144e-06 | BT6: 0.00011393927 | BU6: 5.5733387e-07 | BV6: 2.6581523e-06 | BW6: 1.1316399e-05 | BX6: 7.0905558e-05 | BY6: 6.4905237e-05 | BZ6: 1.5531782e-06 | CA6: 1.0711194e-05 | CB6: 1.6134963e-06 | CC6: 1.3274952e-06 | CD6: 3.062559e-06 | CE6: 3.7396935e-06 | CF6: 3.7962726e-07 | CG6: 8.530795e-07 | CH6: 4.5248467e-05 | CI6: 1.0309869e-05 | CJ6: 1.846343e-07 | CK6: 9.6659257e-07 | CL6: 2.5606441e-07 | CM6: 1.3960805e-06 | CN6: 3.6051323e-07 | CO6: 1.8494645e-05 | CP6: 1.0030309e-07 | CQ6: 5.0529018e-07 | CR6: 3.8328693e-06 | CS6: 2.1519882e-06 | CT6: 2.7188277e-06 | CU6: 3.9592228e-06 | CV6: 5.6055277e-07 | CW6: 2.0691159e-06 | CX6: 1.9547597e-06 | CY6: 6.3919136e-06 | CZ6: 9.6689453e-07 | DA6: 1.608081e-06 | DB6: 1.5835398e-06 | DC6: 1.5470728e-06 | DD6: 6.6935977e-07 | DE6: 2.8065074e-07 | DF6: 4.3368546e-07 | DG6: 1.2285126e-06 | DH6: 6546.6653 | DI6: 345.76523 | DJ6: 4631.7332 | DK6: 0 | DL6: 321.66744 | DM6: 3.4734653 | DN6: 35.834991 | DO6: 0 | DP6: =SUM(DK6:DM6) -> 325.1409 | DQ6: =SUM(DL6:DN6) -> 360.97589
A7: EU | B7: Sector | C7: Fishing, operating of fish hatcheries and fish farms; service activities incidental to fishing (05) | D7: 5.4525929e-06 | E7: 0.00038631281 | F7: 0.00038098778 | G7: 0.030494783 | H7: 4.8163126e-06 | I7: 4.9920519e-06 | J7: 0.0021191534 | K7: 0.0022837874 | L7: 0.00090268567 | M7: 7.9124528e-05 | N7: 1.5978572e-05 | O7: 3.8044854e-06 | P7: 1.1703906e-05 | Q7: 6.8120673e-06 | R7: 8.4368429e-06 | S7: 3.1201415e-06 | T7: 0.00020679061 | U7: 0.00022679116 | V7: 4.8317298e-05 | W7: 5.7811307e-05 | X7: 7.8912875e-06 | Y7: 9.2011369e-06 | Z7: 3.6421669e-06 | AA7: 4.0664143e-06 | AB7: 4.5694837e-06 | AC7: 1.8129009e-06 | AD7: 4.10363e-06 | AE7: 3.1789454e-06 | AF7: 4.3375097e-06 | AG7: 1.8938541e-05 | AH7: 4.1427405e-05 | AI7: 7.8800241e-05 | AJ7: 1.9486903e-05 | AK7: 4.604584e-05 | AL7: 9.1825912e-05 | AM7: 2.7742518e-06 | AN7: 0.045456841 | AO7: 1.5033159e-05 | AP7: 0.00010362751 | AQ7: 2.1245963e-05 | AR7: 0.00090976908 | AS7: 5.0819214e-05 | AT7: 9.6885846e-06 | AU7: 2.2304218e-06 | AV7: 4.9189416e-06 | AW7: 1.5815555e-05 | AX7: 3.5352606e-05 | AY7: 3.0896854e-05 | AZ7: 8.139177e-05 | BA7: 2.0345203e-05 | BB7: 1.0969509e-05 | BC7: 1.6674155e-05 | BD7: 3.6497466e-05 | BE7: 5.1598359e-05 | BF7: 3.2903214e-07 | BG7: 1.486051e-06 | BH7: 2.2131904e-07 | BI7: 0.00022035389 | BJ7: 1.6783218e-07 | BK7: 4.7798334e-07 | BL7: 0.00022032413 | BM7: 3.4741306e-05 | BN7: 3.782609e-07 | BO7: 5.7729517e-07 | BP7: 3.2133405e-07 | BQ7: 1.1070917e-06 | BR7: 5.8373597e-07 | BS7: 1.3859278e-06 | BT7: 1.9400856e-07 | BU7: 8.4506181e-07 | BV7: 5.1822069e-07 | BW7: 9.7431392e-07 | BX7: 2.9107763e-05 | BY7: 1.2403611e-07 | BZ7: 1.6968734e-07 | CA7: 4.133814e-07 | CB7: 2.4358404e-07 | CC7: 2.6170338e-07 | CD7: 4.7148118e-07 | CE7: 1.5187941e-07 | CF7: 2.6804369e-07 | CG7: 2.1070929e-07 | CH7: 2.1703664e-07 | CI7: 9.8458649e-07 | CJ7: 1.9352748e-07 | CK7: 2.0873675e-07 | CL7: 1.297531e-07 | CM7: 3.5681168e-07 | CN7: 1.3314217e-07 | CO7: 3.0648903e-07 | CP7: 9.3487371e-08 | CQ7: 1.36053e-07 | CR7: 9.7241229e-06 | CS7: 6.6357496e-07 | CT7: 1.0008389e-05 | CU7: 2.2153628e-06 | CV7: 3.8888826e-07 | CW7: 1.8888909e-07 | CX7: 3.5320072e-07 | CY7: 9.9952401e-07 | CZ7: 8.7205105e-07 | DA7: 1.8403001e-06 | DB7: 5.4451858e-06 | DC7: 1.8429252e-07 | DD7: 1.2685859e-07 | DE7: 1.2082563e-07 | DF7: 3.3875855e-07 | DG7: 2.7079187e-06 | DH7: 9300.7622 | DI7: 6.6649199 | DJ7: 95.659851 | DK7: 0 | DL7: 450.69839 | DM7: 0.12423353 | DN7: 3.8911598 | DO7: 0 | DP7: =SUM(DK7:DM7) -> 450.82262 | DQ7: =SUM(DL7:DN7) -> 454.71378
A8: EU | B8: Sector | C8: Extraction of Fossil-Fuels | D8: 0.00097568171 | E8: 0.00093357268 | F8: 0.00050609551 | G8: 0.00023870404 | H8: 0.03008272 | I8: 0.0026977009 | J8: 0.00047192112 | K8: 0.00049905769 | L8: 0.00080741828 | M8: 0.0020781898 | N8: 0.0027180802 | O8: 0.0017439113 | P8: 0.0057588138 | Q8: 0.0015859841 | R8: 0.00029292384 | S8: 0.035223138 | T8: 0.002244923 | U8: 0.00062733698 | V8: 0.0059762392 | W8: 0.00053678787 | X8: 0.0021984124 | Y8: 0.0049337492 | Z8: 0.0028295514 | AA8: 0.0032648901 | AB8: 0.0026450137 | AC8: 0.0071155356 | AD8: 0.0025172566 | AE8: 0.00022537453 | AF8: 0.0016626967 | AG8: 0.00085425024 | AH8: 0.069099996 | AI8: 0.0013648231 | AJ8: 0.0012641907 | AK8: 0.016566821 | AL8: 0.018266864 | AM8: 0.00032028298 | AN8: 7.5453872e-05 | AO8: 0.000142249 | AP8: 0.00083514211 | AQ8: 0.00026553114 | AR8: 0.00014561862 | AS8: 0.00031971073 | AT8: 0.0002095966 | AU8: 0.00017087639 | AV8: 0.00023118383 | AW8: 0.0005229957 | AX8: 0.00046036287 | AY8: 0.00015199904 | AZ8: 0.00013228704 | BA8: 0.00034843201 | BB8: 0.00037145089 | BC8: 0.000508675 | BD8: 0.00040951335 | BE8: 0.00064333639 | BF8: 9.0759379e-06 | BG8: 6.9204814e-06 | BH8: 4.1111287e-06 | BI8: 2.8857369e-06 | BJ8: 8.0834715e-05 | BK8: 2.5975086e-05 | BL8: 8.1644946e-06 | BM8: 7.2940713e-06 | BN8: 4.1234952e-06 | BO8: 1.3753362e-05 | BP8: 0.0018252822 | BQ8: 4.4930233e-05 | BR8: 0.00018782762 | BS8: 2.4884996e-05 | BT8: 6.6228279e-06 | BU8: 0.00098819429 | BV8: 0.00016675945 | BW8: 2.8794208e-05 | BX8: 5.734057e-05 | BY8: 8.0133601e-06 | BZ8: 2.2416607e-05 | CA8: 0.00023941206 | CB8: 3.1888979e-05 | CC8: 9.2816475e-05 | CD8: 0.00027383431 | CE8: 2.5171368e-05 | CF8: 2.5141549e-05 | CG8: 4.6919997e-06 | CH8: 0.00046755682 | CI8: 6.3453343e-06 | CJ8: 0.00060118981 | CK8: 4.0665211e-05 | CL8: 8.788289e-06 | CM8: 0.0013039405 | CN8: 8.8131298e-05 | CO8: 7.6860327e-06 | CP8: 5.3432691e-05 | CQ8: 2.387636e-06 | CR8: 1.6380736e-05 | CS8: 5.5181292e-06 | CT8: 3.8554745e-06 | CU8: 1.0414416e-05 | CV8: 5.2336168e-06 | CW8: 4.3646254e-06 | CX8: 4.9241649e-06 | CY8: 6.2664567e-06 | CZ8: 7.7751966e-06 | DA8: 5.6467672e-06 | DB8: 4.1637073e-06 | DC8: 4.196084e-06 | DD8: 3.4736893e-06 | DE8: 4.9259889e-06 | DF8: 5.0632547e-06 | DG8: 5.2735496e-06 | DH8: 5227.7755 | DI8: 445.42273 | DJ8: 5953.6768 | DK8: 0 | DL8: 141.53321 | DM8: 7.139189 | DN8: 87.740654 | DO8: 0 | DP8: =SUM(DK8:DM8) -> 148.6724 | DQ8: =SUM(DL8:DN8) -> 236.41305
A9: EU | B9: Sector | C9: Mining & Quarrying of raw materials | D9: 0.0011436994 | E9: 0.0010978336 | F9: 0.00038518073 | G9: 0.0040482738 | H9: 0.0008150672 | I9: 0.060972898 | J9: 0.00054454051 | K9: 0.0012641715 | L9: 0.00013278964 | M9: 0.00029234715 | N9: 0.00037470608 | O9: 0.00048368945 | P9: 0.0067320476 | Q9: 0.0090375812 | R9: 0.0010291693 | S9: 0.00029460065 | T9: 0.0016233466 | U9: 0.0022736766 | V9: 0.011070902 | W9: 0.0011608932 | X9: 0.047385669 | Y9: 0.0027027039 | Z9: 0.048487255 | AA9: 0.065427708 | AB9: 0.065193493 | AC9: 0.024580165 | AD9: 0.0032573924 | AE9: 0.00095054333 | AF9: 0.0010549454 | AG9: 0.0016971813 | AH9: 0.00062841672 | AI9: 0.0004462215 | AJ9: 0.00065183323 | AK9: 0.0023276407 | AL9: 0.0012921263 | AM9: 0.0098361662 | AN9: 7.8590124e-05 | AO9: 0.00011977798 | AP9: 0.0010308486 | AQ9: 0.00065655285 | AR9: 0.00017645444 | AS9: 0.0003961277 | AT9: 0.00021015084 | AU9: 0.00018541602 | AV9: 0.00025745729 | AW9: 0.00038975338 | AX9: 0.0010000222 | AY9: 6.6853838e-05 | AZ9: 0.00011227529 | BA9: 0.0012624699 | BB9: 0.0014827991 | BC9: 0.0019704047 | BD9: 0.0019868563 | BE9: 0.00017471437 | BF9: 1.3749989e-05 | BG9: 1.3506838e-05 | BH9: 1.9445013e-05 | BI9: 5.9185976e-05 | BJ9: 1.9307998e-05 | BK9: 0.00026921254 | BL9: 2.288465e-05 | BM9: 1.5647922e-05 | BN9: 1.1810994e-05 | BO9: 2.0096971e-05 | BP9: 1.3522267e-05 | BQ9: 1.4042702e-05 | BR9: 6.6108177e-05 | BS9: 0.00011257911 | BT9: 1.3617222e-05 | BU9: 3.0081618e-05 | BV9: 0.00010459405 | BW9: 0.00025867304 | BX9: 0.00030613862 | BY9: 2.0464972e-05 | BZ9: 0.00044883789 | CA9: 5.7196864e-05 | CB9: 0.00041031779 | CC9: 0.00054666509 | CD9: 0.0012352772 | CE9: 0.00032698016 | CF9: 0.00012194598 | CG9: 3.2960908e-05 | CH9: 0.00014483999 | CI9: 3.4520102e-05 | CJ9: 7.4745875e-06 | CK9: 7.5989515e-05 | CL9: 3.4857823e-06 | CM9: 2.250258e-05 | CN9: 9.9677301e-06 | CO9: 0.00010130187 | CP9: 8.324965e-07 | CQ9: 5.2602988e-06 | CR9: 3.3156339e-05 | CS9: 5.5944545e-06 | CT9: 8.9347133e-06 | CU9: 6.8740113e-06 | CV9: 7.0474271e-06 | CW9: 1.3087142e-05 | CX9: 2.5550006e-05 | CY9: 8.0122776e-06 | CZ9: 4.7615549e-06 | DA9: 3.8093921e-05 | DB9: 2.7086789e-05 | DC9: 7.4654102e-06 | DD9: 5.5051811e-06 | DE9: 7.2664004e-06 | DF9: 1.8170312e-05 | DG9: 1.6449113e-05 | DH9: 1586.9032 | DI9: 114.54862 | DJ9: 3317.4548 | DK9: 0 | DL9: 238.55977 | DM9: 5.3827142 | DN9: 271.64934 | DO9: 0 | DP9: =SUM(DK9:DM9) -> 243.94249 | DQ9: =SUM(DL9:DN9) -> 515.59183
A10: EU | B10: Sector | C10: Processing of meat | D10: 0.00026865809 | E10: 0.060667221 | F10: 0.00071028017 | G10: 0.011688455 | H10: 0.00036901024 | I10: 0.0016640256 | J10: 0.068980294 | K10: 0.050294548 | L10: 0.0019523302 | M10: 0.0019348975 | N10: 0.0003854224 | O10: 0.00042747697 | P10: 0.00072407303 | Q10: 0.00087513723 | R10: 0.00052951252 | S10: 0.00030500038 | T10: 0.002445383 | U10: 0.003274799 | V10: 0.0024566553 | W10: 0.00098896818 | X10: 0.00033130242 | Y10: 0.00034323301 | Z10: 0.00069535568 | AA10: 0.00027614215 | AB10: 0.00028853558 | AC10: 0.00024080346 | AD10: 0.00032932467 | AE10: 0.00025170806 | AF10: 0.00070470966 | AG10: 0.0012085228 | AH10: 0.0004074149 | AI10: 0.00037490386 | AJ10: 0.00026200963 | AK10: 0.00029083048 | AL10: 0.00038597049 | AM10: 0.000291019 | AN10: 5.0714657e-05 | AO10: 0.00029461728 | AP10: 0.0025119993 | AQ10: 0.0013310955 | AR10: 0.021112258 | AS10: 0.00073129383 | AT10: 0.00065637286 | AU10: 0.00028018005 | AV10: 0.0010085432 | AW10: 0.0025184437 | AX10: 0.0014706156 | AY10: 0.002364959 | AZ10: 0.0048024239 | BA10: 0.00031907097 | BB10: 0.00034127333 | BC10: 0.0006752977 | BD10: 0.00058379281 | BE10: 0.00091314137 | BF10: 9.8367684e-05 | BG10: 0.00059918057 | BH10: 2.3847628e-05 | BI10: 0.00035306165 | BJ10: 1.7483728e-05 | BK10: 2.0456984e-05 | BL10: 0.0018279406 | BM10: 0.0013909321 | BN10: 3.6598464e-05 | BO10: 0.00011036877 | BP10: 1.443367e-05 | BQ10: 1.7024464e-05 | BR10: 4.1191551e-05 | BS10: 0.0003820904 | BT10: 2.599323e-05 | BU10: 1.273762e-05 | BV10: 0.0001050995 | BW10: 0.00048440105 | BX10: 0.00040445776 | BY10: 3.7363262e-05 | BZ10: 1.1264425e-05 | CA10: 0.00013340055 | CB10: 2.2534643e-05 | CC10: 1.4683326e-05 | CD10: 0.00012472785 | CE10: 7.7693467e-06 | CF10: 6.7964767e-05 | CG10: 1.9794403e-05 | CH10: 1.4370594e-05 | CI10: 0.00016466973 | CJ10: 2.1045756e-05 | CK10: 2.3687614e-05 | CL10: 8.7508285e-06 | CM10: 2.2095614e-05 | CN10: 1.9939694e-05 | CO10: 5.7203861e-06 | CP10: 6.3160682e-06 | CQ10: 8.2958625e-06 | CR10: 0.00021345026 | CS10: 3.3107637e-05 | CT10: 0.00076526836 | CU10: 2.3232979e-05 | CV10: 1.8142732e-05 | CW10: 6.6147914e-06 | CX10: 0.00015043178 | CY10: 4.0453097e-05 | CZ10: 4.4042555e-05 | DA10: 8.1865663e-05 | DB10: 0.00018106403 | DC10: 1.0359594e-05 | DD10: 1.5752409e-05 | DE10: 1.6167785e-05 | DF10: 1.551835e-05 | DG10: 5.3100846e-05 | DH10: 231893.02 | DI10: 829.84077 | DJ10: 2721.3509 | DK10: 0 | DL10: 24667.798 | DM10: 27.683211 | DN10: 179.45972 | DO10: 0 | DP10: =SUM(DK10:DM10) -> 24695.481 | DQ10: =SUM(DL10:DN10) -> 24874.94
A11: EU | B11: Sector | C11: Processing of other food&beverage | D11: 0.00016031951 | E11: 0.13313782 | F11: 0.0011454115 | G11: 0.013178364 | H11: 0.00044747178 | I11: 0.0018684348 | J11: 0.056344983 | K11: 0.075054825 | L11: 0.0017802467 | M11: 0.005719802 | N11: 0.00067472946 | O11: 0.0007045112 | P11: 0.00108731 | Q11: 0.0013224039 | R11: 0.0012477644 | S11: 0.00041933545 | T11: 0.0084281373 | U11: 0.006994472 | V11: 0.0097082982 | W11: 0.00089762111 | X11: 0.00024304429 | Y11: 0.00025915861 | Z11: 0.0013385603 | AA11: 0.00025820935 | AB11: 0.00021607444 | AC11: 0.0004249282 | AD11: 0.00043893365 | AE11: 0.00030184725 | AF11: 0.0010547937 | AG11: 0.0020678114 | AH11: 0.00085308549 | AI11: 0.00046992952 | AJ11: 0.00027184507 | AK11: 0.00037835961 | AL11: 0.00069234852 | AM11: 0.00057922806 | AN11: 2.7482119e-05 | AO11: 0.00036641551 | AP11: 0.0031020688 | AQ11: 0.0012112938 | AR11: 0.024430244 | AS11: 0.00070983822 | AT11: 0.00068622201 | AU11: 0.00026066066 | AV11: 0.0010368087 | AW11: 0.0023360684 | AX11: 0.0017567904 | AY11: 0.0026972427 | AZ11: 0.006092627 | BA11: 0.00040428507 | BB11: 0.00030529866 | BC11: 0.0014453 | BD11: 0.0011255893 | BE11: 0.00099941606 | BF11: 3.9817107e-05 | BG11: 0.0014970086 | BH11: 7.0141152e-05 | BI11: 0.00032405346 | BJ11: 1.8404606e-05 | BK11: 3.1299463e-05 | BL11: 0.00069091769 | BM11: 0.0023074653 | BN11: 4.8613515e-05 | BO11: 0.00011084214 | BP11: 2.659258e-05 | BQ11: 2.2343659e-05 | BR11: 5.708766e-05 | BS11: 0.00053037749 | BT11: 3.8310557e-05 | BU11: 2.4549831e-05 | BV11: 0.00010291816 | BW11: 0.00048847018 | BX11: 0.00030319487 | BY11: 5.5485881e-05 | BZ11: 1.6316996e-05 | CA11: 0.00014271534 | CB11: 2.6964853e-05 | CC11: 2.7183919e-05 | CD11: 0.00014208623 | CE11: 1.5296585e-05 | CF11: 9.0921345e-05 | CG11: 2.2087417e-05 | CH11: 3.508505e-05 | CI11: 0.00016075671 | CJ11: 2.6537752e-05 | CK11: 4.246578e-05 | CL11: 1.8623961e-05 | CM11: 3.831557e-05 | CN11: 3.2577756e-05 | CO11: 6.4717256e-05 | CP11: 5.8471472e-06 | CQ11: 1.3869927e-05 | CR11: 0.00026382525 | CS11: 6.7827202e-05 | CT11: 0.0013296079 | CU11: 7.0997612e-05 | CV11: 2.2758022e-05 | CW11: 7.5238122e-06 | CX11: 7.4764752e-05 | CY11: 5.0144222e-05 | CZ11: 4.3402613e-05 | DA11: 0.00010032069 | DB11: 0.0001797063 | DC11: 1.0392185e-05 | DD11: 1.2886588e-05 | DE11: 7.3136096e-06 | DF11: 4.199996e-05 | DG11: 6.4226618e-05 | DH11: 302148.24 | DI11: 778.89246 | DJ11: 3807.3481 | DK11: 0 | DL11: 41634.874 | DM11: 78.812984 | DN11: 267.34237 | DO11: 0 | DP11: =SUM(DK11:DM11) -> 41713.687 | DQ11: =SUM(DL11:DN11) -> 41981.029
A12: EU | B12: Sector | C12: Manufacture of tobacco products (16) | D12: 3.7399894e-05 | E12: 0.0001160723 | F12: 3.7767514e-05 | G12: 3.7303171e-05 | H12: 5.6889878e-05 | I12: 2.4077202e-05 | J12: 8.5223082e-05 | K12: 5.6610339e-05 | L12: 0.019573098 | M12: 5.2792796e-05 | N12: 1.2561443e-05 | O12: 6.1467749e-05 | P12: 4.2468078e-05 | Q12: 2.5661502e-05 | R12: 6.9785846e-05 | S12: 2.4545028e-05 | T12: 3.8007609e-05 | U12: 4.1920164e-05 | V12: 7.7480137e-05 | W12: 3.513901e-05 | X12: 1.6422075e-05 | Y12: 1.2426554e-05 | Z12: 1.2315881e-05 | AA12: 1.2456416e-05 | AB12: 1.5871182e-05 | AC12: 0.0018251556 | AD12: 0.00047174205 | AE12: 3.541001e-05 | AF12: 2.5444271e-05 | AG12: 1.9414583e-05 | AH12: 4.2582616e-05 | AI12: 4.3308818e-05 | AJ12: 7.8552909e-06 | AK12: 3.7974051e-05 | AL12: 1.2495977e-05 | AM12: 4.771792e-05 | AN12: 2.4252792e-06 | AO12: 2.3348378e-05 | AP12: 3.3922475e-05 | AQ12: 0.00018123372 | AR12: 0.00030150227 | AS12: 3.7304304e-05 | AT12: 4.8193014e-05 | AU12: 8.8573798e-06 | AV12: 6.2401625e-05 | AW12: 6.8050334e-05 | AX12: 0.0001256226 | AY12: 1.8917344e-05 | AZ12: 1.3191852e-05 | BA12: 3.9858208e-05 | BB12: 2.274689e-05 | BC12: 0.00015160901 | BD12: 8.9140454e-05 | BE12: 0.00016408823 | BF12: 1.545209e-06 | BG12: 9.0114364e-07 | BH12: 5.5751214e-06 | BI12: 8.3658099e-07 | BJ12: 2.2422437e-06 | BK12: 1.6114217e-06 | BL12: 5.5056017e-06 | BM12: 3.0401668e-06 | BN12: 0.00010283163 | BO12: 2.447666e-06 | BP12: 2.0291012e-06 | BQ12: 3.6791629e-07 | BR12: 6.7180056e-07 | BS12: 1.3492814e-06 | BT12: 1.7546432e-06 | BU12: 1.5835859e-06 | BV12: 6.7660633e-07 | BW12: 1.147171e-06 | BX12: 2.5613501e-05 | BY12: 6.0702775e-07 | BZ12: 2.5001917e-06 | CA12: 1.697276e-06 | CB12: 3.3831079e-06 | CC12: 3.2022612e-06 | CD12: 1.3402333e-06 | CE12: 1.3095054e-05 | CF12: 1.012394e-05 | CG12: 1.115933e-06 | CH12: 2.5126039e-06 | CI12: 1.0011232e-05 | CJ12: 3.1866996e-06 | CK12: 3.9695273e-06 | CL12: 9.7109707e-07 | CM12: 1.5454164e-05 | CN12: 1.6514489e-06 | CO12: 6.6589892e-07 | CP12: 4.2027164e-07 | CQ12: 1.0148521e-06 | CR12: 3.1232696e-05 | CS12: 1.3821205e-06 | CT12: 3.1115029e-06 | CU12: 1.148362e-06 | CV12: 1.9302933e-06 | CW12: 9.6948087e-07 | CX12: 6.0030678e-06 | CY12: 2.4267799e-06 | CZ12: 8.6801099e-07 | DA12: 2.1852465e-06 | DB12: 1.249432e-06 | DC12: 5.333628e-07 | DD12: 2.9430994e-07 | DE12: 1.0172475e-06 | DF12: 6.394353e-06 | DG12: 3.7623438e-06 | DH12: 12663.349 | DI12: 29.155915 | DJ12: 932.3822 | DK12: 0 | DL12: 3921.8808 | DM12: 0.28552523 | DN12: 10.197401 | DO12: 0 | DP12: =SUM(DK12:DM12) -> 3922.1663 | DQ12: =SUM(DL12:DN12) -> 3932.3637
A13: EU | B13: Sector | C13: Manufacture of textiles | D13: 0.0016972133 | E13: 0.0013499216 | F13: 0.0017816692 | G13: 0.015902484 | H13: 0.0012804951 | I13: 0.0010624291 | J13: 0.00048420072 | K13: 0.00092895795 | L13: 0.0017706041 | M13: 0.17973568 | N13: 0.0020700558 | O13: 0.0042028952 | P13: 0.0021708441 | Q13: 0.0029811457 | R13: 0.0037829534 | S13: 0.00015112924 | T13: 0.0013691539 | U13: 0.0012991025 | V13: 0.0054587096 | W13: 0.0075879944 | X13: 0.0038526708 | Y13: 0.0038877188 | Z13: 0.0019107081 | AA13: 0.00099658906 | AB13: 0.00091154008 | AC13: 0.0010437242 | AD13: 0.0010419 | AE13: 0.0025118773 | AF13: 0.010677855 | AG13: 0.0024685511 | AH13: 0.00064725488 | AI13: 0.00040137359 | AJ13: 0.00044524889 | AK13: 0.00067032303 | AL13: 0.00070946554 | AM13: 0.001519698 | AN13: 0.00065932747 | AO13: 0.00073013612 | AP13: 0.001794271 | AQ13: 0.00072629123 | AR13: 0.0022185669 | AS13: 0.00050645215 | AT13: 0.00050495153 | AU13: 0.00011942516 | AV13: 0.0010280466 | AW13: 0.00082761427 | AX13: 0.0012302432 | AY13: 0.00033990967 | AZ13: 0.0016378326 | BA13: 0.0015803912 | BB13: 0.0016086746 | BC13: 0.0026626511 | BD13: 0.0033882167 | BE13: 0.0017253892 | BF13: 5.9876762e-05 | BG13: 3.5976814e-05 | BH13: 5.226545e-05 | BI13: 0.00016271792 | BJ13: 3.624256e-05 | BK13: 5.7725113e-05 | BL13: 2.3352388e-05 | BM13: 3.6419718e-05 | BN13: 0.00013210245 | BO13: 0.0050893093 | BP13: 0.00010380963 | BQ13: 3.7775513e-05 | BR13: 8.1525651e-05 | BS13: 0.00017219811 | BT13: 0.00019846231 | BU13: 1.5889679e-05 | BV13: 0.00010148994 | BW13: 0.00028468625 | BX13: 0.0013039247 | BY13: 0.00025880622 | BZ13: 5.8107191e-05 | CA13: 0.00023468891 | CB13: 6.0216973e-05 | CC13: 4.3237653e-05 | CD13: 5.4243667e-05 | CE13: 2.4778265e-05 | CF13: 2.0912267e-05 | CG13: 9.2795181e-05 | CH13: 0.0005898107 | CI13: 0.00018686699 | CJ13: 2.4047767e-05 | CK13: 6.8904134e-05 | CL13: 2.3870263e-05 | CM13: 4.8937629e-05 | CN13: 4.9710687e-05 | CO13: 0.00018825622 | CP13: 8.7093122e-05 | CQ13: 3.4041478e-05 | CR13: 0.00025733218 | CS13: 0.00010186389 | CT13: 9.0280939e-05 | CU13: 4.3107838e-05 | CV13: 2.5473681e-05 | CW13: 1.1431569e-05 | CX13: 5.6722867e-05 | CY13: 0.00014986368 | CZ13: 6.9122514e-05 | DA13: 6.0719327e-05 | DB13: 0.00013186135 | DC13: 0.00014627637 | DD13: 8.2799979e-05 | DE13: 4.7022064e-05 | DF13: 7.111515e-05 | DG13: 0.00013391953 | DH13: 135292.6 | DI13: 755.84039 | DJ13: 4510.4066 | DK13: 0 | DL13: 34673.503 | DM13: 44.046308 | DN13: 1129.0517 | DO13: 0 | DP13: =SUM(DK13:DM13) -> 34717.549 | DQ13: =SUM(DL13:DN13) -> 35846.601
A14: EU | B14: Sector | C14: Manufacture of wood and of products of wood and cork, except furniture; manufacture of articles of straw and plaiting materials (20) | D14: 0.0021690015 | E14: 0.0015930662 | F14: 0.004855802 | G14: 0.0044096184 | H14: 0.0031393215 | I14: 0.0029929704 | J14: 0.00076627663 | K14: 0.0016092907 | L14: 0.0012540444 | M14: 0.00091527493 | N14: 0.1355152 | O14: 0.12742074 | P14: 0.023908897 | Q14: 0.00070699786 | R14: 0.0039499611 | S14: 0.00013943205 | T14: 0.0013753769 | U14: 0.0012828193 | V14: 0.00061664229 | W14: 0.0019385998 | X14: 0.0053702244 | Y14: 0.0055487553 | Z14: 0.0073092968 | AA14: 0.0010755288 | AB14: 0.0011623773 | AC14: 0.0027828939 | AD14: 0.0033078035 | AE14: 0.0018504061 | AF14: 0.047971111 | AG14: 0.0057926875 | AH14: 0.0015742202 | AI14: 0.0038979969 | AJ14: 0.0022171974 | AK14: 0.0004594627 | AL14: 0.0023625234 | AM14: 0.014824563 | AN14: 0.00014822395 | AO14: 0.00032207239 | AP14: 0.00071456198 | AQ14: 0.00047014494 | AR14: 0.0012510605 | AS14: 0.00050784578 | AT14: 0.00046007013 | AU14: 0.0014052604 | AV14: 0.00056210835 | AW14: 0.00054384816 | AX14: 0.00033166077 | AY14: 0.00037954724 | AZ14: 0.00020573262 | BA14: 0.001415942 | BB14: 0.0014869155 | BC14: 0.001306157 | BD14: 0.0010419355 | BE14: 0.0022549222 | BF14: 1.268794e-05 | BG14: 7.8852902e-06 | BH14: 3.9357479e-05 | BI14: 2.3963766e-05 | BJ14: 1.3317303e-05 | BK14: 1.402275e-05 | BL14: 1.5476047e-05 | BM14: 2.0716829e-05 | BN14: 5.12503e-05 | BO14: 1.5745967e-05 | BP14: 0.0048425438 | BQ14: 0.019553205 | BR14: 0.0041831298 | BS14: 7.6842293e-05 | BT14: 0.00017913963 | BU14: 5.7839153e-06 | BV14: 5.0319447e-05 | BW14: 0.0003044581 | BX14: 4.4152409e-05 | BY14: 3.4492416e-05 | BZ14: 6.436299e-05 | CA14: 0.00096192773 | CB14: 6.967445e-05 | CC14: 2.2037529e-05 | CD14: 0.00022984621 | CE14: 2.0033961e-05 | CF14: 1.9781257e-05 | CG14: 4.2910885e-05 | CH14: 0.0010292703 | CI14: 7.4123035e-05 | CJ14: 2.8516385e-06 | CK14: 2.4405922e-05 | CL14: 6.5595666e-06 | CM14: 8.4884495e-06 | CN14: 9.9782958e-06 | CO14: 0.00083071425 | CP14: 1.4194622e-06 | CQ14: 1.0772268e-05 | CR14: 5.9653214e-05 | CS14: 2.2737894e-05 | CT14: 2.4558579e-05 | CU14: 1.6605656e-05 | CV14: 1.0289933e-05 | CW14: 6.5327077e-05 | CX14: 1.8602623e-05 | CY14: 1.1608935e-05 | CZ14: 1.975414e-05 | DA14: 2.8592517e-05 | DB14: 1.1933116e-05 | DC14: 5.4570237e-05 | DD14: 3.1131374e-05 | DE14: 8.4732541e-06 | DF14: 5.7859329e-06 | DG14: 2.1847419e-05 | DH14: 10427.412 | DI14: 84.393385 | DJ14: 8824.3183 | DK14: 0 | DL14: 1298.8994 | DM14: 2.217063 | DN14: 1033.4581 | DO14: 0 | DP14: =SUM(DK14:DM14) -> 1301.1165 | DQ14: =SUM(DL14:DN14) -> 2334.5746
A15: EU | B15: Sector | C15: Re-processing of secondary wood material into new wood material | D15: 0.00093446963 | E15: 0.00064331456 | F15: 0.00098693174 | G15: 0.0015860649 | H15: 0.00084907279 | I15: 0.0010414048 | J15: 0.00033109542 | K15: 0.0007105377 | L15: 0.00041906843 | M15: 0.00040255805 | N15: 0.037038259 | O15: 0.064066658 | P15: 0.0038309048 | Q15: 0.00023199661 | R15: 0.00082253068 | S15: 3.5683902e-05 | T15: 0.00051182837 | U15: 0.00066087603 | V15: 0.00020522979 | W15: 0.00082310201 | X15: 0.0016197254 | Y15: 0.002375107 | Z15: 0.0026212677 | AA15: 0.00035010829 | AB15: 0.00038187285 | AC15: 0.00055794619 | AD15: 0.00069532862 | AE15: 0.0006698696 | AF15: 0.019503601 | AG15: 0.0019161871 | AH15: 0.0001993361 | AI15: 0.00027201195 | AJ15: 0.0002724452 | AK15: 0.00016019967 | AL15: 0.00023332378 | AM15: 0.0052982383 | AN15: 3.0653218e-05 | AO15: 0.00011898207 | AP15: 0.00027943975 | AQ15: 0.00017238342 | AR15: 0.0004544296 | AS15: 0.00016707684 | AT15: 0.00022203479 | AU15: 0.00031423706 | AV15: 0.00025552969 | AW15: 9.0977115e-05 | AX15: 0.00011552774 | AY15: 0.00010126886 | AZ15: 6.9255498e-05 | BA15: 0.00044102694 | BB15: 0.00049022084 | BC15: 0.00032244264 | BD15: 0.00026492256 | BE15: 0.00096143125 | BF15: 3.3128365e-06 | BG15: 1.5249325e-06 | BH15: 9.2983301e-06 | BI15: 4.4303501e-06 | BJ15: 3.4036101e-06 | BK15: 4.0002249e-06 | BL15: 4.6929195e-06 | BM15: 6.1234227e-06 | BN15: 1.6166242e-05 | BO15: 5.1250726e-06 | BP15: 0.0010373199 | BQ15: 0.0038852901 | BR15: 0.00064241537 | BS15: 2.1801688e-05 | BT15: 4.6168029e-05 | BU15: 1.0021425e-06 | BV15: 1.0797938e-05 | BW15: 6.412052e-05 | BX15: 1.2898151e-05 | BY15: 1.1454958e-05 | BZ15: 1.479773e-05 | CA15: 0.00019614231 | CB15: 1.5709772e-05 | CC15: 5.734631e-06 | CD15: 4.782888e-05 | CE15: 6.0410446e-06 | CF15: 5.076185e-06 | CG15: 1.2119069e-05 | CH15: 0.00023836434 | CI15: 1.647981e-05 | CJ15: 8.8264631e-07 | CK15: 4.0266678e-06 | CL15: 1.1444622e-06 | CM15: 2.9705877e-06 | CN15: 2.4425078e-06 | CO15: 0.00015169898 | CP15: 4.7877294e-07 | CQ15: 2.9590467e-06 | CR15: 1.2858945e-05 | CS15: 5.6826678e-06 | CT15: 5.3303077e-06 | CU15: 4.3840634e-06 | CV15: 2.7190392e-06 | CW15: 9.6938362e-06 | CX15: 5.6830411e-06 | CY15: 3.8768337e-06 | CZ15: 4.846541e-06 | DA15: 6.5731981e-06 | DB15: 3.0493722e-06 | DC15: 1.385675e-05 | DD15: 8.5123114e-06 | DE15: 2.7027953e-06 | DF15: 1.4549917e-06 | DG15: 5.2773928e-06 | DH15: 3737.491 | DI15: 31.353547 | DJ15: 3211.0441 | DK15: 0 | DL15: 343.03997 | DM15: 0.49500641 | DN15: 248.47679 | DO15: 0 | DP15: =SUM(DK15:DM15) -> 343.53498 | DQ15: =SUM(DL15:DN15) -> 592.01176
... A55: EU | B55: Sector | C55: Waste water | D55: 0.00036420575 | E55: 0.00034308381 | F55: 0.00010616213 | G55: 0.0002947443 | H55: 0.00039161943 | I55: 0.00043828457 | J55: 0.00019224683 | K55: 0.0003193193 | L55: 0.00015057903 | M55: 0.00040378859 | N55: 0.00042591952 | O55: 0.00058021053 | P55: 0.0019569761 | Q55: 0.0030652493 | R55: 0.00019230256 | S55: 0.00015182856 | T55: 0.0011556468 | U55: 0.00098557563 | V55: 0.00017129045 | W55: 0.00028087552 | X55: 0.00036143702 | Y55: 0.00051889809 | Z55: 0.00050809326 | AA55: 0.00050346758 | AB55: 0.00052332688 | AC55: 0.0018156596 | AD55: 0.0014706075 | AE55: 0.0001412659 | AF55: 0.00019205537 | AG55: 0.0010498975 | AH55: 0.00042431655 | AI55: 0.00028373989 | AJ55: 0.00034926816 | AK55: 0.00038429478 | AL55: 0.001607635 | AM55: 0.00074198253 | AN55: 2.8921737e-05 | AO55: 0.0003708804 | AP55: 5.6122072e-05 | AQ55: 0.00027436675 | AR55: 0.00032594091 | AS55: 0.00021436691 | AT55: 0.0001631459 | AU55: 0.00029981566 | AV55: 0.00013834216 | AW55: 0.00023423265 | AX55: 0.0008553035 | AY55: 0.0002494391 | AZ55: 0.00026817775 | BA55: 0.0092425435 | BB55: 0.011358221 | BC55: 0.012358771 | BD55: 0.016906112 | BE55: 0.00049092627 | BF55: 1.7546386e-06 | BG55: 9.2235112e-06 | BH55: 1.3671602e-07 | BI55: 2.385534e-07 | BJ55: 1.4295207e-06 | BK55: 1.6351627e-06 | BL55: 7.8842319e-06 | BM55: 3.6873611e-06 | BN55: 1.7755382e-06 | BO55: 6.3629866e-06 | BP55: 4.2982007e-06 | BQ55: 7.1136412e-07 | BR55: 3.6014492e-06 | BS55: 9.4014733e-06 | BT55: 8.6800507e-07 | BU55: 8.0108541e-07 | BV55: 2.7112472e-06 | BW55: 6.4638323e-06 | BX55: 2.5048909e-05 | BY55: 6.2635677e-05 | BZ55: 1.1381268e-06 | CA55: 2.7470576e-06 | CB55: 1.1660665e-06 | CC55: 1.9316412e-06 | CD55: 3.9178115e-06 | CE55: 5.8208243e-06 | CF55: 6.4153049e-06 | CG55: 1.2809539e-06 | CH55: 1.2806706e-06 | CI55: 4.374155e-06 | CJ55: 8.0322375e-06 | CK55: 2.0394056e-05 | CL55: 5.0309182e-07 | CM55: 7.3776352e-07 | CN55: 9.161734e-07 | CO55: 1.4869605e-06 | CP55: 4.0322633e-07 | CQ55: 1.2026959e-06 | CR55: 8.4022927e-07 | CS55: 1.3265886e-06 | CT55: 1.2022479e-06 | CU55: 8.4187183e-06 | CV55: 1.1593212e-05 | CW55: 3.8500244e-07 | CX55: 2.0498887e-06 | CY55: 1.7771573e-06 | CZ55: 2.099425e-06 | DA55: 2.3004175e-06 | DB55: 1.1625424e-06 | DC55: 4.1390327e-05 | DD55: 5.0820979e-05 | DE55: 1.4654121e-05 | DF55: 8.827339e-06 | DG55: 1.2600123e-06 | DH55: 4827.7242 | DI55: 749.43164 | DJ55: 100.46277 | DK55: 0 | DL55: 150.6389 | DM55: 37.1186 | DN55: 5.3427964 | DO55: 0 | DP55: =SUM(DK55:DM55) -> 187.7575 | DQ55: =SUM(DL55:DN55) -> 193.1003
A56: EU | B56: Sector | C56: Landfill of Waste | D56: 0.0006494639 | E56: 0.00037780387 | F56: 0.00022778385 | G56: 0.0005530776 | H56: 0.0010036063 | I56: 0.0012823384 | J56: 0.00032473863 | K56: 0.00070873232 | L56: 0.00052068439 | M56: 0.00099813156 | N56: 0.0010588236 | O56: 0.0014260044 | P56: 0.004208223 | Q56: 0.0042753833 | R56: 0.00053137237 | S56: 0.00052470214 | T56: 0.0018864504 | U56: 0.001687644 | V56: 0.00040551711 | W56: 0.00064198479 | X56: 0.000900472 | Y56: 0.0013194647 | Z56: 0.001341411 | AA56: 0.0013398698 | AB56: 0.0016653114 | AC56: 0.0054264091 | AD56: 0.003861282 | AE56: 0.00034856767 | AF56: 0.00047023444 | AG56: 0.0034955621 | AH56: 0.001219851 | AI56: 0.0006172867 | AJ56: 0.00069132333 | AK56: 0.0010139462 | AL56: 0.0040221436 | AM56: 0.0013151943 | AN56: 5.5535866e-05 | AO56: 0.00098912511 | AP56: 0.00013112597 | AQ56: 0.00055966587 | AR56: 0.00087659574 | AS56: 0.00048658289 | AT56: 0.00039791015 | AU56: 0.00051631689 | AV56: 0.00030020252 | AW56: 0.0006354037 | AX56: 0.0021893624 | AY56: 0.0004139021 | AZ56: 0.00049790224 | BA56: 0.02386325 | BB56: 0.032392755 | BC56: 0.035940693 | BD56: 0.054782812 | BE56: 0.00078998342 | BF56: 4.1731339e-05 | BG56: 1.3527311e-05 | BH56: 5.0500624e-07 | BI56: 4.8843113e-07 | BJ56: 1.0681971e-05 | BK56: 2.8591438e-05 | BL56: 8.9083472e-05 | BM56: 5.9023484e-06 | BN56: 8.0347866e-06 | BO56: 2.327519e-05 | BP56: 1.1643689e-05 | BQ56: 1.3971072e-06 | BR56: 5.204983e-05 | BS56: 1.6651079e-05 | BT56: 4.7538559e-06 | BU56: 1.7024339e-05 | BV56: 5.8286032e-06 | BW56: 8.6038478e-06 | BX56: 5.1203903e-05 | BY56: 7.8759803e-06 | BZ56: 2.7144701e-06 | CA56: 3.7916865e-06 | CB56: 4.2742799e-06 | CC56: 1.071125e-05 | CD56: 5.2769826e-06 | CE56: 2.5256967e-05 | CF56: 1.522255e-05 | CG56: 3.5705262e-06 | CH56: 2.9346432e-06 | CI56: 1.2036058e-05 | CJ56: 4.0447856e-05 | CK56: 9.2093643e-05 | CL56: 1.5774634e-05 | CM56: 8.8743975e-05 | CN56: 7.8388705e-06 | CO56: 7.1533481e-06 | CP56: 5.5765253e-07 | CQ56: 2.0961526e-05 | CR56: 2.6497384e-06 | CS56: 2.7082502e-05 | CT56: 2.9970339e-05 | CU56: 2.829609e-05 | CV56: 7.9231859e-06 | CW56: 2.9375943e-06 | CX56: 9.1155579e-06 | CY56: 1.2660474e-05 | CZ56: 1.1447333e-05 | DA56: 5.6800238e-06 | DB56: 6.0405878e-06 | DC56: 0.0001083685 | DD56: 0.0001101596 | DE56: 2.1620213e-05 | DF56: 6.8475208e-05 | DG56: 1.2078788e-05 | DH56: 8371.3053 | DI56: 1989.3462 | DJ56: 262.89317 | DK56: 0 | DL56: 284.74994 | DM56: 54.786716 | DN56: 6.2933704 | DO56: 0 | DP56: =SUM(DG56:DI56) -> 10360.652 | DQ56: =SUM(DH56:DJ56) -> 10623.545
A57: EU | B57: Sector | C57: Other Services | D57: 0.0055578685 | E57: 0.0010094508 | F57: 0.010541579 | G57: 0.0018451094 | H57: 0.0094662641 | I57: 0.005144664 | J57: 0.0012567408 | K57: 0.0033812367 | L57: 0.020361652 | M57: 0.004462953 | N57: 0.0028486367 | O57: 0.0011749597 | P57: 0.0022744404 | Q57: 0.0013292871 | R57: 0.0020956521 | S57: 0.00086731784 | T57: 0.0009066786 | U57: 0.0010408239 | V57: 0.009134257 | W57: 0.001001993 | X57: 0.0017692251 | Y57: 0.0012370083 | Z57: 0.002385883 | AA57: 0.0014092055 | AB57: 0.0017802475 | AC57: 0.0014630984 | AD57: 0.00092424307 | AE57: 0.0013494943 | AF57: 0.0020908867 | AG57: 0.00092244258 | AH57: 0.00092480812 | AI57: 0.0014317762 | AJ57: 0.00053862239 | AK57: 0.0023570632 | AL57: 0.0027566599 | AM57: 0.00060714782 | AN57: 0.0017354213 | AO57: 0.00057124034 | AP57: 0.0011296148 | AQ57: 0.00028509358 | AR57: 0.0024074813 | AS57: 0.00089549255 | AT57: 0.002050445 | AU57: 0.00079007543 | AV57: 0.0029926738 | AW57: 0.002041868 | AX57: 0.00050163517 | AY57: 0.00072665027 | AZ57: 0.0034525956 | BA57: 0.0045067509 | BB57: 0.0040676984 | BC57: 0.0038552526 | BD57: 0.001754033 | BE57: 0.022810275 | BF57: 6.4072117e-06 | BG57: 3.2533679e-06 | BH57: 5.9252152e-06 | BI57: 9.6588431e-06 | BJ57: 5.6894725e-06 | BK57: 7.088619e-06 | BL57: 1.0679219e-05 | BM57: 1.9785506e-05 | BN57: 1.0485053e-05 | BO57: 1.0589548e-05 | BP57: 2.1184849e-05 | BQ57: 5.7857979e-05 | BR57: 2.0813379e-05 | BS57: 7.4521388e-06 | BT57: 2.1072155e-05 | BU57: 2.6048035e-06 | BV57: 5.2740762e-06 | BW57: 7.7536029e-06 | BX57: 2.0972625e-05 | BY57: 4.5323086e-06 | BZ57: 8.1554986e-06 | CA57: 7.6504099e-06 | CB57: 1.52971e-05 | CC57: 8.3780627e-06 | CD57: 3.491797e-05 | CE57: 7.4119603e-06 | CF57: 1.4151775e-05 | CG57: 9.434353e-06 | CH57: 8.8711566e-06 | CI57: 6.1092022e-05 | CJ57: 1.0286438e-05 | CK57: 1.6171983e-05 | CL57: 3.0581311e-06 | CM57: 7.0227583e-06 | CN57: 8.3626775e-06 | CO57: 6.1424056e-06 | CP57: 2.2975213e-06 | CQ57: 7.851888e-06 | CR57: 1.760588e-05 | CS57: 7.8927226e-06 | CT57: 9.4220776e-06 | CU57: 1.1976981e-05 | CV57: 9.8746853e-06 | CW57: 3.6711812e-06 | CX57: 9.8625612e-06 | CY57: 8.356106e-06 | CZ57: 6.385397e-06 | DA57: 9.4255561e-06 | DB57: 8.9795977e-06 | DC57: 4.8181576e-05 | DD57: 8.2477813e-06 | DE57: 1.8356374e-05 | DF57: 6.5521604e-06 | DG57: 2.8917722e-05 | DH57: 306568.43 | DI57: 3732.278 | DJ57: 489.62977 | DK57: 0 | DL57: 40220.69 | DM57: 23.312053 | DN57: 91.67345 | DO57: 0 | DP57: =SUM(DG57:DI57) -> 310300.7 | DQ57: =SUM(DH57:DJ57) -> 310790.33
A58: RoW | B58: Sector | C58: Agriculture | D58: 0.0049012756 | E58: 0.030756168 | F58: 0.010376431 | G58: 0.00088162703 | H58: 0.00031626635 | I58: 0.00026050586 | J58: 0.0071624225 | K58: 0.022483125 | L58: 0.096469377 | M58: 0.0041965952 | N58: 0.00043865715 | O58: 0.00067150532 | P58: 0.00039990889 | Q58: 0.00069761764 | R58: 0.00022090877 | S58: 0.00064314314 | T58: 0.0011068278 | U58: 0.0016742772 | V58: 0.0009084964 | W58: 0.00031207687 | X58: 0.00030116387 | Y58: 0.00025096224 | Z58: 0.0003804656 | AA58: 0.00012235234 | AB58: 0.00013452789 | AC58: 0.00052486834 | AD58: 0.00050289532 | AE58: 0.00014126265 | AF58: 0.00020923657 | AG58: 0.00028790737 | AH58: 0.00014642959 | AI58: 0.0010364868 | AJ58: 4.5524023e-05 | AK58: 0.00010369093 | AL58: 0.00018049046 | AM58: 0.00020021763 | AN58: 7.3848419e-06 | AO58: 5.4773142e-05 | AP58: 0.00038085224 | AQ58: 0.00046692206 | AR58: 0.0012229019 | AS58: 0.00024741787 | AT58: 0.00011424326 | AU58: 1.7803415e-05 | AV58: 7.2621713e-05 | AW58: 0.00019190339 | AX58: 0.00022198894 | AY58: 6.3786469e-05 | AZ58: 0.00062703033 | BA58: 0.00023928087 | BB58: 6.7257339e-05 | BC58: 0.00018810279 | BD58: 0.00013189912 | BE58: 0.00022411077 | BF58: 0.086851402 | BG58: 0.07997635 | BH58: 0.024475596 | BI58: 0.003455806 | BJ58: 0.0017905901 | BK58: 0.0021023828 | BL58: 0.055373975 | BM58: 0.2310364 | BN58: 0.17501068 | BO58: 0.026414994 | BP58: 0.019220669 | BQ58: 0.00076463223 | BR58: 0.034285253 | BS58: 0.00049752115 | BT58: 0.0066164859 | BU58: 0.00056627665 | BV58: 0.053909798 | BW58: 0.0015374129 | BX58: 0.025153589 | BY58: 0.0018760078 | BZ58: 0.0010319155 | CA58: 0.00028890165 | CB58: 0.002138563 | CC58: 0.0010857359 | CD58: 0.00010858787 | CE58: 0.0010610712 | CF58: 0.00018334932 | CG58: 0.00043042731 | CH58: 0.001217109 | CI58: 0.0064126512 | CJ58: 0.001417859 | CK58: 0.0019400326 | CL58: 0.0011654676 | CM58: 0.0050035197 | CN58: 0.0015120574 | CO58: 0.0041715014 | CP58: 4.5075627e-05 | CQ58: 0.00052831485 | CR58: 0.017003786 | CS58: 0.0012181572 | CT58: 0.014769773 | CU58: 0.0009989194 | CV58: 0.00064703592 | CW58: 0.0012323429 | CX58: 0.0019914728 | CY58: 0.0028108794 | CZ58: 0.00084147186 | DA58: 0.0017412855 | DB58: 0.00371807 | DC58: 0.00056385949 | DD58: 0.00048772602 | DE58: 0.00088631577 | DF58: 0.0039689081 | DG58: 0.0054215785 | DH58: 33630.685 | DI58: 182.39294 | DJ58: 1595.8359 | DK58: 0 | DL58: 672489.13 | DM58: 11091.222 | DN58: 30464.006 | DO58: 0 | DP58: =SUM(DG58:DI58) -> 33813.083 | DQ58: =SUM(DH58:DJ58) -> 35408.914
A59: RoW | B59: Sector | C59: Animal Farming | D59: 0.00054084762 | E59: 0.00087897561 | F59: 0.00029448706 | G59: 0.00040565513 | H59: 0.00027378928 | I59: 0.00014285731 | J59: 0.00078953415 | K59: 0.00097054103 | L59: 0.0016714781 | M59: 0.00027563569 | N59: 0.00028299813 | O59: 0.00040425535 | P59: 0.00022782727 | Q59: 0.00029976569 | R59: 6.5938642e-05 | S59: 0.00059711371 | T59: 0.00044747656 | U59: 0.00071171846 | V59: 0.00052562789 | W59: 0.00015934405 | X59: 0.00017926864 | Y59: 0.00015027538 | Z59: 0.00020291451 | AA59: 7.0128275e-05 | AB59: 8.1001564e-05 | AC59: 0.00017413662 | AD59: 0.0001345578 | AE59: 4.4472343e-05 | AF59: 0.00011178802 | AG59: 0.00012129262 | AH59: 0.00011424892 | AI59: 6.8375195e-05 | AJ59: 2.5494549e-05 | AK59: 0.00010676123 | AL59: 0.00010051768 | AM59: 4.3737594e-05 | AN59: 6.2112035e-06 | AO59: 2.5544672e-05 | AP59: 0.00014960812 | AQ59: 7.7385181e-05 | AR59: 0.00024225 | AS59: 5.2477774e-05 | AT59: 2.7778289e-05 | AU59: 9.2752035e-06 | AV59: 3.5109974e-05 | AW59: 0.00010990328 | AX59: 3.9599444e-05 | AY59: 2.0197714e-05 | AZ59: 0.00014616853 | BA59: 8.5786777e-05 | BB59: 7.8979235e-05 | BC59: 0.00014199141 | BD59: 0.00011840266 | BE59: 0.00016762889 | BF59: 0.0009033683 | BG59: 0.13343497 | BH59: 0.0040120638 | BI59: 0.0037336745 | BJ59: 0.00090641646 | BK59: 0.0020578273 | BL59: 0.24513962 | BM59: 0.025437157 | BN59: 0.0044519302 | BO59: 0.010830767 | BP59: 0.0014976094 | BQ59: 0.00021104678 | BR59: 0.002534366 | BS59: 0.00020911 | BT59: 0.00060883013 | BU59: 0.00067683073 | BV59: 0.0007851766 | BW59: 0.00044790131 | BX59: 0.0069637042 | BY59: 0.0016134367 | BZ59: 0.00091518166 | CA59: 0.00013620136 | CB59: 0.00088342528 | CC59: 0.0010647363 | CD59: 0.00011090716 | CE59: 0.00061264722 | CF59: 9.3258326e-05 | CG59: 0.00026309587 | CH59: 0.0066265122 | CI59: 0.0062017146 | CJ59: 0.00070589667 | CK59: 0.0014097802 | CL59: 0.00068233442 | CM59: 0.0030964815 | CN59: 0.0015249723 | CO59: 0.00068437918 | CP59: 6.845172e-05 | CQ59: 0.00049765582 | CR59: 0.010868107 | CS59: 0.0012888397 | CT59: 0.009808863 | CU59: 0.0040772415 | CV59: 0.00036488402 | CW59: 0.00031289862 | CX59: 0.0015660146 | CY59: 0.0029569284 | CZ59: 0.00092083683 | DA59: 0.0016268717 | DB59: 0.0010667192 | DC59: 0.0011780361 | DD59: 0.0010072698 | DE59: 0.00449465 | DF59: 0.0029122332 | DG59: 0.0019177152 | DH59: 2240.8765 | DI59: 73.52287 | DJ59: 348.40819 | DK59: 0 | DL59: 199679.12 | DM59: 8086.4068 | DN59: 91918.778 | DO59: 0 | DP59: =SUM(DG59:DI59) -> 2314.4013 | DQ59: =SUM(DH59:DJ59) -> 2662.8075
A60: RoW | B60: Sector | C60: Forestry, logging and related service activities (02) | D60: 4.2567492e-05 | E60: 6.8854037e-05 | F60: 0.0039058615 | G60: 3.6201574e-05 | H60: 3.9306063e-05 | I60: 3.9589751e-05 | J60: 3.7789845e-05 | K60: 9.5976167e-05 | L60: 5.318861e-05 | M60: 2.0731354e-05 | N60: 0.004034939 | O60: 0.00025641141 | P60: 0.0052118913 | Q60: 6.5044402e-05 | R60: 0.00078242746 | S60: 9.604959e-06 | T60: 5.2346509e-05 | U60: 0.00011386889 | V60: 0.00010899237 | W60: 4.2138225e-05 | X60: 4.7585689e-05 | Y60: 5.0013966e-05 | Z60: 6.941086e-05 | AA60: 2.6330862e-05 | AB60: 2.8709942e-05 | AC60: 1.6571455e-05 | AD60: 1.8317352e-05 | AE60: 6.5250193e-06 | AF60: 0.00019051483 | AG60: 1.5833029e-05 | AH60: 9.9881324e-06 | AI60: 0.00014370689 | AJ60: 3.7986568e-06 | AK60: 5.1211486e-06 | AL60: 1.0664021e-05 | AM60: 1.9703382e-05 | AN60: 1.8162116e-06 | AO60: 5.5180577e-06 | AP60: 6.4420512e-06 | AQ60: 1.0815123e-05 | AR60: 1.0573218e-05 | AS60: 4.2743743e-06 | AT60: 7.7040024e-06 | AU60: 2.4663696e-06 | AV60: 3.5001532e-06 | AW60: 1.4399606e-05 | AX60: 0.00012933412 | AY60: 2.4505964e-06 | AZ60: 1.3608798e-05 | BA60: 1.0425958e-05 | BB60: 9.9484754e-06 | BC60: 2.1456438e-05 | BD60: 2.131141e-05 | BE60: 9.2028185e-06 | BF60: 0.00059165243 | BG60: 0.00034227681 | BH60: 0.10612858 | BI60: 0.00015308137 | BJ60: 0.0006241812 | BK60: 0.0001213492 | BL60: 0.00059793804 | BM60: 0.0016783047 | BN60: 0.0022912546 | BO60: 0.0014763696 | BP60: 0.20110922 | BQ60: 0.0017323827 | BR60: 0.063060834 | BS60: 0.0005345775 | BT60: 0.021727267 | BU60: 3.0698962e-05 | BV60: 0.00027101804 | BW60: 0.00013389172 | BX60: 0.0040918032 | BY60: 0.01104735 | BZ60: 9.8362947e-05 | CA60: 0.0011574223 | CB60: 0.00020196599 | CC60: 5.5206117e-05 | CD60: 2.2891543e-05 | CE60: 3.2279391e-05 | CF60: 1.1785701e-05 | CG60: 3.4362831e-05 | CH60: 0.00536308 | CI60: 0.0018127175 | CJ60: 2.2079183e-05 | CK60: 0.00013478334 | CL60: 2.3819052e-05 | CM60: 2.2691383e-05 | CN60: 2.2197076e-05 | CO60: 0.0025400975 | CP60: 1.1668935e-05 | CQ60: 1.9178244e-05 | CR60: 4.6265434e-05 | CS60: 5.7689559e-05 | CT60: 0.0003455387 | CU60: 0.0003836875 | CV60: 2.0836968e-05 | CW60: 1.9217472e-05 | CX60: 3.0108756e-05 | CY60: 0.0008074738 | CZ60: 7.0182847e-05 | DA60: 4.5327932e-05 | DB60: 5.4999986e-05 | DC60: 7.2221942e-05 | DD60: 8.9673775e-05 | DE60: 2.8226338e-05 | DF60: 4.3946351e-05 | DG60: 7.0920241e-05 | DH60: 230.6586 | DI60: 12.298189 | DJ60: 116.18041 | DK60: 0 | DL60: 42348.051 | DM60: 264.55897 | DN60: 7621.564 | DO60: 0 | DP60: =SUM(DG60:DI60) -> 242.95686 | DQ60: =SUM(DH60:DJ60) -> 359.1372
A61: RoW | B61: Sector | C61: Fishing, operating of fish hatcheries and fish farms; service activities incidental to fishing (05) | D61: 8.0643593e-06 | E61: 7.6236219e-05 | F61: 2.681353e-05 | G61: 0.0048355172 | H61: 6.9390215e-06 | I61: 6.5219034e-06 | J61: 0.001841588 | K61: 0.0018409794 | L61: 0.00031373285 | M61: 1.917294e-05 | N61: 3.027029e-05 | O61: 5.0293274e-05 | P61: 9.2139853e-06 | Q61: 9.3996251e-06 | R61: 4.9250194e-06 | S61: 4.0067909e-06 | T61: 3.5162075e-05 | U61: 5.8424837e-05 | V61: 4.0395732e-05 | W61: 5.6204281e-06 | X61: 7.5182097e-06 | Y61: 1.1316831e-05 | Z61: 7.7746879e-06 | AA61: 3.1203216e-06 | AB61: 5.4433901e-06 | AC61: 5.6691362e-06 | AD61: 4.1489871e-06 | AE61: 3.8357465e-06 | AF61: 1.0257743e-05 | AG61: 8.7548576e-06 | AH61: 2.9553786e-06 | AI61: 3.4434045e-06 | AJ61: 1.6570332e-06 | AK61: 1.5212656e-06 | AL61: 3.2869597e-06 | AM61: 3.8472449e-06 | AN61: 5.5113817e-07 | AO61: 5.1254584e-06 | AP61: 1.5760777e-05 | AQ61: 2.043158e-05 | AR61: 0.00032076522 | AS61: 1.6477898e-05 | AT61: 4.3613045e-06 | AU61: 1.6228081e-06 | AV61: 6.7974285e-06 | AW61: 1.0916327e-05 | AX61: 7.3045484e-06 | AY61: 8.1175847e-06 | AZ61: 2.8567905e-05 | BA61: 4.2810215e-06 | BB61: 4.1435114e-06 | BC61: 4.9843758e-06 | BD61: 5.591709e-06 | BE61: 6.8964402e-06 | BF61: 0.00040983497 | BG61: 0.00063710918 | BH61: 0.00032618005 | BI61: 0.020914928 | BJ61: 6.5029469e-05 | BK61: 0.00018879608 | BL61: 0.14964201 | BM61: 0.001548236 | BN61: 0.00039052719 | BO61: 0.00015533315 | BP61: 0.00015203298 | BQ61: 3.6378961e-05 | BR61: 0.00026899631 | BS61: 9.906891e-06 | BT61: 5.8800848e-05 | BU61: 2.7875294e-05 | BV61: 0.0001145307 | BW61: 1.2668629e-05 | BX61: 0.0010639523 | BY61: 1.1930313e-05 | BZ61: 6.9825409e-05 | CA61: 7.8428503e-06 | CB61: 6.2962482e-05 | CC61: 5.8716835e-05 | CD61: 4.9237021e-06 | CE61: 4.1318603e-05 | CF61: 2.3673237e-06 | CG61: 2.3101771e-05 | CH61: 0.0001226249 | CI61: 0.00041902376 | CJ61: 0.00012916152 | CK61: 0.00020546504 | CL61: 9.3117115e-05 | CM61: 0.00036902129 | CN61: 0.00016163783 | CO61: 3.5630137e-05 | CP61: 2.0133997e-06 | CQ61: 8.7824173e-05 | CR61: 0.0016080933 | CS61: 0.00017879124 | CT61: 0.0050806997 | CU61: 0.00016913356 | CV61: 4.1896194e-05 | CW61: 2.6593202e-05 | CX61: 0.00016832977 | CY61: 0.00017148961 | CZ61: 4.5516965e-05 | DA61: 0.000105619 | DB61: 0.00055224821 | DC61: 3.6065486e-05 | DD61: 4.0240506e-05 | DE61: 1.9178634e-05 | DF61: 0.00033307188 | DG61: 0.00041338211 | DH61: 3144.3506 | DI61: 5.5107608 | DJ61: 31.202717 | DK61: 0 | DL61: 57440.94 | DM61: 117.10438 | DN61: 3059.4967 | DO61: 0 | DP61: =SUM(DG61:DI61) -> 3149.8618 | DQ61: =SUM(DH61:DJ61) -> 3181.0641
A62: RoW | B62: Sector | C62: Extraction of Fossil-Fuels | D62: 0.0015421043 | E62: 0.000679103 | F62: 0.00036894996 | G62: 0.0014562282 | H62: 0.091176137 | I62: 0.0033391855 | J62: 0.00078292647 | K62: 0.00092368658 | L62: 0.00053060368 | M62: 0.0083743989 | N62: 0.0078738069 | O62: 0.004852185 | P62: 0.0076661679 | Q62: 0.0017664856 | R62: 0.0006798398 | S62: 0.54187306 | T62: 0.011460463 | U62: 0.0043301848 | V62: 0.036707919 | W62: 0.0047827164 | X62: 0.010754264 | Y62: 0.0023211146 | Z62: 0.0069339981 | AA62: 0.0046324714 | AB62: 0.002337366 | AC62: 0.0094082473 | AD62: 0.0022180335 | AE62: 0.00063344744 | AF62: 0.0093218221 | AG62: 0.00071368042 | AH62: 0.081875937 | AI62: 0.0071869623 | AJ62: 0.0010919486 | AK62: 0.065678357 | AL62: 0.018692538 | AM62: 0.00045383559 | AN62: 9.4547226e-05 | AO62: 0.00023992803 | AP62: 0.00017271682 | AQ62: 0.00050837906 | AR62: 0.00024757362 | AS62: 0.00084755257 | AT62: 0.00024436775 | AU62: 0.00023870752 | AV62: 0.00023639274 | AW62: 0.0012569825 | AX62: 0.00098111578 | AY62: 0.00025739706 | AZ62: 0.0006937347 | BA62: 0.00047842485 | BB62: 0.00042835294 | BC62: 0.0011986161 | BD62: 0.0010502886 | BE62: 0.00048537878 | BF62: 0.0023189793 | BG62: 0.0011260311 | BH62: 0.0014388078 | BI62: 0.0012607708 | BJ62: 0.083761317 | BK62: 0.011203672 | BL62: 0.0011337111 | BM62: 0.0010004341 | BN62: 0.0017828027 | BO62: 0.0098025314 | BP62: 0.011598651 | BQ62: 0.021974932 | BR62: 0.020137608 | BS62: 0.0037946327 | BT62: 0.0031773398 | BU62: 0.59463215 | BV62: 0.088072515 | BW62: 0.0050019135 | BX62: 0.040969132 | BY62: 0.015922208 | BZ62: 0.0054250635 | CA62: 0.00511805 | CB62: 0.034431842 | CC62: 0.11196701 | CD62: 0.023542651 | CE62: 0.017889706 | CF62: 0.0027871604 | CG62: 0.0016325814 | CH62: 0.013519876 | CI62: 0.002194607 | CJ62: 0.17772466 | CK62: 0.0033313438 | CL62: 0.001325702 | CM62: 0.12024275 | CN62: 0.0095164721 | CO62: 0.0026628938 | CP62: 0.0038815582 | CQ62: 0.00067762874 | CR62: 0.0054376869 | CS62: 0.0010499475 | CT62: 0.0008526775 | CU62: 0.0048380739 | CV62: 0.0010251783 | CW62: 0.00057200514 | CX62: 0.0012087912 | CY62: 0.004391292 | CZ62: 0.0019908275 | DA62: 0.0017947994 | DB62: 0.001604738 | DC62: 0.0014565936 | DD62: 0.0019465534 | DE62: 0.0017910499 | DF62: 0.0024868538 | DG62: 0.0023221545 | DH62: 2416.9352 | DI62: 392.38548 | DJ62: 21083.117 | DK62: 0 | DL62: 80824.015 | DM62: 2171.3194 | DN62: 227533.73 | DO62: 0 | DP62: =SUM(DG62:DI62) -> 2809.323 | DQ62: =SUM(DH62:DJ62) -> 23892.438
A63: RoW | B63: Sector | C63: Mining & Quarrying of raw materials | D63: 0.0011660551 | E63: 0.00091878201 | F63: 0.0001497561 | G63: 0.0013651954 | H63: 0.0002392417 | I63: 0.0061206365 | J63: 0.0010218967 | K63: 0.0012805083 | L63: 0.00049249277 | M63: 0.00048990575 | N63: 0.00028837611 | O63: 0.00049419752 | P63: 0.00097543235 | Q63: 0.0016293835 | R63: 0.00021659335 | S63: 0.00064207574 | T63: 0.0025890604 | U63: 0.0037144696 | V63: 0.0060558992 | W63: 0.0005146578 | X63: 0.010462561 | Y63: 0.0014858565 | Z63: 0.010587389 | AA63: 0.0033619507 | AB63: 0.0057080291 | AC63: 0.044512997 | AD63: 0.0056724464 | AE63: 0.0003078598 | AF63: 0.0028122142 | AG63: 0.00068372331 | AH63: 0.00033245703 | AI63: 0.00013914871 | AJ63: 0.00014037086 | AK63: 0.00027350288 | AL63: 0.00029096802 | AM63: 0.00036112904 | AN63: 1.9369554e-05 | AO63: 5.5276532e-05 | AP63: 0.00022479051 | AQ63: 0.00014138861 | AR63: 0.00036790185 | AS63: 6.0505825e-05 | AT63: 6.1280367e-05 | AU63: 1.6757653e-05 | AV63: 9.109589e-05 | AW63: 0.00044427644 | AX63: 0.00011835257 | AY63: 5.5708823e-05 | AZ63: 0.00035752214 | BA63: 0.00025655067 | BB63: 0.00023091316 | BC63: 0.00044514027 | BD63: 0.00032789309 | BE63: 0.00013039705 | BF63: 0.0012721552 | BG63: 0.0021003534 | BH63: 0.0018593088 | BI63: 0.0017050131 | BJ63: 0.0024821809 | BK63: 0.087121043 | BL63: 0.0015721167 | BM63: 0.0013939277 | BN63: 0.0019381863 | BO63: 0.00097930621 | BP63: 0.0016968258 | BQ63: 0.00024429224 | BR63: 0.006908165 | BS63: 0.0024577216 | BT63: 0.0019017546 | BU63: 0.0024179273 | BV63: 0.0053210532 | BW63: 0.0048712157 | BX63: 0.026570311 | BY63: 0.0078107735 | BZ63: 0.051478066 | CA63: 0.0025693071 | CB63: 0.065341726 | CC63: 0.075924624 | CD63: 0.026363243 | CE63: 0.12719083 | CF63: 0.018649242 | CG63: 0.0020423681 | CH63: 0.0057179878 | CI63: 0.0078552437 | CJ63: 0.002090662 | CK63: 0.0028212094 | CL63: 0.0015426873 | CM63: 0.0037331907 | CN63: 0.0036900099 | CO63: 0.017412952 | CP63: 3.9040816e-05 | CQ63: 0.00044373831 | CR63: 0.0084799759 | CS63: 0.0005521738 | CT63: 0.00095040351 | CU63: 0.0008376548 | CV63: 0.00050094649 | CW63: 0.00080996142 | CX63: 0.0012802539 | CY63: 0.0015576928 | CZ63: 0.0010825615 | DA63: 0.00092998846 | DB63: 0.00096379488 | DC63: 0.00088416283 | DD63: 0.0015215314 | DE63: 0.0023780164 | DF63: 0.0046272719 | DG63: 0.001555702 | DH63: 1524.6505 | DI63: 192.75052 | DJ63: 1311.6432 | DK63: 0 | DL63: 18484.142 | DM63: 1409.1892 | DN63: 47664.793 | DO63: 0 | DP63: =SUM(DG63:DI63) -> 1717.4026 | DQ63: =SUM(DH63:DJ63) -> 3029.0442
A64: RoW | B64: Sector | C64: Processing of meat | D64: 0.00021535583 | E64: 0.0040367329 | F64: 5.6059325e-05 | G64: 0.0018698745 | H64: 0.00010283029 | I64: 0.00040548926 | J64: 0.012297601 | K64: 0.015702643 | L64: 0.00023371919 | M64: 0.00056083773 | N64: 0.00014644801 | O64: 0.00023553073 | P64: 0.00028160055 | Q64: 0.00051958131 | R64: 0.00013747932 | S64: 0.00010896792 | T64: 0.0014531922 | U64: 0.0018706109 | V64: 0.0012794725 | W64: 0.00020439558 | X64: 0.00043590101 | Y64: 0.00016848368 | Z64: 0.0005769142 | AA64: 0.00014128982 | AB64: 0.00019120825 | AC64: 0.0001588921 | AD64: 0.00015886887 | AE64: 4.7201501e-05 | AF64: 0.00027124317 | AG64: 0.00076459439 | AH64: 0.00011482633 | AI64: 7.7069622e-05 | AJ64: 3.56825e-05 | AK64: 7.6194424e-05 | AL64: 0.00013311153 | AM64: 4.0490089e-05 | AN64: 4.4030366e-06 | AO64: 2.3771538e-05 | AP64: 0.00047033642 | AQ64: 0.00010471359 | AR64: 0.0016699552 | AS64: 6.6318285e-05 | AT64: 5.3730022e-05 | AU64: 2.5515524e-05 | AV64: 6.4162058e-05 | AW64: 0.00039658097 | AX64: 9.9459642e-05 | AY64: 0.00013312702 | AZ64: 0.00080183804 | BA64: 6.4678279e-05 | BB64: 7.5462429e-05 | BC64: 0.00011904825 | BD64: 9.3774175e-05 | BE64: 0.00013546011 | BF64: 0.0014659469 | BG64: 0.019543677 | BH64: 0.00089821243 | BI64: 0.011072132 | BJ64: 0.00040377019 | BK64: 0.0019828352 | BL64: 0.1017989 | BM64: 0.037574149 | BN64: 0.0015497458 | BO64: 0.014766847 | BP64: 0.00053781687 | BQ64: 0.00016691351 | BR64: 0.0017418092 | BS64: 0.0018992846 | BT64: 0.00064224128 | BU64: 0.0010136541 | BV64: 0.0029816982 | BW64: 0.0038381163 | BX64: 0.012424653 | BY64: 0.0004638396 | BZ64: 0.00068927182 | CA64: 0.0011902853 | CB64: 0.0023941225 | CC64: 0.00059887997 | CD64: 0.0053505872 | CE64: 0.00029019126 | CF64: 0.00025006203 | CG64: 0.0010997818 | CH64: 0.0033258503 | CI64: 0.007583302 | CJ64: 0.0014619223 | CK64: 0.0015627848 | CL64: 0.00024693693 | CM64: 0.00062126542 | CN64: 0.00060979904 | CO64: 0.00021630025 | CP64: 3.8334761e-05 | CQ64: 0.00039059348 | CR64: 0.0060897085 | CS64: 0.00064933833 | CT64: 0.023205549 | CU64: 0.0010619987 | CV64: 0.0003553104 | CW64: 0.0004111763 | CX64: 0.0031619406 | CY64: 0.00170473 | CZ64: 0.0027033806 | DA64: 0.0036571027 | DB64: 0.0086321853 | DC64: 0.00054998338 | DD64: 0.00064591601 | DE64: 0.0010670675 | DF64: 0.00048903395 | DG64: 0.003209058 | DH64: 8628.2125 | DI64: 107.14125 | DJ64: 335.02608 | DK64: 0 | DL64: 765190.79 | DM64: 4182.6447 | DN64: 21391.893 | DO64: 0 | DP64: =SUM(DG64:DI64) -> 8735.3569 | DQ64: =SUM(DH64:DJ64) -> 9070.3798
A65: RoW | B65: Sector | C65: Processing of other food&beverage | D65: 0.00019294284 | E65: 0.0048472212 | F65: 4.9090776e-05 | G65: 0.00092900838 | H65: 5.9657078e-05 | I65: 0.00077023833 | J65: 0.0042069685 | K65: 0.0070969407 | L65: 0.0001320834 | M65: 0.0003930441 | N65: 0.00010199494 | O65: 0.00016671588 | P65: 0.00036821406 | Q65: 0.000469505 | R65: 0.00015648497 | S65: 8.2311573e-05 | T65: 0.0011005219 | U65: 0.0014552504 | V65: 0.0015260223 | W65: 0.00018061327 | X65: 0.0009493768 | Y65: 0.00016977035 | Z65: 0.00096964469 | AA65: 0.00038843737 | AB65: 0.00059039633 | AC65: 0.00018067337 | AD65: 0.00011895649 | AE65: 4.1721909e-05 | AF65: 0.00047906509 | AG65: 0.00044193692 | AH65: 8.3139053e-05 | AI65: 6.5800627e-05 | AJ65: 3.3489017e-05 | AK65: 4.9087917e-05 | AL65: 9.6969925e-05 | AM65: 6.3336049e-05 | AN65: 5.1278386e-06 | AO65: 4.1948074e-05 | AP65: 0.00035739804 | AQ65: 0.00011688463 | AR65: 0.0016420107 | AS65: 5.6633228e-05 | AT65: 6.4243427e-05 | AU65: 1.7077616e-05 | AV65: 7.3382769e-05 | AW65: 0.00023322113 | AX65: 0.00013091829 | AY65: 0.00015154713 | AZ65: 0.0004547091 | BA65: 5.9694813e-05 | BB65: 5.8738034e-05 | BC65: 0.00011521751 | BD65: 8.7245582e-05 | BE65: 9.1070664e-05 | BF65: 0.00089388837 | BG65: 0.12582942 | BH65: 0.0048487424 | BI65: 0.01173613 | BJ65: 0.0004285985 | BK65: 0.0041407351 | BL65: 0.023971349 | BM65: 0.14610532 | BN65: 0.002467494 | BO65: 0.003439127 | BP65: 0.00055167992 | BQ65: 0.00070561142 | BR65: 0.0016131162 | BS65: 0.0046391992 | BT65: 0.0023598125 | BU65: 0.00036538735 | BV65: 0.0017929339 | BW65: 0.0066798767 | BX65: 0.0071632435 | BY65: 0.0089028925 | BZ65: 0.0017245636 | CA65: 0.0028258905 | CB65: 0.0045919093 | CC65: 0.0017010381 | CD65: 0.021328907 | CE65: 0.00091503201 | CF65: 0.0004603269 | CG65: 0.0004089539 | CH65: 0.0016998127 | CI65: 0.0028187888 | CJ65: 0.00069165605 | CK65: 0.0010594701 | CL65: 0.00022652534 | CM65: 0.00045547383 | CN65: 0.00036243355 | CO65: 0.0013721551 | CP65: 7.4373648e-05 | CQ65: 0.00032883452 | CR65: 0.0037763212 | CS65: 0.00081280622 | CT65: 0.034729615 | CU65: 0.0011949669 | CV65: 0.00029226663 | CW65: 0.00017281167 | CX65: 0.00088430012 | CY65: 0.0041707399 | CZ65: 0.0018041868 | DA65: 0.0022119199 | DB65: 0.0073602803 | DC65: 0.0004436005 | DD65: 0.00054064482 | DE65: 0.00058370854 | DF65: 0.00074460881 | DG65: 0.0046972292 | DH65: 20162.387 | DI65: 72.074348 | DJ65: 365.46672 | DK65: 0 | DL65: 1217362.3 | DM65: 13514.191 | DN65: 31267.179 | DO65: 0 | DP65: =SUM(DG65:DI65) -> 20234.466 | DQ65: =SUM(DH65:DJ65) -> 20599.928
A66: RoW | B66: Sector | C66: Manufacture of tobacco products (16) | D66: 1.6193368e-05 | E66: 5.9332484e-06 | F66: 1.7344334e-06 | G66: 9.3808519e-06 | H66: 7.3232755e-06 | I66: 7.1459396e-06 | J66: 1.305112e-05 | K66: 1.2145331e-05 | L66: 0.0011560118 | M66: 1.7266387e-05 | N66: 5.4229407e-06 | O66: 9.1254806e-06 | P66: 1.379438e-05 | Q66: 1.6703596e-05 | R66: 7.7960662e-06 | S66: 4.5080662e-06 | T66: 1.9403323e-05 | U66: 3.9288459e-05 | V66: 3.4313933e-05 | W66: 7.6857008e-06 | X66: 7.4478932e-06 | Y66: 8.1597575e-06 | Z66: 8.4622194e-06 | AA66: 2.7786247e-06 | AB66: 3.0179429e-06 | AC66: 0.00033527893 | AD66: 8.6984234e-05 | AE66: 7.0269101e-06 | AF66: 5.8475585e-06 | AG66: 4.084764e-06 | AH66: 8.3591633e-06 | AI66: 7.8331856e-06 | AJ66: 1.5062706e-06 | AK66: 7.6214773e-06 | AL66: 4.3109552e-06 | AM66: 9.0127104e-06 | AN66: 4.3030526e-07 | AO66: 1.5043128e-06 | AP66: 2.9184835e-06 | AQ66: 2.2790865e-05 | AR66: 6.2597659e-05 | AS66: 5.639119e-06 | AT66: 6.9508706e-06 | AU66: 9.6187875e-07 | AV66: 1.0993723e-05 | AW66: 9.0717654e-06 | AX66: 2.2821376e-05 | AY66: 1.7439287e-06 | AZ66: 6.2660344e-06 | BA66: 6.5546576e-06 | BB66: 3.5760295e-06 | BC66: 2.9521114e-05 | BD66: 1.7163849e-05 | BE66: 2.5064436e-05 | BF66: 2.9395443e-05 | BG66: 1.5105051e-05 | BH66: 4.1819007e-05 | BI66: 1.6630741e-05 | BJ66: 1.9833682e-05 | BK66: 5.0942238e-05 | BL66: 4.1359043e-05 | BM66: 2.7999985e-05 | BN66: 0.040672129 | BO66: 5.2393862e-05 | BP66: 2.274379e-05 | BQ66: 2.6991995e-05 | BR66: 0.00012597006 | BS66: 5.0334595e-05 | BT66: 3.5611191e-05 | BU66: 1.7900091e-05 | BV66: 4.0342553e-05 | BW66: 0.00012322865 | BX66: 0.00021588323 | BY66: 1.5435431e-05 | BZ66: 2.6905874e-05 | CA66: 3.9012746e-05 | CB66: 3.4100166e-05 | CC66: 2.7026492e-05 | CD66: 2.8471302e-05 | CE66: 0.0012233472 | CF66: 0.00017314656 | CG66: 4.4063466e-05 | CH66: 2.5540184e-05 | CI66: 0.00013444423 | CJ66: 6.1506027e-05 | CK66: 7.9893781e-05 | CL66: 1.3515695e-05 | CM66: 0.00016106195 | CN66: 2.3154872e-05 | CO66: 2.5088187e-05 | CP66: 1.7085101e-06 | CQ66: 1.1251943e-05 | CR66: 0.00015569593 | CS66: 5.413662e-05 | CT66: 0.00020943782 | CU66: 2.8365091e-05 | CV66: 4.9474171e-05 | CW66: 1.146807e-05 | CX66: 9.8404714e-05 | CY66: 2.6176485e-05 | CZ66: 8.2469609e-05 | DA66: 1.7950765e-05 | DB66: 1.7367251e-05 | DC66: 4.5987219e-05 | DD66: 3.0213444e-05 | DE66: 3.7217661e-05 | DF66: 5.8550863e-05 | DG66: 0.00012875644 | DH66: 760.14975 | DI66: 3.0884756 | DJ66: 24.450448 | DK66: 0 | DL66: 134348.99 | DM66: 25.40735 | DN66: 1357.6348 | DO66: 0 | DP66: =SUM(DG66:DI66) -> 763.23835 | DQ66: =SUM(DH66:DJ66) -> 787.68867
A67: RoW | B67: Sector | C67: Manufacture of textiles | D67: 0.00050217609 | E67: 0.00047102827 | F67: 0.0006989207 | G67: 0.0037120607 | H67: 0.00037098678 | I67: 0.00035448458 | J67: 0.00012768103 | K67: 0.0003643054 | L67: 0.0011953046 | M67: 0.049430649 | N67: 0.00045966377 | O67: 0.000933596 | P67: 0.00091421997 | Q67: 0.0016501842 | R67: 0.00058009117 | S67: 7.8187753e-05 | T67: 0.0005273392 | U67: 0.00084568593 | V67: 0.0023415865 | W67: 0.0025040194 | X67: 0.0013915332 | Y67: 0.0013858972 | Z67: 0.00060167049 | AA67: 0.00026393009 | AB67: 0.00024387453 | AC67: 0.00030209149 | AD67: 0.00032352039 | AE67: 0.00070913485 | AF67: 0.0035243955 | AG67: 0.00028502584 | AH67: 0.00014952037 | AI67: 5.6026522e-05 | AJ67: 6.4432293e-05 | AK67: 7.643208e-05 | AL67: 0.00016690588 | AM67: 0.00042040663 | AN67: 0.00035483866 | AO67: 0.00014231618 | AP67: 0.00050656186 | AQ67: 0.00023940086 | AR67: 0.00038000124 | AS67: 0.00014101026 | AT67: 0.00012492737 | AU67: 2.070492e-05 | AV67: 0.00030929439 | AW67: 0.00032674204 | AX67: 0.00040438692 | AY67: 0.00010454878 | AZ67: 0.00059217457 | BA67: 0.0004189245 | BB67: 0.00052297192 | BC67: 0.00055848208 | BD67: 0.00064262921 | BE67: 0.00050747299 | BF67: 0.00159626 | BG67: 0.00086849939 | BH67: 0.0015389765 | BI67: 0.0054888419 | BJ67: 0.00095035704 | BK67: 0.002794996 | BL67: 0.00058019094 | BM67: 0.0014235228 | BN67: 0.0044422876 | BO67: 0.35400951 | BP67: 0.0048555986 | BQ67: 0.00040095926 | BR67: 0.0019720047 | BS67: 0.0010977756 | BT67: 0.011721635 | BU67: 0.00033137371 | BV67: 0.0012305405 | BW67: 0.0010724514 | BX67: 0.0087870004 | BY67: 0.016003684 | BZ67: 0.0051019969 | CA67: 0.0082699656 | CB67: 0.0044948453 | CC67: 0.0016989622 | CD67: 0.0008937639 | CE67: 0.0015643723 | CF67: 0.00040583112 | CG67: 0.0038660496 | CH67: 0.038239553 | CI67: 0.0056896281 | CJ67: 0.0018589216 | CK67: 0.0039132823 | CL67: 0.00045835661 | CM67: 0.0018452687 | CN67: 0.0011332043 | CO67: 0.0031476117 | CP67: 0.00032795329 | CQ67: 0.0004971174 | CR67: 0.0040710301 | CS67: 0.0011498882 | CT67: 0.0020874148 | CU67: 0.0021170297 | CV67: 0.0012299648 | CW67: 0.00092482865 | CX67: 0.0021525366 | CY67: 0.020680827 | CZ67: 0.0030213406 | DA67: 0.001234521 | DB67: 0.0047796331 | DC67: 0.0035037581 | DD67: 0.0027998028 | DE67: 0.0049681099 | DF67: 0.0025254279 | DG67: 0.0073024943 | DH67: 60382.629 | DI67: 88.959889 | DJ67: 991.21781 | DK67: 0 | DL67: 654051.11 | DM67: 2458.9157 | DN67: 37154.3 | DO67: 0 | DP67: =SUM(DG67:DI67) -> 60471.596 | DQ67: =SUM(DH67:DJ67) -> 61462.806
... A109: RoW | B109: Sector | C109: Waste water | D109: 3.1399117e-05 | E109: 2.8474462e-06 | F109: 1.2538175e-06 | G109: 0.00044235379 | H109: 1.1160993e-05 | I109: 8.8905906e-06 | J109: 1.1879844e-05 | K109: 5.23118e-06 | L109: 2.1236986e-06 | M109: 3.251188e-06 | N109: 5.2729466e-06 | O109: 5.6181653e-06 | P109: 3.318272e-05 | Q109: 3.4423671e-05 | R109: 2.6716727e-06 | S109: 8.8783094e-05 | T109: 1.1743231e-05 | U109: 1.562565e-05 | V109: 2.4762895e-05 | W109: 5.818882e-06 | X109: 3.4236495e-06 | Y109: 4.4895161e-06 | Z109: 6.7217622e-06 | AA109: 4.8750802e-05 | AB109: 5.7913512e-06 | AC109: 0.00050732489 | AD109: 1.929718e-05 | AE109: 2.8805467e-06 | AF109: 1.8787955e-06 | AG109: 7.8488292e-06 | AH109: 8.7143581e-06 | AI109: 2.3481425e-06 | AJ109: 3.6059292e-06 | AK109: 6.0281899e-06 | AL109: 2.268627e-05 | AM109: 3.2765564e-06 | AN109: 6.7765117e-07 | AO109: 3.8232754e-06 | AP109: 8.3212957e-07 | AQ109: 5.4851556e-06 | AR109: 4.4814634e-06 | AS109: 3.8650652e-06 | AT109: 3.4310677e-06 | AU109: 4.0614046e-06 | AV109: 1.7664936e-05 | AW109: 7.7013087e-06 | AX109: 5.3851676e-06 | AY109: 1.2932171e-06 | AZ109: 2.558159e-06 | BA109: 0.00028535221 | BB109: 0.00016887671 | BC109: 0.00018292101 | BD109: 0.00034716933 | BE109: 5.9933782e-06 | BF109: 0.0028660326 | BG109: 0.0049871807 | BH109: 2.3336561e-05 | BI109: 2.3585454e-05 | BJ109: 0.0016449957 | BK109: 0.00076664251 | BL109: 0.0005072046 | BM109: 0.00028991892 | BN109: 0.00016931802 | BO109: 0.0031431659 | BP109: 0.00020136381 | BQ109: 0.00094796782 | BR109: 0.0025747518 | BS109: 0.0019507631 | BT109: 0.00041062986 | BU109: 8.537096e-05 | BV109: 0.00069859595 | BW109: 0.0021139409 | BX109: 0.00095796626 | BY109: 0.00081293872 | BZ109: 0.0002009496 | CA109: 0.0031474476 | CB109: 0.00080774588 | CC109: 0.00050276973 | CD109: 0.00025167384 | CE109: 0.00034694987 | CF109: 0.0013295479 | CG109: 0.00044235509 | CH109: 0.00065324628 | CI109: 0.0005153614 | CJ109: 0.0014194667 | CK109: 0.012011681 | CL109: 0.000245017 | CM109: 0.0001979738 | CN109: 0.020910619 | CO109: 0.00029733016 | CP109: 4.2839928e-05 | CQ109: 0.00021382481 | CR109: 1.9859868e-05 | CS109: 0.000138556 | CT109: 0.00055380615 | CU109: 0.0005749385 | CV109: 0.00037290821 | CW109: 0.00029500939 | CX109: 0.00065076736 | CY109: 0.00076507046 | CZ109: 0.001539546 | DA109: 0.0013482162 | DB109: 0.00083511087 | DC109: 0.002911081 | DD109: 0.0070697614 | DE109: 0.018052861 | DF109: 0.010874824 | DG109: 0.00050564543 | DH109: 111.57312 | DI109: 38.057759 | DJ109: 0.89708538 | DK109: 0 | DL109: 70437.546 | DM109: 51433.711 | DN109: 349.52491 | DO109: 0 | DP109: =SUM(DG109:DI109) -> 149.63139 | DQ109: =SUM(DH109:DJ109) -> 150.52797
A110: RoW | B110: Sector | C110: Landfill of Waste | D110: 0.00026461982 | E110: 2.0229767e-05 | F110: 1.4289927e-05 | G110: 0.00081524833 | H110: 0.00026452322 | I110: 5.3813493e-05 | J110: 3.0041429e-05 | K110: 3.7698684e-05 | L110: 3.0418821e-05 | M110: 1.7529271e-05 | N110: 0.00016840533 | O110: 4.6062215e-05 | P110: 7.635911e-05 | Q110: 8.3096062e-05 | R110: 2.7064263e-05 | S110: 0.00060294696 | T110: 4.6093742e-05 | U110: 8.2842002e-05 | V110: 9.2051963e-05 | W110: 3.0913561e-05 | X110: 4.7273514e-05 | Y110: 2.378281e-05 | Z110: 5.0449638e-05 | AA110: 5.9239708e-05 | AB110: 3.0928342e-05 | AC110: 0.0017004968 | AD110: 0.00015538137 | AE110: 1.81506e-05 | AF110: 2.8509504e-05 | AG110: 0.00023272371 | AH110: 7.3318517e-05 | AI110: 1.4269732e-05 | AJ110: 9.63489e-06 | AK110: 4.3558061e-05 | AL110: 6.2591095e-05 | AM110: 1.5078177e-05 | AN110: 1.7014118e-06 | AO110: 1.1691888e-05 | AP110: 6.0305055e-06 | AQ110: 1.8498777e-05 | AR110: 1.634287e-05 | AS110: 1.7151963e-05 | AT110: 1.3430887e-05 | AU110: 9.4246152e-06 | AV110: 6.3900185e-05 | AW110: 3.4453957e-05 | AX110: 1.8624838e-05 | AY110: 4.4831876e-06 | AZ110: 1.1760592e-05 | BA110: 0.00056609109 | BB110: 0.0006607023 | BC110: 0.00052690179 | BD110: 0.0010633698 | BE110: 2.1437305e-05 | BF110: 0.0024569767 | BG110: 0.0044946593 | BH110: 0.00019712598 | BI110: 0.00011295176 | BJ110: 0.0029128383 | BK110: 0.0021133309 | BL110: 0.0022503366 | BM110: 0.0014560342 | BN110: 0.0010627993 | BO110: 0.0011059653 | BP110: 0.00097391262 | BQ110: 0.002977704 | BR110: 0.012915351 | BS110: 0.0072054726 | BT110: 0.0010585839 | BU110: 0.00049249483 | BV110: 0.0013768406 | BW110: 0.0070672068 | BX110: 0.0016569356 | BY110: 0.00042503675 | BZ110: 0.00082576673 | CA110: 0.009915637 | CB110: 0.0019038604 | CC110: 0.0027486404 | CD110: 0.0010477006 | CE110: 0.0014468188 | CF110: 0.004390605 | CG110: 0.00079596078 | CH110: 0.00054336708 | CI110: 0.0012454341 | CJ110: 0.006047064 | CK110: 0.012627546 | CL110: 0.0032648419 | CM110: 0.0035261741 | CN110: 0.010439395 | CO110: 0.0011092621 | CP110: 0.00020730517 | CQ110: 0.001525012 | CR110: 0.00048452462 | CS110: 0.0014299862 | CT110: 0.0035738763 | CU110: 0.0043084664 | CV110: 0.0014038965 | CW110: 0.0013497121 | CX110: 0.00075013447 | CY110: 0.00309394 | CZ110: 0.0031324902 | DA110: 0.002947105 | DB110: 0.0015404434 | DC110: 0.011998011 | DD110: 0.040337576 | DE110: 0.015747031 | DF110: 0.045374811 | DG110: 0.00073383492 | DH110: 402.07239 | DI110: 155.18592 | DJ110: 22.792667 | DK110: 0 | DL110: 89536.443 | DM110: 15654.264 | DN110: 883.28267 | DO110: 0
A111: RoW | B111: Sector | C111: Other Services | D111: 2.8699733e-05 | E111: 2.7622125e-05 | F111: 1.1110183e-05 | G111: 5.4057588e-05 | H111: 3.2335933e-05 | I111: 5.1814584e-05 | J111: 4.9190535e-05 | K111: 3.5829033e-05 | L111: 2.4021619e-05 | M111: 4.1046638e-05 | N111: 2.6864389e-05 | O111: 3.5242196e-05 | P111: 3.1169329e-05 | Q111: 5.7497684e-05 | R111: 2.8143777e-05 | S111: 3.1039413e-05 | T111: 4.4727855e-05 | U111: 7.0369018e-05 | V111: 6.5939993e-05 | W111: 2.1095149e-05 | X111: 2.0567131e-05 | Y111: 1.9636303e-05 | Z111: 3.9095577e-05 | AA111: 2.1074219e-05 | AB111: 2.1505868e-05 | AC111: 0.0008963375 | AD111: 2.1000858e-05 | AE111: 1.6463258e-05 | AF111: 2.4281988e-05 | AG111: 1.8895306e-05 | AH111: 1.5934251e-05 | AI111: 1.3231073e-05 | AJ111: 1.2259452e-05 | AK111: 2.7100295e-05 | AL111: 1.8473217e-05 | AM111: 1.4127515e-05 | AN111: 1.1820501e-05 | AO111: 1.1520682e-05 | AP111: 1.5928825e-05 | AQ111: 2.2307239e-05 | AR111: 3.3123882e-05 | AS111: 4.0353944e-05 | AT111: 3.5312928e-05 | AU111: 4.9034658e-05 | AV111: 3.5061939e-05 | AW111: 3.878409e-05 | AX111: 2.1476515e-05 | AY111: 1.4673461e-05 | AZ111: 3.421674e-05 | BA111: 6.7165693e-05 | BB111: 8.1567324e-05 | BC111: 5.5060401e-05 | BD111: 3.7904558e-05 | BE111: 0.00053274807 | BF111: 0.0023126489 | BG111: 0.00091396341 | BH111: 0.002604307 | BI111: 0.0021448864 | BJ111: 0.0018444442 | BK111: 0.0020357449 | BL111: 0.000940665 | BM111: 0.0020574028 | BN111: 0.0026236427 | BO111: 0.0018009711 | BP111: 0.0025746538 | BQ111: 0.0020269613 | BR111: 0.001592979 | BS111: 0.0010521759 | BT111: 0.0022861861 | BU111: 0.00057314172 | BV111: 0.00055367771 | BW111: 0.00083730171 | BX111: 0.0021713921 | BY111: 0.0016176915 | BZ111: 0.0013279077 | CA111: 0.00014655446 | CB111: 0.0046406793 | CC111: 0.002659902 | CD111: 0.0058476702 | CE111: 0.0023020092 | CF111: 0.0022483936 | CG111: 0.0016164343 | CH111: 0.001612074 | CI111: 0.0016314903 | CJ111: 0.0069314859 | CK111: 0.0052815087 | CL111: 0.00072592287 | CM111: 0.0021065534 | CN111: 0.0030001319 | CO111: 0.0021206099 | CP111: 0.00016235225 | CQ111: 0.0012344927 | CR111: 0.0031395578 | CS111: 0.00096549862 | CT111: 0.0043559713 | CU111: 0.0058015751 | CV111: 0.00376295 | CW111: 0.0060657857 | CX111: 0.0037236267 | CY111: 0.012330017 | CZ111: 0.0028037404 | DA111: 0.005874691 | DB111: 0.0080268192 | DC111: 0.010238551 | DD111: 0.0033793082 | DE111: 0.0071664486 | DF111: 0.0018692222 | DG111: 0.021803695 | DH111: 1446.9049 | DI111: 187.11879 | DJ111: 38.851352 | DK111: 0 | DL111: 990690.34 | DM111: 19520.955 | DN111: 8498.4239 | DO111: 0
A112: - | B112: Factor of production | C112: Indirect Taxes | D112: 0.00076346401 | E112: 0.011551448 | F112: 0.015460877 | G112: 0.044933201 | H112: 0.0056747159 | I112: 0.034242393 | J112: 0.031543996 | K112: 0.034531404 | L112: 0.067220985 | M112: 0.03840436 | N112: 0.021057611 | O112: 0.02834519 | P112: 0.036383023 | Q112: 0.028008302 | R112: 0.022360055 | S112: 0.058512624 | T112: 0.042666584 | U112: 0.02280902 | V112: 0.024956776 | W112: 0.027658971 | X112: 0.024054396 | Y112: 0.02104046 | Z112: 0.027584754 | AA112: 0.026736514 | AB112: 0.019298591 | AC112: 0.020575569 | AD112: 0.019955662 | AE112: 0.018618028 | AF112: 0.023746866 | AG112: 0.028566802 | AH112: 0.040258852 | AI112: 0.032803349 | AJ112: 0.051295629 | AK112: 0.045060807 | AL112: 0.042969001 | AM112: 0.022842179 | AN112: 0.014181312 | AO112: 0.04777436 | AP112: 0.06536104 | AQ112: 0.038233109 | AR112: 0.045629765 | AS112: 0.040726558 | AT112: 0.028718779 | AU112: 0.063163426 | AV112: 0.028609739 | AW112: 0.011223995 | AX112: 0.025045427 | AY112: 0.015169911 | AZ112: 0.02511193 | BA112: 0.026703379 | BB112: 0.030799389 | BC112: 0.034272409 | BD112: 0.031956705 | BE112: 0.019690215 | BF112: 0.041971417 | BG112: 0.022942133 | BH112: 0.066500686 | BI112: 0.011322194 | BJ112: 0.11408363 | BK112: 0.052792212 | BL112: 0.034062092 | BM112: 0.053720854 | BN112: 0.12076889 | BO112: 0.058794971 | BP112: 0.052613269 | BQ112: 0.035097328 | BR112: 0.056093213 | BS112: 0.027513056 | BT112: 0.047578904 | BU112: 0.10552614 | BV112: 0.034503409 | BW112: 0.030239535 | BX112: 0.044802197 | BY112: 0.033772337 | BZ112: 0.055461174 | CA112: 0.033570172 | CB112: 0.054301428 | CC112: 0.048741999 | CD112: 0.02787945 | CE112: 0.060347108 | CF112: 0.017620141 | CG112: 0.044589734 | CH112: 0.049242405 | CI112: -0.024406255 | CJ112: 0.06386321 | CK112: 0.042738701 | CL112: 0.094705684 | CM112: 0.041743054 | CN112: 0.056042187 | CO112: 0.04738665 | CP112: 0.0095617377 | CQ112: 0.074934629 | CR112: 0.093815809 | CS112: 0.058855394 | CT112: 0.089048116 | CU112: 0.059879082 | CV112: 0.035782426 | CW112: 0.10032672 | CX112: 0.040242523 | CY112: 0.018670704 | CZ112: 0.018054396 | DA112: 0.024748497 | DB112: 0.028792558 | DC112: 0.037813519 | DD112: 0.025906408 | DE112: 0.02596547 | DF112: 0.030481898 | DG112: 0.031632679 | DH112: 0 | DI112: 0 | DJ112: 0 | DK112: 0 | DL112: 0 | DM112: 0 | DN112: 0 | DO112: 0
A113: - | B113: Factor of production | C113: Wages | D113: 0.1211053 | E113: 0.080669272 | F113: 0.14539874 | G113: 0.18807704 | H113: 0.22864142 | I113: 0.18317787 | J113: 0.16507052 | K113: 0.1299739 | L113: 0.15555144 | M113: 0.23513673 | N113: 0.18701907 | O113: 0.2228405 | P113: 0.14799793 | Q113: 0.1217063 | R113: 0.2098286 | S113: 0.030749391 | T113: 0.19970374 | U113: 0.16127094 | V113: 0.077632919 | W113: 0.19006956 | X113: 0.17116753 | Y113: 0.24029018 | Z113: 0.23949162 | AA113: 0.1987616 | AB113: 0.19517803 | AC113: 0.12592816 | AD113: 0.1206668 | AE113: 0.23135776 | AF113: 0.27722266 | AG113: 0.20232016 | AH113: 0.10521409 | AI113: 0.077203366 | AJ113: 0.059969361 | AK113: 0.1859994 | AL113: 0.15930136 | AM113: 0.23563414 | AN113: 0.48442709 | AO113: 0.49814435 | AP113: 0.21889995 | AQ113: 0.39992865 | AR113: 0.35636139 | AS113: 0.28168794 | AT113: 0.30009204 | AU113: 0.041444142 | AV113: 0.088744307 | AW113: 0.42599282 | AX113: 0.49624721 | AY113: 0.69001191 | AZ113: 0.52094704 | BA113: 0.204691 | BB113: 0.21321856 | BC113: 0.21066373 | BD113: 0.2480061 | BE113: 0.49003008 | BF113: 0.31580346 | BG113: 0.22578619 | BH113: 0.34170174 | BI113: 0.64327669 | BJ113: 0.11311798 | BK113: 0.1875374 | BL113: 0.089471486 | BM113: 0.11419499 | BN113: 0.066328275 | BO113: 0.15104881 | BP113: 0.14243726 | BQ113: 0.24820336 | BR113: 0.10541524 | BS113: 0.28651964 | BT113: 0.19355516 | BU113: 0.037374318 | BV113: 0.084638632 | BW113: 0.19125828 | BX113: 0.072403016 | BY113: 0.19628025 | BZ113: 0.1047566 | CA113: 0.29168275 | CB113: 0.14072719 | CC113: 0.14357463 | CD113: 0.15591897 | CE113: 0.082934293 | CF113: 0.089304581 | CG113: 0.16514201 | CH113: 0.16823599 | CI113: 0.25232015 | CJ113: 0.18416727 | CK113: 0.11221038 | CL113: 0.099119815 | CM113: 0.14764993 | CN113: 0.12718498 | CO113: 0.23650558 | CP113: 0.40679382 | CQ113: 0.57030458 | CR113: 0.16814612 | CS113: 0.41271077 | CT113: 0.38512293 | CU113: 0.30145398 | CV113: 0.32312948 | CW113: 0.044202095 | CX113: 0.10194284 | CY113: 0.46694008 | CZ113: 0.47525775 | DA113: 0.60506628 | DB113: 0.29171248 | DC113: 0.31026318 | DD113: 0.24425583 | DE113: 0.33682133 | DF113: 0.3770125 | DG113: 0.37958916 | DH113: 0 | DI113: 0 | DJ113: 0 | DK113: 0 | DL113: 0 | DM113: 0 | DN113: 0 | DO113: 0
A114: - | B114: Factor of production | C114: Operating surplus: Consumption of fixed capital | D114: 0.13474656 | E114: 0.11793363 | F114: 0.066031346 | G114: 0.083755819 | H114: 0.10346613 | I114: 0.084015021 | J114: 0.029170289 | K114: 0.043591374 | L114: 0.068243931 | M114: 0.040811154 | N114: 0.044719733 | O114: 0.040839759 | P114: 0.061622945 | Q114: 0.089235282 | R114: 0.044111156 | S114: 0.017881931 | T114: 0.056447611 | U114: 0.057637221 | V114: 0.027844903 | W114: 0.042415321 | X114: 0.063609567 | Y114: 0.078441558 | Z114: 0.058521073 | AA114: 0.052339335 | AB114: 0.051072535 | AC114: 0.040826065 | AD114: 0.047948953 | AE114: 0.043192999 | AF114: 0.045906143 | AG114: 0.028281985 | AH114: 0.13300123 | AI114: 0.33448046 | AJ114: 0.16272258 | AK114: 0.053500837 | AL114: 0.16703927 | AM114: 0.044940318 | AN114: 0.039474552 | AO114: 0.075981968 | AP114: 0.024530782 | AQ114: 0.061655233 | AR114: 0.087357836 | AS114: 0.10357416 | AT114: 0.064611199 | AU114: 0.28031869 | AV114: 0.37399651 | AW114: 0.072076431 | AX114: 0.14381269 | AY114: 0.079769711 | AZ114: 0.063833002 | BA114: 0.17962502 | BB114: 0.15566243 | BC114: 0.14603193 | BD114: 0.11755749 | BE114: 0.039496567 | BF114: 0.070535789 | BG114: 0.059250941 | BH114: 0.033070177 | BI114: 0.033594056 | BJ114: 0.092466681 | BK114: 0.092042809 | BL114: 0.016740822 | BM114: 0.025755177 | BN114: 0.14544512 | BO114: 0.035947409 | BP114: 0.031796195 | BQ114: 0.036553044 | BR114: 0.046577661 | BS114: 0.051714058 | BT114: 0.051104715 | BU114: 0.040038798 | BV114: 0.044299144 | BW114: 0.076460097 | BX114: 0.051301225 | BY114: 0.043948308 | BZ114: 0.049093393 | CA114: 0.061663367 | CB114: 0.04792804 | CC114: 0.052551111 | CD114: 0.029024956 | CE114: 0.050987869 | CF114: 0.076109313 | CG114: 0.05129126 | CH114: 0.049307625 | CI114: 0.091152741 | CJ114: 0.16466834 | CK114: 0.44077939 | CL114: 0.11712201 | CM114: 0.13725602 | CN114: 0.1912467 | CO114: 0.060389268 | CP114: 0.060107635 | CQ114: 0.10461702 | CR114: 0.037231583 | CS114: 0.080633627 | CT114: 0.082074727 | CU114: 0.083927948 | CV114: 0.089555364 | CW114: 0.25337925 | CX114: 0.31231832 | CY114: 0.048085896 | CZ114: 0.11639754 | DA114: 0.079537874 | DB114: 0.058686264 | DC114: 0.079273511 | DD114: 0.12409183 | DE114: 0.15365837 | DF114: 0.17533879 | DG114: 0.045694989 | DH114: 0 | DI114: 0 | DJ114: 0 | DK114: 0 | DL114: 0 | DM114: 0 | DN114: 0 | DO114: 0
A115: - | B115: Factor of production | C115: Operation Surplus | D115: 0.348185 | E115: 0.18112768 | F115: 0.30998165 | G115: 0.20725485 | H115: 0.19980341 | I115: 0.15679062 | J115: 0.065157573 | K115: 0.098960918 | L115: 0.21360241 | M115: 0.066396171 | N115: 0.071722623 | O115: 0.085018212 | P115: 0.053107889 | Q115: 0.070155958 | R115: 0.10796538 | S115: 0.032422102 | T115: 0.13229754 | U115: 0.17836248 | V115: 0.11138029 | W115: 0.064571463 | X115: 0.081999273 | Y115: 0.11641116 | Z115: 0.069507842 | AA115: 0.061622643 | AB115: 0.055699406 | AC115: 0.023044405 | AD115: 0.038469322 | AE115: 0.075993729 | AF115: 0.098609765 | AG115: 0.10110787 | AH115: 0.12443677 | AI115: 0.1639975 | AJ115: 0.15155475 | AK115: 0.11896775 | AL115: 0.10781456 | AM115: 0.099472078 | AN115: 0.30884987 | AO115: 0.1300676 | AP115: 0.25954266 | AQ115: 0.20149201 | AR115: 0.19734394 | AS115: 0.079152235 | AT115: 0.14138444 | AU115: 0.40431829 | AV115: 0.079858609 | AW115: 0.012906129 | AX115: 0.0067992407 | AY115: 0.028331191 | AZ115: 0.11719214 | BA115: 0.053272834 | BB115: 0.062965977 | BC115: 0.079636341 | BD115: 0.092518726 | BE115: 0.15308346 | BF115: 0.21319186 | BG115: 0.11666762 | BH115: 0.25173639 | BI115: 0.11174628 | BJ115: 0.33795997 | BK115: 0.16173739 | BL115: 0.0554175 | BM115: 0.073616504 | BN115: 0.15876969 | BO115: 0.044853415 | BP115: 0.072357315 | BQ115: 0.1077358 | BR115: 0.046482983 | BS115: 0.051947968 | BT115: 0.080689536 | BU115: 0.036539858 | BV115: 0.05214895 | BW115: 0.10002834 | BX115: 0.073256537 | BY115: 0.03803233 | BZ115: 0.095287381 | CA115: 0.08242652 | CB115: 0.064401526 | CC115: 0.06765014 | CD115: 0.042008089 | CE115: 0.048006456 | CF115: 0.099029577 | CG115: 0.04650251 | CH115: 0.11895864 | CI115: 0.098587953 | CJ115: 0.032818168 | CK115: 0.082301142 | CL115: 0.062085139 | CM115: 0.10683631 | CN115: 0.17620616 | CO115: 0.049731186 | CP115: 0.4545925 | CQ115: 0.097773947 | CR115: 0.19675263 | CS115: 0.24518364 | CT115: 0.12743302 | CU115: 0.086411481 | CV115: 0.13872125 | CW115: 0.33191681 | CX115: 0.087531873 | CY115: -0.0071741258 | CZ115: 0.0054595169 | DA115: 0.010862054 | DB115: 0.088646629 | DC115: 0.0093777774 | DD115: 0.067619039 | DE115: 0.065425439 | DF115: 0.078230095 | DG115: 0.063219953 | DH115: 0 | DI115: 0 | DJ115: 0 | DK115: 0 | DL115: 0 | DM115: 0 | DN115: 0 | DO115: 0
A116: - | B116: Satellite account | C116: Employment male | D116: 0.017633678 | E116: 0.011948831 | F116: 0.011321312 | G116: 0.02271532 | H116: 0.0064521651 | I116: 0.0034416136 | J116: 0.0028468145 | K116: 0.002416609 | L116: 0.0021494471 | M116: 0.0027577583 | N116: 0.0060096843 | O116: 0.0058477018 | P116: 0.0046408463 | Q116: 0.0026009565 | R116: 0.0027437762 | S116: 0.00044722093 | T116: 0.0018182315 | U116: 0.0015558779 | V116: 0.0057432946 | W116: 0.0031991597 | X116: 0.0040856392 | Y116: 0.0050041567 | Z116: 0.0052115821 | AA116: 0.0043539716 | AB116: 0.0040077082 | AC116: 0.0025074707 | AD116: 0.0025801932 | AE116: 0.0034631639 | AF116: 0.0085342723 | AG116: 0.0035087222 | AH116: 0.0015689784 | AI116: 0.001044042 | AJ116: 0.00086669516 | AK116: 0.0023068681 | AL116: 0.0035206165 | AM116: 0.0077013001 | AN116: 0.013120812 | AO116: 0.0084242018 | AP116: 0.009697508 | AQ116: 0.010524952 | AR116: 0.0047806123 | AS116: 0.0045835027 | AT116: 0.0044254094 | AU116: 0.00050906648 | AV116: 0.0012188126 | AW116: 0.0094796633 | AX116: 0.0073050129 | AY116: 0.005802074 | AZ116: 0.0038941515 | BA116: 0.0046570268 | BB116: 0.0050798368 | BC116: 0.0063535975 | BD116: 0.0071721855 | BE116: 0.0046667908 | BF116: 0.21584505 | BG116: 0.14998406 | BH116: 0.13790025 | BI116: 0.38636502 | BJ116: 0.016210053 | BK116: 0.030086211 | BL116: 0.0079156961 | BM116: 0.0088068313 | BN116: 0.0041061846 | BO116: 0.014795198 | BP116: 0.019539922 | BQ116: 0.015059506 | BR116: 0.014970042 | BS116: 0.0044912275 | BT116: 0.014852345 | BU116: 0.0049957808 | BV116: 0.0088327044 | BW116: 0.0022126363 | BX116: 0.0061130365 | BY116: 0.024743723 | BZ116: 0.011863548 | CA116: 0.012216441 | CB116: 0.019534466 | CC116: 0.017618477 | CD116: 0.0029907261 | CE116: 0.012602518 | CF116: 0.0029575175 | CG116: 0.015711237 | CH116: 0.020422022 | CI116: 0.026087151 | CJ116: 0.013011412 | CK116: 0.011078845 | CL116: 0.0070155528 | CM116: 0.018704072 | CN116: 0.018503141 | CO116: 0.02398188 | CP116: 0.014014347 | CQ116: 0.021799398 | CR116: 0.014752469 | CS116: 0.031323026 | CT116: 0.015710463 | CU116: 0.02340044 | CV116: 0.0084362814 | CW116: 0.0013255676 | CX116: 0.0024050244 | CY116: 0.023658293 | CZ116: 0.016528012 | DA116: 0.024273369 | DB116: 0.0082716781 | DC116: 0.0064274917 | DD116: 0.0056812744 | DE116: 0.046240663 | DF116: 0.008915937 | DG116: 0.018360508 | DH116: 0 | DI116: 0 | DJ116: 0 | DK116: 0 | DL116: 0 | DM116: 0 | DN116: 0 | DO116: 0
A117: - | B117: Satellite account | C117: Employment female | D117: 0.010738629 | E117: 0.0074100292 | F117: 0.0062797225 | G117: 0.012422368 | H117: 0.00086723963 | I117: 0.00047990936 | J117: 0.0025249077 | K117: 0.0019284411 | L117: 0.0018988142 | M117: 0.006609221 | N117: 0.0014796378 | O117: 0.0013340139 | P117: 0.0023168794 | Q117: 0.00085635488 | R117: 0.0016786566 | S117: 0.00017121837 | T117: 0.00071271428 | U117: 0.00067849236 | V117: 0.0031726456 | W117: 0.0013909287 | X117: 0.0014111325 | Y117: 0.0016004917 | Z117: 0.0015897709 | AA117: 0.0013874353 | AB117: 0.00097378039 | AC117: 0.00042084468 | AD117: 0.00035637865 | AE117: 0.0010452 | AF117: 0.0042042888 | AG117: 0.0014173085 | AH117: 0.00044782368 | AI117: 0.0002883684 | AJ117: 0.0002500236 | AK117: 0.00065608532 | AL117: 0.00092336059 | AM117: 0.00075343725 | AN117: 0.0015462662 | AO117: 0.0080821457 | AP117: 0.0092470668 | AQ117: 0.010501395 | AR117: 0.0055774639 | AS117: 0.0013030531 | AT117: 0.0039762299 | AU117: 0.00053353058 | AV117: 0.0013393192 | AW117: 0.0086134563 | AX117: 0.0061202598 | AY117: 0.014290437 | AZ117: 0.013839331 | BA117: 0.0011177471 | BB117: 0.0012681231 | BC117: 0.0016779962 | BD117: 0.0018185554 | BE117: 0.014310982 | BF117: 0.11303084 | BG117: 0.077004114 | BH117: 0.075642596 | BI117: 0.16068879 | BJ117: 0.005324451 | BK117: 0.011052076 | BL117: 0.0043064674 | BM117: 0.0046988859 | BN117: 0.0080943584 | BO117: 0.01186886 | BP117: 0.003787196 | BQ117: 0.002296414 | BR117: 0.0044510366 | BS117: 0.0012251053 | BT117: 0.0056451007 | BU117: 0.00047855027 | BV117: 0.0030408026 | BW117: 0.00049747236 | BX117: 0.001563768 | BY117: 0.010010009 | BZ117: 0.0029557976 | CA117: 0.0017893836 | CB117: 0.0044508177 | CC117: 0.0035721588 | CD117: 0.0007568575 | CE117: 0.0010701677 | CF117: 0.00035117499 | CG117: 0.0051397526 | CH117: 0.006057662 | CI117: 0.011744705 | CJ117: 0.0023517896 | CK117: 0.0021301679 | CL117: 0.0010584223 | CM117: 0.0027088382 | CN117: 0.0029803528 | CO117: 0.0027086998 | CP117: 0.0017422532 | CQ117: 0.018252924 | CR117: 0.012615408 | CS117: 0.026711722 | CT117: 0.014718815 | CU117: 0.0039304486 | CV117: 0.0049704957 | CW117: 0.00085251596 | CX117: 0.0016508603 | CY117: 0.014514545 | CZ117: 0.0082133651 | DA117: 0.028067374 | DB117: 0.014542275 | DC117: 0.0014223846 | DD117: 0.0013226156 | DE117: 0.0035223507 | DF117: 0.0027226206 | DG117: 0.021712666 | DH117: 0 | DI117: 0 | DJ117: 0 | DK117: 0 | DL117: 0 | DM117: 0 | DN117: 0 | DO117: 0
A118: - | B118: Satellite account | C118: Employment hours male | D118: 0.03520586 | E118: 0.023934727 | F118: 0.023030467 | G118: 0.044698849 | H118: 0.013240672 | I118: 0.0068149572 | J118: 0.0050778249 | K118: 0.0045357931 | L118: 0.0038953213 | M118: 0.0054189929 | N118: 0.011584397 | O118: 0.011207277 | P118: 0.0082376329 | Q118: 0.0048879535 | R118: 0.0051325396 | S118: 0.0008788904 | T118: 0.0030910538 | U118: 0.0029383992 | V118: 0.011087593 | W118: 0.0055777356 | X118: 0.007683888 | Y118: 0.0093954097 | Z118: 0.0098749804 | AA118: 0.008313297 | AB118: 0.0076651354 | AC118: 0.0045733635 | AD118: 0.0048434468 | AE118: 0.0062425975 | AF118: 0.015379465 | AG118: 0.006208985 | AH118: 0.0030041441 | AI118: 0.0020076487 | AJ118: 0.0016294844 | AK118: 0.0041791466 | AL118: 0.0068574618 | AM118: 0.01506684 | AN118: 0.024012585 | AO118: 0.015473257 | AP118: 0.016983502 | AQ118: 0.018778348 | AR118: 0.0080626459 | AS118: 0.0087660393 | AT118: 0.0075318957 | AU118: 0.00081417704 | AV118: 0.0019791247 | AW118: 0.017636808 | AX118: 0.012629713 | AY118: 0.008676413 | AZ118: 0.0062492002 | BA118: 0.0081671176 | BB118: 0.0092064152 | BC118: 0.012173466 | BD118: 0.013983443 | BE118: 0.0080848897 | BF118: 0.44380046 | BG118: 0.31013243 | BH118: 0.27329076 | BI118: 0.76158004 | BJ118: 0.037586825 | BK118: 0.069333266 | BL118: 0.018054902 | BM118: 0.020310209 | BN118: 0.0093643554 | BO118: 0.035472072 | BP118: 0.044476951 | BQ118: 0.033579403 | BR118: 0.032811491 | BS118: 0.0094472045 | BT118: 0.034425296 | BU118: 0.011853797 | BV118: 0.019198746 | BW118: 0.0047152839 | BX118: 0.014229999 | BY118: 0.058287858 | BZ118: 0.028163483 | CA118: 0.027101574 | CB118: 0.046418279 | CC118: 0.041437452 | CD118: 0.0064237758 | CE118: 0.029766018 | CF118: 0.0068068169 | CG118: 0.036342777 | CH118: 0.046287204 | CI118: 0.062601736 | CJ118: 0.028884361 | CK118: 0.025168831 | CL118: 0.015450123 | CM118: 0.041930787 | CN118: 0.042219991 | CO118: 0.055479469 | CP118: 0.029216502 | CQ118: 0.051588664 | CR118: 0.034793459 | CS118: 0.070900169 | CT118: 0.036316523 | CU118: 0.053714815 | CV118: 0.018632599 | CW118: 0.0026598039 | CX118: 0.0052064753 | CY118: 0.050149479 | CZ118: 0.03757045 | DA118: 0.051552651 | DB118: 0.018387623 | DC118: 0.013718684 | DD118: 0.011594187 | DE118: 0.11059579 | DF118: 0.018470038 | DG118: 0.0410542 | DH118: 0 | DI118: 0 | DJ118: 0 | DK118: 0 | DL118: 0 | DM118: 0 | DN118: 0 | DO118: 0
A119: - | B119: Satellite account | C119: Employment hours female | D119: 0.020971609 | E119: 0.014490496 | F119: 0.012286924 | G119: 0.023307994 | H119: 0.0017751321 | I119: 0.00094766899 | J119: 0.0044401952 | K119: 0.0036109054 | L119: 0.003492922 | M119: 0.013385529 | N119: 0.0028701012 | O119: 0.0025482903 | P119: 0.0042936156 | Q119: 0.0016324133 | R119: 0.0031212852 | S119: 0.00034444381 | T119: 0.0012176076 | U119: 0.0012986069 | V119: 0.0061430975 | W119: 0.0024581996 | X119: 0.0026605231 | Y119: 0.0030055639 | Z119: 0.0029938913 | AA119: 0.0026636429 | AB119: 0.0018287711 | AC119: 0.00077229357 | AD119: 0.00065781592 | AE119: 0.0019140083 | AF119: 0.0076370643 | AG119: 0.0026067288 | AH119: 0.00085094178 | AI119: 0.00054724876 | AJ119: 0.0004658413 | AK119: 0.0011685142 | AL119: 0.0018035796 | AM119: 0.0014353296 | AN119: 0.0027694219 | AO119: 0.014754228 | AP119: 0.016126186 | AQ119: 0.01869041 | AR119: 0.0095542479 | AS119: 0.002437006 | AT119: 0.0067159755 | AU119: 0.00085100933 | AV119: 0.0021824748 | AW119: 0.016110071 | AX119: 0.010435614 | AY119: 0.021848313 | AZ119: 0.022228269 | BA119: 0.0019506946 | BB119: 0.0022953905 | BC119: 0.0032424405 | BD119: 0.003561714 | BE119: 0.02214817 | BF119: 0.22874394 | BG119: 0.15677956 | BH119: 0.14767432 | BI119: 0.33163133 | BJ119: 0.012276419 | BK119: 0.025548486 | BL119: 0.009718254 | BM119: 0.010708346 | BN119: 0.018762694 | BO119: 0.028009282 | BP119: 0.0085647088 | BQ119: 0.0051194014 | BR119: 0.0099285193 | BS119: 0.0026109104 | BT119: 0.012860876 | BU119: 0.0011004102 | BV119: 0.0066229562 | BW119: 0.0010613773 | BX119: 0.0035306577 | BY119: 0.02355452 | BZ119: 0.0069967514 | CA119: 0.0039106979 | CB119: 0.010542786 | CC119: 0.0082699539 | CD119: 0.001628776 | CE119: 0.0024896652 | CF119: 0.00081043802 | CG119: 0.011930957 | CH119: 0.013326611 | CI119: 0.027463006 | CJ119: 0.0050588176 | CK119: 0.0047677183 | CL119: 0.002224409 | CM119: 0.005865199 | CN119: 0.0066382845 | CO119: 0.0063076162 | CP119: 0.0036321659 | CQ119: 0.042463946 | CR119: 0.028867273 | CS119: 0.059490375 | CT119: 0.032804232 | CU119: 0.0088136184 | CV119: 0.010545026 | CW119: 0.0015983259 | CX119: 0.0034564939 | CY119: 0.029916917 | CZ119: 0.0182021 | DA119: 0.054354915 | DB119: 0.030303323 | DC119: 0.0029893913 | DD119: 0.0026467101 | DE119: 0.0082519956 | DF119: 0.0055884226 | DG119: 0.044673864 | DH119: 0 | DI119: 0 | DJ119: 0 | DK119: 0 | DL119: 0 | DM119: 0 | DN119: 0 | DO119: 0
A120: - | B120: Satellite account | C120: Employment: Vulnerable employment | D120: 0.020882063 | E120: 0.014834701 | F120: 0.011591428 | G120: 0.023285022 | H120: 0.00011757537 | I120: 0.00017505849 | J120: 0.00035721132 | K120: 0.00036298337 | L120: 0.00033404008 | M120: 0.00080668671 | N120: 0.00079219652 | O120: 0.00070234665 | P120: 0.00025750573 | Q120: 0.00029789442 | R120: 0.00038684031 | S120: 4.7138834e-05 | T120: 0.00010587179 | U120: 0.00013175467 | V120: 0.00068367305 | W120: 0.00019282217 | X120: 0.00041316103 | Y120: 0.00055703737 | Z120: 0.0005838575 | AA120: 0.00042041732 | AB120: 0.00049570074 | AC120: 0.00015088011 | AD120: 0.00022759026 | AE120: 0.00028718672 | AF120: 0.0011669519 | AG120: 0.00044622766 | AH120: 3.2355145e-05 | AI120: 2.675477e-05 | AJ120: 1.4898558e-05 | AK120: 4.907907e-05 | AL120: 0.00012763943 | AM120: 0.0020805707 | AN120: 0.0033127138 | AO120: 0.0036336921 | AP120: 0.0041712517 | AQ120: 0.0040205819 | AR120: 0.0021426512 | AS120: 0.00066966187 | AT120: 0.0013458382 | AU120: 0.00020337275 | AV120: 0.00048038207 | AW120: 0.0054462837 | AX120: 4.0252663e-05 | AY120: 0.00088833946 | AZ120: 0.0015470838 | BA120: 0.00022175131 | BB120: 0.00025194554 | BC120: 0.00035202947 | BD120: 0.00040130228 | BE120: 0.0034955594 | BF120: 0.23443072 | BG120: 0.15317547 | BH120: 0.19180127 | BI120: 0.4439707 | BJ120: 0.0069724555 | BK120: 0.013287828 | BL120: 0.0038053261 | BM120: 0.0047025834 | BN120: 0.0045280696 | BO120: 0.01304501 | BP120: 0.0069020167 | BQ120: 0.0030802431 | BR120: 0.0036312578 | BS120: 0.00051944642 | BT120: 0.0066717632 | BU120: 0.0030051565 | BV120: 0.0026642749 | BW120: 0.00030418624 | BX120: 0.0044433943 | BY120: 0.013319062 | BZ120: 0.0063981442 | CA120: 0.0023874788 | CB120: 0.011311769 | CC120: 0.0098473763 | CD120: 0.00030479306 | CE120: 0.0064070714 | CF120: 0.00052601436 | CG120: 0.0075441577 | CH120: 0.01119084 | CI120: 0.017558014 | CJ120: 0.0040563524 | CK120: 0.0033810454 | CL120: 0.0020859577 | CM120: 0.0060257646 | CN120: 0.0064848014 | CO120: 0.01318563 | CP120: 0.0062005474 | CQ120: 0.019432404 | CR120: 0.014181527 | CS120: 0.025215659 | CT120: 0.015027238 | CU120: 0.012068157 | CV120: 0.003790634 | CW120: 0.0006661621 | CX120: 0.0010167728 | CY120: 0.0092214801 | CZ120: 0.0085871838 | DA120: 0.013891029 | DB120: 0.0064255299 | DC120: 0.0013433582 | DD120: 0.001206194 | DE120: 0.041328572 | DF120: 0.00097473563 | DG120: 0.013858422 | DH120: 0 | DI120: 0 | DJ120: 0 | DK120: 0 | DL120: 0 | DM120: 0 | DN120: 0 | DO120: 0
