Workbook

Sheet global.pars
A1: label | B1: name | C1: value
A2: nPeriods | B2: Time Span of the Simulation | C2: 100
A3: max.iterations | B3: Maximum Number of Algorithm Iterations | C3: 100
A4: tolerance | B4: Tolerance of Algorithm | C4: 1e-06
A5: consistency.threshold | B5: SFC Consistency Threshold | C5: 0.01
A6: shock | B6: Shock Number | C6: 0
A7: t.shock | B7: Time of Shock | C7: 70
A8: rho | B8: Shock Parameter | C8: 0.25
A9: sigma_en | B9: Conversion Rate of Energy Resources into Reserves | C9: 0.003
A10: sigma_mat | B10: Conversion Rate of Matter Resources into Reserves | C10: 0.0005
A11: tcre | B11: Transient Climate Response to Cumulative Carbon Emissions | C11: 0.0001
A12: par_xr | B12: Sensitivity of Z1 Exchange Rate to CAB/YN | C12: 0.15
A13: fnc | B13: Non-CO2 Fraction of Total Anthropocentric Forcing | C13: 0.5

Sheet aggregate.pars
A1: label | B1: name | C1: industry | D1: type | E1: Z1 | F1: Z2
A2: alpha1 | B2: Propensity to Consume out of Wages | C2: aggregate | D2: households | E2: 0.85436972 | F2: 0.85436972
A3: alpha2 | B3: Propensity to Consume out of Profits | C3: aggregate | D3: households | E3: 0.4190559 | F3: 0.4190559
A4: alpha3 | B4: Propensity to Consume out of Wealth | C4: aggregate | D4: households | E4: 0.099375767 | F4: 0.099375767
A5: beta_e | B5: CO2 Intensity | C5: aggregate | D5: ecological | E5: 1 | F5: 1
A6: beta10 | B6: Initial Consumption Share Parameter (Disabled) | C6: aggregate | D6: households | E6: 0.29 | F6: 0.27
A7: beta20 | B7: Initial Consumption Share Parameter (Disabled) | C7: aggregate | D7: households | E7: 0.03 | F7: 0.05
A8: beta30 | B8: Initial Consumption Share Parameter (Disabled) | C8: aggregate | D8: households | E8: 0.68 | F8: 0.68
A9: beta31 | B9: Initial Consumption Share Parameter (Disabled) | C9: aggregate | D9: households | E9: 0 | F9: 0
A10: beta32 | B10: Initial Consumption Share Parameter (Disabled) | C10: aggregate | D10: households | E10: 0 | F10: 0
A11: ce | B11: Circular economy (0 = off; 1 = on) | C11: aggregate | D11: ecological | E11: 0 | F11: 0
A12: delta_g | B12: Government Depreciation Rate of Fixed Capital | C12: aggregate | D12: investment | E12: 0 | F12: 0
A13: g_g | B13: Growth Rate of Government Spending | C13: aggregate | D13: govt.central.bank | E13: 0 | F13: 0
... A58: rep | B58: Repayment Rate of Personal Loans | C58: aggregate | D58: ecological | E58: 0.001 | F58: 0.001

Sheet global.vars
A1: label | B1: variable | C1: name | D1: area | E1: industry | F1: t1
A2: conv_en | B2: conv_en | C2: Global Energy Resources Converted into Reserves | D2: global | E2: aggregate | F2: 0
A3: conv_mat | B3: conv_mat | C3: Global Material Resources Converted into Reserves | D3: global | E3: aggregate | F3: 0
A4: ken | B4: ken | C4: Global Stock of Energy Reserves | D4: global | E4: aggregate | F4: 37000
A5: kmat | B5: kmat | C5: Global Stock of Material Reserves | D5: global | E5: aggregate | F5: 10000000
A6: res_en | B6: res_en | C6: Global Stock of Energy Resources | D6: global | E6: aggregate | F6: 542000
A7: res_mat | B7: res_mat | C7: Global Stock of Material Resources | D7: global | E7: aggregate | F7: 390000000
A8: temp | B8: temp | C8: Atmospheric Temperature | D8: global | E8: aggregate | F8: 0

Sheet aggregate.vars
A1: variable | B1: name | C1: industry | D1: dynamic | E1: type | F1: Z1 | G1: Z2
A2: a_d | B2: Demand for Advances | C2: aggregate | D2: endogenous | E2: commercial.banks | F2: 0 | G2: 0
A3: a_s | B3: Central Bank Advances: Supply | C3: aggregate | D3: endogenous | E3: govt.central.bank | F3: 0 | G3: 0
A4: af | B4: Amortization Funds | C4: aggregate | D4: endogenous | E4: investment | F4: 0 | G4: 0
A5: b_b | B5: Holdings of Bills | C5: aggregate | D5: endogenous | E5: commercial.banks | F5: 0 | G5: 0
A6: b_cb | B6: Central Bank Holdings of Domestic Bills | C6: aggregate | D6: endogenous | E6: govt.central.bank | F6: 0 | G6: 0
A7: b_cb_d_Z2 | B7: Z2 Bills held by Z1 Central Bank | C7: aggregate | D7: endogenous | E7: govt.central.bank | F7: 0 | G7: 0
A8: b_cb_s_Z2 | B8: Supply of Z2 bills to Z1 Central Bank | C8: aggregate | D8: endogenous | E8: govt.central.bank | F8: 0 | G8: 0
A9: b_h_Z1 | B9: Private Demand for Z1 Bills | C9: aggregate | D9: endogenous | E9: portfolio.choices | F9: 0 | G9: 0
A10: b_h_Z2 | B10: Private Demand for Z2 Bills | C10: aggregate | D10: endogenous | E10: portfolio.choices | F10: 0 | G10: 0
A11: b_s | B11: Supply of Government Bills (Government Debt) | C11: aggregate | D11: endogenous | E11: govt.central.bank | F11: 0 | G11: 0
A12: b_s_Z1 | B12: Supply of Z1 Bills to Households | C12: aggregate | D12: endogenous | E12: govt.central.bank | F12: 0 | G12: 0
A13: b_s_Z2 | B13: Supply of Z2 Bills to Households | C13: aggregate | D13: endogenous | E13: govt.central.bank | F13: 0 | G13: 0
... A70: nex | B70: Nominal Exports | C70: aggregate | D70: endogenous | E70: balance.of.payments | F70: 0 | G70: 0
A71: nh | B71: Domestic Employment | C71: aggregate | D71: endogenous | F71: 0 | G71: 0
A72: nimp | B72: Nominal Imports | C72: aggregate | D72: endogenous | E72: balance.of.payments | F72: 0 | G72: 0
A73: or | B73: Quantity of Reserves | C73: aggregate | D73: endogenous | E73: govt.central.bank | F73: 0 | G73: 0
A74: p_or | B74: Price of Reserves | C74: aggregate | D74: endogenous | E74: govt.central.bank | F74: 1 | G74: 1
A75: pa | B75: Average Price of Domestic Consumption | C75: aggregate | D75: endogenous | E75: prices | F75: 0 | G75: 0
A76: pg | B76: Average Price of Government Spending | C76: aggregate | D76: endogenous | E76: prices | F76: 1 | G76: 1
A77: pid | B77: Average Price of Investment | C77: aggregate | D77: endogenous | E77: prices | F77: 1 | G77: 1
A78: pid_g | B78: Average Price of Government Investment | C78: aggregate | D78: endogenous | E78: prices | F78: 1 | G78: 1
A79: pim | B79: Average Price of Imports | C79: aggregate | D79: endogenous | E79: prices | F79: 1 | G79: 1
A80: r_e | B80: Return Rate on Shares | C80: aggregate | D80: endogenous | E80: investment | F80: 0 | G80: 0
A81: r_star | B81: Policy Rate | C81: aggregate | D81: endogenous | E81: portfolio.choices | F81: 0.012115993 | G81: 0.010294681
A82: rb | B82: Interest Rate on Bills | C82: aggregate | D82: endogenous | E82: portfolio.choices | F82: 0.03 | G82: 0.03
A83: rec | B83: Recycled Matter | C83: aggregate | D83: endogenous | E83: ecological | F83: 0 | G83: 0
... A114: yn | B114: Net Income / Value Added | C114: aggregate | D114: endogenous | E114: production | F114: 0 | G114: 0

Sheet industry.vars
A1: variable | B1: name | C1: area | D1: dynamic | E1: type | F1: 1 | G1: 2 | H1: 3 | I1: 4 | J1: 5 | K1: 6 | L1: 7 | M1: 8 | N1: 9 | O1: 10 | P1: 11 | Q1: 12 | R1: 13 | S1: 14 | T1: 15 | U1: 16 | V1: 17 | W1: 18 | X1: 19 | Y1: 20 | Z1: 21 | AA1: 22 | AB1: 23 | AC1: 24 | AD1: 25 | AE1: 26 | AF1: 27 | AG1: 28 | AH1: 29 | AI1: 30 | AJ1: 31 | AK1: 32 | AL1: 33 | AM1: 34 | AN1: 35 | AO1: 36 | AP1: 37 | AQ1: 38 | AR1: 39 | AS1: 40 | AT1: 41 | AU1: 42 | AV1: 43 | AW1: 44 | AX1: 45 | AY1: 46 | AZ1: 47 | BA1: 48 | BB1: 49 | BC1: 50 | BD1: 51 | BE1: 52 | BF1: 53 | BG1: 54
A2: beta_Z1 | B2: Z1 Sector Share of Z1 Household Consumption | C2: Z1 | D2: exogenous | F2: 0.013844114 | G2: 0.0049606998 | H2: 0.0010452624 | I2: 0.0014849907 | J2: 0.00083468405 | K2: 0.00025337025 | L2: 0.037024813 | M2: 0.048241995 | N2: 0.0020218725 | O2: 0.021601267 | P2: 0.0016648753 | Q2: 0.00059674027 | R2: 4.5200922e-05 | S2: 7.7440804e-05 | T2: 0.014650851 | U2: 0.019899025 | V2: 0.0017777596 | W2: 0.00042783189 | X2: 0.0020109559 | Y2: 0.0045585608 | Z2: 3.110773e-05 | AA2: 1.0918521e-05 | AB2: 0.0028902128 | AC2: 0.00016652631 | AD2: 3.6390004e-05 | AE2: 0.00056998673 | AF2: 0.00025391127 | AG2: 0.039918567 | AH2: 0.0098837912 | AI2: 0.0003091554 | AJ2: 0.010761352 | AK2: 0.0019968031 | AL2: 0.014069233 | AM2: 0.0027709507 | AN2: 0.006772066 | AO2: 0.0063176031 | AP2: 5.4340816e-06 | AQ2: 0.029404956 | AR2: 0.0018293271 | AS2: 0.03027168 | AT2: 0.11323634 | AU2: 0.066958243 | AV2: 0.10050478 | AW2: 0.17034441 | AX2: 0.0033514647 | AY2: 0.0028243816 | AZ2: 0.0071925149 | BA2: 0.019960592 | BB2: 0.056676196 | BC2: 0.0041821159 | BD2: 0.0014236024 | BE2: 0.00077081054 | BF2: 0.0013365905 | BG2: 0.048947737
A3: beta_Z1 | B3: Z2 Sector Share of Z1 Household Consumption | C3: Z2 | D3: exogenous | F3: 0.0053695873 | G3: 0.00035778581 | H3: 3.6827721e-05 | I3: 0.0005020375 | J3: 0.00038589593 | K3: 0.00024343078 | L3: 0.0013776092 | M3: 0.0032191939 | N3: 0.00012136804 | O3: 0.0096408917 | P3: 0.00017105312 | Q3: 9.8332967e-06 | R3: 3.6834134e-06 | S3: 1.0205041e-05 | T3: 0.00070997941 | U3: 0.0035727161 | V3: 7.0977218e-05 | W3: 1.083514e-05 | X3: 0.00050027569 | Y3: 0.001303104 | Z3: 4.2597882e-06 | AA3: 3.0147659e-07 | AB3: 0.0005569324 | AC3: 1.0350695e-05 | AD3: 4.3408316e-07 | AE3: 5.8572955e-05 | AF3: 3.6120274e-06 | AG3: 0.0099850309 | AH3: 0.0024643854 | AI3: 7.5894913e-06 | AJ3: 1.6075583e-05 | AK3: 6.2559554e-06 | AL3: 1.2678854e-05 | AM3: 3.8120093e-06 | AN3: 4.6149339e-06 | AO3: 5.2697978e-05 | AP3: 9.56364e-09 | AQ3: 7.7460687e-05 | AR3: 7.0970321e-06 | AS3: 0.00073965363 | AT3: 0.011172376 | AU3: 0.0080519144 | AV3: 0.0027149424 | AW3: 0.0020810878 | AX3: 3.0147695e-05 | AY3: 0.00022582039 | AZ3: 8.0710359e-05 | BA3: 0.00020885709 | BB3: 0.00045204803 | BC3: 2.0205713e-05 | BD3: 1.7691005e-05 | BE3: 1.7814136e-05 | BF3: 6.4196218e-05 | BG3: 0.00023101765
A4: beta_Z2 | B4: Z1 Sector Share of Z2 Household Consumption | C4: Z1 | D4: exogenous | F4: 0.00047120683 | G4: 3.123948e-05 | H4: 1.3568424e-05 | I4: 1.9011147e-05 | J4: 5.9700871e-06 | K4: 1.0062816e-05 | L4: 0.0010405254 | M4: 0.0017562226 | N4: 0.00016543093 | O4: 0.0014625813 | P4: 5.4789564e-05 | Q4: 1.446995e-05 | R4: 1.2639988e-06 | S4: 1.620305e-06 | T4: 0.00048828426 | U4: 0.0010145107 | V4: 3.9426039e-05 | W4: 1.3714443e-05 | X4: 0.001144728 | Y4: 0.00031266761 | Z4: 1.5888578e-05 | AA4: 6.4672171e-06 | AB4: 0.00014399197 | AC4: 8.6948503e-06 | AD4: 1.4264186e-06 | AE4: 2.6854822e-05 | AF4: 1.3299921e-05 | AG4: 0.0052496145 | AH4: 0.00069209807 | AI4: 3.8554875e-06 | AJ4: 5.6719521e-06 | AK4: 8.4277845e-07 | AL4: 6.011987e-06 | AM4: 1.3801019e-06 | AN4: 5.6765911e-06 | AO4: 4.110481e-05 | AP4: 6.4483852e-08 | AQ4: 9.8499665e-05 | AR4: 3.738902e-06 | AS4: 0.00087320199 | AT4: 0.0042842419 | AU4: 0.0017235829 | AV4: 0.0014917297 | AW4: 0.00060799328 | AX4: 2.4411659e-05 | AY4: 4.6879374e-05 | AZ4: 0.00015323595 | BA4: 8.9137497e-05 | BB4: 0.00014701033 | BC4: 1.8687359e-05 | BD4: 8.9404415e-06 | BE4: 6.3541789e-06 | BF4: 1.2011188e-05 | BG4: 0.0016965702
A5: beta_Z2 | B5: Z2 Sector Share of Z2 Household Consumption | C5: Z2 | D5: exogenous | F5: 0.028366619 | G5: 0.0084227703 | H5: 0.0017863055 | I5: 0.0024229466 | J5: 0.0034092804 | K5: 0.00077968937 | L5: 0.032276917 | M5: 0.051350201 | N5: 0.0056670455 | O5: 0.027588875 | P5: 0.00071279641 | Q5: 3.7776582e-05 | R5: 3.7951279e-05 | S5: 9.7647898e-06 | T5: 0.011333779 | U5: 0.01957389 | V5: 0.00016564471 | W5: 9.5928798e-06 | X5: 0.014116134 | Y5: 0.0037441534 | Z5: 0.00046260256 | AA5: 1.9921612e-06 | AB5: 0.0013391091 | AC5: 7.1639826e-05 | AD5: 1.2322953e-06 | AE5: 0.00048728948 | AF5: 1.6042025e-05 | AG5: 0.044449688 | AH5: 0.011366164 | AI5: 6.1120441e-05 | AJ5: 0.0086919324 | AK5: 0.0014362438 | AL5: 0.0072799921 | AM5: 0.0043581816 | AN5: 0.0036062723 | AO5: 0.0021816875 | AP5: 2.0481518e-07 | AQ5: 0.021970661 | AR5: 0.00036796489 | AS5: 0.031697264 | AT5: 0.10728806 | AU5: 0.050279189 | AV5: 0.10394181 | AW5: 0.13208963 | AX5: 0.0087461406 | AY5: 0.0023970646 | AZ5: 0.052331505 | BA5: 0.02976693 | BB5: 0.08626271 | BC5: 0.00075366174 | BD5: 0.00037663915 | BE5: 0.0029711633 | BF5: 0.003776784 | BG5: 0.041788833
A6: d | B6: Final Demand on Z1 Industry | C6: Z1 | D6: endogenous | E6: production | F6: 0 | G6: 0 | H6: 0 | I6: 0 | J6: 0 | K6: 0 | L6: 0 | M6: 0 | N6: 0 | O6: 0 | P6: 0 | Q6: 0 | R6: 0 | S6: 0 | T6: 0 | U6: 0 | V6: 0 | W6: 0 | X6: 0 | Y6: 0 | Z6: 0 | AA6: 0 | AB6: 0 | AC6: 0 | AD6: 0 | AE6: 0 | AF6: 0 | AG6: 0 | AH6: 0 | AI6: 0 | AJ6: 0 | AK6: 0 | AL6: 0 | AM6: 0 | AN6: 0 | AO6: 0 | AP6: 0 | AQ6: 0 | AR6: 0 | AS6: 0 | AT6: 0 | AU6: 0 | AV6: 0 | AW6: 0 | AX6: 0 | AY6: 0 | AZ6: 0 | BA6: 0 | BB6: 0 | BC6: 0 | BD6: 0 | BE6: 0 | BF6: 0 | BG6: 0
A7: d | B7: Final Demand on Z2 Industry | C7: Z2 | D7: endogenous | E7: production | F7: 0 | G7: 0 | H7: 0 | I7: 0 | J7: 0 | K7: 0 | L7: 0 | M7: 0 | N7: 0 | O7: 0 | P7: 0 | Q7: 0 | R7: 0 | S7: 0 | T7: 0 | U7: 0 | V7: 0 | W7: 0 | X7: 0 | Y7: 0 | Z7: 0 | AA7: 0 | AB7: 0 | AC7: 0 | AD7: 0 | AE7: 0 | AF7: 0 | AG7: 0 | AH7: 0 | AI7: 0 | AJ7: 0 | AK7: 0 | AL7: 0 | AM7: 0 | AN7: 0 | AO7: 0 | AP7: 0 | AQ7: 0 | AR7: 0 | AS7: 0 | AT7: 0 | AU7: 0 | AV7: 0 | AW7: 0 | AX7: 0 | AY7: 0 | AZ7: 0 | BA7: 0 | BB7: 0 | BC7: 0 | BD7: 0 | BE7: 0 | BF7: 0 | BG7: 0
A8: dc | B8: Durable Consumption Goods | C8: Z1 | D8: endogenous | E8: ecological | F8: 0 | G8: 0 | H8: 0 | I8: 0 | J8: 0 | K8: 0 | L8: 0 | M8: 0 | N8: 0 | O8: 0 | P8: 0 | Q8: 0 | R8: 0 | S8: 0 | T8: 0 | U8: 0 | V8: 0 | W8: 0 | X8: 0 | Y8: 0 | Z8: 0 | AA8: 0 | AB8: 0 | AC8: 0 | AD8: 0 | AE8: 0 | AF8: 0 | AG8: 0 | AH8: 0 | AI8: 0 | AJ8: 0 | AK8: 0 | AL8: 0 | AM8: 0 | AN8: 0 | AO8: 0 | AP8: 0 | AQ8: 0 | AR8: 0 | AS8: 0 | AT8: 0 | AU8: 0 | AV8: 0 | AW8: 0 | AX8: 0 | AY8: 0 | AZ8: 0 | BA8: 0 | BB8: 0 | BC8: 0 | BD8: 0 | BE8: 0 | BF8: 0 | BG8: 0
A9: dc | B9: Durable Consumption Goods | C9: Z2 | D9: endogenous | E9: ecological | F9: 0 | G9: 0 | H9: 0 | I9: 0 | J9: 0 | K9: 0 | L9: 0 | M9: 0 | N9: 0 | O9: 0 | P9: 0 | Q9: 0 | R9: 0 | S9: 0 | T9: 0 | U9: 0 | V9: 0 | W9: 0 | X9: 0 | Y9: 0 | Z9: 0 | AA9: 0 | AB9: 0 | AC9: 0 | AD9: 0 | AE9: 0 | AF9: 0 | AG9: 0 | AH9: 0 | AI9: 0 | AJ9: 0 | AK9: 0 | AL9: 0 | AM9: 0 | AN9: 0 | AO9: 0 | AP9: 0 | AQ9: 0 | AR9: 0 | AS9: 0 | AT9: 0 | AU9: 0 | AV9: 0 | AW9: 0 | AX9: 0 | AY9: 0 | AZ9: 0 | BA9: 0 | BB9: 0 | BC9: 0 | BD9: 0 | BE9: 0 | BF9: 0 | BG9: 0
A10: emis_j | B10: Annual CO2 Emissions | C10: Z1 | D10: endogenous | E10: ecological | F10: 0 | G10: 0 | H10: 0 | I10: 0 | J10: 0 | K10: 0 | L10: 0 | M10: 0 | N10: 0 | O10: 0 | P10: 0 | Q10: 0 | R10: 0 | S10: 0 | T10: 0 | U10: 0 | V10: 0 | W10: 0 | X10: 0 | Y10: 0 | Z10: 0 | AA10: 0 | AB10: 0 | AC10: 0 | AD10: 0 | AE10: 0 | AF10: 0 | AG10: 0 | AH10: 0 | AI10: 0 | AJ10: 0 | AK10: 0 | AL10: 0 | AM10: 0 | AN10: 0 | AO10: 0 | AP10: 0 | AQ10: 0 | AR10: 0 | AS10: 0 | AT10: 0 | AU10: 0 | AV10: 0 | AW10: 0 | AX10: 0 | AY10: 0 | AZ10: 0 | BA10: 0 | BB10: 0 | BC10: 0 | BD10: 0 | BE10: 0 | BF10: 0 | BG10: 0
A11: emis_j | B11: Annual CO2 Emissions | C11: Z2 | D11: endogenous | E11: ecological | F11: 0 | G11: 0 | H11: 0 | I11: 0 | J11: 0 | K11: 0 | L11: 0 | M11: 0 | N11: 0 | O11: 0 | P11: 0 | Q11: 0 | R11: 0 | S11: 0 | T11: 0 | U11: 0 | V11: 0 | W11: 0 | X11: 0 | Y11: 0 | Z11: 0 | AA11: 0 | AB11: 0 | AC11: 0 | AD11: 0 | AE11: 0 | AF11: 0 | AG11: 0 | AH11: 0 | AI11: 0 | AJ11: 0 | AK11: 0 | AL11: 0 | AM11: 0 | AN11: 0 | AO11: 0 | AP11: 0 | AQ11: 0 | AR11: 0 | AS11: 0 | AT11: 0 | AU11: 0 | AV11: 0 | AW11: 0 | AX11: 0 | AY11: 0 | AZ11: 0 | BA11: 0 | BB11: 0 | BC11: 0 | BD11: 0 | BE11: 0 | BF11: 0 | BG11: 0
A12: eps | B12: Carbon Intensity | C12: Z1 | D12: exogenous | E12: ecological | F12: 568.79952 | G12: 2241.1199 | H12: 200.16538 | I12: 278.73907 | J12: 2570.5896 | K12: 954.53386 | L12: 47.828932 | M12: 58.857689 | N12: 219.03719 | O12: 30.846739 | P12: 55.615115 | Q12: 86.940062 | R12: 298.92455 | S12: 71.864394 | T12: 67.413795 | U12: 410.8344 | V12: 152.1438 | W12: 146.00559 | X12: 285.49063 | Y12: 14.707036 | Z12: 459.48734 | AA12: 600.73566 | AB12: 634.9624 | AC12: 1254.7799 | AD12: 1278.0706 | AE12: 276.54822 | AF12: 429.88479 | AG12: 22.347235 | AH12: 81.301967 | AI12: 1018.9513 | AJ12: 2770.8566 | AK12: 842.56443 | AL12: 95.842341 | AM12: 383.01701 | AN12: 4653.5563 | AO12: 19.816537 | AP12: 4577.1976 | AQ12: 36.193573 | AR12: 59.354604 | AS12: 20.055238 | AT12: 16.59838 | AU12: 320.70869 | AV12: 19.696819 | AW12: 10.775117 | AX12: 23.40054 | AY12: 19.552502 | AZ12: 18.077121 | BA12: 14.810873 | BB12: 15.653615 | BC12: 202.80412 | BD12: 224.77065 | BE12: 1597.0383 | BF12: 5723.6428 | BG12: 18.776869
A13: eps | B13: Carbon Intensity | C13: Z2 | D13: exogenous | E13: ecological | F13: 1072.9098 | G13: 4122.2841 | H13: 147.10102 | I13: 60.623675 | J13: 1676.5572 | K13: 587.05198 | L13: 116.44834 | M13: 71.177611 | N13: 884.45546 | O13: 203.65715 | P13: 469.39627 | Q13: 840.20978 | R13: 394.59968 | S13: 1054.7892 | T13: 190.94983 | U13: 497.86119 | V13: 167.99975 | W13: 7062.9215 | X13: 447.13886 | Y13: 64.927114 | Z13: 307.98563 | AA13: 10228.114 | AB13: 1096.1289 | AC13: 8707.6964 | AD13: 22089.369 | AE13: 730.71414 | AF13: 5690.0866 | AG13: 59.14027 | AH13: 219.00006 | AI13: 1450.4533 | AJ13: 10361.036 | AK13: 937.58928 | AL13: 67.065844 | AM13: 1558.6062 | AN13: 7151.673 | AO13: 34.284489 | AP13: 105260.26 | AQ13: 15.429905 | AR13: 814.27989 | AS13: 31.367964 | AT13: 24.125571 | AU13: 440.55788 | AV13: 21.435832 | AW13: 15.088698 | AX13: 26.277851 | AY13: 54.716356 | AZ13: 32.878902 | BA13: 24.946338 | BB13: 32.361604 | BC13: 974.99487 | BD13: 432.34665 | BE13: 3063.0319 | BF13: 5054.1305 | BG13: 48.2241
A14: eps_en | B14: Energy Intensity of Output | C14: Z1 | D14: exogenous | E14: ecological | F14: 1.0795189 | G14: 0.84171279 | H14: 0.69838011 | I14: 11.430738 | J14: 2.5644837 | K14: 0.11007846 | L14: 202.99842 | M14: 429.43045 | N14: 44975.353 | O14: 2363.6782 | P14: 135.37085 | Q14: 155.17142 | R14: 1495.0467 | S14: 6380.2343 | T14: 1754.7778 | U14: 19991.793 | V14: 124.98121 | W14: 55.192562 | X14: 164.42115 | Y14: 460.13429 | Z14: 6.6541198 | AA14: 8.3022567 | AB14: 9.5655522 | AC14: 7.1024357 | AD14: 11.419636 | AE14: 81.679797 | AF14: 145.92433 | AG14: 114.71345 | AH14: 139.59823 | AI14: 98.137059 | AJ14: 497.60511 | AK14: 912.87867 | AL14: 9.5012852 | AM14: 74.006497 | AN14: 163.8929 | AO14: 6.2210555 | AP14: 648.85456 | AQ14: 6404.9826 | AR14: 2907.8329 | AS14: 9.1647787 | AT14: 914.48335 | AU14: 212.89513 | AV14: 501.06924 | AW14: 460.76816 | AX14: 176.41677 | AY14: 385.75869 | AZ14: 161.61231 | BA14: 4218.749 | BB14: 16667.454 | BC14: 854.0657 | BD14: 63.331661 | BE14: 47.38698 | BF14: 21.053192 | BG14: 1064.8622
A15: eps_en | B15: Energy Intensity of Output | C15: Z2 | D15: exogenous | E15: ecological | F15: 0.86994505 | G15: 0.29310794 | H15: 0.85378678 | I15: 2.86275 | J15: 2.0714802 | K15: 0.15796793 | L15: 61.547055 | M15: 23.188168 | N15: 25251.86 | O15: 1395.6408 | P15: 601.54499 | Q15: 483.45532 | R15: 508.21028 | S15: 32657149 | T15: 1318.2699 | U15: 12957.249 | V15: 4222.2463 | W15: 735690.81 | X15: 433.51415 | Y15: 791.56448 | Z15: 229.27607 | AA15: 1729.687 | AB15: 277.26268 | AC15: 205.20368 | AD15: 4633.4398 | AE15: 973.8169 | AF15: 2189.0839 | AG15: 612.1505 | AH15: 762.78664 | AI15: 642.31257 | AJ15: 10795.767 | AK15: 1222.5407 | AL15: 77.413452 | AM15: 3655.5196 | AN15: 6313.6285 | AO15: 42.434609 | AP15: 1086766.1 | AQ15: 32.761556 | AR15: 84.06961 | AS15: 26.992782 | AT15: 582.5352 | AU15: 412.17135 | AV15: 3673.2441 | AW15: 14532.546 | AX15: 713.66222 | AY15: 319.11877 | AZ15: 446.907 | BA15: 1605.6513 | BB15: 3950.613 | BC15: 4480.246 | BD15: 154.80614 | BE15: 11627.565 | BF15: 80.50502 | BG15: 467.92584
A16: eta | B16: Share of Imports | C16: Z1 | D16: exogenous | F16: 0.053361169 | G16: 0.0040128461 | H16: 0.00054121911 | I16: 0.0047938579 | J16: 0.036005861 | K16: 0.0045647642 | L16: 0.013669046 | M16: 0.031044054 | N16: 0.0011870454 | O16: 0.092624338 | P16: 0.0022825122 | Q16: 0.00012170914 | R16: 0.0003593964 | S16: 0.00019461773 | T16: 0.0075850781 | U16: 0.040618313 | V16: 0.0078289955 | W16: 0.00044133574 | X16: 0.01654476 | Y16: 0.01372378 | Z16: 0.00018136398 | AA16: 9.7300528e-06 | AB16: 0.005591619 | AC16: 0.0001796589 | AD16: 9.4323047e-06 | AE16: 0.0032469058 | AF16: 0.00015764682 | AG16: 0.30873968 | AH16: 0.030705391 | AI16: 0.00023008088 | AJ16: 0.0003310145 | AK16: 0.00011100929 | AL16: 0.00032193851 | AM16: 7.6240896e-05 | AN16: 0.00018960098 | AO16: 0.011737443 | AP16: 2.2686155e-06 | AQ16: 0.0014621435 | AR16: 0.00012939681 | AS16: 0.010631591 | AT16: 0.10722867 | AU16: 0.081741593 | AV16: 0.049787117 | AW16: 0.01986798 | AX16: 0.00031384252 | AY16: 0.006730771 | AZ16: 0.0090160749 | BA16: 0.0058968002 | BB16: 0.0097742202 | BC16: 0.00024748371 | BD16: 0.000224586 | BE16: 0.00022684537 | BF16: 0.00087413577 | BG16: 0.0025210196
A17: eta | B17: Share of Imports | C17: Z2 | D17: exogenous | F17: 0.011073165 | G17: 0.0013767005 | H17: 0.0003512261 | I17: 0.00044243217 | J17: 0.00023002764 | K17: 0.00050166593 | L17: 0.02420308 | M17: 0.040847141 | N17: 0.0038261524 | O17: 0.034878401 | P17: 0.0022715188 | Q17: 0.0005760218 | R17: 6.9257408e-05 | S17: 7.0822798e-05 | T17: 0.012010442 | U17: 0.025221024 | V17: 0.0020280689 | W17: 0.00061880509 | X17: 0.0271086 | Y17: 0.0087650085 | Z17: 0.00043640973 | AA17: 0.00017366827 | AB17: 0.0034816995 | AC17: 0.00033827535 | AD17: 6.2885851e-05 | AE17: 0.0025079803 | AF17: 0.0010465337 | AG17: 0.44013502 | AH17: 0.02120673 | AI17: 0.00017119736 | AJ17: 0.00039348645 | AK17: 6.0468557e-05 | AL17: 0.00046399771 | AM17: 0.00013074707 | AN17: 0.00030476449 | AO17: 0.015842434 | AP17: 2.6720637e-05 | AQ17: 0.0033082327 | AR17: 0.00012223699 | AS17: 0.027802529 | AT17: 0.099807095 | AU17: 0.042793104 | AV17: 0.062712345 | AW17: 0.014896235 | AX17: 0.00064366492 | AY17: 0.0018335276 | AZ17: 0.01305901 | BA17: 0.0037024414 | BB17: 0.0053957368 | BC17: 0.00053709828 | BD17: 0.00036355909 | BE17: 0.00018788474 | BF17: 0.00033648931 | BG17: 0.039246227
A18: eta_en | B18: Shares of Renewable Energy in Total Energy | C18: Z1 | D18: exogenous | F18: 0.14 | G18: 0.14 | H18: 0.14 | I18: 0.14 | J18: 0.14 | K18: 0.14 | L18: 0.14 | M18: 0.14 | N18: 0.14 | O18: 0.14 | P18: 0.14 | Q18: 0.14 | R18: 0.14 | S18: 0.14 | T18: 0.14 | U18: 0.14 | V18: 0.14 | W18: 0.14 | X18: 0.14 | Y18: 0.14 | Z18: 0.14 | AA18: 0.14 | AB18: 0.14 | AC18: 0.14 | AD18: 0.14 | AE18: 0.14 | AF18: 0.14 | AG18: 0.14 | AH18: 0.14 | AI18: 0.14 | AJ18: 0.14 | AK18: 0.14 | AL18: 0.14 | AM18: 0.14 | AN18: 0.14 | AO18: 0.14 | AP18: 0.14 | AQ18: 0.14 | AR18: 0.14 | AS18: 0.14 | AT18: 0.14 | AU18: 0.14 | AV18: 0.14 | AW18: 0.14 | AX18: 0.14 | AY18: 0.14 | AZ18: 0.14 | BA18: 0.14 | BB18: 0.14 | BC18: 0.14 | BD18: 0.14 | BE18: 0.14 | BF18: 0.14 | BG18: 0.14
A19: eta_en | B19: Shares of Renewable Energy in Total Energy | C19: Z2 | D19: exogenous | F19: 0.14 | G19: 0.14 | H19: 0.14 | I19: 0.14 | J19: 0.14 | K19: 0.14 | L19: 0.14 | M19: 0.14 | N19: 0.14 | O19: 0.14 | P19: 0.14 | Q19: 0.14 | R19: 0.14 | S19: 0.14 | T19: 0.14 | U19: 0.14 | V19: 0.14 | W19: 0.14 | X19: 0.14 | Y19: 0.14 | Z19: 0.14 | AA19: 0.14 | AB19: 0.14 | AC19: 0.14 | AD19: 0.14 | AE19: 0.14 | AF19: 0.14 | AG19: 0.14 | AH19: 0.14 | AI19: 0.14 | AJ19: 0.14 | AK19: 0.14 | AL19: 0.14 | AM19: 0.14 | AN19: 0.14 | AO19: 0.14 | AP19: 0.14 | AQ19: 0.14 | AR19: 0.14 | AS19: 0.14 | AT19: 0.14 | AU19: 0.14 | AV19: 0.14 | AW19: 0.14 | AX19: 0.14 | AY19: 0.14 | AZ19: 0.14 | BA19: 0.14 | BB19: 0.14 | BC19: 0.14 | BD19: 0.14 | BE19: 0.14 | BF19: 0.14 | BG19: 0.14
A20: g_pop | B20: Growth Rate of Native Labour Force | C20: Z1 | D20: exogenous | F20: 0 | G20: 0 | H20: 0 | I20: 0 | J20: 0 | K20: 0 | L20: 0 | M20: 0 | N20: 0 | O20: 0 | P20: 0 | Q20: 0 | R20: 0 | S20: 0 | T20: 0 | U20: 0 | V20: 0 | W20: 0 | X20: 0 | Y20: 0 | Z20: 0 | AA20: 0 | AB20: 0 | AC20: 0 | AD20: 0 | AE20: 0 | AF20: 0 | AG20: 0 | AH20: 0 | AI20: 0 | AJ20: 0 | AK20: 0 | AL20: 0 | AM20: 0 | AN20: 0 | AO20: 0 | AP20: 0 | AQ20: 0 | AR20: 0 | AS20: 0 | AT20: 0 | AU20: 0 | AV20: 0 | AW20: 0 | AX20: 0 | AY20: 0 | AZ20: 0 | BA20: 0 | BB20: 0 | BC20: 0 | BD20: 0 | BE20: 0 | BF20: 0 | BG20: 0
A21: g_pop | B21: Growth Rate of Native Labour Force | C21: Z2 | D21: exogenous | F21: 0 | G21: 0 | H21: 0 | I21: 0 | J21: 0 | K21: 0 | L21: 0 | M21: 0 | N21: 0 | O21: 0 | P21: 0 | Q21: 0 | R21: 0 | S21: 0 | T21: 0 | U21: 0 | V21: 0 | W21: 0 | X21: 0 | Y21: 0 | Z21: 0 | AA21: 0 | AB21: 0 | AC21: 0 | AD21: 0 | AE21: 0 | AF21: 0 | AG21: 0 | AH21: 0 | AI21: 0 | AJ21: 0 | AK21: 0 | AL21: 0 | AM21: 0 | AN21: 0 | AO21: 0 | AP21: 0 | AQ21: 0 | AR21: 0 | AS21: 0 | AT21: 0 | AU21: 0 | AV21: 0 | AW21: 0 | AX21: 0 | AY21: 0 | AZ21: 0 | BA21: 0 | BB21: 0 | BC21: 0 | BD21: 0 | BE21: 0 | BF21: 0 | BG21: 0
A22: gamma_imm_0 | B22: Autonomous Immigration from Z1 to Z2 (by industry) | C22: Z1 | D22: exogenous | F22: 0 | G22: 0 | H22: 0 | I22: 0 | J22: 0 | K22: 0 | L22: 0 | M22: 0 | N22: 0 | O22: 0 | P22: 0 | Q22: 0 | R22: 0 | S22: 0 | T22: 0 | U22: 0 | V22: 0 | W22: 0 | X22: 0 | Y22: 0 | Z22: 0 | AA22: 0 | AB22: 0 | AC22: 0 | AD22: 0 | AE22: 0 | AF22: 0 | AG22: 0 | AH22: 0 | AI22: 0 | AJ22: 0 | AK22: 0 | AL22: 0 | AM22: 0 | AN22: 0 | AO22: 0 | AP22: 0 | AQ22: 0 | AR22: 0 | AS22: 0 | AT22: 0 | AU22: 0 | AV22: 0 | AW22: 0 | AX22: 0 | AY22: 0 | AZ22: 0 | BA22: 0 | BB22: 0 | BC22: 0 | BD22: 0 | BE22: 0 | BF22: 0 | BG22: 0
A23: gamma_imm_0 | B23: Autonomous Immigration from Z2 to Z1 (by industry) | C23: Z2 | D23: exogenous | F23: 0 | G23: 0 | H23: 0 | I23: 0 | J23: 0 | K23: 0 | L23: 0 | M23: 0 | N23: 0 | O23: 0 | P23: 0 | Q23: 0 | R23: 0 | S23: 0 | T23: 0 | U23: 0 | V23: 0 | W23: 0 | X23: 0 | Y23: 0 | Z23: 0 | AA23: 0 | AB23: 0 | AC23: 0 | AD23: 0 | AE23: 0 | AF23: 0 | AG23: 0 | AH23: 0 | AI23: 0 | AJ23: 0 | AK23: 0 | AL23: 0 | AM23: 0 | AN23: 0 | AO23: 0 | AP23: 0 | AQ23: 0 | AR23: 0 | AS23: 0 | AT23: 0 | AU23: 0 | AV23: 0 | AW23: 0 | AX23: 0 | AY23: 0 | AZ23: 0 | BA23: 0 | BB23: 0 | BC23: 0 | BD23: 0 | BE23: 0 | BF23: 0 | BG23: 0
A24: gamma_imm_1 | B24: Immigration from Z1 to Z2 (by industry) Depending on Unemployment Rate | C24: Z1 | D24: exogenous | F24: 0 | G24: 0 | H24: 0 | I24: 0 | J24: 0 | K24: 0 | L24: 0 | M24: 0 | N24: 0 | O24: 0 | P24: 0 | Q24: 0 | R24: 0 | S24: 0 | T24: 0 | U24: 0 | V24: 0 | W24: 0 | X24: 0 | Y24: 0 | Z24: 0 | AA24: 0 | AB24: 0 | AC24: 0 | AD24: 0 | AE24: 0 | AF24: 0 | AG24: 0 | AH24: 0 | AI24: 0 | AJ24: 0 | AK24: 0 | AL24: 0 | AM24: 0 | AN24: 0 | AO24: 0 | AP24: 0 | AQ24: 0 | AR24: 0 | AS24: 0 | AT24: 0 | AU24: 0 | AV24: 0 | AW24: 0 | AX24: 0 | AY24: 0 | AZ24: 0 | BA24: 0 | BB24: 0 | BC24: 0 | BD24: 0 | BE24: 0 | BF24: 0 | BG24: 0
A25: gamma_imm_1 | B25: Immigration from Z2 to Z1 (by industry) Depending on Unemployment Rate | C25: Z2 | D25: exogenous | F25: 0 | G25: 0 | H25: 0 | I25: 0 | J25: 0 | K25: 0 | L25: 0 | M25: 0 | N25: 0 | O25: 0 | P25: 0 | Q25: 0 | R25: 0 | S25: 0 | T25: 0 | U25: 0 | V25: 0 | W25: 0 | X25: 0 | Y25: 0 | Z25: 0 | AA25: 0 | AB25: 0 | AC25: 0 | AD25: 0 | AE25: 0 | AF25: 0 | AG25: 0 | AH25: 0 | AI25: 0 | AJ25: 0 | AK25: 0 | AL25: 0 | AM25: 0 | AN25: 0 | AO25: 0 | AP25: 0 | AQ25: 0 | AR25: 0 | AS25: 0 | AT25: 0 | AU25: 0 | AV25: 0 | AW25: 0 | AX25: 0 | AY25: 0 | AZ25: 0 | BA25: 0 | BB25: 0 | BC25: 0 | BD25: 0 | BE25: 0 | BF25: 0 | BG25: 0
A26: gamma_imm_2 | B26: Immigration from Z1 to Z2 (by industry) Depending on Wage Gap | C26: Z1 | D26: exogenous | F26: 0 | G26: 0 | H26: 0 | I26: 0 | J26: 0 | K26: 0 | L26: 0 | M26: 0 | N26: 0 | O26: 0 | P26: 0 | Q26: 0 | R26: 0 | S26: 0 | T26: 0 | U26: 0 | V26: 0 | W26: 0 | X26: 0 | Y26: 0 | Z26: 0 | AA26: 0 | AB26: 0 | AC26: 0 | AD26: 0 | AE26: 0 | AF26: 0 | AG26: 0 | AH26: 0 | AI26: 0 | AJ26: 0 | AK26: 0 | AL26: 0 | AM26: 0 | AN26: 0 | AO26: 0 | AP26: 0 | AQ26: 0 | AR26: 0 | AS26: 0 | AT26: 0 | AU26: 0 | AV26: 0 | AW26: 0 | AX26: 0 | AY26: 0 | AZ26: 0 | BA26: 0 | BB26: 0 | BC26: 0 | BD26: 0 | BE26: 0 | BF26: 0 | BG26: 0
A27: gamma_imm_2 | B27: Immigration from Z2 to Z1 (by industry) Depending on Wage Gap | C27: Z2 | D27: exogenous | F27: 0 | G27: 0 | H27: 0 | I27: 0 | J27: 0 | K27: 0 | L27: 0 | M27: 0 | N27: 0 | O27: 0 | P27: 0 | Q27: 0 | R27: 0 | S27: 0 | T27: 0 | U27: 0 | V27: 0 | W27: 0 | X27: 0 | Y27: 0 | Z27: 0 | AA27: 0 | AB27: 0 | AC27: 0 | AD27: 0 | AE27: 0 | AF27: 0 | AG27: 0 | AH27: 0 | AI27: 0 | AJ27: 0 | AK27: 0 | AL27: 0 | AM27: 0 | AN27: 0 | AO27: 0 | AP27: 0 | AQ27: 0 | AR27: 0 | AS27: 0 | AT27: 0 | AU27: 0 | AV27: 0 | AW27: 0 | AX27: 0 | AY27: 0 | AZ27: 0 | BA27: 0 | BB27: 0 | BC27: 0 | BD27: 0 | BE27: 0 | BF27: 0 | BG27: 0
... A37: ineq_j | B37: Functional Inequality by Industry | C37: Z2 | D37: endogenous | F37: 0 | G37: 0 | H37: 0 | I37: 0 | J37: 0 | K37: 0 | L37: 0 | M37: 0 | N37: 0 | O37: 0 | P37: 0 | Q37: 0 | R37: 0 | S37: 0 | T37: 0 | U37: 0 | V37: 0 | W37: 0 | X37: 0 | Y37: 0 | Z37: 0 | AA37: 0 | AB37: 0 | AC37: 0 | AD37: 0 | AE37: 0 | AF37: 0 | AG37: 0 | AH37: 0 | AI37: 0 | AJ37: 0 | AK37: 0 | AL37: 0 | AM37: 0 | AN37: 0 | AO37: 0 | AP37: 0 | AQ37: 0 | AR37: 0 | AS37: 0 | AT37: 0 | AU37: 0 | AV37: 0 | AW37: 0 | AX37: 0 | AY37: 0 | AZ37: 0 | BA37: 0 | BB37: 0 | BC37: 0 | BD37: 0 | BE37: 0 | BF37: 0 | BG37: 0
A38: int_j | B38: Interest Payments | C38: Z1 | D38: endogenous | E38: govt.central.bank | F38: 0 | G38: 0 | H38: 0 | I38: 0 | J38: 0 | K38: 0 | L38: 0 | M38: 0 | N38: 0 | O38: 0 | P38: 0 | Q38: 0 | R38: 0 | S38: 0 | T38: 0 | U38: 0 | V38: 0 | W38: 0 | X38: 0 | Y38: 0 | Z38: 0 | AA38: 0 | AB38: 0 | AC38: 0 | AD38: 0 | AE38: 0 | AF38: 0 | AG38: 0 | AH38: 0 | AI38: 0 | AJ38: 0 | AK38: 0 | AL38: 0 | AM38: 0 | AN38: 0 | AO38: 0 | AP38: 0 | AQ38: 0 | AR38: 0 | AS38: 0 | AT38: 0 | AU38: 0 | AV38: 0 | AW38: 0 | AX38: 0 | AY38: 0 | AZ38: 0 | BA38: 0 | BB38: 0 | BC38: 0 | BD38: 0 | BE38: 0 | BF38: 0 | BG38: 0
A39: int_j | B39: Interest Payments | C39: Z2 | D39: endogenous | E39: govt.central.bank | F39: 0 | G39: 0 | H39: 0 | I39: 0 | J39: 0 | K39: 0 | L39: 0 | M39: 0 | N39: 0 | O39: 0 | P39: 0 | Q39: 0 | R39: 0 | S39: 0 | T39: 0 | U39: 0 | V39: 0 | W39: 0 | X39: 0 | Y39: 0 | Z39: 0 | AA39: 0 | AB39: 0 | AC39: 0 | AD39: 0 | AE39: 0 | AF39: 0 | AG39: 0 | AH39: 0 | AI39: 0 | AJ39: 0 | AK39: 0 | AL39: 0 | AM39: 0 | AN39: 0 | AO39: 0 | AP39: 0 | AQ39: 0 | AR39: 0 | AS39: 0 | AT39: 0 | AU39: 0 | AV39: 0 | AW39: 0 | AX39: 0 | AY39: 0 | AZ39: 0 | BA39: 0 | BB39: 0 | BC39: 0 | BD39: 0 | BE39: 0 | BF39: 0 | BG39: 0
A40: iota_Z1 | B40: Z1 Sector Share of Z1 Firm Investment | C40: Z1 | D40: exogenous | F40: 0.0016420411 | G40: 0.0041551413 | H40: 0.0018845891 | I40: 3.892269e-05 | J40: 0.00242247 | K40: 0.0013498272 | L40: 0.0011072806 | M40: 0.0015491581 | N40: 0.00037937362 | O40: 0.001835223 | P40: 0.0035904949 | Q40: 0.0013065301 | R40: 0.0002753431 | S40: 0.00060519328 | T40: 0.0040508387 | U40: 0.0033362055 | V40: 0.0030071313 | W40: 0.0010068888 | X40: 0.00022848318 | Y40: 0.0027557255 | Z40: 0.00021957594 | AA40: 8.0746559e-05 | AB40: 0.00097694253 | AC40: 0.0010055258 | AD40: 0.00022660542 | AE40: 0.0031129185 | AF40: 0.001038252 | AG40: 0.2126446 | AH40: 0.016004153 | AI40: 0.0011834309 | AJ40: 0.0027625626 | AK40: 0.00044599334 | AL40: 0.0037657629 | AM40: 0.0017998142 | AN40: 0.0021200692 | AO40: 0.45929474 | AP40: 0.00055717846 | AQ40: 0.0029583642 | AR40: 0.0012038944 | AS40: 0.024670445 | AT40: 0.0067661148 | AU40: 0.0055471625 | AV40: 0.10460427 | AW40: 0.018972309 | AX40: 0.001991671 | AY40: 0.00056447703 | AZ40: 0.0029972302 | BA40: 0.00025697574 | BB40: 0.00057692931 | BC40: 0.00012313648 | BD40: 7.2048139e-05 | BE40: 4.0876935e-05 | BF40: 0.00010696765 | BG40: 0.00019922368
A41: iota_Z1 | B41: Z2 Sector Share of Z1 Firm Investment | C41: Z2 | D41: exogenous | F41: 0.00064932388 | G41: 0.00014176255 | H41: 4.7272226e-05 | I41: 1.269596e-05 | J41: 0.0085784332 | K41: 0.00053368976 | L41: 0.00013631755 | M41: 0.00014870343 | N41: 9.9485541e-06 | O41: 0.00040331303 | P41: 0.00017804289 | Q41: 7.6593985e-06 | R41: 8.5336937e-05 | S41: 2.6325809e-05 | T41: 0.00022152014 | U41: 0.0015998185 | V41: 0.00023282513 | W41: 2.1450627e-05 | X41: 0.00027482906 | Y41: 0.00037398834 | Z41: 3.6281057e-05 | AA41: 1.7954427e-06 | AB41: 8.5588545e-05 | AC41: 2.0002696e-05 | AD41: 1.3174045e-06 | AE41: 0.00071343181 | AF41: 3.27732e-05 | AG41: 0.056991567 | AH41: 0.0019909417 | AI41: 3.962145e-05 | AJ41: 3.5396758e-05 | AK41: 1.1180679e-05 | AL41: 3.4921156e-05 | AM41: 6.7500998e-06 | AN41: 3.6349299e-05 | AO41: 0.0030242719 | AP41: 5.8754428e-07 | AQ41: 0.00019109264 | AR41: 1.5244728e-05 | AS41: 0.00063424478 | AT41: 0.00019749238 | AU41: 0.00031735013 | AV41: 0.006328988 | AW41: 5.8154194e-05 | AX41: 5.4684395e-06 | AY41: 1.1060404e-05 | AZ41: 3.0965542e-05 | BA41: 8.1417242e-06 | BB41: 1.1193311e-05 | BC41: 6.0424539e-07 | BD41: 6.9905713e-07 | BE41: 3.6501182e-07 | BF41: 9.2740258e-06 | BG41: 1.5808086e-05
A42: iota_Z2 | B42: Z1 Sector Share of Z2 Firm Investment | C42: Z1 | D42: exogenous | F42: 1.8104929e-05 | G42: 5.6350374e-05 | H42: 3.1549326e-06 | I42: 3.4257989e-07 | J42: 7.7247363e-06 | K42: 2.391616e-05 | L42: 1.5799734e-05 | M42: 2.3536972e-05 | N42: 8.9778489e-07 | O42: 9.940234e-05 | P42: 9.098623e-05 | Q42: 2.1876036e-05 | R42: 3.1973381e-06 | S42: 2.765791e-06 | T42: 6.0092346e-05 | U42: 0.0001533413 | V42: 5.5258557e-05 | W42: 1.4977927e-05 | X42: 2.4756757e-05 | Y42: 0.00013718598 | Z42: 6.2645174e-06 | AA42: 2.1904877e-06 | AB42: 1.4159168e-05 | AC42: 1.1982591e-05 | AD42: 2.6168837e-06 | AE42: 0.0001692595 | AF42: 6.6662186e-05 | AG42: 0.028796827 | AH42: 0.00047152593 | AI42: 7.1825783e-06 | AJ42: 2.3283683e-05 | AK42: 3.6115082e-06 | AL42: 2.8737378e-05 | AM42: 8.807656e-06 | AN42: 1.3778818e-05 | AO42: 0.0013460472 | AP42: 2.2790145e-06 | AQ42: 9.2843865e-05 | AR42: 3.1115035e-06 | AS42: 0.00066135817 | AT42: 7.7214952e-05 | AU42: 0.00018996146 | AV42: 0.0023832861 | AW42: 7.7696393e-05 | AX42: 6.8866293e-06 | AY42: 1.9589914e-05 | AZ42: 1.9794846e-05 | BA42: 5.522897e-06 | BB42: 9.3627218e-06 | BC42: 1.3657893e-06 | BD42: 4.3734581e-06 | BE42: 4.7038279e-07 | BF42: 5.5407185e-07 | BG42: 8.0709818e-06
A43: iota_Z2 | B43: Z2 Sector Share of Z2 Firm Investment | C43: Z2 | D43: exogenous | F43: 0.0026820681 | G43: 0.0080925807 | H43: 0.00067100676 | I43: 0.0002693598 | J43: 0.020032197 | K43: 0.0041964351 | L43: 0.0018833542 | M43: 0.00275278 | N43: 0.00011952693 | O43: 0.0032710854 | P43: 0.001668943 | Q43: 4.3578641e-05 | R43: 0.00021638927 | S43: 1.4290971e-05 | T43: 0.0015766548 | U43: 0.0029695645 | V43: 0.00053962449 | W43: 2.5424198e-05 | X43: 0.0022696435 | Y43: 0.0019650859 | Z43: 0.00035179114 | AA43: 2.1976085e-06 | AB43: 0.00061516001 | AC43: 0.00020329906 | AD43: 3.061189e-06 | AE43: 0.005527187 | AF43: 9.912853e-05 | AG43: 0.29979559 | AH43: 0.014215834 | AI43: 0.00024223869 | AJ43: 0.00037616698 | AK43: 9.3657924e-05 | AL43: 0.00082048282 | AM43: 0.00017754448 | AN43: 0.00027288041 | AO43: 0.44722357 | AP43: 2.4431453e-05 | AQ43: 0.0039944178 | AR43: 0.00015160014 | AS43: 0.021631568 | AT43: 0.0023201744 | AU43: 0.0064024701 | AV43: 0.076607406 | AW43: 0.022585158 | AX43: 9.5906297e-05 | AY43: 0.0021625029 | AZ43: 0.0010152623 | BA43: 0.00035390774 | BB43: 0.0011464436 | BC43: 8.4441859e-06 | BD43: 1.3824231e-05 | BE43: 3.0772369e-05 | BF43: 7.7764701e-05 | BG43: 0.00074820599
A44: iota_g_Z1 | B44: Z1 Sector Share of Z1 Public Investment | C44: Z1 | D44: exogenous | F44: 0.0016420411 | G44: 0.0041551413 | H44: 0.0018845891 | I44: 3.892269e-05 | J44: 0.00242247 | K44: 0.0013498272 | L44: 0.0011072806 | M44: 0.0015491581 | N44: 0.00037937362 | O44: 0.001835223 | P44: 0.0035904949 | Q44: 0.0013065301 | R44: 0.0002753431 | S44: 0.00060519328 | T44: 0.0040508387 | U44: 0.0033362055 | V44: 0.0030071313 | W44: 0.0010068888 | X44: 0.00022848318 | Y44: 0.0027557255 | Z44: 0.00021957594 | AA44: 8.0746559e-05 | AB44: 0.00097694253 | AC44: 0.0010055258 | AD44: 0.00022660542 | AE44: 0.0031129185 | AF44: 0.001038252 | AG44: 0.2126446 | AH44: 0.016004153 | AI44: 0.0011834309 | AJ44: 0.0027625626 | AK44: 0.00044599334 | AL44: 0.0037657629 | AM44: 0.0017998142 | AN44: 0.0021200692 | AO44: 0.45929474 | AP44: 0.00055717846 | AQ44: 0.0029583642 | AR44: 0.0012038944 | AS44: 0.024670445 | AT44: 0.0067661148 | AU44: 0.0055471625 | AV44: 0.10460427 | AW44: 0.018972309 | AX44: 0.001991671 | AY44: 0.00056447703 | AZ44: 0.0029972302 | BA44: 0.00025697574 | BB44: 0.00057692931 | BC44: 0.00012313648 | BD44: 7.2048139e-05 | BE44: 4.0876935e-05 | BF44: 0.00010696765 | BG44: 0.00019922368
A45: iota_g_Z1 | B45: Z2 Sector Share of Z1 Public Investment | C45: Z2 | D45: exogenous | F45: 0.00064932388 | G45: 0.00014176255 | H45: 4.7272226e-05 | I45: 1.269596e-05 | J45: 0.0085784332 | K45: 0.00053368976 | L45: 0.00013631755 | M45: 0.00014870343 | N45: 9.9485541e-06 | O45: 0.00040331303 | P45: 0.00017804289 | Q45: 7.6593985e-06 | R45: 8.5336937e-05 | S45: 2.6325809e-05 | T45: 0.00022152014 | U45: 0.0015998185 | V45: 0.00023282513 | W45: 2.1450627e-05 | X45: 0.00027482906 | Y45: 0.00037398834 | Z45: 3.6281057e-05 | AA45: 1.7954427e-06 | AB45: 8.5588545e-05 | AC45: 2.0002696e-05 | AD45: 1.3174045e-06 | AE45: 0.00071343181 | AF45: 3.27732e-05 | AG45: 0.056991567 | AH45: 0.0019909417 | AI45: 3.962145e-05 | AJ45: 3.5396758e-05 | AK45: 1.1180679e-05 | AL45: 3.4921156e-05 | AM45: 6.7500998e-06 | AN45: 3.6349299e-05 | AO45: 0.0030242719 | AP45: 5.8754428e-07 | AQ45: 0.00019109264 | AR45: 1.5244728e-05 | AS45: 0.00063424478 | AT45: 0.00019749238 | AU45: 0.00031735013 | AV45: 0.006328988 | AW45: 5.8154194e-05 | AX45: 5.4684395e-06 | AY45: 1.1060404e-05 | AZ45: 3.0965542e-05 | BA45: 8.1417242e-06 | BB45: 1.1193311e-05 | BC45: 6.0424539e-07 | BD45: 6.9905713e-07 | BE45: 3.6501182e-07 | BF45: 9.2740258e-06 | BG45: 1.5808086e-05
A46: iota_g_Z2 | B46: Z1 Sector Share of Z2 Public Investment | C46: Z1 | D46: exogenous | F46: 1.8104929e-05 | G46: 5.6350374e-05 | H46: 3.1549326e-06 | I46: 3.4257989e-07 | J46: 7.7247363e-06 | K46: 2.391616e-05 | L46: 1.5799734e-05 | M46: 2.3536972e-05 | N46: 8.9778489e-07 | O46: 9.940234e-05 | P46: 9.098623e-05 | Q46: 2.1876036e-05 | R46: 3.1973381e-06 | S46: 2.765791e-06 | T46: 6.0092346e-05 | U46: 0.0001533413 | V46: 5.5258557e-05 | W46: 1.4977927e-05 | X46: 2.4756757e-05 | Y46: 0.00013718598 | Z46: 6.2645174e-06 | AA46: 2.1904877e-06 | AB46: 1.4159168e-05 | AC46: 1.1982591e-05 | AD46: 2.6168837e-06 | AE46: 0.0001692595 | AF46: 6.6662186e-05 | AG46: 0.028796827 | AH46: 0.00047152593 | AI46: 7.1825783e-06 | AJ46: 2.3283683e-05 | AK46: 3.6115082e-06 | AL46: 2.8737378e-05 | AM46: 8.807656e-06 | AN46: 1.3778818e-05 | AO46: 0.0013460472 | AP46: 2.2790145e-06 | AQ46: 9.2843865e-05 | AR46: 3.1115035e-06 | AS46: 0.00066135817 | AT46: 7.7214952e-05 | AU46: 0.00018996146 | AV46: 0.0023832861 | AW46: 7.7696393e-05 | AX46: 6.8866293e-06 | AY46: 1.9589914e-05 | AZ46: 1.9794846e-05 | BA46: 5.522897e-06 | BB46: 9.3627218e-06 | BC46: 1.3657893e-06 | BD46: 4.3734581e-06 | BE46: 4.7038279e-07 | BF46: 5.5407185e-07 | BG46: 8.0709818e-06
A47: iota_g_Z2 | B47: Z2 Sector Share of Z2 Public Investment | C47: Z2 | D47: exogenous | F47: 0.0026820681 | G47: 0.0080925807 | H47: 0.00067100676 | I47: 0.0002693598 | J47: 0.020032197 | K47: 0.0041964351 | L47: 0.0018833542 | M47: 0.00275278 | N47: 0.00011952693 | O47: 0.0032710854 | P47: 0.001668943 | Q47: 4.3578641e-05 | R47: 0.00021638927 | S47: 1.4290971e-05 | T47: 0.0015766548 | U47: 0.0029695645 | V47: 0.00053962449 | W47: 2.5424198e-05 | X47: 0.0022696435 | Y47: 0.0019650859 | Z47: 0.00035179114 | AA47: 2.1976085e-06 | AB47: 0.00061516001 | AC47: 0.00020329906 | AD47: 3.061189e-06 | AE47: 0.005527187 | AF47: 9.912853e-05 | AG47: 0.29979559 | AH47: 0.014215834 | AI47: 0.00024223869 | AJ47: 0.00037616698 | AK47: 9.3657924e-05 | AL47: 0.00082048282 | AM47: 0.00017754448 | AN47: 0.00027288041 | AO47: 0.44722357 | AP47: 2.4431453e-05 | AQ47: 0.0039944178 | AR47: 0.00015160014 | AS47: 0.021631568 | AT47: 0.0023201744 | AU47: 0.0064024701 | AV47: 0.076607406 | AW47: 0.022585158 | AX47: 9.5906297e-05 | AY47: 0.0021625029 | AZ47: 0.0010152623 | BA47: 0.00035390774 | BB47: 0.0011464436 | BC47: 8.4441859e-06 | BD47: 1.3824231e-05 | BE47: 3.0772369e-05 | BF47: 7.7764701e-05 | BG47: 0.00074820599
A48: kappa | B48: Target Fixed Capital to Output Ratio | C48: Z1 | D48: exogenous | E48: investment | F48: 0.325 | G48: 0.325 | H48: 0.325 | I48: 0.325 | J48: 0.325 | K48: 0.325 | L48: 0.325 | M48: 0.325 | N48: 0.325 | O48: 0.325 | P48: 0.325 | Q48: 0.325 | R48: 0.325 | S48: 0.325 | T48: 0.325 | U48: 0.325 | V48: 0.325 | W48: 0.325 | X48: 0.325 | Y48: 0.325 | Z48: 0.325 | AA48: 0.325 | AB48: 0.325 | AC48: 0.325 | AD48: 0.325 | AE48: 0.325 | AF48: 0.325 | AG48: 0.325 | AH48: 0.325 | AI48: 0.325 | AJ48: 0.325 | AK48: 0.325 | AL48: 0.325 | AM48: 0.325 | AN48: 0.325 | AO48: 0.325 | AP48: 0.325 | AQ48: 0.325 | AR48: 0.325 | AS48: 0.325 | AT48: 0.325 | AU48: 0.325 | AV48: 0.325 | AW48: 0.325 | AX48: 0.325 | AY48: 0.325 | AZ48: 0.325 | BA48: 0.325 | BB48: 0.325 | BC48: 0.325 | BD48: 0.325 | BE48: 0.325 | BF48: 0.325 | BG48: 0.325
A49: kappa | B49: Target Fixed Capital to Output Ratio | C49: Z2 | D49: exogenous | E49: investment | F49: 0.33 | G49: 0.33 | H49: 0.33 | I49: 0.33 | J49: 0.33 | K49: 0.33 | L49: 0.33 | M49: 0.33 | N49: 0.33 | O49: 0.33 | P49: 0.33 | Q49: 0.33 | R49: 0.33 | S49: 0.33 | T49: 0.33 | U49: 0.33 | V49: 0.33 | W49: 0.33 | X49: 0.33 | Y49: 0.33 | Z49: 0.33 | AA49: 0.33 | AB49: 0.33 | AC49: 0.33 | AD49: 0.33 | AE49: 0.33 | AF49: 0.33 | AG49: 0.33 | AH49: 0.33 | AI49: 0.33 | AJ49: 0.33 | AK49: 0.33 | AL49: 0.33 | AM49: 0.33 | AN49: 0.33 | AO49: 0.33 | AP49: 0.33 | AQ49: 0.33 | AR49: 0.33 | AS49: 0.33 | AT49: 0.33 | AU49: 0.33 | AV49: 0.33 | AW49: 0.33 | AX49: 0.33 | AY49: 0.33 | AZ49: 0.33 | BA49: 0.33 | BB49: 0.33 | BC49: 0.33 | BD49: 0.33 | BE49: 0.33 | BF49: 0.33 | BG49: 0.33
A50: lambda_j | B50: Land Intensity by Industry | C50: Z1 | D50: exogenous | E50: ecological | F50: 3.9288984 | G50: 1.8101792 | H50: 40.269958 | I50: 0.0066614726 | J50: 1.1038646e-05 | K50: 4.7831111e-06 | L50: 0.00081084439 | M50: 0.001304088 | N50: 3.1798406e-05 | O50: 0.0019573089 | P50: 0.2953876 | Q50: 0.045101516 | R50: 0.026337842 | S50: 0.0053505401 | T50: 0.038091295 | U50: 0 | V50: 6.9363063e-05 | W50: 7.889157e-05 | X50: 0.00063377889 | Y50: 0.00018810806 | Z50: 4.2670457e-06 | AA50: 2.2544382e-06 | AB50: 5.4625025e-06 | AC50: 6.9727594e-05 | AD50: 1.8957928e-06 | AE50: 0 | AF50: 0 | AG50: 0.003578026 | AH50: 0.29468033 | AI50: 0.00037660188 | AJ50: 6.8703733e-05 | AK50: 9.746677e-06 | AL50: 0.00018203798 | AM50: 0.00010090343 | AN50: 0.00071913929 | AO50: 0.050430212 | AP50: 8.3504534e-05 | AQ50: 0.000143332 | AR50: 5.6322433e-05 | AS50: 0.16415795 | AT50: 0.073347856 | AU50: 0.004622931 | AV50: 0.0053372382 | AW50: 0.003107775 | AX50: 8.4702228e-05 | AY50: 0.00097779941 | AZ50: 0.20962116 | BA50: 0.014800109 | BB50: 0.0040649546 | BC50: 0.0002848503 | BD50: 0.00017622586 | BE50: 0.00040272122 | BF50: 0.00048945952 | BG50: 0.011693959
A51: lambda_j | B51: Land Intensity by Industry | C51: Z2 | D51: exogenous | E51: ecological | F51: 68.87181 | G51: 97.934271 | H51: 774.53882 | I51: 0.70129363 | J51: 0.035979643 | K51: 0.044217711 | L51: 0.29916798 | M51: 0.12677074 | N51: 0.0014369194 | O51: 0.34617431 | P51: 1.6507618 | Q51: 0.31304341 | R51: 0.12137185 | S51: 3.859213e-06 | T51: 0.091520841 | U51: 0.040521037 | V51: 0.012200913 | W51: 0 | X51: 0.012409084 | Y51: 0.14920616 | Z51: 0.029850277 | AA51: 0 | AB51: 0.018946649 | AC51: 0.01988293 | AD51: 0 | AE51: 0.0074307168 | AF51: 0.00013773324 | AG51: 0.048711779 | AH51: 0.10805541 | AI51: 0.032638372 | AJ51: 0.15291404 | AK51: 0.044926543 | AL51: 0.18995337 | AM51: 0.030728293 | AN51: 0.04739078 | AO51: 0.92129401 | AP51: 0 | AQ51: 0.12843168 | AR51: 0.11442959 | AS51: 0.28638551 | AT51: 0.1002352 | AU51: 0.14909379 | AV51: 0.0058415193 | AW51: 0.021881894 | AX51: 3.6671324e-05 | AY51: 0.052690647 | AZ51: 0.61573482 | BA51: 0.047316798 | BB51: 0.053919354 | BC51: 0.00020730397 | BD51: 6.8644167e-05 | BE51: 0.00032917993 | BF51: 0.071715381 | BG51: 0.03904177
A52: land_j | B52: Land Used by Industry | C52: Z1 | D52: exogenous | E52: ecological | F52: 0 | G52: 0 | H52: 0 | I52: 0 | J52: 0 | K52: 0 | L52: 0 | M52: 0 | N52: 0 | O52: 0 | P52: 0 | Q52: 0 | R52: 0 | S52: 0 | T52: 0 | U52: 0 | V52: 0 | W52: 0 | X52: 0 | Y52: 0 | Z52: 0 | AA52: 0 | AB52: 0 | AC52: 0 | AD52: 0 | AE52: 0 | AF52: 0 | AG52: 0 | AH52: 0 | AI52: 0 | AJ52: 0 | AK52: 0 | AL52: 0 | AM52: 0 | AN52: 0 | AO52: 0 | AP52: 0 | AQ52: 0 | AR52: 0 | AS52: 0 | AT52: 0 | AU52: 0 | AV52: 0 | AW52: 0 | AX52: 0 | AY52: 0 | AZ52: 0 | BA52: 0 | BB52: 0 | BC52: 0 | BD52: 0 | BE52: 0 | BF52: 0 | BG52: 0
A53: land_j | B53: Land Used by Industry | C53: Z2 | D53: exogenous | E53: ecological | F53: 0 | G53: 0 | H53: 0 | I53: 0 | J53: 0 | K53: 0 | L53: 0 | M53: 0 | N53: 0 | O53: 0 | P53: 0 | Q53: 0 | R53: 0 | S53: 0 | T53: 0 | U53: 0 | V53: 0 | W53: 0 | X53: 0 | Y53: 0 | Z53: 0 | AA53: 0 | AB53: 0 | AC53: 0 | AD53: 0 | AE53: 0 | AF53: 0 | AG53: 0 | AH53: 0 | AI53: 0 | AJ53: 0 | AK53: 0 | AL53: 0 | AM53: 0 | AN53: 0 | AO53: 0 | AP53: 0 | AQ53: 0 | AR53: 0 | AS53: 0 | AT53: 0 | AU53: 0 | AV53: 0 | AW53: 0 | AX53: 0 | AY53: 0 | AZ53: 0 | BA53: 0 | BB53: 0 | BC53: 0 | BD53: 0 | BE53: 0 | BF53: 0 | BG53: 0
A54: mu | B54: Costing Margin (Mark-up) | C54: Z1 | D54: exogenous | F54: 0.348185 | G54: 0.18112768 | H54: 0.30998165 | I54: 0.20725485 | J54: 0.19980341 | K54: 0.15679062 | L54: 0.065157573 | M54: 0.098960918 | N54: 0.21360242 | O54: 0.066396171 | P54: 0.071722623 | Q54: 0.085018211 | R54: 0.05310789 | S54: 0.070155959 | T54: 0.10796538 | U54: 0.032422102 | V54: 0.13229754 | W54: 0.17836248 | X54: 0.11138029 | Y54: 0.064571463 | Z54: 0.081999273 | AA54: 0.11641116 | AB54: 0.069507842 | AC54: 0.061622643 | AD54: 0.055699406 | AE54: 0.023044405 | AF54: 0.038469322 | AG54: 0.075993729 | AH54: 0.098609766 | AI54: 0.10110787 | AJ54: 0.12443677 | AK54: 0.1639975 | AL54: 0.15155475 | AM54: 0.11896775 | AN54: 0.10781456 | AO54: 0.099472078 | AP54: 0.30884987 | AQ54: 0.1300676 | AR54: 0.25954266 | AS54: 0.20149201 | AT54: 0.19734394 | AU54: 0.079152235 | AV54: 0.14138444 | AW54: 0.40431829 | AX54: 0.079858609 | AY54: 0.012906129 | AZ54: 0.0067992407 | BA54: 0.028331191 | BB54: 0.11719214 | BC54: 0.053272834 | BD54: 0.062965977 | BE54: 0.079636341 | BF54: 0.092518726 | BG54: 0.15308346
A55: mu | B55: Costing Margin (Mark-up) | C55: Z2 | D55: exogenous | F55: 0.21319186 | G55: 0.11666762 | H55: 0.25173639 | I55: 0.11174628 | J55: 0.33795997 | K55: 0.16173739 | L55: 0.0554175 | M55: 0.073616504 | N55: 0.15876969 | O55: 0.044853415 | P55: 0.072357315 | Q55: 0.1077358 | R55: 0.046482983 | S55: 0.051947968 | T55: 0.080689536 | U55: 0.036539858 | V55: 0.05214895 | W55: 0.10002834 | X55: 0.073256537 | Y55: 0.03803233 | Z55: 0.095287381 | AA55: 0.08242652 | AB55: 0.064401526 | AC55: 0.06765014 | AD55: 0.042008089 | AE55: 0.048006456 | AF55: 0.099029577 | AG55: 0.04650251 | AH55: 0.11895864 | AI55: 0.098587953 | AJ55: 0.032818168 | AK55: 0.082301142 | AL55: 0.062085139 | AM55: 0.10683631 | AN55: 0.17620616 | AO55: 0.049731186 | AP55: 0.4545925 | AQ55: 0.097773947 | AR55: 0.19675263 | AS55: 0.24518364 | AT55: 0.12743302 | AU55: 0.086411481 | AV55: 0.13872125 | AW55: 0.33191681 | AX55: 0.087531873 | AY55: -0.0071741258 | AZ55: 0.0054595169 | BA55: 0.010862054 | BB55: 0.088646629 | BC55: 0.0093777774 | BD55: 0.067619039 | BE55: 0.065425439 | BF55: 0.078230095 | BG55: 0.063219953
A56: mu_mat | B56: Matter Intensity of Output | C56: Z1 | D56: exogenous | F56: 4.6762863 | G56: 5.6877473 | H56: 7.628251 | I56: 0.42344645 | J56: 70.482678 | K56: 56.256618 | L56: 0.0064495827 | M56: 0.0038115747 | N56: 0.00011029978 | O56: 0.00043732041 | P56: 0.024310365 | Q56: 0.01479444 | R56: 0.010367031 | S56: 0.0010622512 | T56: 0.0024441423 | U56: 0.0063281792 | V56: 0.15903421 | W56: 0.18459277 | X56: 0.060532496 | Y56: 0.0017117764 | Z56: 1.1479714 | AA56: 1.28626 | AB56: 1.1573632 | AC56: 1.0197603 | AD56: 0.78080651 | AE56: 0.058906335 | AF56: 0.045769207 | AG56: 0.0057991161 | AH56: 0.014522212 | AI56: 0.16811218 | AJ56: 0.15819257 | AK56: 0.03149496 | AL56: 0.14372814 | AM56: 0.17030635 | AN56: 0.43276347 | AO56: 0.051084523 | AP56: 0.12264436 | AQ56: 0.00010032725 | AR56: 0.00034880399 | AS56: 0.03811411 | AT56: 0.0009879851 | AU56: 0.023379535 | AV56: 0.00093946444 | AW56: 0.0016527091 | AX56: 0.0026543484 | AY56: 0.0016131935 | AZ56: 0.0047461902 | BA56: 0.0002116956 | BB56: 6.0260093e-05 | BC56: 0.0058426557 | BD56: 0.019007518 | BE56: 0.027828014 | BF56: 0.03504251 | BG56: 0.0011927939
A57: mu_mat | B57: Matter Intensity of Output | C57: Z2 | D57: exogenous | F57: 6.2850848 | G57: 11.203669 | H57: 11.37626 | I57: 0.38176086 | J57: 16.893178 | K57: 59.084561 | L57: 0.059388794 | M57: 0.12763653 | N57: 0.00068892741 | O57: 0.0033319434 | P57: 0.022233881 | Q57: 0.030703756 | R57: 0.039004168 | S57: 1.5779959e-06 | T57: 0.0048749398 | U57: 0.01243826 | V57: 0.024773482 | W57: 0.0012065063 | X57: 0.024952052 | Y57: 0.0043162316 | Z57: 0.033757534 | AA57: 0.1085828 | AB57: 0.069783543 | AC57: 0.1642587 | AD57: 0.065526619 | AE57: 0.019702217 | AF57: 0.15579644 | AG57: 0.003566975 | AH57: 0.0087972551 | AI57: 0.052941301 | AJ57: 0.024420652 | AK57: 0.046989724 | AL57: 0.019936018 | AM57: 0.032716486 | AN57: 0.026370041 | AO57: 0.019710471 | AP57: 0.001356115 | AQ57: 0.011792783 | AR57: 0.17845532 | AS57: 0.037297672 | AT57: 0.001391124 | AU57: 0.025648001 | AV57: 0.00022616972 | AW57: 6.6155627e-05 | AX57: 0.0016213772 | AY57: 0.0074565312 | AZ57: 0.0048214251 | BA57: 0.0013788105 | BB57: 0.00038493303 | BC57: 0.002483576 | BD57: 0.010534241 | BE57: 0.00025152004 | BF57: 0.067779504 | BG57: 0.0038933654
A58: n_j | B58: Labour by Industry | C58: Z1 | D58: endogenous | E58: labor.market | F58: 0 | G58: 0 | H58: 0 | I58: 0 | J58: 0 | K58: 0 | L58: 0 | M58: 0 | N58: 0 | O58: 0 | P58: 0 | Q58: 0 | R58: 0 | S58: 0 | T58: 0 | U58: 0 | V58: 0 | W58: 0 | X58: 0 | Y58: 0 | Z58: 0 | AA58: 0 | AB58: 0 | AC58: 0 | AD58: 0 | AE58: 0 | AF58: 0 | AG58: 0 | AH58: 0 | AI58: 0 | AJ58: 0 | AK58: 0 | AL58: 0 | AM58: 0 | AN58: 0 | AO58: 0 | AP58: 0 | AQ58: 0 | AR58: 0 | AS58: 0 | AT58: 0 | AU58: 0 | AV58: 0 | AW58: 0 | AX58: 0 | AY58: 0 | AZ58: 0 | BA58: 0 | BB58: 0 | BC58: 0 | BD58: 0 | BE58: 0 | BF58: 0 | BG58: 0
A59: n_j | B59: Labour by Industry | C59: Z2 | D59: endogenous | E59: labor.market | F59: 0 | G59: 0 | H59: 0 | I59: 0 | J59: 0 | K59: 0 | L59: 0 | M59: 0 | N59: 0 | O59: 0 | P59: 0 | Q59: 0 | R59: 0 | S59: 0 | T59: 0 | U59: 0 | V59: 0 | W59: 0 | X59: 0 | Y59: 0 | Z59: 0 | AA59: 0 | AB59: 0 | AC59: 0 | AD59: 0 | AE59: 0 | AF59: 0 | AG59: 0 | AH59: 0 | AI59: 0 | AJ59: 0 | AK59: 0 | AL59: 0 | AM59: 0 | AN59: 0 | AO59: 0 | AP59: 0 | AQ59: 0 | AR59: 0 | AS59: 0 | AT59: 0 | AU59: 0 | AV59: 0 | AW59: 0 | AX59: 0 | AY59: 0 | AZ59: 0 | BA59: 0 | BB59: 0 | BC59: 0 | BD59: 0 | BE59: 0 | BF59: 0 | BG59: 0
A60: nf_j | B60: Female Employment | C60: Z1 | D60: endogenous | E60: labor.market | F60: 0 | G60: 0 | H60: 0 | I60: 0 | J60: 0 | K60: 0 | L60: 0 | M60: 0 | N60: 0 | O60: 0 | P60: 0 | Q60: 0 | R60: 0 | S60: 0 | T60: 0 | U60: 0 | V60: 0 | W60: 0 | X60: 0 | Y60: 0 | Z60: 0 | AA60: 0 | AB60: 0 | AC60: 0 | AD60: 0 | AE60: 0 | AF60: 0 | AG60: 0 | AH60: 0 | AI60: 0 | AJ60: 0 | AK60: 0 | AL60: 0 | AM60: 0 | AN60: 0 | AO60: 0 | AP60: 0 | AQ60: 0 | AR60: 0 | AS60: 0 | AT60: 0 | AU60: 0 | AV60: 0 | AW60: 0 | AX60: 0 | AY60: 0 | AZ60: 0 | BA60: 0 | BB60: 0 | BC60: 0 | BD60: 0 | BE60: 0 | BF60: 0 | BG60: 0
A61: nf_j | B61: Female Employment | C61: Z2 | D61: endogenous | E61: labor.market | F61: 0 | G61: 0 | H61: 0 | I61: 0 | J61: 0 | K61: 0 | L61: 0 | M61: 0 | N61: 0 | O61: 0 | P61: 0 | Q61: 0 | R61: 0 | S61: 0 | T61: 0 | U61: 0 | V61: 0 | W61: 0 | X61: 0 | Y61: 0 | Z61: 0 | AA61: 0 | AB61: 0 | AC61: 0 | AD61: 0 | AE61: 0 | AF61: 0 | AG61: 0 | AH61: 0 | AI61: 0 | AJ61: 0 | AK61: 0 | AL61: 0 | AM61: 0 | AN61: 0 | AO61: 0 | AP61: 0 | AQ61: 0 | AR61: 0 | AS61: 0 | AT61: 0 | AU61: 0 | AV61: 0 | AW61: 0 | AX61: 0 | AY61: 0 | AZ61: 0 | BA61: 0 | BB61: 0 | BC61: 0 | BD61: 0 | BE61: 0 | BF61: 0 | BG61: 0
A62: omega_j | B62: Water Intensity by Industry | C62: Z1 | D62: exogenous | E62: ecological | F62: 1.8364697 | G62: 0.0083250769 | H62: 0.086917621 | I62: 0.0031934377 | J62: 0.00011086536 | K62: 4.8099955e-05 | L62: 0.0064102616 | M62: 0.0084915706 | N62: 0.00011741251 | O62: 0.0048979896 | P62: 0.00094242738 | Q62: 0.00011582217 | R62: 0.0084399035 | S62: 0.006465229 | T62: 0.0054959122 | U62: 0.00035410039 | V62: 0.0074098443 | W62: 0.0033156917 | X62: 0.010494816 | Y62: 0.0015942484 | Z62: 0.00063234754 | AA62: 0.00027459578 | AB62: 0.0012978219 | AC62: 0.0039614799 | AD62: 0.00092816082 | AE62: 0.0020245852 | AF62: 0.0012543587 | AG62: 0.0018448949 | AH62: 0.0057677425 | AI62: 0.00025678611 | AJ62: 0.018191757 | AK62: 0.00075934028 | AL62: 0.00011228992 | AM62: 0.00031233162 | AN62: 0.00057277815 | AO62: 0.0027217009 | AP62: 2.6671793e-06 | AQ62: 0.00031089921 | AR62: 0.00010818299 | AS62: 0.17144171 | AT62: 0.0011997563 | AU62: 0.00033652617 | AV62: 0.0018363838 | AW62: 0.00048004595 | AX62: 7.6214634e-05 | AY62: 0.0021606026 | AZ62: 0.020417266 | BA62: 0.00091487636 | BB62: 0.0050056865 | BC62: 4.4878235e-05 | BD62: 1.7473613e-05 | BE62: 5.8012427e-05 | BF62: 5.9210625e-05 | BG62: 0.00062427235
A63: omega_j | B63: Water Intensity by Industry | C63: Z2 | D63: exogenous | E63: ecological | F63: 37.625431 | G63: 0.35206203 | H63: 0.016765696 | I63: 0.12778686 | J63: 0.0033040756 | K63: 0.0026572065 | L63: 0.12126427 | M63: 0.050323872 | N63: 0.00024556734 | O63: 0.047323643 | P63: 0.0030551694 | Q63: 2.2101649e-05 | R63: 0.13244633 | S63: 0.0044302346 | T63: 0.070066286 | U63: 0.0040305543 | V63: 0.41273727 | W63: 0.0014036769 | X63: 0.062301705 | Y63: 0.024432936 | Z63: 0.0044088126 | AA63: 9.6823625e-05 | AB63: 0.0090473653 | AC63: 0.054187989 | AD63: 0.00038932128 | AE63: 0.10630765 | AF63: 0.0019417517 | AG63: 0.06850245 | AH63: 0.090372483 | AI63: 0.0003367601 | AJ63: 0.12654591 | AK63: 0.00073654701 | AL63: 0.00056039621 | AM63: 0.0039043919 | AN63: 0.00043363755 | AO63: 0.0094524784 | AP63: 6.1899015e-10 | AQ63: 0.0056470327 | AR63: 0.0011599865 | AS63: 0.054428034 | AT63: 0.0012680991 | AU63: 0.0029677525 | AV63: 0.00022950594 | AW63: 0.00023958355 | AX63: 0.00016508096 | AY63: 0.004620602 | AZ63: 0.035135352 | BA63: 0.0023101244 | BB63: 0.0018732574 | BC63: 2.1552966e-05 | BD63: 7.1588358e-06 | BE63: 2.8168607e-05 | BF63: 0.0017488498 | BG63: 0.0029438526
A64: p | B64: Market Prices | C64: Z1 | D64: endogenous | E64: prices | F64: 1 | G64: 1 | H64: 1 | I64: 1 | J64: 1 | K64: 1 | L64: 1 | M64: 1 | N64: 1 | O64: 1 | P64: 1 | Q64: 1 | R64: 1 | S64: 1 | T64: 1 | U64: 1 | V64: 1 | W64: 1 | X64: 1 | Y64: 1 | Z64: 1 | AA64: 1 | AB64: 1 | AC64: 1 | AD64: 1 | AE64: 1 | AF64: 1 | AG64: 1 | AH64: 1 | AI64: 1 | AJ64: 1 | AK64: 1 | AL64: 1 | AM64: 1 | AN64: 1 | AO64: 1 | AP64: 1 | AQ64: 1 | AR64: 1 | AS64: 1 | AT64: 1 | AU64: 1 | AV64: 1 | AW64: 1 | AX64: 1 | AY64: 1 | AZ64: 1 | BA64: 1 | BB64: 1 | BC64: 1 | BD64: 1 | BE64: 1 | BF64: 1 | BG64: 1
A65: p | B65: Market Prices | C65: Z2 | D65: endogenous | E65: prices | F65: 1 | G65: 1 | H65: 1 | I65: 1 | J65: 1 | K65: 1 | L65: 1 | M65: 1 | N65: 1 | O65: 1 | P65: 1 | Q65: 1 | R65: 1 | S65: 1 | T65: 1 | U65: 1 | V65: 1 | W65: 1 | X65: 1 | Y65: 1 | Z65: 1 | AA65: 1 | AB65: 1 | AC65: 1 | AD65: 1 | AE65: 1 | AF65: 1 | AG65: 1 | AH65: 1 | AI65: 1 | AJ65: 1 | AK65: 1 | AL65: 1 | AM65: 1 | AN65: 1 | AO65: 1 | AP65: 1 | AQ65: 1 | AR65: 1 | AS65: 1 | AT65: 1 | AU65: 1 | AV65: 1 | AW65: 1 | AX65: 1 | AY65: 1 | AZ65: 1 | BA65: 1 | BB65: 1 | BC65: 1 | BD65: 1 | BE65: 1 | BF65: 1 | BG65: 1
A66: p_t | B66: Reproduction Prices (including Capital Depreciation) | C66: Z1 | D66: endogenous | E66: prices | F66: 1 | G66: 1 | H66: 1 | I66: 1 | J66: 1 | K66: 1 | L66: 1 | M66: 1 | N66: 1 | O66: 1 | P66: 1 | Q66: 1 | R66: 1 | S66: 1 | T66: 1 | U66: 1 | V66: 1 | W66: 1 | X66: 1 | Y66: 1 | Z66: 1 | AA66: 1 | AB66: 1 | AC66: 1 | AD66: 1 | AE66: 1 | AF66: 1 | AG66: 1 | AH66: 1 | AI66: 1 | AJ66: 1 | AK66: 1 | AL66: 1 | AM66: 1 | AN66: 1 | AO66: 1 | AP66: 1 | AQ66: 1 | AR66: 1 | AS66: 1 | AT66: 1 | AU66: 1 | AV66: 1 | AW66: 1 | AX66: 1 | AY66: 1 | AZ66: 1 | BA66: 1 | BB66: 1 | BC66: 1 | BD66: 1 | BE66: 1 | BF66: 1 | BG66: 1
A67: p_t | B67: Reproduction Prices (including Capital Depreciation) | C67: Z2 | D67: endogenous | E67: prices | F67: 1 | G67: 1 | H67: 1 | I67: 1 | J67: 1 | K67: 1 | L67: 1 | M67: 1 | N67: 1 | O67: 1 | P67: 1 | Q67: 1 | R67: 1 | S67: 1 | T67: 1 | U67: 1 | V67: 1 | W67: 1 | X67: 1 | Y67: 1 | Z67: 1 | AA67: 1 | AB67: 1 | AC67: 1 | AD67: 1 | AE67: 1 | AF67: 1 | AG67: 1 | AH67: 1 | AI67: 1 | AJ67: 1 | AK67: 1 | AL67: 1 | AM67: 1 | AN67: 1 | AO67: 1 | AP67: 1 | AQ67: 1 | AR67: 1 | AS67: 1 | AT67: 1 | AU67: 1 | AV67: 1 | AW67: 1 | AX67: 1 | AY67: 1 | AZ67: 1 | BA67: 1 | BB67: 1 | BC67: 1 | BD67: 1 | BE67: 1 | BF67: 1 | BG67: 1
A68: parw0 | B68: Autonomous Component of Female Worker Share by Industry | C68: Z1 | D68: exogenous | E68: production | F68: 0.25 | G68: 0.25 | H68: 0.25 | I68: 0.25 | J68: 0.25 | K68: 0.25 | L68: 0.25 | M68: 0.25 | N68: 0.25 | O68: 0.25 | P68: 0.25 | Q68: 0.25 | R68: 0.25 | S68: 0.25 | T68: 0.25 | U68: 0.25 | V68: 0.25 | W68: 0.25 | X68: 0.25 | Y68: 0.25 | Z68: 0.25 | AA68: 0.25 | AB68: 0.25 | AC68: 0.25 | AD68: 0.25 | AE68: 0.25 | AF68: 0.25 | AG68: 0.25 | AH68: 0.25 | AI68: 0.25 | AJ68: 0.25 | AK68: 0.25 | AL68: 0.25 | AM68: 0.25 | AN68: 0.25 | AO68: 0.25 | AP68: 0.25 | AQ68: 0.25 | AR68: 0.25 | AS68: 0.25 | AT68: 0.25 | AU68: 0.25 | AV68: 0.25 | AW68: 0.25 | AX68: 0.25 | AY68: 0.25 | AZ68: 0.25 | BA68: 0.25 | BB68: 0.25 | BC68: 0.25 | BD68: 0.25 | BE68: 0.25 | BF68: 0.25 | BG68: 0.25
A69: parw0 | B69: Autonomous Component of Female Worker Share by Industry | C69: Z2 | D69: exogenous | E69: production | F69: 0.22 | G69: 0.22 | H69: 0.22 | I69: 0.22 | J69: 0.22 | K69: 0.22 | L69: 0.22 | M69: 0.22 | N69: 0.22 | O69: 0.22 | P69: 0.22 | Q69: 0.22 | R69: 0.22 | S69: 0.22 | T69: 0.22 | U69: 0.22 | V69: 0.22 | W69: 0.22 | X69: 0.22 | Y69: 0.22 | Z69: 0.22 | AA69: 0.22 | AB69: 0.22 | AC69: 0.22 | AD69: 0.22 | AE69: 0.22 | AF69: 0.22 | AG69: 0.22 | AH69: 0.22 | AI69: 0.22 | AJ69: 0.22 | AK69: 0.22 | AL69: 0.22 | AM69: 0.22 | AN69: 0.22 | AO69: 0.22 | AP69: 0.22 | AQ69: 0.22 | AR69: 0.22 | AS69: 0.22 | AT69: 0.22 | AU69: 0.22 | AV69: 0.22 | AW69: 0.22 | AX69: 0.22 | AY69: 0.22 | AZ69: 0.22 | BA69: 0.22 | BB69: 0.22 | BC69: 0.22 | BD69: 0.22 | BE69: 0.22 | BF69: 0.22 | BG69: 0.22
... A121: zeta_dc | B121: Share of Durable Consumption Goods Discarded per Year | C121: Z2 | D121: exogenous | E121: ecological | F121: 0 | G121: 0 | H121: 0 | I121: 0 | J121: 0 | K121: 0 | L121: 0 | M121: 0 | N121: 0 | O121: 0 | P121: 0.015 | Q121: 0 | R121: 0 | S121: 0 | T121: 0 | U121: 0 | V121: 0 | W121: 0 | X121: 0 | Y121: 0 | Z121: 0.015 | AA121: 0 | AB121: 0.015 | AC121: 0 | AD121: 0 | AE121: 0.015 | AF121: 0 | AG121: 0.015 | AH121: 0.015 | AI121: 0 | AJ121: 0 | AK121: 0 | AL121: 0 | AM121: 0 | AN121: 0 | AO121: 0 | AP121: 0 | AQ121: 0 | AR121: 0 | AS121: 0 | AT121: 0 | AU121: 0 | AV121: 0 | AW121: 0 | AX121: 0 | AY121: 0 | AZ121: 0 | BA121: 0 | BB121: 0 | BC121: 0 | BD121: 0 | BE121: 0 | BF121: 0 | BG121: 0

Sheet A.matrix
A1: NA | B1: EU.Agriculture | C1: EU.Animal.Farming | D1: EU.Forestry,.logging.and.related.service.activities.(02) | E1: EU.Fishing,.operating.of.fish.hatcheries.and.fish.farms;.service.activities.incidental.to.fishing.(05) | F1: EU.Extraction.of.Fossil-Fuels | G1: EU.Mining.&.Quarrying.of.raw.materials | H1: EU.Processing.of.meat | I1: EU.Processing.of.other.food&beverage | J1: EU.Manufacture.of.tobacco.products.(16) | K1: EU.Manufacture.of.textiles | L1: EU.Manufacture.of.wood.and.of.products.of.wood.and.cork,.except.furniture;.manufacture.of.articles.of.straw.and.plaiting.materials.(20) | M1: EU.Re-processing.of.secondary.wood.material.into.new.wood.material | N1: EU.Pulp | O1: EU.Re-processing.of.secondary.paper.into.new.pulp | P1: EU.Paper | Q1: EU.Processing.of.Fossil.Fuels | R1: EU.Plastics,.basic | S1: EU.Re-processing.of.secondary.plastic.into.new.plastic | T1: EU.Manufacture.of.Chemicals | U1: EU.Manufacture.of.rubber.and.plastic.products.(25) | V1: EU.Manufacture.of.glass.and.glass.products | W1: EU.Re-processing.of.secondary.glass.into.new.glass | X1: EU.Manufacture.of.other.non-metallic.mineral.products | Y1: EU.Manufacture.of.cement,.lime.and.plaster | Z1: EU.Re-processing.of.ash.into.clinker | AA1: EU.Manufacture.of.Metals | AB1: EU.Re-processing.of.Metals | AC1: EU.Manufacture.of.durable.goods | AD1: EU.Manufacture.of.furniture;.manufacturing.n.e.c..(36) | AE1: EU.Recycling | AF1: EU.Production.of.electricity.by.fossil.fuels | AG1: EU.Production.of.electricity.by.renewable.energy | AH1: EU.Transmission.&.Distribution | AI1: EU.Manufacture.of.gas;.distribution.of.gaseous.fuels.through.mains | AJ1: EU.Water | AK1: EU.Construction.(45) | AL1: EU.Re-processing.of.secondary.construction.material.into.aggregates | AM1: EU.Sale,.maintenance,.repair.of.motor.vehicles,.motor.vehicles.parts,.motorcycles,.motor.cycles.parts.and.accessoiries | AN1: EU.Retail.sale.of.automotive.fuel | AO1: EU.Retail.&.Wholesale.trade | AP1: EU.Leisure.Services | AQ1: EU.Transport | AR1: EU.KIBS | AS1: EU.Real.estate.activities.(70) | AT1: EU.Renting.of.machinery.and.equipment.without.operator.and.of.personal.and.household.goods.(71) | AU1: EU.Research.and.development.(73) | AV1: EU.Public.administration.and.defence;.compulsory.social.security.(75) | AW1: EU.Education.(80) | AX1: EU.Health.and.social.work.(85) | AY1: EU.Incineration.of.Waste | AZ1: EU.Biogas.&.Composting | BA1: EU.Waste.water | BB1: EU.Landfill.of.Waste | BC1: EU.Other.Services | BD1: RoW.Agriculture | BE1: RoW.Animal.Farming | BF1: RoW.Forestry,.logging.and.related.service.activities.(02) | BG1: RoW.Fishing,.operating.of.fish.hatcheries.and.fish.farms;.service.activities.incidental.to.fishing.(05) | BH1: RoW.Extraction.of.Fossil-Fuels | BI1: RoW.Mining.&.Quarrying.of.raw.materials | BJ1: RoW.Processing.of.meat | BK1: RoW.Processing.of.other.food&beverage | BL1: RoW.Manufacture.of.tobacco.products.(16) | BM1: RoW.Manufacture.of.textiles | BN1: RoW.Manufacture.of.wood.and.of.products.of.wood.and.cork,.except.furniture;.manufacture.of.articles.of.straw.and.plaiting.materials.(20) | BO1: RoW.Re-processing.of.secondary.wood.material.into.new.wood.material | BP1: RoW.Pulp | BQ1: RoW.Re-processing.of.secondary.paper.into.new.pulp | BR1: RoW.Paper | BS1: RoW.Processing.of.Fossil.Fuels | BT1: RoW.Plastics,.basic | BU1: RoW.Re-processing.of.secondary.plastic.into.new.plastic | BV1: RoW.Manufacture.of.Chemicals | BW1: RoW.Manufacture.of.rubber.and.plastic.products.(25) | BX1: RoW.Manufacture.of.glass.and.glass.products | BY1: RoW.Re-processing.of.secondary.glass.into.new.glass | BZ1: RoW.Manufacture.of.other.non-metallic.mineral.products | CA1: RoW.Manufacture.of.cement,.lime.and.plaster | CB1: RoW.Re-processing.of.ash.into.clinker | CC1: RoW.Manufacture.of.Metals | CD1: RoW.Re-processing.of.Metals | CE1: RoW.Manufacture.of.durable.goods | CF1: RoW.Manufacture.of.furniture;.manufacturing.n.e.c..(36) | CG1: RoW.Recycling | CH1: RoW.Production.of.electricity.by.fossil.fuels | CI1: RoW.Production.of.electricity.by.renewable.energy | CJ1: RoW.Transmission.&.Distribution | CK1: RoW.Manufacture.of.gas;.distribution.of.gaseous.fuels.through.mains | CL1: RoW.Water | CM1: RoW.Construction.(45) | CN1: RoW.Re-processing.of.secondary.construction.material.into.aggregates | CO1: RoW.Sale,.maintenance,.repair.of.motor.vehicles,.motor.vehicles.parts,.motorcycles,.motor.cycles.parts.and.accessoiries | CP1: RoW.Retail.sale.of.automotive.fuel | CQ1: RoW.Retail.&.Wholesale.trade | CR1: RoW.Leisure.Services | CS1: RoW.Transport | CT1: RoW.KIBS | CU1: RoW.Real.estate.activities.(70) | CV1: RoW.Renting.of.machinery.and.equipment.without.operator.and.of.personal.and.household.goods.(71) | CW1: RoW.Research.and.development.(73) | CX1: RoW.Public.administration.and.defence;.compulsory.social.security.(75) | CY1: RoW.Education.(80) | CZ1: RoW.Health.and.social.work.(85) | DA1: RoW.Incineration.of.Waste | DB1: RoW.Biogas.&.Composting | DC1: RoW.Waste.water | DD1: RoW.Landfill.of.Waste | DE1: RoW.Other.Services
A2: EU.Agriculture | B2: 0.040220156 | C2: 0.099055571 | D2: 0.0088905906 | E2: 0.0017446989 | F2: 0.00021454789 | G2: 0.00033375483 | H2: 0.02990604 | I2: 0.10068127 | J2: 0.027559426 | K2: 0.0020989284 | L2: 0.00042225668 | M2: 0.00053993283 | N2: 0.00043894504 | O2: 0.00039797988 | P2: 0.0002136884 | Q2: 0.00024589338 | R2: 0.0022605377 | S2: 0.0028010487 | T2: 0.0025443375 | U2: 0.00016564498 | V2: 5.5541188e-05 | W2: 6.2681557e-05 | X2: 0.00014919291 | Y2: 7.8002687e-05 | Z2: 8.0086314e-05 | AA2: 7.3510857e-05 | AB2: 0.00010451732 | AC2: 8.751572e-05 | AD2: 0.0001297952 | AE2: 0.00013730428 | AF2: 9.573513e-05 | AG2: 0.0010134057 | AH2: 9.5849738e-05 | AI2: 7.0766266e-05 | AJ2: 0.00018945833 | AK2: 0.00022426122 | AL2: 0.00056012152 | AM2: 4.9125008e-05 | AN2: 0.00030493358 | AO2: 0.0012201294 | AP2: 0.0060530021 | AQ2: 0.00018717819 | AR2: 0.00045925383 | AS2: 7.4341708e-05 | AT2: 0.00035519504 | AU2: 0.00055376749 | AV2: 0.0011089647 | AW2: 0.0004610448 | AX2: 0.0013058866 | AY2: 0.00058796508 | AZ2: 0.00025040786 | BA2: 0.00048730153 | BB2: 0.00043382507 | BC2: 0.00045122728 | BD2: 0.00051400186 | BE2: 0.00072943981 | BF2: 0.00040191954 | BG2: 3.3412405e-05 | BH2: 4.3632105e-05 | BI2: 6.9057266e-05 | BJ2: 0.00025773294 | BK2: 0.0011827594 | BL2: 0.0035040028 | BM2: 0.00032788943 | BN2: 0.00015264439 | BO2: 2.6398217e-05 | BP2: 0.00020885532 | BQ2: 5.1903576e-05 | BR2: 4.3977203e-05 | BS2: 4.3497161e-05 | BT2: 2.442304e-05 | BU2: 9.1334687e-05 | BV2: 0.0010018642 | BW2: 2.4468088e-06 | BX2: 2.0089723e-05 | BY2: 1.3865261e-05 | BZ2: 2.2294429e-05 | CA2: 2.336985e-05 | CB2: 1.3346499e-05 | CC2: 8.6523949e-05 | CD2: 8.8912329e-06 | CE2: 1.1233747e-05 | CF2: 1.8777958e-05 | CG2: 0.00013592084 | CH2: 0.00013474128 | CI2: 0.00015189251 | CJ2: 0.00010877803 | CK2: 0.00050433019 | CL2: 1.5177389e-05 | CM2: 3.6955501e-05 | CN2: 1.1468242e-06 | CO2: 3.3641555e-05 | CP2: 0.00088188592 | CQ2: 3.8427406e-05 | CR2: 0.00022327253 | CS2: 3.0728517e-05 | CT2: 5.0612115e-05 | CU2: 8.6577733e-05 | CV2: 0.00023397863 | CW2: 7.7424732e-05 | CX2: 1.6849608e-05 | CY2: 0.00013234027 | CZ2: 0.00011047333 | DA2: 1.9364969e-06 | DB2: 1.5318832e-06 | DC2: 2.643965e-06 | DD2: 0.00033723313 | DE2: 0.00017756765
A3: EU.Animal Farming | B3: 9.8298293e-05 | C3: 0.0086007575 | D3: 0.00015511801 | E3: 0.00015922693 | F3: 0.00021091683 | G3: 0.00010636645 | H3: 0.22150298 | I3: 0.059257922 | J3: 0.0020070049 | K3: 0.0013633485 | L3: 0.0001261304 | M3: 0.00010370054 | N3: 9.4611581e-05 | O3: 0.00012975777 | P3: 8.4457107e-05 | Q3: 5.2835873e-05 | R3: 0.00013696093 | S3: 0.00021709949 | T3: 0.00012441217 | U3: 5.1670577e-05 | V3: 3.1830989e-05 | W3: 3.525101e-05 | X3: 6.0119279e-05 | Y3: 6.355321e-05 | Z3: 5.56696e-05 | AA3: 6.0030669e-05 | AB3: 4.7682628e-05 | AC3: 7.0084197e-05 | AD3: 7.7613946e-05 | AE3: 6.9496431e-05 | AF3: 0.00010535877 | AG3: 9.2597089e-05 | AH3: 0.00017776581 | AI3: 7.1602852e-05 | AJ3: 5.7073215e-05 | AK3: 6.2860763e-05 | AL3: 0.00073101182 | AM3: 3.4561983e-05 | AN3: 0.0001655975 | AO3: 0.00070264574 | AP3: 0.0013072231 | AQ3: 0.0001208633 | AR3: 0.00016579296 | AS3: 3.2031e-05 | AT3: 0.00030568593 | AU3: 0.00019227326 | AV3: 0.00023201621 | AW3: 0.00011590286 | AX3: 0.0002564465 | AY3: 0.00057810082 | AZ3: 0.00021018164 | BA3: 0.00019912081 | BB3: 0.00012450539 | BC3: 0.0004246123 | BD3: 1.6540377e-05 | BE3: 5.1830957e-05 | BF3: 4.7748956e-06 | BG3: 3.168992e-06 | BH3: 8.1523081e-06 | BI3: 2.2102762e-05 | BJ3: 0.00012074044 | BK3: 6.9213932e-05 | BL3: 2.0140707e-06 | BM3: 5.5766256e-05 | BN3: 4.6700311e-06 | BO3: 2.669822e-05 | BP3: 3.8954956e-06 | BQ3: 1.1992087e-05 | BR3: 2.2273405e-06 | BS3: 0.00013275725 | BT3: 2.9742931e-06 | BU3: 1.4189513e-05 | BV3: 0.00016473343 | BW3: 7.3713659e-06 | BX3: 2.3544306e-06 | BY3: 5.9115356e-06 | BZ3: 1.4568504e-06 | CA3: 1.8955303e-06 | CB3: 5.7837912e-06 | CC3: 4.418151e-05 | CD3: 2.4924024e-06 | CE3: 1.9335085e-06 | CF3: 1.2819866e-05 | CG3: 1.4400424e-05 | CH3: 1.0455059e-06 | CI3: 8.9375167e-06 | CJ3: 5.4096136e-07 | CK3: 2.3341345e-05 | CL3: 7.1281453e-07 | CM3: 2.1965719e-06 | CN3: 1.0712888e-06 | CO3: 2.278121e-06 | CP3: 6.8431547e-06 | CQ3: 3.842944e-06 | CR3: 2.7011694e-05 | CS3: 2.3030468e-06 | CT3: 3.8671963e-06 | CU3: 7.6132743e-06 | CV3: 3.0217672e-05 | CW3: 1.4707473e-05 | CX3: 2.6678292e-06 | CY3: 3.1126531e-05 | CZ3: 1.4184415e-05 | DA3: 2.063203e-06 | DB3: 2.1128044e-06 | DC3: 3.1101022e-06 | DD3: 2.2815613e-06 | DE3: 3.7049851e-05
A4: EU.Forestry, logging and related service activities (02) | B4: 0.00040925073 | C4: 0.0017671034 | D4: 0.21730829 | E4: 0.00030649516 | F4: 0.0009142111 | G4: 0.000766745 | H4: 0.00018376385 | I4: 0.00064722645 | J4: 0.0027556711 | K4: 0.00027100054 | L4: 0.11180325 | M4: 0.0025250698 | N4: 0.044479462 | O4: 0.00025261355 | P4: 0.0066357023 | Q4: 1.8868502e-05 | R4: 0.00017710174 | S4: 0.00022618621 | T4: 0.00035968108 | U4: 0.00039503101 | V4: 0.00028744748 | W4: 0.0001637239 | X4: 0.00024552518 | Y4: 0.00016080363 | Z4: 0.00012627772 | AA4: 7.9739423e-05 | AB4: 6.1039211e-05 | AC4: 5.4821244e-05 | AD4: 0.0025059156 | AE4: 0.00017590149 | AF4: 7.1730759e-05 | AG4: 0.0033805799 | AH4: 6.5401615e-05 | AI4: 2.8406702e-05 | AJ4: 0.00014838132 | AK4: 0.00063586879 | AL4: 1.7073037e-05 | AM4: 3.5563516e-05 | AN4: 5.4764465e-05 | AO4: 0.00011445592 | AP4: 0.0001133158 | AQ4: 4.622908e-05 | AR4: 5.5722516e-05 | AS4: 4.4585482e-05 | AT4: 1.6478819e-05 | AU4: 5.3667903e-05 | AV4: 0.00014506183 | AW4: 3.7306216e-05 | AX4: 2.8009088e-05 | AY4: 6.5038401e-05 | AZ4: 5.0581611e-05 | BA4: 7.6652121e-05 | BB4: 8.3558585e-05 | BC4: 9.8723499e-05 | BD4: 4.6929857e-06 | BE4: 1.4454166e-05 | BF4: 0.00032935255 | BG4: 8.1797621e-07 | BH4: 4.9805543e-06 | BI4: 1.3163564e-06 | BJ4: 9.7801051e-07 | BK4: 1.3659457e-05 | BL4: 6.6143738e-05 | BM4: 1.1932866e-05 | BN4: 0.00087302482 | BO4: 0.00020963987 | BP4: 0.00016469236 | BQ4: 2.513144e-06 | BR4: 0.00011393927 | BS4: 5.5733387e-07 | BT4: 2.6581523e-06 | BU4: 1.1316399e-05 | BV4: 7.0905558e-05 | BW4: 6.4905237e-05 | BX4: 1.5531782e-06 | BY4: 1.0711194e-05 | BZ4: 1.6134963e-06 | CA4: 1.3274952e-06 | CB4: 3.062559e-06 | CC4: 3.7396935e-06 | CD4: 3.7962726e-07 | CE4: 8.530795e-07 | CF4: 4.5248467e-05 | CG4: 1.0309869e-05 | CH4: 1.846343e-07 | CI4: 9.6659257e-07 | CJ4: 2.5606441e-07 | CK4: 1.3960805e-06 | CL4: 3.6051323e-07 | CM4: 1.8494645e-05 | CN4: 1.0030309e-07 | CO4: 5.0529018e-07 | CP4: 3.8328693e-06 | CQ4: 2.1519882e-06 | CR4: 2.7188277e-06 | CS4: 3.9592228e-06 | CT4: 5.6055277e-07 | CU4: 2.0691159e-06 | CV4: 1.9547597e-06 | CW4: 6.3919136e-06 | CX4: 9.6689453e-07 | CY4: 1.608081e-06 | CZ4: 1.5835398e-06 | DA4: 1.5470728e-06 | DB4: 6.6935977e-07 | DC4: 2.8065074e-07 | DD4: 4.3368546e-07 | DE4: 1.2285126e-06
A5: EU.Fishing, operating of fish hatcheries and fish farms; service activities incidental to fishing (05) | B5: 5.4525929e-06 | C5: 0.00038631281 | D5: 0.00038098778 | E5: 0.030494783 | F5: 4.8163126e-06 | G5: 4.9920519e-06 | H5: 0.0021191534 | I5: 0.0022837874 | J5: 0.00090268567 | K5: 7.9124528e-05 | L5: 1.5978572e-05 | M5: 3.8044854e-06 | N5: 1.1703906e-05 | O5: 6.8120673e-06 | P5: 8.4368429e-06 | Q5: 3.1201415e-06 | R5: 0.00020679061 | S5: 0.00022679116 | T5: 4.8317298e-05 | U5: 5.7811307e-05 | V5: 7.8912875e-06 | W5: 9.2011369e-06 | X5: 3.6421669e-06 | Y5: 4.0664143e-06 | Z5: 4.5694837e-06 | AA5: 1.8129009e-06 | AB5: 4.10363e-06 | AC5: 3.1789454e-06 | AD5: 4.3375097e-06 | AE5: 1.8938541e-05 | AF5: 4.1427405e-05 | AG5: 7.8800241e-05 | AH5: 1.9486903e-05 | AI5: 4.604584e-05 | AJ5: 9.1825912e-05 | AK5: 2.7742518e-06 | AL5: 0.045456841 | AM5: 1.5033159e-05 | AN5: 0.00010362751 | AO5: 2.1245963e-05 | AP5: 0.00090976908 | AQ5: 5.0819214e-05 | AR5: 9.6885846e-06 | AS5: 2.2304218e-06 | AT5: 4.9189416e-06 | AU5: 1.5815555e-05 | AV5: 3.5352606e-05 | AW5: 3.0896854e-05 | AX5: 8.139177e-05 | AY5: 2.0345203e-05 | AZ5: 1.0969509e-05 | BA5: 1.6674155e-05 | BB5: 3.6497466e-05 | BC5: 5.1598359e-05 | BD5: 3.2903214e-07 | BE5: 1.486051e-06 | BF5: 2.2131904e-07 | BG5: 0.00022035389 | BH5: 1.6783218e-07 | BI5: 4.7798334e-07 | BJ5: 0.00022032413 | BK5: 3.4741306e-05 | BL5: 3.782609e-07 | BM5: 5.7729517e-07 | BN5: 3.2133405e-07 | BO5: 1.1070917e-06 | BP5: 5.8373597e-07 | BQ5: 1.3859278e-06 | BR5: 1.9400856e-07 | BS5: 8.4506181e-07 | BT5: 5.1822069e-07 | BU5: 9.7431392e-07 | BV5: 2.9107763e-05 | BW5: 1.2403611e-07 | BX5: 1.6968734e-07 | BY5: 4.133814e-07 | BZ5: 2.4358404e-07 | CA5: 2.6170338e-07 | CB5: 4.7148118e-07 | CC5: 1.5187941e-07 | CD5: 2.6804369e-07 | CE5: 2.1070929e-07 | CF5: 2.1703664e-07 | CG5: 9.8458649e-07 | CH5: 1.9352748e-07 | CI5: 2.0873675e-07 | CJ5: 1.297531e-07 | CK5: 3.5681168e-07 | CL5: 1.3314217e-07 | CM5: 3.0648903e-07 | CN5: 9.3487371e-08 | CO5: 1.36053e-07 | CP5: 9.7241229e-06 | CQ5: 6.6357496e-07 | CR5: 1.0008389e-05 | CS5: 2.2153628e-06 | CT5: 3.8888826e-07 | CU5: 1.8888909e-07 | CV5: 3.5320072e-07 | CW5: 9.9952401e-07 | CX5: 8.7205105e-07 | CY5: 1.8403001e-06 | CZ5: 5.4451858e-06 | DA5: 1.8429252e-07 | DB5: 1.2685859e-07 | DC5: 1.2082563e-07 | DD5: 3.3875855e-07 | DE5: 2.7079187e-06
A6: EU.Extraction of Fossil-Fuels | B6: 0.00097568171 | C6: 0.00093357268 | D6: 0.00050609551 | E6: 0.00023870404 | F6: 0.03008272 | G6: 0.0026977009 | H6: 0.00047192112 | I6: 0.00049905769 | J6: 0.00080741828 | K6: 0.0020781898 | L6: 0.0027180802 | M6: 0.0017439113 | N6: 0.0057588138 | O6: 0.0015859841 | P6: 0.00029292384 | Q6: 0.035223138 | R6: 0.002244923 | S6: 0.00062733698 | T6: 0.0059762392 | U6: 0.00053678787 | V6: 0.0021984124 | W6: 0.0049337492 | X6: 0.0028295514 | Y6: 0.0032648901 | Z6: 0.0026450137 | AA6: 0.0071155356 | AB6: 0.0025172566 | AC6: 0.00022537453 | AD6: 0.0016626967 | AE6: 0.00085425024 | AF6: 0.069099996 | AG6: 0.0013648231 | AH6: 0.0012641907 | AI6: 0.016566821 | AJ6: 0.018266864 | AK6: 0.00032028298 | AL6: 7.5453872e-05 | AM6: 0.000142249 | AN6: 0.00083514211 | AO6: 0.00026553114 | AP6: 0.00014561862 | AQ6: 0.00031971073 | AR6: 0.0002095966 | AS6: 0.00017087639 | AT6: 0.00023118383 | AU6: 0.0005229957 | AV6: 0.00046036287 | AW6: 0.00015199904 | AX6: 0.00013228704 | AY6: 0.00034843201 | AZ6: 0.00037145089 | BA6: 0.000508675 | BB6: 0.00040951335 | BC6: 0.00064333639 | BD6: 9.0759379e-06 | BE6: 6.9204814e-06 | BF6: 4.1111287e-06 | BG6: 2.8857369e-06 | BH6: 8.0834715e-05 | BI6: 2.5975086e-05 | BJ6: 8.1644946e-06 | BK6: 7.2940713e-06 | BL6: 4.1234952e-06 | BM6: 1.3753362e-05 | BN6: 0.0018252822 | BO6: 4.4930233e-05 | BP6: 0.00018782762 | BQ6: 2.4884996e-05 | BR6: 6.6228279e-06 | BS6: 0.00098819429 | BT6: 0.00016675945 | BU6: 2.8794208e-05 | BV6: 5.734057e-05 | BW6: 8.0133601e-06 | BX6: 2.2416607e-05 | BY6: 0.00023941206 | BZ6: 3.1888979e-05 | CA6: 9.2816475e-05 | CB6: 0.00027383431 | CC6: 2.5171368e-05 | CD6: 2.5141549e-05 | CE6: 4.6919997e-06 | CF6: 0.00046755682 | CG6: 6.3453343e-06 | CH6: 0.00060118981 | CI6: 4.0665211e-05 | CJ6: 8.788289e-06 | CK6: 0.0013039405 | CL6: 8.8131298e-05 | CM6: 7.6860327e-06 | CN6: 5.3432691e-05 | CO6: 2.387636e-06 | CP6: 1.6380736e-05 | CQ6: 5.5181292e-06 | CR6: 3.8554745e-06 | CS6: 1.0414416e-05 | CT6: 5.2336168e-06 | CU6: 4.3646254e-06 | CV6: 4.9241649e-06 | CW6: 6.2664567e-06 | CX6: 7.7751966e-06 | CY6: 5.6467672e-06 | CZ6: 4.1637073e-06 | DA6: 4.196084e-06 | DB6: 3.4736893e-06 | DC6: 4.9259889e-06 | DD6: 5.0632547e-06 | DE6: 5.2735496e-06
A7: EU.Mining & Quarrying of raw materials | B7: 0.0011436994 | C7: 0.0010978336 | D7: 0.00038518073 | E7: 0.0040482738 | F7: 0.0008150672 | G7: 0.060972898 | H7: 0.00054454051 | I7: 0.0012641715 | J7: 0.00013278964 | K7: 0.00029234715 | L7: 0.00037470608 | M7: 0.00048368945 | N7: 0.0067320476 | O7: 0.0090375812 | P7: 0.0010291693 | Q7: 0.00029460065 | R7: 0.0016233466 | S7: 0.0022736766 | T7: 0.011070902 | U7: 0.0011608932 | V7: 0.047385669 | W7: 0.0027027039 | X7: 0.048487255 | Y7: 0.065427708 | Z7: 0.065193493 | AA7: 0.024580165 | AB7: 0.0032573924 | AC7: 0.00095054333 | AD7: 0.0010549454 | AE7: 0.0016971813 | AF7: 0.00062841672 | AG7: 0.0004462215 | AH7: 0.00065183323 | AI7: 0.0023276407 | AJ7: 0.0012921263 | AK7: 0.0098361662 | AL7: 7.8590124e-05 | AM7: 0.00011977798 | AN7: 0.0010308486 | AO7: 0.00065655285 | AP7: 0.00017645444 | AQ7: 0.0003961277 | AR7: 0.00021015084 | AS7: 0.00018541602 | AT7: 0.00025745729 | AU7: 0.00038975338 | AV7: 0.0010000222 | AW7: 6.6853838e-05 | AX7: 0.00011227529 | AY7: 0.0012624699 | AZ7: 0.0014827991 | BA7: 0.0019704047 | BB7: 0.0019868563 | BC7: 0.00017471437 | BD7: 1.3749989e-05 | BE7: 1.3506838e-05 | BF7: 1.9445013e-05 | BG7: 5.9185976e-05 | BH7: 1.9307998e-05 | BI7: 0.00026921254 | BJ7: 2.288465e-05 | BK7: 1.5647922e-05 | BL7: 1.1810994e-05 | BM7: 2.0096971e-05 | BN7: 1.3522267e-05 | BO7: 1.4042702e-05 | BP7: 6.6108177e-05 | BQ7: 0.00011257911 | BR7: 1.3617222e-05 | BS7: 3.0081618e-05 | BT7: 0.00010459405 | BU7: 0.00025867304 | BV7: 0.00030613862 | BW7: 2.0464972e-05 | BX7: 0.00044883789 | BY7: 5.7196864e-05 | BZ7: 0.00041031779 | CA7: 0.00054666509 | CB7: 0.0012352772 | CC7: 0.00032698016 | CD7: 0.00012194598 | CE7: 3.2960908e-05 | CF7: 0.00014483999 | CG7: 3.4520102e-05 | CH7: 7.4745875e-06 | CI7: 7.5989515e-05 | CJ7: 3.4857823e-06 | CK7: 2.250258e-05 | CL7: 9.9677301e-06 | CM7: 0.00010130187 | CN7: 8.324965e-07 | CO7: 5.2602988e-06 | CP7: 3.3156339e-05 | CQ7: 5.5944545e-06 | CR7: 8.9347133e-06 | CS7: 6.8740113e-06 | CT7: 7.0474271e-06 | CU7: 1.3087142e-05 | CV7: 2.5550006e-05 | CW7: 8.0122776e-06 | CX7: 4.7615549e-06 | CY7: 3.8093921e-05 | CZ7: 2.7086789e-05 | DA7: 7.4654102e-06 | DB7: 5.5051811e-06 | DC7: 7.2664004e-06 | DD7: 1.8170312e-05 | DE7: 1.6449113e-05
A8: EU.Processing of meat | B8: 0.00026865809 | C8: 0.060667221 | D8: 0.00071028017 | E8: 0.011688455 | F8: 0.00036901024 | G8: 0.0016640256 | H8: 0.068980294 | I8: 0.050294548 | J8: 0.0019523302 | K8: 0.0019348975 | L8: 0.0003854224 | M8: 0.00042747697 | N8: 0.00072407303 | O8: 0.00087513723 | P8: 0.00052951252 | Q8: 0.00030500038 | R8: 0.002445383 | S8: 0.003274799 | T8: 0.0024566553 | U8: 0.00098896818 | V8: 0.00033130242 | W8: 0.00034323301 | X8: 0.00069535568 | Y8: 0.00027614215 | Z8: 0.00028853558 | AA8: 0.00024080346 | AB8: 0.00032932467 | AC8: 0.00025170806 | AD8: 0.00070470966 | AE8: 0.0012085228 | AF8: 0.0004074149 | AG8: 0.00037490386 | AH8: 0.00026200963 | AI8: 0.00029083048 | AJ8: 0.00038597049 | AK8: 0.000291019 | AL8: 5.0714657e-05 | AM8: 0.00029461728 | AN8: 0.0025119993 | AO8: 0.0013310955 | AP8: 0.021112258 | AQ8: 0.00073129383 | AR8: 0.00065637286 | AS8: 0.00028018005 | AT8: 0.0010085432 | AU8: 0.0025184437 | AV8: 0.0014706156 | AW8: 0.002364959 | AX8: 0.0048024239 | AY8: 0.00031907097 | AZ8: 0.00034127333 | BA8: 0.0006752977 | BB8: 0.00058379281 | BC8: 0.00091314137 | BD8: 9.8367684e-05 | BE8: 0.00059918057 | BF8: 2.3847628e-05 | BG8: 0.00035306165 | BH8: 1.7483728e-05 | BI8: 2.0456984e-05 | BJ8: 0.0018279406 | BK8: 0.0013909321 | BL8: 3.6598464e-05 | BM8: 0.00011036877 | BN8: 1.443367e-05 | BO8: 1.7024464e-05 | BP8: 4.1191551e-05 | BQ8: 0.0003820904 | BR8: 2.599323e-05 | BS8: 1.273762e-05 | BT8: 0.0001050995 | BU8: 0.00048440105 | BV8: 0.00040445776 | BW8: 3.7363262e-05 | BX8: 1.1264425e-05 | BY8: 0.00013340055 | BZ8: 2.2534643e-05 | CA8: 1.4683326e-05 | CB8: 0.00012472785 | CC8: 7.7693467e-06 | CD8: 6.7964767e-05 | CE8: 1.9794403e-05 | CF8: 1.4370594e-05 | CG8: 0.00016466973 | CH8: 2.1045756e-05 | CI8: 2.3687614e-05 | CJ8: 8.7508285e-06 | CK8: 2.2095614e-05 | CL8: 1.9939694e-05 | CM8: 5.7203861e-06 | CN8: 6.3160682e-06 | CO8: 8.2958625e-06 | CP8: 0.00021345026 | CQ8: 3.3107637e-05 | CR8: 0.00076526836 | CS8: 2.3232979e-05 | CT8: 1.8142732e-05 | CU8: 6.6147914e-06 | CV8: 0.00015043178 | CW8: 4.0453097e-05 | CX8: 4.4042555e-05 | CY8: 8.1865663e-05 | CZ8: 0.00018106403 | DA8: 1.0359594e-05 | DB8: 1.5752409e-05 | DC8: 1.6167785e-05 | DD8: 1.551835e-05 | DE8: 5.3100846e-05
A9: EU.Processing of other food&beverage | B9: 0.00016031951 | C9: 0.13313782 | D9: 0.0011454115 | E9: 0.013178364 | F9: 0.00044747178 | G9: 0.0018684348 | H9: 0.056344983 | I9: 0.075054825 | J9: 0.0017802467 | K9: 0.005719802 | L9: 0.00067472946 | M9: 0.0007045112 | N9: 0.00108731 | O9: 0.0013224039 | P9: 0.0012477644 | Q9: 0.00041933545 | R9: 0.0084281373 | S9: 0.006994472 | T9: 0.0097082982 | U9: 0.00089762111 | V9: 0.00024304429 | W9: 0.00025915861 | X9: 0.0013385603 | Y9: 0.00025820935 | Z9: 0.00021607444 | AA9: 0.0004249282 | AB9: 0.00043893365 | AC9: 0.00030184725 | AD9: 0.0010547937 | AE9: 0.0020678114 | AF9: 0.00085308549 | AG9: 0.00046992952 | AH9: 0.00027184507 | AI9: 0.00037835961 | AJ9: 0.00069234852 | AK9: 0.00057922806 | AL9: 2.7482119e-05 | AM9: 0.00036641551 | AN9: 0.0031020688 | AO9: 0.0012112938 | AP9: 0.024430244 | AQ9: 0.00070983822 | AR9: 0.00068622201 | AS9: 0.00026066066 | AT9: 0.0010368087 | AU9: 0.0023360684 | AV9: 0.0017567904 | AW9: 0.0026972427 | AX9: 0.006092627 | AY9: 0.00040428507 | AZ9: 0.00030529866 | BA9: 0.0014453 | BB9: 0.0011255893 | BC9: 0.00099941606 | BD9: 3.9817107e-05 | BE9: 0.0014970086 | BF9: 7.0141152e-05 | BG9: 0.00032405346 | BH9: 1.8404606e-05 | BI9: 3.1299463e-05 | BJ9: 0.00069091769 | BK9: 0.0023074653 | BL9: 4.8613515e-05 | BM9: 0.00011084214 | BN9: 2.659258e-05 | BO9: 2.2343659e-05 | BP9: 5.708766e-05 | BQ9: 0.00053037749 | BR9: 3.8310557e-05 | BS9: 2.4549831e-05 | BT9: 0.00010291816 | BU9: 0.00048847018 | BV9: 0.00030319487 | BW9: 5.5485881e-05 | BX9: 1.6316996e-05 | BY9: 0.00014271534 | BZ9: 2.6964853e-05 | CA9: 2.7183919e-05 | CB9: 0.00014208623 | CC9: 1.5296585e-05 | CD9: 9.0921345e-05 | CE9: 2.2087417e-05 | CF9: 3.508505e-05 | CG9: 0.00016075671 | CH9: 2.6537752e-05 | CI9: 4.246578e-05 | CJ9: 1.8623961e-05 | CK9: 3.831557e-05 | CL9: 3.2577756e-05 | CM9: 6.4717256e-05 | CN9: 5.8471472e-06 | CO9: 1.3869927e-05 | CP9: 0.00026382525 | CQ9: 6.7827202e-05 | CR9: 0.0013296079 | CS9: 7.0997612e-05 | CT9: 2.2758022e-05 | CU9: 7.5238122e-06 | CV9: 7.4764752e-05 | CW9: 5.0144222e-05 | CX9: 4.3402613e-05 | CY9: 0.00010032069 | CZ9: 0.0001797063 | DA9: 1.0392185e-05 | DB9: 1.2886588e-05 | DC9: 7.3136096e-06 | DD9: 4.199996e-05 | DE9: 6.4226618e-05
A10: EU.Manufacture of tobacco products (16) | B10: 3.7399894e-05 | C10: 0.0001160723 | D10: 3.7767514e-05 | E10: 3.7303171e-05 | F10: 5.6889878e-05 | G10: 2.4077202e-05 | H10: 8.5223082e-05 | I10: 5.6610339e-05 | J10: 0.019573098 | K10: 5.2792796e-05 | L10: 1.2561443e-05 | M10: 6.1467749e-05 | N10: 4.2468078e-05 | O10: 2.5661502e-05 | P10: 6.9785846e-05 | Q10: 2.4545028e-05 | R10: 3.8007609e-05 | S10: 4.1920164e-05 | T10: 7.7480137e-05 | U10: 3.513901e-05 | V10: 1.6422075e-05 | W10: 1.2426554e-05 | X10: 1.2315881e-05 | Y10: 1.2456416e-05 | Z10: 1.5871182e-05 | AA10: 0.0018251556 | AB10: 0.00047174205 | AC10: 3.541001e-05 | AD10: 2.5444271e-05 | AE10: 1.9414583e-05 | AF10: 4.2582616e-05 | AG10: 4.3308818e-05 | AH10: 7.8552909e-06 | AI10: 3.7974051e-05 | AJ10: 1.2495977e-05 | AK10: 4.771792e-05 | AL10: 2.4252792e-06 | AM10: 2.3348378e-05 | AN10: 3.3922475e-05 | AO10: 0.00018123372 | AP10: 0.00030150227 | AQ10: 3.7304304e-05 | AR10: 4.8193014e-05 | AS10: 8.8573798e-06 | AT10: 6.2401625e-05 | AU10: 6.8050334e-05 | AV10: 0.0001256226 | AW10: 1.8917344e-05 | AX10: 1.3191852e-05 | AY10: 3.9858208e-05 | AZ10: 2.274689e-05 | BA10: 0.00015160901 | BB10: 8.9140454e-05 | BC10: 0.00016408823 | BD10: 1.545209e-06 | BE10: 9.0114364e-07 | BF10: 5.5751214e-06 | BG10: 8.3658099e-07 | BH10: 2.2422437e-06 | BI10: 1.6114217e-06 | BJ10: 5.5056017e-06 | BK10: 3.0401668e-06 | BL10: 0.00010283163 | BM10: 2.447666e-06 | BN10: 2.0291012e-06 | BO10: 3.6791629e-07 | BP10: 6.7180056e-07 | BQ10: 1.3492814e-06 | BR10: 1.7546432e-06 | BS10: 1.5835859e-06 | BT10: 6.7660633e-07 | BU10: 1.147171e-06 | BV10: 2.5613501e-05 | BW10: 6.0702775e-07 | BX10: 2.5001917e-06 | BY10: 1.697276e-06 | BZ10: 3.3831079e-06 | CA10: 3.2022612e-06 | CB10: 1.3402333e-06 | CC10: 1.3095054e-05 | CD10: 1.012394e-05 | CE10: 1.115933e-06 | CF10: 2.5126039e-06 | CG10: 1.0011232e-05 | CH10: 3.1866996e-06 | CI10: 3.9695273e-06 | CJ10: 9.7109707e-07 | CK10: 1.5454164e-05 | CL10: 1.6514489e-06 | CM10: 6.6589892e-07 | CN10: 4.2027164e-07 | CO10: 1.0148521e-06 | CP10: 3.1232696e-05 | CQ10: 1.3821205e-06 | CR10: 3.1115029e-06 | CS10: 1.148362e-06 | CT10: 1.9302933e-06 | CU10: 9.6948087e-07 | CV10: 6.0030678e-06 | CW10: 2.4267799e-06 | CX10: 8.6801099e-07 | CY10: 2.1852465e-06 | CZ10: 1.249432e-06 | DA10: 5.333628e-07 | DB10: 2.9430994e-07 | DC10: 1.0172475e-06 | DD10: 6.394353e-06 | DE10: 3.7623438e-06
A11: EU.Manufacture of textiles | B11: 0.0016972133 | C11: 0.0013499216 | D11: 0.0017816692 | E11: 0.015902484 | F11: 0.0012804951 | G11: 0.0010624291 | H11: 0.00048420072 | I11: 0.00092895795 | J11: 0.0017706041 | K11: 0.17973568 | L11: 0.0020700558 | M11: 0.0042028952 | N11: 0.0021708441 | O11: 0.0029811457 | P11: 0.0037829534 | Q11: 0.00015112924 | R11: 0.0013691539 | S11: 0.0012991025 | T11: 0.0054587096 | U11: 0.0075879944 | V11: 0.0038526708 | W11: 0.0038877188 | X11: 0.0019107081 | Y11: 0.00099658906 | Z11: 0.00091154008 | AA11: 0.0010437242 | AB11: 0.0010419 | AC11: 0.0025118773 | AD11: 0.010677855 | AE11: 0.0024685511 | AF11: 0.00064725488 | AG11: 0.00040137359 | AH11: 0.00044524889 | AI11: 0.00067032303 | AJ11: 0.00070946554 | AK11: 0.001519698 | AL11: 0.00065932747 | AM11: 0.00073013612 | AN11: 0.001794271 | AO11: 0.00072629123 | AP11: 0.0022185669 | AQ11: 0.00050645215 | AR11: 0.00050495153 | AS11: 0.00011942516 | AT11: 0.0010280466 | AU11: 0.00082761427 | AV11: 0.0012302432 | AW11: 0.00033990967 | AX11: 0.0016378326 | AY11: 0.0015803912 | AZ11: 0.0016086746 | BA11: 0.0026626511 | BB11: 0.0033882167 | BC11: 0.0017253892 | BD11: 5.9876762e-05 | BE11: 3.5976814e-05 | BF11: 5.226545e-05 | BG11: 0.00016271792 | BH11: 3.624256e-05 | BI11: 5.7725113e-05 | BJ11: 2.3352388e-05 | BK11: 3.6419718e-05 | BL11: 0.00013210245 | BM11: 0.0050893093 | BN11: 0.00010380963 | BO11: 3.7775513e-05 | BP11: 8.1525651e-05 | BQ11: 0.00017219811 | BR11: 0.00019846231 | BS11: 1.5889679e-05 | BT11: 0.00010148994 | BU11: 0.00028468625 | BV11: 0.0013039247 | BW11: 0.00025880622 | BX11: 5.8107191e-05 | BY11: 0.00023468891 | BZ11: 6.0216973e-05 | CA11: 4.3237653e-05 | CB11: 5.4243667e-05 | CC11: 2.4778265e-05 | CD11: 2.0912267e-05 | CE11: 9.2795181e-05 | CF11: 0.0005898107 | CG11: 0.00018686699 | CH11: 2.4047767e-05 | CI11: 6.8904134e-05 | CJ11: 2.3870263e-05 | CK11: 4.8937629e-05 | CL11: 4.9710687e-05 | CM11: 0.00018825622 | CN11: 8.7093122e-05 | CO11: 3.4041478e-05 | CP11: 0.00025733218 | CQ11: 0.00010186389 | CR11: 9.0280939e-05 | CS11: 4.3107838e-05 | CT11: 2.5473681e-05 | CU11: 1.1431569e-05 | CV11: 5.6722867e-05 | CW11: 0.00014986368 | CX11: 6.9122514e-05 | CY11: 6.0719327e-05 | CZ11: 0.00013186135 | DA11: 0.00014627637 | DB11: 8.2799979e-05 | DC11: 4.7022064e-05 | DD11: 7.111515e-05 | DE11: 0.00013391953
A12: EU.Manufacture of wood and of products of wood and cork, except furniture; manufacture of articles of straw and plaiting materials (20) | B12: 0.0021690015 | C12: 0.0015930662 | D12: 0.004855802 | E12: 0.0044096184 | F12: 0.0031393215 | G12: 0.0029929704 | H12: 0.00076627663 | I12: 0.0016092907 | J12: 0.0012540444 | K12: 0.00091527493 | L12: 0.1355152 | M12: 0.12742074 | N12: 0.023908897 | O12: 0.00070699786 | P12: 0.0039499611 | Q12: 0.00013943205 | R12: 0.0013753769 | S12: 0.0012828193 | T12: 0.00061664229 | U12: 0.0019385998 | V12: 0.0053702244 | W12: 0.0055487553 | X12: 0.0073092968 | Y12: 0.0010755288 | Z12: 0.0011623773 | AA12: 0.0027828939 | AB12: 0.0033078035 | AC12: 0.0018504061 | AD12: 0.047971111 | AE12: 0.0057926875 | AF12: 0.0015742202 | AG12: 0.0038979969 | AH12: 0.0022171974 | AI12: 0.0004594627 | AJ12: 0.0023625234 | AK12: 0.014824563 | AL12: 0.00014822395 | AM12: 0.00032207239 | AN12: 0.00071456198 | AO12: 0.00047014494 | AP12: 0.0012510605 | AQ12: 0.00050784578 | AR12: 0.00046007013 | AS12: 0.0014052604 | AT12: 0.00056210835 | AU12: 0.00054384816 | AV12: 0.00033166077 | AW12: 0.00037954724 | AX12: 0.00020573262 | AY12: 0.001415942 | AZ12: 0.0014869155 | BA12: 0.001306157 | BB12: 0.0010419355 | BC12: 0.0022549222 | BD12: 1.268794e-05 | BE12: 7.8852902e-06 | BF12: 3.9357479e-05 | BG12: 2.3963766e-05 | BH12: 1.3317303e-05 | BI12: 1.402275e-05 | BJ12: 1.5476047e-05 | BK12: 2.0716829e-05 | BL12: 5.12503e-05 | BM12: 1.5745967e-05 | BN12: 0.0048425438 | BO12: 0.019553205 | BP12: 0.0041831298 | BQ12: 7.6842293e-05 | BR12: 0.00017913963 | BS12: 5.7839153e-06 | BT12: 5.0319447e-05 | BU12: 0.0003044581 | BV12: 4.4152409e-05 | BW12: 3.4492416e-05 | BX12: 6.436299e-05 | BY12: 0.00096192773 | BZ12: 6.967445e-05 | CA12: 2.2037529e-05 | CB12: 0.00022984621 | CC12: 2.0033961e-05 | CD12: 1.9781257e-05 | CE12: 4.2910885e-05 | CF12: 0.0010292703 | CG12: 7.4123035e-05 | CH12: 2.8516385e-06 | CI12: 2.4405922e-05 | CJ12: 6.5595666e-06 | CK12: 8.4884495e-06 | CL12: 9.9782958e-06 | CM12: 0.00083071425 | CN12: 1.4194622e-06 | CO12: 1.0772268e-05 | CP12: 5.9653214e-05 | CQ12: 2.2737894e-05 | CR12: 2.4558579e-05 | CS12: 1.6605656e-05 | CT12: 1.0289933e-05 | CU12: 6.5327077e-05 | CV12: 1.8602623e-05 | CW12: 1.1608935e-05 | CX12: 1.975414e-05 | CY12: 2.8592517e-05 | CZ12: 1.1933116e-05 | DA12: 5.4570237e-05 | DB12: 3.1131374e-05 | DC12: 8.4732541e-06 | DD12: 5.7859329e-06 | DE12: 2.1847419e-05
A13: EU.Re-processing of secondary wood material into new wood material | B13: 0.00093446963 | C13: 0.00064331456 | D13: 0.00098693174 | E13: 0.0015860649 | F13: 0.00084907279 | G13: 0.0010414048 | H13: 0.00033109542 | I13: 0.0007105377 | J13: 0.00041906843 | K13: 0.00040255805 | L13: 0.037038259 | M13: 0.064066658 | N13: 0.0038309048 | O13: 0.00023199661 | P13: 0.00082253068 | Q13: 3.5683902e-05 | R13: 0.00051182837 | S13: 0.00066087603 | T13: 0.00020522979 | U13: 0.00082310201 | V13: 0.0016197254 | W13: 0.002375107 | X13: 0.0026212677 | Y13: 0.00035010829 | Z13: 0.00038187285 | AA13: 0.00055794619 | AB13: 0.00069532862 | AC13: 0.0006698696 | AD13: 0.019503601 | AE13: 0.0019161871 | AF13: 0.0001993361 | AG13: 0.00027201195 | AH13: 0.0002724452 | AI13: 0.00016019967 | AJ13: 0.00023332378 | AK13: 0.0052982383 | AL13: 3.0653218e-05 | AM13: 0.00011898207 | AN13: 0.00027943975 | AO13: 0.00017238342 | AP13: 0.0004544296 | AQ13: 0.00016707684 | AR13: 0.00022203479 | AS13: 0.00031423706 | AT13: 0.00025552969 | AU13: 9.0977115e-05 | AV13: 0.00011552774 | AW13: 0.00010126886 | AX13: 6.9255498e-05 | AY13: 0.00044102694 | AZ13: 0.00049022084 | BA13: 0.00032244264 | BB13: 0.00026492256 | BC13: 0.00096143125 | BD13: 3.3128365e-06 | BE13: 1.5249325e-06 | BF13: 9.2983301e-06 | BG13: 4.4303501e-06 | BH13: 3.4036101e-06 | BI13: 4.0002249e-06 | BJ13: 4.6929195e-06 | BK13: 6.1234227e-06 | BL13: 1.6166242e-05 | BM13: 5.1250726e-06 | BN13: 0.0010373199 | BO13: 0.0038852901 | BP13: 0.00064241537 | BQ13: 2.1801688e-05 | BR13: 4.6168029e-05 | BS13: 1.0021425e-06 | BT13: 1.0797938e-05 | BU13: 6.412052e-05 | BV13: 1.2898151e-05 | BW13: 1.1454958e-05 | BX13: 1.479773e-05 | BY13: 0.00019614231 | BZ13: 1.5709772e-05 | CA13: 5.734631e-06 | CB13: 4.782888e-05 | CC13: 6.0410446e-06 | CD13: 5.076185e-06 | CE13: 1.2119069e-05 | CF13: 0.00023836434 | CG13: 1.647981e-05 | CH13: 8.8264631e-07 | CI13: 4.0266678e-06 | CJ13: 1.1444622e-06 | CK13: 2.9705877e-06 | CL13: 2.4425078e-06 | CM13: 0.00015169898 | CN13: 4.7877294e-07 | CO13: 2.9590467e-06 | CP13: 1.2858945e-05 | CQ13: 5.6826678e-06 | CR13: 5.3303077e-06 | CS13: 4.3840634e-06 | CT13: 2.7190392e-06 | CU13: 9.6938362e-06 | CV13: 5.6830411e-06 | CW13: 3.8768337e-06 | CX13: 4.846541e-06 | CY13: 6.5731981e-06 | CZ13: 3.0493722e-06 | DA13: 1.385675e-05 | DB13: 8.5123114e-06 | DC13: 2.7027953e-06 | DD13: 1.4549917e-06 | DE13: 5.2773928e-06
... A109: RoW.Other Services | B109: 2.8699733e-05 | C109: 2.7622125e-05 | D109: 1.1110183e-05 | E109: 5.4057588e-05 | F109: 3.2335933e-05 | G109: 5.1814584e-05 | H109: 4.9190535e-05 | I109: 3.5829033e-05 | J109: 2.4021619e-05 | K109: 4.1046638e-05 | L109: 2.6864389e-05 | M109: 3.5242196e-05 | N109: 3.1169329e-05 | O109: 5.7497684e-05 | P109: 2.8143777e-05 | Q109: 3.1039413e-05 | R109: 4.4727855e-05 | S109: 7.0369018e-05 | T109: 6.5939993e-05 | U109: 2.1095149e-05 | V109: 2.0567131e-05 | W109: 1.9636303e-05 | X109: 3.9095577e-05 | Y109: 2.1074219e-05 | Z109: 2.1505868e-05 | AA109: 0.0008963375 | AB109: 2.1000858e-05 | AC109: 1.6463258e-05 | AD109: 2.4281988e-05 | AE109: 1.8895306e-05 | AF109: 1.5934251e-05 | AG109: 1.3231073e-05 | AH109: 1.2259452e-05 | AI109: 2.7100295e-05 | AJ109: 1.8473217e-05 | AK109: 1.4127515e-05 | AL109: 1.1820501e-05 | AM109: 1.1520682e-05 | AN109: 1.5928825e-05 | AO109: 2.2307239e-05 | AP109: 3.3123882e-05 | AQ109: 4.0353944e-05 | AR109: 3.5312928e-05 | AS109: 4.9034658e-05 | AT109: 3.5061939e-05 | AU109: 3.878409e-05 | AV109: 2.1476515e-05 | AW109: 1.4673461e-05 | AX109: 3.421674e-05 | AY109: 6.7165693e-05 | AZ109: 8.1567324e-05 | BA109: 5.5060401e-05 | BB109: 3.7904558e-05 | BC109: 0.00053274807 | BD109: 0.0023126489 | BE109: 0.00091396341 | BF109: 0.002604307 | BG109: 0.0021448864 | BH109: 0.0018444442 | BI109: 0.0020357449 | BJ109: 0.000940665 | BK109: 0.0020574028 | BL109: 0.0026236427 | BM109: 0.0018009711 | BN109: 0.0025746538 | BO109: 0.0020269613 | BP109: 0.001592979 | BQ109: 0.0010521759 | BR109: 0.0022861861 | BS109: 0.00057314172 | BT109: 0.00055367771 | BU109: 0.00083730171 | BV109: 0.0021713921 | BW109: 0.0016176915 | BX109: 0.0013279077 | BY109: 0.00014655446 | BZ109: 0.0046406793 | CA109: 0.002659902 | CB109: 0.0058476702 | CC109: 0.0023020092 | CD109: 0.0022483936 | CE109: 0.0016164343 | CF109: 0.001612074 | CG109: 0.0016314903 | CH109: 0.0069314859 | CI109: 0.0052815087 | CJ109: 0.00072592287 | CK109: 0.0021065534 | CL109: 0.0030001319 | CM109: 0.0021206099 | CN109: 0.00016235225 | CO109: 0.0012344927 | CP109: 0.0031395578 | CQ109: 0.00096549862 | CR109: 0.0043559713 | CS109: 0.0058015751 | CT109: 0.00376295 | CU109: 0.0060657857 | CV109: 0.0037236267 | CW109: 0.012330017 | CX109: 0.0028037404 | CY109: 0.005874691 | CZ109: 0.0080268192 | DA109: 0.010238551 | DB109: 0.0033793082 | DC109: 0.0071664486 | DD109: 0.0018692222 | DE109: 0.021803695

Sheet B.matrix
A1: NA | B1: EU.Agriculture | C1: EU.Animal.Farming | D1: EU.Forestry,.logging.and.related.service.activities.(02) | E1: EU.Fishing,.operating.of.fish.hatcheries.and.fish.farms;.service.activities.incidental.to.fishing.(05) | F1: EU.Extraction.of.Fossil-Fuels | G1: EU.Mining.&.Quarrying.of.raw.materials | H1: EU.Processing.of.meat | I1: EU.Processing.of.other.food&beverage | J1: EU.Manufacture.of.tobacco.products.(16) | K1: EU.Manufacture.of.textiles | L1: EU.Manufacture.of.wood.and.of.products.of.wood.and.cork,.except.furniture;.manufacture.of.articles.of.straw.and.plaiting.materials.(20) | M1: EU.Re-processing.of.secondary.wood.material.into.new.wood.material | N1: EU.Pulp | O1: EU.Re-processing.of.secondary.paper.into.new.pulp | P1: EU.Paper | Q1: EU.Processing.of.Fossil.Fuels | R1: EU.Plastics,.basic | S1: EU.Re-processing.of.secondary.plastic.into.new.plastic | T1: EU.Manufacture.of.Chemicals | U1: EU.Manufacture.of.rubber.and.plastic.products.(25) | V1: EU.Manufacture.of.glass.and.glass.products | W1: EU.Re-processing.of.secondary.glass.into.new.glass | X1: EU.Manufacture.of.other.non-metallic.mineral.products | Y1: EU.Manufacture.of.cement,.lime.and.plaster | Z1: EU.Re-processing.of.ash.into.clinker | AA1: EU.Manufacture.of.Metals | AB1: EU.Re-processing.of.Metals | AC1: EU.Manufacture.of.durable.goods | AD1: EU.Manufacture.of.furniture;.manufacturing.n.e.c..(36) | AE1: EU.Recycling | AF1: EU.Production.of.electricity.by.fossil.fuels | AG1: EU.Production.of.electricity.by.renewable.energy | AH1: EU.Transmission.&.Distribution | AI1: EU.Manufacture.of.gas;.distribution.of.gaseous.fuels.through.mains | AJ1: EU.Water | AK1: EU.Construction.(45) | AL1: EU.Re-processing.of.secondary.construction.material.into.aggregates | AM1: EU.Sale,.maintenance,.repair.of.motor.vehicles,.motor.vehicles.parts,.motorcycles,.motor.cycles.parts.and.accessoiries | AN1: EU.Retail.sale.of.automotive.fuel | AO1: EU.Retail.&.Wholesale.trade | AP1: EU.Leisure.Services | AQ1: EU.Transport | AR1: EU.KIBS | AS1: EU.Real.estate.activities.(70) | AT1: EU.Renting.of.machinery.and.equipment.without.operator.and.of.personal.and.household.goods.(71) | AU1: EU.Research.and.development.(73) | AV1: EU.Public.administration.and.defence;.compulsory.social.security.(75) | AW1: EU.Education.(80) | AX1: EU.Health.and.social.work.(85) | AY1: EU.Incineration.of.Waste | AZ1: EU.Biogas.&.Composting | BA1: EU.Waste.water | BB1: EU.Landfill.of.Waste | BC1: EU.Other.Services | BD1: RoW.Agriculture | BE1: RoW.Animal.Farming | BF1: RoW.Forestry,.logging.and.related.service.activities.(02) | BG1: RoW.Fishing,.operating.of.fish.hatcheries.and.fish.farms;.service.activities.incidental.to.fishing.(05) | BH1: RoW.Extraction.of.Fossil-Fuels | BI1: RoW.Mining.&.Quarrying.of.raw.materials | BJ1: RoW.Processing.of.meat | BK1: RoW.Processing.of.other.food&beverage | BL1: RoW.Manufacture.of.tobacco.products.(16) | BM1: RoW.Manufacture.of.textiles | BN1: RoW.Manufacture.of.wood.and.of.products.of.wood.and.cork,.except.furniture;.manufacture.of.articles.of.straw.and.plaiting.materials.(20) | BO1: RoW.Re-processing.of.secondary.wood.material.into.new.wood.material | BP1: RoW.Pulp | BQ1: RoW.Re-processing.of.secondary.paper.into.new.pulp | BR1: RoW.Paper | BS1: RoW.Processing.of.Fossil.Fuels | BT1: RoW.Plastics,.basic | BU1: RoW.Re-processing.of.secondary.plastic.into.new.plastic | BV1: RoW.Manufacture.of.Chemicals | BW1: RoW.Manufacture.of.rubber.and.plastic.products.(25) | BX1: RoW.Manufacture.of.glass.and.glass.products | BY1: RoW.Re-processing.of.secondary.glass.into.new.glass | BZ1: RoW.Manufacture.of.other.non-metallic.mineral.products | CA1: RoW.Manufacture.of.cement,.lime.and.plaster | CB1: RoW.Re-processing.of.ash.into.clinker | CC1: RoW.Manufacture.of.Metals | CD1: RoW.Re-processing.of.Metals | CE1: RoW.Manufacture.of.durable.goods | CF1: RoW.Manufacture.of.furniture;.manufacturing.n.e.c..(36) | CG1: RoW.Recycling | CH1: RoW.Production.of.electricity.by.fossil.fuels | CI1: RoW.Production.of.electricity.by.renewable.energy | CJ1: RoW.Transmission.&.Distribution | CK1: RoW.Manufacture.of.gas;.distribution.of.gaseous.fuels.through.mains | CL1: RoW.Water | CM1: RoW.Construction.(45) | CN1: RoW.Re-processing.of.secondary.construction.material.into.aggregates | CO1: RoW.Sale,.maintenance,.repair.of.motor.vehicles,.motor.vehicles.parts,.motorcycles,.motor.cycles.parts.and.accessoiries | CP1: RoW.Retail.sale.of.automotive.fuel | CQ1: RoW.Retail.&.Wholesale.trade | CR1: RoW.Leisure.Services | CS1: RoW.Transport | CT1: RoW.KIBS | CU1: RoW.Real.estate.activities.(70) | CV1: RoW.Renting.of.machinery.and.equipment.without.operator.and.of.personal.and.household.goods.(71) | CW1: RoW.Research.and.development.(73) | CX1: RoW.Public.administration.and.defence;.compulsory.social.security.(75) | CY1: RoW.Education.(80) | CZ1: RoW.Health.and.social.work.(85) | DA1: RoW.Incineration.of.Waste | DB1: RoW.Biogas.&.Composting | DC1: RoW.Waste.water | DD1: RoW.Landfill.of.Waste | DE1: RoW.Other.Services
A2: EU.Agriculture | B2: 1 | C2: 1 | D2: 1 | E2: 1 | F2: 1 | G2: 1 | H2: 1 | I2: 1 | J2: 1 | K2: 1 | L2: 1 | M2: 1 | N2: 1 | O2: 1 | P2: 1 | Q2: 1 | R2: 1 | S2: 1 | T2: 1 | U2: 1 | V2: 1 | W2: 1 | X2: 1 | Y2: 1 | Z2: 1 | AA2: 1 | AB2: 1 | AC2: 1 | AD2: 1 | AE2: 1 | AF2: 1 | AG2: 1 | AH2: 1 | AI2: 1 | AJ2: 1 | AK2: 1 | AL2: 1 | AM2: 1 | AN2: 1 | AO2: 1 | AP2: 1 | AQ2: 1 | AR2: 1 | AS2: 1 | AT2: 1 | AU2: 1 | AV2: 1 | AW2: 1 | AX2: 1 | AY2: 1 | AZ2: 1 | BA2: 1 | BB2: 1 | BC2: 1 | BD2: 1 | BE2: 1 | BF2: 1 | BG2: 1 | BH2: 1 | BI2: 1 | BJ2: 1 | BK2: 1 | BL2: 1 | BM2: 1 | BN2: 1 | BO2: 1 | BP2: 1 | BQ2: 1 | BR2: 1 | BS2: 1 | BT2: 1 | BU2: 1 | BV2: 1 | BW2: 1 | BX2: 1 | BY2: 1 | BZ2: 1 | CA2: 1 | CB2: 1 | CC2: 1 | CD2: 1 | CE2: 1 | CF2: 1 | CG2: 1 | CH2: 1 | CI2: 1 | CJ2: 1 | CK2: 1 | CL2: 1 | CM2: 1 | CN2: 1 | CO2: 1 | CP2: 1 | CQ2: 1 | CR2: 1 | CS2: 1 | CT2: 1 | CU2: 1 | CV2: 1 | CW2: 1 | CX2: 1 | CY2: 1 | CZ2: 1 | DA2: 1 | DB2: 1 | DC2: 1 | DD2: 1 | DE2: 1
A3: EU.Animal Farming | B3: 1 | C3: 1 | D3: 1 | E3: 1 | F3: 1 | G3: 1 | H3: 1 | I3: 1 | J3: 1 | K3: 1 | L3: 1 | M3: 1 | N3: 1 | O3: 1 | P3: 1 | Q3: 1 | R3: 1 | S3: 1 | T3: 1 | U3: 1 | V3: 1 | W3: 1 | X3: 1 | Y3: 1 | Z3: 1 | AA3: 1 | AB3: 1 | AC3: 1 | AD3: 1 | AE3: 1 | AF3: 1 | AG3: 1 | AH3: 1 | AI3: 1 | AJ3: 1 | AK3: 1 | AL3: 1 | AM3: 1 | AN3: 1 | AO3: 1 | AP3: 1 | AQ3: 1 | AR3: 1 | AS3: 1 | AT3: 1 | AU3: 1 | AV3: 1 | AW3: 1 | AX3: 1 | AY3: 1 | AZ3: 1 | BA3: 1 | BB3: 1 | BC3: 1 | BD3: 1 | BE3: 1 | BF3: 1 | BG3: 1 | BH3: 1 | BI3: 1 | BJ3: 1 | BK3: 1 | BL3: 1 | BM3: 1 | BN3: 1 | BO3: 1 | BP3: 1 | BQ3: 1 | BR3: 1 | BS3: 1 | BT3: 1 | BU3: 1 | BV3: 1 | BW3: 1 | BX3: 1 | BY3: 1 | BZ3: 1 | CA3: 1 | CB3: 1 | CC3: 1 | CD3: 1 | CE3: 1 | CF3: 1 | CG3: 1 | CH3: 1 | CI3: 1 | CJ3: 1 | CK3: 1 | CL3: 1 | CM3: 1 | CN3: 1 | CO3: 1 | CP3: 1 | CQ3: 1 | CR3: 1 | CS3: 1 | CT3: 1 | CU3: 1 | CV3: 1 | CW3: 1 | CX3: 1 | CY3: 1 | CZ3: 1 | DA3: 1 | DB3: 1 | DC3: 1 | DD3: 1 | DE3: 1
A4: EU.Forestry, logging and related service activities (02) | B4: 1 | C4: 1 | D4: 1 | E4: 1 | F4: 1 | G4: 1 | H4: 1 | I4: 1 | J4: 1 | K4: 1 | L4: 1 | M4: 1 | N4: 1 | O4: 1 | P4: 1 | Q4: 1 | R4: 1 | S4: 1 | T4: 1 | U4: 1 | V4: 1 | W4: 1 | X4: 1 | Y4: 1 | Z4: 1 | AA4: 1 | AB4: 1 | AC4: 1 | AD4: 1 | AE4: 1 | AF4: 1 | AG4: 1 | AH4: 1 | AI4: 1 | AJ4: 1 | AK4: 1 | AL4: 1 | AM4: 1 | AN4: 1 | AO4: 1 | AP4: 1 | AQ4: 1 | AR4: 1 | AS4: 1 | AT4: 1 | AU4: 1 | AV4: 1 | AW4: 1 | AX4: 1 | AY4: 1 | AZ4: 1 | BA4: 1 | BB4: 1 | BC4: 1 | BD4: 1 | BE4: 1 | BF4: 1 | BG4: 1 | BH4: 1 | BI4: 1 | BJ4: 1 | BK4: 1 | BL4: 1 | BM4: 1 | BN4: 1 | BO4: 1 | BP4: 1 | BQ4: 1 | BR4: 1 | BS4: 1 | BT4: 1 | BU4: 1 | BV4: 1 | BW4: 1 | BX4: 1 | BY4: 1 | BZ4: 1 | CA4: 1 | CB4: 1 | CC4: 1 | CD4: 1 | CE4: 1 | CF4: 1 | CG4: 1 | CH4: 1 | CI4: 1 | CJ4: 1 | CK4: 1 | CL4: 1 | CM4: 1 | CN4: 1 | CO4: 1 | CP4: 1 | CQ4: 1 | CR4: 1 | CS4: 1 | CT4: 1 | CU4: 1 | CV4: 1 | CW4: 1 | CX4: 1 | CY4: 1 | CZ4: 1 | DA4: 1 | DB4: 1 | DC4: 1 | DD4: 1 | DE4: 1
A5: EU.Fishing, operating of fish hatcheries and fish farms; service activities incidental to fishing (05) | B5: 1 | C5: 1 | D5: 1 | E5: 1 | F5: 1 | G5: 1 | H5: 1 | I5: 1 | J5: 1 | K5: 1 | L5: 1 | M5: 1 | N5: 1 | O5: 1 | P5: 1 | Q5: 1 | R5: 1 | S5: 1 | T5: 1 | U5: 1 | V5: 1 | W5: 1 | X5: 1 | Y5: 1 | Z5: 1 | AA5: 1 | AB5: 1 | AC5: 1 | AD5: 1 | AE5: 1 | AF5: 1 | AG5: 1 | AH5: 1 | AI5: 1 | AJ5: 1 | AK5: 1 | AL5: 1 | AM5: 1 | AN5: 1 | AO5: 1 | AP5: 1 | AQ5: 1 | AR5: 1 | AS5: 1 | AT5: 1 | AU5: 1 | AV5: 1 | AW5: 1 | AX5: 1 | AY5: 1 | AZ5: 1 | BA5: 1 | BB5: 1 | BC5: 1 | BD5: 1 | BE5: 1 | BF5: 1 | BG5: 1 | BH5: 1 | BI5: 1 | BJ5: 1 | BK5: 1 | BL5: 1 | BM5: 1 | BN5: 1 | BO5: 1 | BP5: 1 | BQ5: 1 | BR5: 1 | BS5: 1 | BT5: 1 | BU5: 1 | BV5: 1 | BW5: 1 | BX5: 1 | BY5: 1 | BZ5: 1 | CA5: 1 | CB5: 1 | CC5: 1 | CD5: 1 | CE5: 1 | CF5: 1 | CG5: 1 | CH5: 1 | CI5: 1 | CJ5: 1 | CK5: 1 | CL5: 1 | CM5: 1 | CN5: 1 | CO5: 1 | CP5: 1 | CQ5: 1 | CR5: 1 | CS5: 1 | CT5: 1 | CU5: 1 | CV5: 1 | CW5: 1 | CX5: 1 | CY5: 1 | CZ5: 1 | DA5: 1 | DB5: 1 | DC5: 1 | DD5: 1 | DE5: 1
A6: EU.Extraction of Fossil-Fuels | B6: 1 | C6: 1 | D6: 1 | E6: 1 | F6: 1 | G6: 1 | H6: 1 | I6: 1 | J6: 1 | K6: 1 | L6: 1 | M6: 1 | N6: 1 | O6: 1 | P6: 1 | Q6: 1 | R6: 1 | S6: 1 | T6: 1 | U6: 1 | V6: 1 | W6: 1 | X6: 1 | Y6: 1 | Z6: 1 | AA6: 1 | AB6: 1 | AC6: 1 | AD6: 1 | AE6: 1 | AF6: 1 | AG6: 1 | AH6: 1 | AI6: 1 | AJ6: 1 | AK6: 1 | AL6: 1 | AM6: 1 | AN6: 1 | AO6: 1 | AP6: 1 | AQ6: 1 | AR6: 1 | AS6: 1 | AT6: 1 | AU6: 1 | AV6: 1 | AW6: 1 | AX6: 1 | AY6: 1 | AZ6: 1 | BA6: 1 | BB6: 1 | BC6: 1 | BD6: 1 | BE6: 1 | BF6: 1 | BG6: 1 | BH6: 1 | BI6: 1 | BJ6: 1 | BK6: 1 | BL6: 1 | BM6: 1 | BN6: 1 | BO6: 1 | BP6: 1 | BQ6: 1 | BR6: 1 | BS6: 1 | BT6: 1 | BU6: 1 | BV6: 1 | BW6: 1 | BX6: 1 | BY6: 1 | BZ6: 1 | CA6: 1 | CB6: 1 | CC6: 1 | CD6: 1 | CE6: 1 | CF6: 1 | CG6: 1 | CH6: 1 | CI6: 1 | CJ6: 1 | CK6: 1 | CL6: 1 | CM6: 1 | CN6: 1 | CO6: 1 | CP6: 1 | CQ6: 1 | CR6: 1 | CS6: 1 | CT6: 1 | CU6: 1 | CV6: 1 | CW6: 1 | CX6: 1 | CY6: 1 | CZ6: 1 | DA6: 1 | DB6: 1 | DC6: 1 | DD6: 1 | DE6: 1
A7: EU.Mining & Quarrying of raw materials | B7: 1 | C7: 1 | D7: 1 | E7: 1 | F7: 1 | G7: 1 | H7: 1 | I7: 1 | J7: 1 | K7: 1 | L7: 1 | M7: 1 | N7: 1 | O7: 1 | P7: 1 | Q7: 1 | R7: 1 | S7: 1 | T7: 1 | U7: 1 | V7: 1 | W7: 1 | X7: 1 | Y7: 1 | Z7: 1 | AA7: 1 | AB7: 1 | AC7: 1 | AD7: 1 | AE7: 1 | AF7: 1 | AG7: 1 | AH7: 1 | AI7: 1 | AJ7: 1 | AK7: 1 | AL7: 1 | AM7: 1 | AN7: 1 | AO7: 1 | AP7: 1 | AQ7: 1 | AR7: 1 | AS7: 1 | AT7: 1 | AU7: 1 | AV7: 1 | AW7: 1 | AX7: 1 | AY7: 1 | AZ7: 1 | BA7: 1 | BB7: 1 | BC7: 1 | BD7: 1 | BE7: 1 | BF7: 1 | BG7: 1 | BH7: 1 | BI7: 1 | BJ7: 1 | BK7: 1 | BL7: 1 | BM7: 1 | BN7: 1 | BO7: 1 | BP7: 1 | BQ7: 1 | BR7: 1 | BS7: 1 | BT7: 1 | BU7: 1 | BV7: 1 | BW7: 1 | BX7: 1 | BY7: 1 | BZ7: 1 | CA7: 1 | CB7: 1 | CC7: 1 | CD7: 1 | CE7: 1 | CF7: 1 | CG7: 1 | CH7: 1 | CI7: 1 | CJ7: 1 | CK7: 1 | CL7: 1 | CM7: 1 | CN7: 1 | CO7: 1 | CP7: 1 | CQ7: 1 | CR7: 1 | CS7: 1 | CT7: 1 | CU7: 1 | CV7: 1 | CW7: 1 | CX7: 1 | CY7: 1 | CZ7: 1 | DA7: 1 | DB7: 1 | DC7: 1 | DD7: 1 | DE7: 1
A8: EU.Processing of meat | B8: 1 | C8: 1 | D8: 1 | E8: 1 | F8: 1 | G8: 1 | H8: 1 | I8: 1 | J8: 1 | K8: 1 | L8: 1 | M8: 1 | N8: 1 | O8: 1 | P8: 1 | Q8: 1 | R8: 1 | S8: 1 | T8: 1 | U8: 1 | V8: 1 | W8: 1 | X8: 1 | Y8: 1 | Z8: 1 | AA8: 1 | AB8: 1 | AC8: 1 | AD8: 1 | AE8: 1 | AF8: 1 | AG8: 1 | AH8: 1 | AI8: 1 | AJ8: 1 | AK8: 1 | AL8: 1 | AM8: 1 | AN8: 1 | AO8: 1 | AP8: 1 | AQ8: 1 | AR8: 1 | AS8: 1 | AT8: 1 | AU8: 1 | AV8: 1 | AW8: 1 | AX8: 1 | AY8: 1 | AZ8: 1 | BA8: 1 | BB8: 1 | BC8: 1 | BD8: 1 | BE8: 1 | BF8: 1 | BG8: 1 | BH8: 1 | BI8: 1 | BJ8: 1 | BK8: 1 | BL8: 1 | BM8: 1 | BN8: 1 | BO8: 1 | BP8: 1 | BQ8: 1 | BR8: 1 | BS8: 1 | BT8: 1 | BU8: 1 | BV8: 1 | BW8: 1 | BX8: 1 | BY8: 1 | BZ8: 1 | CA8: 1 | CB8: 1 | CC8: 1 | CD8: 1 | CE8: 1 | CF8: 1 | CG8: 1 | CH8: 1 | CI8: 1 | CJ8: 1 | CK8: 1 | CL8: 1 | CM8: 1 | CN8: 1 | CO8: 1 | CP8: 1 | CQ8: 1 | CR8: 1 | CS8: 1 | CT8: 1 | CU8: 1 | CV8: 1 | CW8: 1 | CX8: 1 | CY8: 1 | CZ8: 1 | DA8: 1 | DB8: 1 | DC8: 1 | DD8: 1 | DE8: 1
A9: EU.Processing of other food&beverage | B9: 1 | C9: 1 | D9: 1 | E9: 1 | F9: 1 | G9: 1 | H9: 1 | I9: 1 | J9: 1 | K9: 1 | L9: 1 | M9: 1 | N9: 1 | O9: 1 | P9: 1 | Q9: 1 | R9: 1 | S9: 1 | T9: 1 | U9: 1 | V9: 1 | W9: 1 | X9: 1 | Y9: 1 | Z9: 1 | AA9: 1 | AB9: 1 | AC9: 1 | AD9: 1 | AE9: 1 | AF9: 1 | AG9: 1 | AH9: 1 | AI9: 1 | AJ9: 1 | AK9: 1 | AL9: 1 | AM9: 1 | AN9: 1 | AO9: 1 | AP9: 1 | AQ9: 1 | AR9: 1 | AS9: 1 | AT9: 1 | AU9: 1 | AV9: 1 | AW9: 1 | AX9: 1 | AY9: 1 | AZ9: 1 | BA9: 1 | BB9: 1 | BC9: 1 | BD9: 1 | BE9: 1 | BF9: 1 | BG9: 1 | BH9: 1 | BI9: 1 | BJ9: 1 | BK9: 1 | BL9: 1 | BM9: 1 | BN9: 1 | BO9: 1 | BP9: 1 | BQ9: 1 | BR9: 1 | BS9: 1 | BT9: 1 | BU9: 1 | BV9: 1 | BW9: 1 | BX9: 1 | BY9: 1 | BZ9: 1 | CA9: 1 | CB9: 1 | CC9: 1 | CD9: 1 | CE9: 1 | CF9: 1 | CG9: 1 | CH9: 1 | CI9: 1 | CJ9: 1 | CK9: 1 | CL9: 1 | CM9: 1 | CN9: 1 | CO9: 1 | CP9: 1 | CQ9: 1 | CR9: 1 | CS9: 1 | CT9: 1 | CU9: 1 | CV9: 1 | CW9: 1 | CX9: 1 | CY9: 1 | CZ9: 1 | DA9: 1 | DB9: 1 | DC9: 1 | DD9: 1 | DE9: 1
A10: EU.Manufacture of tobacco products (16) | B10: 1 | C10: 1 | D10: 1 | E10: 1 | F10: 1 | G10: 1 | H10: 1 | I10: 1 | J10: 1 | K10: 1 | L10: 1 | M10: 1 | N10: 1 | O10: 1 | P10: 1 | Q10: 1 | R10: 1 | S10: 1 | T10: 1 | U10: 1 | V10: 1 | W10: 1 | X10: 1 | Y10: 1 | Z10: 1 | AA10: 1 | AB10: 1 | AC10: 1 | AD10: 1 | AE10: 1 | AF10: 1 | AG10: 1 | AH10: 1 | AI10: 1 | AJ10: 1 | AK10: 1 | AL10: 1 | AM10: 1 | AN10: 1 | AO10: 1 | AP10: 1 | AQ10: 1 | AR10: 1 | AS10: 1 | AT10: 1 | AU10: 1 | AV10: 1 | AW10: 1 | AX10: 1 | AY10: 1 | AZ10: 1 | BA10: 1 | BB10: 1 | BC10: 1 | BD10: 1 | BE10: 1 | BF10: 1 | BG10: 1 | BH10: 1 | BI10: 1 | BJ10: 1 | BK10: 1 | BL10: 1 | BM10: 1 | BN10: 1 | BO10: 1 | BP10: 1 | BQ10: 1 | BR10: 1 | BS10: 1 | BT10: 1 | BU10: 1 | BV10: 1 | BW10: 1 | BX10: 1 | BY10: 1 | BZ10: 1 | CA10: 1 | CB10: 1 | CC10: 1 | CD10: 1 | CE10: 1 | CF10: 1 | CG10: 1 | CH10: 1 | CI10: 1 | CJ10: 1 | CK10: 1 | CL10: 1 | CM10: 1 | CN10: 1 | CO10: 1 | CP10: 1 | CQ10: 1 | CR10: 1 | CS10: 1 | CT10: 1 | CU10: 1 | CV10: 1 | CW10: 1 | CX10: 1 | CY10: 1 | CZ10: 1 | DA10: 1 | DB10: 1 | DC10: 1 | DD10: 1 | DE10: 1
A11: EU.Manufacture of textiles | B11: 1 | C11: 1 | D11: 1 | E11: 1 | F11: 1 | G11: 1 | H11: 1 | I11: 1 | J11: 1 | K11: 1 | L11: 1 | M11: 1 | N11: 1 | O11: 1 | P11: 1 | Q11: 1 | R11: 1 | S11: 1 | T11: 1 | U11: 1 | V11: 1 | W11: 1 | X11: 1 | Y11: 1 | Z11: 1 | AA11: 1 | AB11: 1 | AC11: 1 | AD11: 1 | AE11: 1 | AF11: 1 | AG11: 1 | AH11: 1 | AI11: 1 | AJ11: 1 | AK11: 1 | AL11: 1 | AM11: 1 | AN11: 1 | AO11: 1 | AP11: 1 | AQ11: 1 | AR11: 1 | AS11: 1 | AT11: 1 | AU11: 1 | AV11: 1 | AW11: 1 | AX11: 1 | AY11: 1 | AZ11: 1 | BA11: 1 | BB11: 1 | BC11: 1 | BD11: 1 | BE11: 1 | BF11: 1 | BG11: 1 | BH11: 1 | BI11: 1 | BJ11: 1 | BK11: 1 | BL11: 1 | BM11: 1 | BN11: 1 | BO11: 1 | BP11: 1 | BQ11: 1 | BR11: 1 | BS11: 1 | BT11: 1 | BU11: 1 | BV11: 1 | BW11: 1 | BX11: 1 | BY11: 1 | BZ11: 1 | CA11: 1 | CB11: 1 | CC11: 1 | CD11: 1 | CE11: 1 | CF11: 1 | CG11: 1 | CH11: 1 | CI11: 1 | CJ11: 1 | CK11: 1 | CL11: 1 | CM11: 1 | CN11: 1 | CO11: 1 | CP11: 1 | CQ11: 1 | CR11: 1 | CS11: 1 | CT11: 1 | CU11: 1 | CV11: 1 | CW11: 1 | CX11: 1 | CY11: 1 | CZ11: 1 | DA11: 1 | DB11: 1 | DC11: 1 | DD11: 1 | DE11: 1
A12: EU.Manufacture of wood and of products of wood and cork, except furniture; manufacture of articles of straw and plaiting materials (20) | B12: 1 | C12: 1 | D12: 1 | E12: 1 | F12: 1 | G12: 1 | H12: 1 | I12: 1 | J12: 1 | K12: 1 | L12: 1 | M12: 1 | N12: 1 | O12: 1 | P12: 1 | Q12: 1 | R12: 1 | S12: 1 | T12: 1 | U12: 1 | V12: 1 | W12: 1 | X12: 1 | Y12: 1 | Z12: 1 | AA12: 1 | AB12: 1 | AC12: 1 | AD12: 1 | AE12: 1 | AF12: 1 | AG12: 1 | AH12: 1 | AI12: 1 | AJ12: 1 | AK12: 1 | AL12: 1 | AM12: 1 | AN12: 1 | AO12: 1 | AP12: 1 | AQ12: 1 | AR12: 1 | AS12: 1 | AT12: 1 | AU12: 1 | AV12: 1 | AW12: 1 | AX12: 1 | AY12: 1 | AZ12: 1 | BA12: 1 | BB12: 1 | BC12: 1 | BD12: 1 | BE12: 1 | BF12: 1 | BG12: 1 | BH12: 1 | BI12: 1 | BJ12: 1 | BK12: 1 | BL12: 1 | BM12: 1 | BN12: 1 | BO12: 1 | BP12: 1 | BQ12: 1 | BR12: 1 | BS12: 1 | BT12: 1 | BU12: 1 | BV12: 1 | BW12: 1 | BX12: 1 | BY12: 1 | BZ12: 1 | CA12: 1 | CB12: 1 | CC12: 1 | CD12: 1 | CE12: 1 | CF12: 1 | CG12: 1 | CH12: 1 | CI12: 1 | CJ12: 1 | CK12: 1 | CL12: 1 | CM12: 1 | CN12: 1 | CO12: 1 | CP12: 1 | CQ12: 1 | CR12: 1 | CS12: 1 | CT12: 1 | CU12: 1 | CV12: 1 | CW12: 1 | CX12: 1 | CY12: 1 | CZ12: 1 | DA12: 1 | DB12: 1 | DC12: 1 | DD12: 1 | DE12: 1
A13: EU.Re-processing of secondary wood material into new wood material | B13: 1 | C13: 1 | D13: 1 | E13: 1 | F13: 1 | G13: 1 | H13: 1 | I13: 1 | J13: 1 | K13: 1 | L13: 1 | M13: 1 | N13: 1 | O13: 1 | P13: 1 | Q13: 1 | R13: 1 | S13: 1 | T13: 1 | U13: 1 | V13: 1 | W13: 1 | X13: 1 | Y13: 1 | Z13: 1 | AA13: 1 | AB13: 1 | AC13: 1 | AD13: 1 | AE13: 1 | AF13: 1 | AG13: 1 | AH13: 1 | AI13: 1 | AJ13: 1 | AK13: 1 | AL13: 1 | AM13: 1 | AN13: 1 | AO13: 1 | AP13: 1 | AQ13: 1 | AR13: 1 | AS13: 1 | AT13: 1 | AU13: 1 | AV13: 1 | AW13: 1 | AX13: 1 | AY13: 1 | AZ13: 1 | BA13: 1 | BB13: 1 | BC13: 1 | BD13: 1 | BE13: 1 | BF13: 1 | BG13: 1 | BH13: 1 | BI13: 1 | BJ13: 1 | BK13: 1 | BL13: 1 | BM13: 1 | BN13: 1 | BO13: 1 | BP13: 1 | BQ13: 1 | BR13: 1 | BS13: 1 | BT13: 1 | BU13: 1 | BV13: 1 | BW13: 1 | BX13: 1 | BY13: 1 | BZ13: 1 | CA13: 1 | CB13: 1 | CC13: 1 | CD13: 1 | CE13: 1 | CF13: 1 | CG13: 1 | CH13: 1 | CI13: 1 | CJ13: 1 | CK13: 1 | CL13: 1 | CM13: 1 | CN13: 1 | CO13: 1 | CP13: 1 | CQ13: 1 | CR13: 1 | CS13: 1 | CT13: 1 | CU13: 1 | CV13: 1 | CW13: 1 | CX13: 1 | CY13: 1 | CZ13: 1 | DA13: 1 | DB13: 1 | DC13: 1 | DD13: 1 | DE13: 1
... A109: RoW.Other Services | B109: 1 | C109: 1 | D109: 1 | E109: 1 | F109: 1 | G109: 1 | H109: 1 | I109: 1 | J109: 1 | K109: 1 | L109: 1 | M109: 1 | N109: 1 | O109: 1 | P109: 1 | Q109: 1 | R109: 1 | S109: 1 | T109: 1 | U109: 1 | V109: 1 | W109: 1 | X109: 1 | Y109: 1 | Z109: 1 | AA109: 1 | AB109: 1 | AC109: 1 | AD109: 1 | AE109: 1 | AF109: 1 | AG109: 1 | AH109: 1 | AI109: 1 | AJ109: 1 | AK109: 1 | AL109: 1 | AM109: 1 | AN109: 1 | AO109: 1 | AP109: 1 | AQ109: 1 | AR109: 1 | AS109: 1 | AT109: 1 | AU109: 1 | AV109: 1 | AW109: 1 | AX109: 1 | AY109: 1 | AZ109: 1 | BA109: 1 | BB109: 1 | BC109: 1 | BD109: 1 | BE109: 1 | BF109: 1 | BG109: 1 | BH109: 1 | BI109: 1 | BJ109: 1 | BK109: 1 | BL109: 1 | BM109: 1 | BN109: 1 | BO109: 1 | BP109: 1 | BQ109: 1 | BR109: 1 | BS109: 1 | BT109: 1 | BU109: 1 | BV109: 1 | BW109: 1 | BX109: 1 | BY109: 1 | BZ109: 1 | CA109: 1 | CB109: 1 | CC109: 1 | CD109: 1 | CE109: 1 | CF109: 1 | CG109: 1 | CH109: 1 | CI109: 1 | CJ109: 1 | CK109: 1 | CL109: 1 | CM109: 1 | CN109: 1 | CO109: 1 | CP109: 1 | CQ109: 1 | CR109: 1 | CS109: 1 | CT109: 1 | CU109: 1 | CV109: 1 | CW109: 1 | CX109: 1 | CY109: 1 | CZ109: 1 | DA109: 1 | DB109: 1 | DC109: 1 | DD109: 1 | DE109: 1

Sheet MRIO.flows
D1: EU | E1: EU | F1: EU | G1: EU | H1: EU | I1: EU | J1: EU | K1: EU | L1: EU | M1: EU | N1: EU | O1: EU | P1: EU | Q1: EU | R1: EU | S1: EU | T1: EU | U1: EU | V1: EU | W1: EU | X1: EU | Y1: EU | Z1: EU | AA1: EU | AB1: EU | AC1: EU | AD1: EU | AE1: EU | AF1: EU | AG1: EU | AH1: EU | AI1: EU | AJ1: EU | AK1: EU | AL1: EU | AM1: EU | AN1: EU | AO1: EU | AP1: EU | AQ1: EU | AR1: EU | AS1: EU | AT1: EU | AU1: EU | AV1: EU | AW1: EU | AX1: EU | AY1: EU | AZ1: EU | BA1: EU | BB1: EU | BC1: EU | BD1: EU | BE1: EU | BF1: RoW | BG1: RoW | BH1: RoW | BI1: RoW | BJ1: RoW | BK1: RoW | BL1: RoW | BM1: RoW | BN1: RoW | BO1: RoW | BP1: RoW | BQ1: RoW | BR1: RoW | BS1: RoW | BT1: RoW | BU1: RoW | BV1: RoW | BW1: RoW | BX1: RoW | BY1: RoW | BZ1: RoW | CA1: RoW | CB1: RoW | CC1: RoW | CD1: RoW | CE1: RoW | CF1: RoW | CG1: RoW | CH1: RoW | CI1: RoW | CJ1: RoW | CK1: RoW | CL1: RoW | CM1: RoW | CN1: RoW | CO1: RoW | CP1: RoW | CQ1: RoW | CR1: RoW | CS1: RoW | CT1: RoW | CU1: RoW | CV1: RoW | CW1: RoW | CX1: RoW | CY1: RoW | CZ1: RoW | DA1: RoW | DB1: RoW | DC1: RoW | DD1: RoW | DE1: RoW | DF1: RoW | DG1: RoW | DH1: EU | DI1: EU | DJ1: EU | DK1: EU | DL1: RoW | DM1: RoW | DN1: RoW | DO1: RoW | DP1: INTERMEDIATE DEMAND | DQ1: FINAL DEMAND | DR1: AGGREGATE DEMAND
D2: Sector | E2: Sector | F2: Sector | G2: Sector | H2: Sector | I2: Sector | J2: Sector | K2: Sector | L2: Sector | M2: Sector | N2: Sector | O2: Sector | P2: Sector | Q2: Sector | R2: Sector | S2: Sector | T2: Sector | U2: Sector | V2: Sector | W2: Sector | X2: Sector | Y2: Sector | Z2: Sector | AA2: Sector | AB2: Sector | AC2: Sector | AD2: Sector | AE2: Sector | AF2: Sector | AG2: Sector | AH2: Sector | AI2: Sector | AJ2: Sector | AK2: Sector | AL2: Sector | AM2: Sector | AN2: Sector | AO2: Sector | AP2: Sector | AQ2: Sector | AR2: Sector | AS2: Sector | AT2: Sector | AU2: Sector | AV2: Sector | AW2: Sector | AX2: Sector | AY2: Sector | AZ2: Sector | BA2: Sector | BB2: Sector | BC2: Sector | BD2: Sector | BE2: Sector | BF2: Sector | BG2: Sector | BH2: Sector | BI2: Sector | BJ2: Sector | BK2: Sector | BL2: Sector | BM2: Sector | BN2: Sector | BO2: Sector | BP2: Sector | BQ2: Sector | BR2: Sector | BS2: Sector | BT2: Sector | BU2: Sector | BV2: Sector | BW2: Sector | BX2: Sector | BY2: Sector | BZ2: Sector | CA2: Sector | CB2: Sector | CC2: Sector | CD2: Sector | CE2: Sector | CF2: Sector | CG2: Sector | CH2: Sector | CI2: Sector | CJ2: Sector | CK2: Sector | CL2: Sector | CM2: Sector | CN2: Sector | CO2: Sector | CP2: Sector | CQ2: Sector | CR2: Sector | CS2: Sector | CT2: Sector | CU2: Sector | CV2: Sector | CW2: Sector | CX2: Sector | CY2: Sector | CZ2: Sector | DA2: Sector | DB2: Sector | DC2: Sector | DD2: Sector | DE2: Sector | DF2: Sector | DG2: Sector | DH2: Consumption category | DI2: Consumption category | DJ2: Consumption category | DK2: Consumption category | DL2: Consumption category | DM2: Consumption category | DN2: Consumption category | DO2: Consumption category
D3: Agriculture | E3: Animal Farming | F3: Forestry, logging and related service activities (02) | G3: Fishing, operating of fish hatcheries and fish farms; service activities incidental to fishing (05) | H3: Extraction of Fossil-Fuels | I3: Mining & Quarrying of raw materials | J3: Processing of meat | K3: Processing of other food&beverage | L3: Manufacture of tobacco products (16) | M3: Manufacture of textiles | N3: Manufacture of wood and of products of wood and cork, except furniture; manufacture of articles of straw and plaiting materials (20) | O3: Re-processing of secondary wood material into new wood material | P3: Pulp | Q3: Re-processing of secondary paper into new pulp | R3: Paper | S3: Processing of Fossil Fuels | T3: Plastics, basic | U3: Re-processing of secondary plastic into new plastic | V3: Manufacture of Chemicals | W3: Manufacture of rubber and plastic products (25) | X3: Manufacture of glass and glass products | Y3: Re-processing of secondary glass into new glass | Z3: Manufacture of other non-metallic mineral products | AA3: Manufacture of cement, lime and plaster | AB3: Re-processing of ash into clinker | AC3: Manufacture of Metals | AD3: Re-processing of Metals | AE3: Manufacture of durable goods | AF3: Manufacture of furniture; manufacturing n.e.c. (36) | AG3: Recycling | AH3: Production of electricity by fossil fuels | AI3: Production of electricity by renewable energy | AJ3: Transmission & Distribution | AK3: Manufacture of gas; distribution of gaseous fuels through mains | AL3: Water | AM3: Construction (45) | AN3: Re-processing of secondary construction material into aggregates | AO3: Sale, maintenance, repair of motor vehicles, motor vehicles parts, motorcycles, motor cycles parts and accessoiries | AP3: Retail sale of automotive fuel | AQ3: Retail & Wholesale trade | AR3: Leisure Services | AS3: Transport | AT3: KIBS | AU3: Real estate activities (70) | AV3: Renting of machinery and equipment without operator and of personal and household goods (71) | AW3: Research and development (73) | AX3: Public administration and defence; compulsory social security (75) | AY3: Education (80) | AZ3: Health and social work (85) | BA3: Incineration of Waste | BB3: Biogas & Composting | BC3: Waste water | BD3: Landfill of Waste | BE3: Other Services | BF3: Agriculture | BG3: Animal Farming | BH3: Forestry, logging and related service activities (02) | BI3: Fishing, operating of fish hatcheries and fish farms; service activities incidental to fishing (05) | BJ3: Extraction of Fossil-Fuels | BK3: Mining & Quarrying of raw materials | BL3: Processing of meat | BM3: Processing of other food&beverage | BN3: Manufacture of tobacco products (16) | BO3: Manufacture of textiles | BP3: Manufacture of wood and of products of wood and cork, except furniture; manufacture of articles of straw and plaiting materials (20) | BQ3: Re-processing of secondary wood material into new wood material | BR3: Pulp | BS3: Re-processing of secondary paper into new pulp | BT3: Paper | BU3: Processing of Fossil Fuels | BV3: Plastics, basic | BW3: Re-processing of secondary plastic into new plastic | BX3: Manufacture of Chemicals | BY3: Manufacture of rubber and plastic products (25) | BZ3: Manufacture of glass and glass products | CA3: Re-processing of secondary glass into new glass | CB3: Manufacture of other non-metallic mineral products | CC3: Manufacture of cement, lime and plaster | CD3: Re-processing of ash into clinker | CE3: Manufacture of Metals | CF3: Re-processing of Metals | CG3: Manufacture of durable goods | CH3: Manufacture of furniture; manufacturing n.e.c. (36) | CI3: Recycling | CJ3: Production of electricity by fossil fuels | CK3: Production of electricity by renewable energy | CL3: Transmission & Distribution | CM3: Manufacture of gas; distribution of gaseous fuels through mains | CN3: Water | CO3: Construction (45) | CP3: Re-processing of secondary construction material into aggregates | CQ3: Sale, maintenance, repair of motor vehicles, motor vehicles parts, motorcycles, motor cycles parts and accessoiries | CR3: Retail sale of automotive fuel | CS3: Retail & Wholesale trade | CT3: Leisure Services | CU3: Transport | CV3: KIBS | CW3: Real estate activities (70) | CX3: Renting of machinery and equipment without operator and of personal and household goods (71) | CY3: Research and development (73) | CZ3: Public administration and defence; compulsory social security (75) | DA3: Education (80) | DB3: Health and social work (85) | DC3: Incineration of Waste | DD3: Biogas & Composting | DE3: Waste water | DF3: Landfill of Waste | DG3: Other Services | DH3: Consumption | DI3: Final consumption expenditure by government | DJ3: GFCF | DK3: Exports: Total (fob) | DL3: Consumption | DM3: Final consumption expenditure by government | DN3: GFCF | DO3: Exports: Total (fob)
A4: EU | B4: Sector | C4: Agriculture | D4: 8803.6991 | E4: 16240.262 | F4: 360.83742 | G4: 25.311202 | H4: 13.129934 | I4: 20.441096 | J4: 11248.607 | K4: 50197.749 | L4: 555.0464 | M4: 573.00978 | N4: 44.470807 | O4: 18.993006 | P4: 7.5353694 | Q4: 13.55555 | R4: 71.622524 | S4: 82.84664 | T4: 579.01984 | U4: 183.68161 | V4: 324.90242 | W4: 42.13407 | X4: 1.3361302 | Y4: 0.57214146 | Z4: 11.433018 | AA4: 7.4762978 | AB4: 1.9506785 | AC4: 20.132222 | AD4: 11.58373 | AE4: 234.37868 | AF4: 24.056063 | AG4: 4.7169939 | AH4: 21.157032 | AI4: 48.754638 | AJ4: 22.960809 | AK4: 10.871347 | AL4: 18.598645 | AM4: 357.71997 | AN4: 1.0825321 | AO4: 14.082722 | AP4: 9.7755484 | AQ4: 1292.4246 | AR4: 6765.0953 | AS4: 286.9124 | AT4: 1531.1713 | AU4: 108.42601 | AV4: 69.029443 | AW4: 73.580716 | AX4: 1057.9237 | AY4: 294.98862 | AZ4: 1413.7604 | BA4: 41.957275 | BB4: 6.9276913 | BC4: 7.6941768 | BD4: 14.983323 | BE4: 178.78636 | BF4: 965.2175 | BG4: 692.84923 | BH4: 88.03311 | BI4: 10.027684 | BJ4: 106.29395 | BK4: 56.264184 | BL4: 333.59113 | BM4: 2368.4797 | BN4: 527.08792 | BO4: 533.44196 | BP4: 42.839671 | BQ4: 0.44490747 | BR4: 9.971673 | BS4: 0.47262363 | BT4: 53.828867 | BU4: 78.205172 | BV4: 6.4553879 | BW4: 0.59234732 | BX4: 2381.9896 | BY4: 2.7466132 | BZ4: 5.393543 | CA4: 0.029553505 | CB4: 11.139308 | CC4: 5.3166818 | CD4: 0.045894036 | CE4: 213.84242 | CF4: 0.54887531 | CG4: 114.69785 | CH4: 16.129967 | CI4: 9.9723009 | CJ4: 124.28609 | CK4: 27.794842 | CL4: 74.950895 | CM4: 123.40404 | CN4: 2.9415742 | CO4: 223.32075 | CP4: 0.00054050234 | CQ4: 40.514858 | CR4: 28.301149 | CS4: 131.90605 | CT4: 868.60511 | CU4: 126.0903 | CV4: 581.15382 | CW4: 366.62994 | CX4: 165.65554 | CY4: 43.541988 | CZ4: 93.481002 | DA4: 232.95168 | DB4: 396.15983 | DC4: 0.16436782 | DD4: 0.070122378 | DE4: 0.52296247 | DF4: 96.476838 | DG4: 233.29362 | DH4: 86708.162 | DI4: 772.08459 | DJ4: 4035.6257 | DK4: 0 | DL4: 11170.928 | DM4: 3.9765862 | DN4: 205.64305 | DO4: 0 | DP4: =SUM(D4:DG4) -> 115991.32 | DQ4: =SUM(DH4:DO4) -> 102896.42 | DR4: =DP4+DQ4 -> 218887.74
A5: EU | B5: Sector | C5: Animal Farming | D5: 21.516292 | E5: 1410.103 | F5: 6.295688 | G5: 2.3099831 | H5: 12.90772 | I5: 6.5145027 | J5: 83314.272 | K5: 29544.863 | L5: 40.421047 | M5: 372.19566 | N5: 13.283675 | O5: 3.6478333 | P5: 1.624197 | Q5: 4.4196655 | R5: 28.307719 | S5: 17.801515 | T5: 35.081518 | U5: 14.23652 | V5: 15.886971 | W5: 13.143119 | X5: 0.76574425 | Y5: 0.32176234 | Z5: 4.6070878 | AA5: 6.0913636 | AB5: 1.3559557 | AC5: 16.440439 | AD5: 5.2847002 | AE5: 187.69476 | AF5: 14.384862 | AG5: 2.387502 | AH5: 23.283812 | AI5: 4.4548176 | AJ5: 42.583807 | AK5: 10.999867 | AL5: 5.6027332 | AM5: 100.26945 | AN5: 1.4128073 | AO5: 9.9079229 | AP5: 5.308718 | AQ5: 744.27893 | AR5: 1461.0087 | AS5: 185.26292 | AT5: 552.76062 | AU5: 46.716625 | AV5: 59.407725 | AW5: 25.547914 | AX5: 221.33746 | AY5: 74.157706 | AZ5: 277.63048 | BA5: 41.253359 | BB5: 5.8148076 | BC5: 3.1439891 | BD5: 4.3001306 | BE5: 168.24091 | BF5: 31.060319 | BG5: 49.230982 | BH5: 1.0458534 | BI5: 0.95107341 | BJ5: 19.86017 | BK5: 18.008154 | BL5: 156.27782 | BM5: 138.60114 | BN5: 0.30296561 | BO5: 90.725894 | BP5: 1.310645 | BQ5: 0.44996364 | BR5: 0.18598812 | BS5: 0.10919755 | BT5: 2.7263039 | BU5: 238.68922 | BV5: 0.78615175 | BW5: 0.092025501 | BX5: 391.66317 | BY5: 8.27457 | BZ5: 0.63210044 | CA5: 0.012600311 | CB5: 0.72790853 | CC5: 0.43123645 | CD5: 0.019888476 | CE5: 109.19383 | CF5: 0.15386147 | CG5: 19.741343 | CH5: 11.012061 | CI5: 1.0565367 | CJ5: 0.96438033 | CK5: 1.6354781 | CL5: 0.37273646 | CM5: 5.7113697 | CN5: 0.13815267 | CO5: 13.273804 | CP5: 0.00050490223 | CQ5: 2.7435637 | CR5: 0.21960793 | CS5: 13.191303 | CT5: 105.08456 | CU5: 9.4502403 | CV5: 44.405097 | CW5: 32.239863 | CX5: 21.393939 | CY5: 8.2711632 | CZ5: 14.801017 | DA5: 54.790409 | DB5: 50.865629 | DC5: 0.1751225 | DD5: 0.096714204 | DE5: 0.61516198 | DF5: 0.65271707 | DG5: 48.677188 | DH5: 31069.75 | DI5: 338.35783 | DJ5: 10212.043 | DK5: 0 | DL5: 740.59621 | DM5: 34.270392 | DN5: 640.05016 | DO5: 0 | DP5: =SUM(D5:DG5) -> 120915.95 | DQ5: =SUM(DH5:DO5) -> 43035.068 | DR5: =DP5+DQ5 -> 163951.02
A6: EU | B6: Sector | C6: Forestry, logging and related service activities (02) | D6: 89.57997 | E6: 289.71842 | F6: 8819.7701 | G6: 4.4464753 | H6: 55.948028 | I6: 46.959943 | J6: 69.119391 | K6: 322.69468 | L6: 55.499172 | M6: 73.983448 | N6: 11774.783 | O6: 88.823391 | P6: 763.57891 | Q6: 8.6042431 | R6: 2224.1065 | S6: 6.3571942 | T6: 45.363287 | U6: 14.832391 | V6: 45.929935 | W6: 100.48155 | X6: 6.914999 | Y6: 1.4944305 | Z6: 18.815196 | AA6: 15.412492 | AB6: 3.0757718 | AC6: 21.838022 | AD6: 6.76502 | AE6: 146.81855 | AF6: 464.44293 | AG6: 6.0429745 | AH6: 15.852174 | AI6: 162.63867 | AJ6: 15.66696 | AK6: 4.3639313 | AL6: 14.566218 | AM6: 1014.2768 | AN6: 0.032996608 | AO6: 10.195033 | AP6: 1.755637 | AQ6: 121.23766 | AR6: 126.6466 | AS6: 70.861333 | AT6: 185.78118 | AU6: 65.027106 | AV6: 3.2025325 | AW6: 7.1310122 | AX6: 138.38523 | AY6: 23.869501 | AZ6: 30.322802 | BA6: 4.6411499 | BB6: 1.3993722 | BC6: 1.2102875 | BD6: 2.8859218 | BE6: 39.116463 | BF6: 8.8127152 | BG6: 13.729107 | BH6: 72.13864 | BI6: 0.24548987 | BJ6: 12.133331 | BK6: 1.0724971 | BL6: 1.2658671 | BM6: 27.35311 | BN6: 9.9496398 | BO6: 19.413531 | BP6: 245.01455 | BQ6: 3.5332062 | BR6: 7.8631387 | BS6: 0.022884189 | BT6: 139.46367 | BU6: 1.0020514 | BV6: 0.70259084 | BW6: 0.073392036 | BX6: 168.58203 | BY6: 72.857993 | BZ6: 0.41698603 | CA6: 0.02283068 | CB6: 0.80617596 | CC6: 0.30200749 | CD6: 0.010531091 | CE6: 9.2425871 | CF6: 0.023435224 | CG6: 8.7100393 | CH6: 38.867712 | CI6: 0.75641906 | CJ6: 0.17030768 | CK6: 0.17687698 | CL6: 0.17643505 | CM6: 0.3416055 | CN6: 0.069872123 | CO6: 111.76247 | CP6: 4.7273205e-05 | CQ6: 0.60852597 | CR6: 0.12300299 | CS6: 7.3869222 | CT6: 10.577153 | CU6: 16.246134 | CV6: 6.4365494 | CW6: 8.7620665 | CX6: 1.3839587 | CY6: 3.5946734 | CZ6: 5.3642951 | DA6: 2.8306211 | DB6: 5.6786091 | DC6: 0.13131392 | DD6: 0.030640128 | DE6: 0.055511251 | DF6: 0.12407026 | DG6: 1.6140561 | DH6: 6546.6653 | DI6: 345.76523 | DJ6: 4631.7332 | DK6: 0 | DL6: 321.66744 | DM6: 3.4734653 | DN6: 35.834991 | DO6: 0 | DP6: =SUM(D6:DG6) -> 28701.3 | DQ6: =SUM(DH6:DO6) -> 11885.14 | DR6: =DP6+DQ6 -> 40586.44
A7: EU | B7: Sector | C7: Fishing, operating of fish hatcheries and fish farms; service activities incidental to fishing (05) | D7: 1.1935058 | E7: 63.336381 | F7: 15.462937 | G7: 442.40274 | H7: 0.29474942 | I7: 0.30574242 | J7: 797.08059 | K7: 1138.6526 | L7: 18.180075 | M7: 21.601083 | N7: 1.6828152 | O7: 0.13382889 | P7: 0.20092095 | Q7: 0.23202509 | R7: 2.8277997 | S7: 1.0512411 | T7: 52.967871 | U7: 14.872061 | V7: 6.1699391 | W7: 14.705098 | X7: 0.18983727 | Y7: 0.08398566 | Z7: 0.27910818 | AA7: 0.38975227 | AB7: 0.11129984 | AC7: 0.49649432 | AD7: 0.45480829 | AE7: 8.5136366 | AF7: 0.80390806 | AG7: 0.65062055 | AH7: 9.1552696 | AI7: 3.7910555 | AJ7: 4.6680886 | AK7: 7.0737141 | AL7: 9.0143175 | AM7: 4.4252201 | AN7: 87.853237 | AO7: 4.3095728 | AP7: 3.3220867 | AQ7: 22.504829 | AR7: 1016.797 | AS7: 77.89723 | AT7: 32.302143 | AU7: 3.2530291 | AV7: 0.95595871 | AW7: 2.1014594 | AX7: 33.725472 | AY7: 19.768622 | AZ7: 88.115206 | BA7: 1.4518367 | BB7: 0.30347838 | BC7: 0.26327414 | BD7: 1.2605387 | BE7: 20.444427 | BF7: 0.61787243 | BG7: 1.4115068 | BH7: 0.04847588 | BI7: 66.132301 | BJ7: 0.40886281 | BK7: 0.38943538 | BL7: 285.17185 | BM7: 69.569587 | BN7: 0.056899713 | BO7: 0.93919915 | BP7: 0.09018245 | BQ7: 0.018658586 | BR7: 0.027870126 | BS7: 0.012619982 | BT7: 0.23746988 | BU7: 1.5193682 | BV7: 0.13697376 | BW7: 0.0063188725 | BX7: 69.205375 | BY7: 0.1392341 | BZ7: 0.045556426 | CA7: 0.00088111356 | CB7: 0.12170564 | CC7: 0.059537975 | CD7: 0.0016212622 | CE7: 0.37536731 | CF7: 0.016546925 | CG7: 2.1513659 | CH7: 0.18643101 | CI7: 0.072237582 | CJ7: 0.1785108 | CK7: 0.038196783 | CL7: 0.089403264 | CM7: 0.087307882 | CN7: 0.025804673 | CO7: 1.8521021 | CP7: 4.4060931e-05 | CQ7: 0.16384997 | CR7: 0.31206286 | CS7: 2.2777897 | CT7: 38.935992 | CU7: 9.0904408 | CV7: 4.465411 | CW7: 0.79988689 | CX7: 0.2500641 | CY7: 0.5621106 | CZ7: 4.8381069 | DA7: 3.2393843 | DB7: 19.526558 | DC7: 0.015642556 | DD7: 0.0058069869 | DE7: 0.023898679 | DF7: 0.096913235 | DG7: 3.5577435 | DH7: 9300.7622 | DI7: 6.6649199 | DJ7: 95.659851 | DK7: 0 | DL7: 450.69839 | DM7: 0.12423353 | DN7: 3.8911598 | DO7: 0 | DP7: =SUM(D7:DG7) -> 4649.6888 | DQ7: =SUM(DH7:DO7) -> 9857.8007 | DR7: =DP7+DQ7 -> 14507.49
A8: EU | B8: Sector | C8: Extraction of Fossil-Fuels | D8: 213.56477 | E8: 153.0602 | F8: 20.540615 | G8: 3.4629964 | H8: 1841.0068 | I8: 165.22296 | J8: 177.50445 | K8: 248.82059 | L8: 16.261391 | M8: 567.34811 | N8: 286.26005 | O8: 61.344885 | P8: 98.861554 | Q8: 54.020036 | R8: 98.180084 | S8: 11867.415 | T8: 575.02026 | U8: 41.13826 | V8: 763.14349 | W8: 136.53935 | X8: 52.88625 | Y8: 45.03402 | Z8: 216.83546 | AA8: 312.92884 | AB8: 64.425131 | AC8: 1948.7127 | AD8: 278.98938 | AE8: 603.58281 | AF8: 308.16191 | AG8: 29.347179 | AH8: 15270.787 | AI8: 65.661219 | AJ8: 302.83693 | AK8: 2545.0497 | AL8: 1793.2118 | AM8: 510.88466 | AN8: 0.14582771 | AO8: 40.778683 | AP8: 26.772952 | AQ8: 281.26441 | AR8: 162.74962 | AS8: 490.06228 | AT8: 698.80377 | AU8: 249.22008 | AV8: 44.928811 | AW8: 69.491978 | AX8: 439.17428 | AY8: 97.252992 | AZ8: 143.21472 | BA8: 24.864159 | BB8: 10.276423 | BC8: 8.03165 | BD8: 14.143652 | BE8: 254.9043 | BF8: 17.043234 | BG8: 6.5733322 | BH8: 0.90046739 | BI8: 0.86606329 | BJ8: 196.92474 | BK8: 21.163117 | BL8: 10.56754 | BM8: 14.606403 | BN8: 0.62027478 | BO8: 22.375288 | BP8: 512.26574 | BQ8: 0.7572404 | BR8: 8.967718 | BS8: 0.22659783 | BT8: 8.1064575 | BU8: 1776.7115 | BV8: 44.077106 | BW8: 0.18674364 | BX8: 136.33049 | BY8: 8.995227 | BZ8: 6.018248 | CA8: 0.51030165 | CB8: 15.93318 | CC8: 21.11591 | CD8: 0.94162236 | CE8: 62.210594 | CF8: 1.552043 | CG8: 47.905854 | CH8: 401.62386 | CI8: 0.46554732 | CJ8: 554.54075 | CK8: 7.4413355 | CL8: 6.0553599 | CM8: 319.05987 | CN8: 17.080984 | CO8: 46.446416 | CP8: 0.025183018 | CQ8: 2.8754536 | CR8: 0.52568438 | CS8: 18.941549 | CT8: 14.99909 | CU8: 42.734143 | CV8: 60.095026 | CW8: 18.48284 | CX8: 3.4862807 | CY8: 3.5241192 | CZ8: 43.136503 | DA8: 9.9397097 | DB8: 14.931148 | DC8: 0.3561592 | DD8: 0.15900909 | DE8: 0.97433489 | DF8: 1.4485137 | DG8: 6.9285451 | DH8: 5227.7755 | DI8: 445.42273 | DJ8: 5953.6768 | DK8: 0 | DL8: 141.53321 | DM8: 7.139189 | DN8: 87.740654 | DO8: 0 | DP8: =SUM(D8:DG8) -> 49334.862 | DQ8: =SUM(DH8:DO8) -> 11863.288 | DR8: =DP8+DQ8 -> 61198.15
A9: EU | B9: Sector | C9: Mining & Quarrying of raw materials | D9: 250.34178 | E9: 179.99094 | F9: 15.633115 | G9: 58.73029 | H9: 49.880604 | I9: 3734.3365 | J9: 204.8189 | K9: 630.29165 | L9: 2.6743811 | M9: 79.811095 | N9: 39.462919 | O9: 17.014555 | P9: 115.56906 | Q9: 307.82808 | R9: 344.94947 | S9: 99.257143 | T9: 415.80809 | U9: 149.09865 | V9: 1413.713 | W9: 295.28909 | X9: 1139.9364 | Y9: 24.6696 | Z9: 3715.6973 | AA9: 6271.028 | AB9: 1587.931 | AC9: 6731.704 | AD9: 361.01916 | AE9: 2545.6808 | AF9: 195.52211 | AG9: 58.305495 | AH9: 138.87726 | AI9: 21.46758 | AJ9: 156.14668 | AK9: 357.57985 | AL9: 126.84477 | AM9: 15689.708 | AN9: 0.15188906 | AO9: 34.336889 | AP9: 33.046904 | AQ9: 695.45494 | AR9: 197.21307 | AS9: 607.19654 | AT9: 700.65161 | AU9: 270.42586 | AV9: 50.034857 | AW9: 51.787679 | AX9: 953.99528 | AY9: 42.774848 | AZ9: 121.54988 | BA9: 90.090041 | BB9: 41.022572 | BC9: 31.11142 | BD9: 68.621457 | BE9: 69.225751 | BF9: 25.820393 | BG9: 12.829301 | BH9: 4.2590738 | BI9: 17.762812 | BJ9: 47.037 | BK9: 219.34005 | BL9: 29.62026 | BM9: 31.335019 | BN9: 1.7766631 | BO9: 32.69568 | BP9: 3.7950264 | BQ9: 0.2366714 | BR9: 3.1562956 | BS9: 1.025123 | BT9: 16.667719 | BU9: 54.084865 | BV9: 27.645828 | BW9: 1.6776132 | BX9: 727.86213 | BY9: 22.97252 | BZ9: 120.50074 | CA9: 0.12191388 | CB9: 205.01338 | CC9: 124.36726 | CD9: 4.2476948 | CE9: 808.12575 | CF9: 7.5279926 | CG9: 336.53464 | CH9: 124.41524 | CI9: 2.5326863 | CJ9: 6.8946001 | CK9: 13.905337 | CL9: 2.4017948 | CM9: 5.5061331 | CN9: 1.9318749 | CO9: 612.16352 | CP9: 0.00039235857 | CQ9: 6.3350299 | CR9: 1.0640407 | CS9: 19.203544 | CT9: 34.759035 | CU9: 28.206573 | CV9: 80.922111 | CW9: 55.420003 | CX9: 18.089259 | CY9: 4.505931 | CZ9: 26.41693 | DA9: 67.054742 | DB9: 97.133831 | DC9: 0.63365617 | DD9: 0.25200119 | DE9: 1.4372561 | DF9: 5.1982267 | DG9: 21.61133 | DH9: 1586.9032 | DI9: 114.54862 | DJ9: 3317.4548 | DK9: 0 | DL9: 238.55977 | DM9: 5.3827142 | DN9: 271.64934 | DO9: 0 | DP9: =SUM(D9:DG9) -> 55711.343 | DQ9: =SUM(DH9:DO9) -> 5534.4985 | DR9: =DP9+DQ9 -> 61245.842
A10: EU | B10: Sector | C10: Processing of meat | D10: 58.805964 | E10: 9946.4529 | F10: 28.827743 | G10: 169.57015 | H10: 22.582744 | I10: 101.91465 | J10: 25945.669 | K10: 25075.896 | L10: 39.319898 | M10: 528.22914 | N10: 40.59153 | O10: 15.03719 | P10: 12.430162 | Q10: 29.807955 | R10: 177.47816 | S10: 102.76103 | T10: 626.36658 | U10: 214.74827 | V10: 313.70574 | W10: 251.5576 | X10: 7.9699982 | Y10: 3.1329445 | Z10: 53.286811 | AA10: 26.467305 | AB10: 7.0279191 | AC10: 65.948199 | AD10: 36.499292 | AE10: 674.10749 | AF10: 130.60992 | AG10: 41.51797 | AH10: 90.036854 | AI10: 18.03651 | AJ10: 62.764418 | AK10: 44.678338 | AL10: 37.889747 | AM10: 464.20557 | AN10: 0.098014878 | AO10: 84.458272 | AP10: 80.529575 | AQ10: 1409.9657 | AR10: 23595.967 | AS10: 1120.9493 | AT10: 2188.3743 | AU10: 408.63745 | AV10: 196.00266 | AW10: 334.63302 | AX10: 1402.9292 | AY10: 1513.1631 | AZ10: 5199.1322 | BA10: 22.768952 | BB10: 9.4415421 | BC10: 10.662515 | BD10: 20.162864 | BE10: 361.80708 | BF10: 184.71959 | BG10: 569.12413 | BH10: 5.2233858 | BI10: 105.96036 | BJ10: 42.592822 | BK10: 16.667262 | BL10: 2365.956 | BM10: 2785.3465 | BN10: 5.5053063 | BO10: 179.5585 | BP10: 4.0508118 | BQ10: 0.28692511 | BR10: 1.9666661 | BS10: 3.4792392 | BT10: 31.816169 | BU10: 22.901444 | BV10: 27.779425 | BW10: 3.1415629 | BX10: 961.62151 | BY10: 41.941335 | BZ10: 3.0241912 | CA10: 0.28434039 | CB10: 11.25933 | CC10: 3.3404822 | CD10: 0.42889634 | CE10: 19.201804 | CF10: 4.1956142 | CG10: 202.10311 | CH10: 12.344112 | CI10: 12.081562 | CJ10: 19.41272 | CK10: 4.3346015 | CL10: 6.0295486 | CM10: 5.406553 | CN10: 3.8645703 | CO10: 34.568085 | CP10: 0.0029767855 | CQ10: 9.9907894 | CR10: 6.8499649 | CS10: 113.64539 | CT10: 2977.1509 | CU10: 95.333378 | CV10: 208.32399 | CW10: 28.011597 | CX10: 106.50484 | CY10: 22.749944 | CZ10: 244.34646 | DA10: 144.10386 | DB10: 649.29965 | DC10: 0.87931145 | DD10: 0.72107087 | DE10: 3.1979035 | DF10: 4.4395441 | DG10: 69.765458 | DH10: 231893.02 | DI10: 829.84077 | DJ10: 2721.3509 | DK10: 0 | DL10: 24667.798 | DM10: 27.683211 | DN10: 179.45972 | DO10: 0 | DP10: =SUM(D10:DG10) -> 115812.45 | DQ10: =SUM(DH10:DO10) -> 260319.16 | DR10: =DP10+DQ10 -> 376131.61
A11: EU | B11: Sector | C11: Processing of other food&beverage | D11: 35.091975 | E11: 21828.082 | F11: 46.488174 | G11: 191.18499 | H11: 27.384445 | I11: 114.43386 | J11: 21193.129 | K11: 37420.895 | L11: 35.85414 | M11: 1561.5123 | N11: 71.060481 | O11: 24.782315 | P11: 18.665851 | Q11: 45.042256 | R11: 418.21659 | S11: 141.28291 | T11: 2158.8044 | U11: 458.66961 | V11: 1239.7135 | W11: 228.32223 | X11: 5.8468107 | Y11: 2.3655345 | Z11: 102.57716 | AA11: 24.748507 | AB11: 5.2629687 | AC11: 116.37395 | AD11: 48.647335 | AE11: 808.38688 | AF11: 195.49401 | AG11: 71.038236 | AH11: 188.52804 | AI11: 22.608165 | AJ11: 65.1205 | AK11: 58.124853 | AL11: 67.966103 | AM11: 923.92899 | AN11: 0.053113967 | AO11: 105.04075 | AP11: 99.445998 | AQ11: 1283.0654 | AR11: 27304.29 | AS11: 1088.0615 | AT11: 2287.8927 | AU11: 380.16878 | AV11: 201.49585 | AW11: 310.40028 | AX11: 1675.9327 | AY11: 1725.767 | AZ11: 6595.9136 | BA11: 28.849842 | BB11: 8.4462802 | BC11: 22.820355 | BD11: 38.875271 | BE11: 395.99104 | BF11: 74.770485 | BG11: 1421.9148 | BH11: 15.363134 | BI11: 97.254468 | BJ11: 44.83621 | BK11: 25.501136 | BL11: 894.27459 | BM11: 4620.7073 | BN11: 7.3126645 | BO11: 180.32862 | BP11: 7.4632118 | BQ11: 0.3765732 | BR11: 2.7256164 | BS11: 4.8295119 | BT11: 46.892794 | BU11: 44.139059 | BV11: 27.202865 | BW11: 3.1679531 | BX11: 720.86317 | BY11: 62.284496 | BZ11: 4.3806688 | CA11: 0.30419467 | CB11: 13.472863 | CC11: 6.1843891 | CD11: 0.48858584 | CE11: 37.805242 | CF11: 5.6127741 | CG11: 225.51506 | CH11: 30.137499 | CI11: 11.79447 | CJ11: 24.478567 | CK11: 7.770822 | CL11: 12.832394 | CM11: 9.3753973 | CN11: 6.3139901 | CO11: 391.08402 | CP11: 0.0027557813 | CQ11: 16.703691 | CR11: 8.4665799 | CS11: 232.82389 | CT11: 5172.621 | CU11: 291.32907 | CV11: 261.31908 | CW11: 31.861019 | CX11: 52.933018 | CY11: 28.200022 | CZ11: 240.79609 | DA11: 176.58927 | DB11: 644.43082 | DC11: 0.88207775 | DD11: 0.58988714 | DE11: 1.4465938 | DF11: 12.015496 | DG11: 84.382827 | DH11: 302148.24 | DI11: 778.89246 | DJ11: 3807.3481 | DK11: 0 | DL11: 41634.874 | DM11: 78.812984 | DN11: 267.34237 | DO11: 0 | DP11: =SUM(D11:DG11) -> 149865.3 | DQ11: =SUM(DH11:DO11) -> 348715.51 | DR11: =DP11+DQ11 -> 498580.81
A12: EU | B12: Sector | C12: Manufacture of tobacco products (16) | D12: 8.1863784 | E12: 19.030173 | F12: 1.5328489 | G12: 0.54117537 | H12: 3.4815553 | I12: 1.4746285 | J12: 32.055095 | K12: 28.224828 | L12: 394.20187 | M12: 14.412492 | N12: 1.3229335 | O12: 2.1622269 | P12: 0.72904948 | Q12: 0.87405367 | R12: 23.390313 | S12: 8.2697352 | T12: 9.735365 | U12: 2.7489574 | V12: 9.8939249 | W12: 8.9380885 | X12: 0.39505872 | Y12: 0.11342645 | Z12: 0.94379619 | AA12: 1.193906 | AB12: 0.38657757 | AC12: 499.85047 | AD12: 52.283513 | AE12: 94.832694 | AF12: 4.7158061 | AG12: 0.66697464 | AH12: 9.4105658 | AI12: 2.083574 | AJ12: 1.8817353 | AK12: 5.8336991 | AL12: 1.2266984 | AM12: 76.115044 | AN12: 0.0046872732 | AO12: 6.6933062 | AP12: 1.0874854 | AQ12: 191.97218 | AR12: 336.97189 | AS12: 57.181167 | AT12: 160.67751 | AU12: 12.918326 | AV12: 12.127279 | AW12: 9.0420482 | AX12: 119.84071 | AY12: 12.103816 | AZ12: 14.281576 | BA12: 2.8442876 | BB12: 0.62930708 | BC12: 2.3938085 | BD12: 3.0787067 | BE12: 65.015436 | BF12: 2.901668 | BG12: 0.85593995 | BH12: 1.2211282 | BI12: 0.25107351 | BJ12: 5.4624211 | BK12: 1.3129006 | BL12: 7.1260583 | BM12: 6.0879446 | BN12: 15.468399 | BO12: 3.9820979 | BP12: 0.56946757 | BQ12: 0.0062007486 | BR12: 0.032074718 | BS12: 0.012286288 | BT12: 2.147714 | BU12: 2.8471883 | BV12: 0.17883754 | BW12: 0.0074399297 | BX12: 60.897567 | BY12: 0.6814061 | BZ12: 0.67123333 | CA12: 0.0036177072 | CB12: 1.6903541 | CC12: 0.72852001 | CD12: 0.0046086029 | CE12: 32.364196 | CF12: 0.62497302 | CG12: 11.393804 | CH12: 2.1582867 | CI12: 0.73450851 | CJ12: 2.939429 | CK12: 0.72638464 | CL12: 0.66911117 | CM12: 3.7814635 | CN12: 0.32007213 | CO12: 4.0240029 | CP12: 0.00019807552 | CQ12: 1.2221965 | CR12: 1.0023078 | CS12: 4.7442714 | CT12: 12.104791 | CU12: 4.7121479 | CV12: 22.164601 | CW12: 4.1054518 | CX12: 4.2501378 | CY12: 1.3647683 | CZ12: 4.8156928 | DA12: 3.8465754 | DB12: 4.4804912 | DC12: 0.045271273 | DD12: 0.013472119 | DE12: 0.20120624 | DF12: 1.829319 | DG12: 4.9430783 | DH12: 12663.349 | DI12: 29.155915 | DJ12: 932.3822 | DK12: 0 | DL12: 3921.8808 | DM12: 0.28552523 | DN12: 10.197401 | DO12: 0 | DP12: =SUM(D12:DG12) -> 2582.7331 | DQ12: =SUM(DH12:DO12) -> 17557.251 | DR12: =DP12+DQ12 -> 20139.984
A13: EU | B13: Sector | C13: Manufacture of textiles | D13: 371.49919 | E13: 221.32103 | F13: 72.31161 | G13: 230.70512 | H13: 78.36393 | I13: 65.069363 | J13: 182.12319 | K13: 463.1606 | L13: 35.659937 | M13: 49068.039 | N13: 218.01207 | O13: 147.8436 | P13: 37.266879 | Q13: 101.54048 | R13: 1267.9428 | S13: 50.918614 | T13: 350.69854 | U13: 85.18997 | V13: 697.05688 | W13: 1930.1103 | X13: 92.682026 | Y13: 35.486118 | Z13: 146.42225 | AA13: 95.519743 | AB13: 22.202565 | AC13: 285.84196 | AD13: 115.47454 | AE13: 6727.1397 | AF13: 1979.0189 | AG13: 84.805374 | AH13: 143.04041 | AI13: 19.309961 | AJ13: 106.65939 | AK13: 102.97724 | AL13: 69.646438 | AM13: 2424.0763 | AN13: 1.2742648 | AO13: 209.30895 | AP13: 57.520669 | AQ13: 769.32546 | AR13: 2479.5657 | AS13: 776.30519 | AT13: 1683.5293 | AU13: 174.1794 | AV13: 199.793 | AW13: 109.96754 | AX13: 1173.6202 | AY13: 217.48317 | AZ13: 1773.1272 | BA13: 112.77695 | BB13: 44.504999 | BC13: 42.041543 | BD13: 117.02123 | BE13: 683.63787 | BF13: 112.43947 | BG13: 34.172124 | BH13: 11.447789 | BI13: 48.834674 | BJ13: 88.291976 | BK13: 47.031349 | BL13: 30.225666 | BM13: 72.930613 | BN13: 19.871447 | BO13: 8279.7765 | BP13: 29.13419 | BQ13: 0.63665695 | BR13: 3.8923937 | BS13: 1.5680017 | BT13: 242.92135 | BU13: 28.568648 | BV13: 26.825363 | BW13: 1.8463209 | BX13: 3100.1556 | BY13: 290.51742 | BZ13: 15.600197 | CA13: 0.50023436 | CB13: 30.087131 | CC13: 9.8366416 | CD13: 0.18652538 | CE13: 61.239047 | CF13: 1.2909601 | CG13: 947.44941 | CH13: 506.638 | CI13: 13.710141 | CJ13: 22.181791 | CK13: 12.608782 | CL13: 16.447233 | CM13: 11.974498 | CN13: 9.6345734 | CO13: 1137.6255 | CP13: 0.041047299 | CQ13: 40.996489 | CR13: 8.2582067 | CS13: 349.65835 | CT13: 351.22317 | CU13: 176.88717 | CV13: 292.50165 | CW13: 48.409161 | CX13: 40.159466 | CY13: 84.280082 | CZ13: 383.48915 | DA13: 106.88106 | DB13: 472.85777 | DC13: 12.415784 | DD13: 3.7901919 | DE13: 9.3007188 | DF13: 20.344872 | DG13: 175.94743 | DH13: 135292.6 | DI13: 755.84039 | DJ13: 4510.4066 | DK13: 0 | DL13: 34673.503 | DM13: 44.046308 | DN13: 1129.0517 | DO13: 0 | DP13: =SUM(D13:DG13) -> 96595.659 | DQ13: =SUM(DH13:DO13) -> 176405.45 | DR13: =DP13+DQ13 -> 273001.1
A14: EU | B14: Sector | C14: Manufacture of wood and of products of wood and cork, except furniture; manufacture of articles of straw and plaiting materials (20) | D14: 474.76783 | E14: 261.18483 | F14: 197.07972 | G14: 63.972492 | H14: 192.12067 | I14: 183.30699 | J14: 288.22086 | K14: 802.36148 | L14: 25.256434 | M14: 249.87107 | N14: 14272.054 | O14: 4482.2295 | P14: 410.44403 | Q14: 24.080978 | R14: 1323.9192 | S14: 46.977583 | T14: 352.29251 | U14: 84.122181 | V14: 78.742924 | W14: 493.10941 | X14: 129.18915 | Y14: 50.647641 | Z14: 560.12934 | AA14: 103.08586 | AB14: 28.312258 | AC14: 762.14371 | AD14: 366.60625 | AE14: 4955.6325 | AF14: 8890.8995 | AG14: 199.00379 | AH14: 347.89556 | AI14: 187.53144 | AJ14: 531.12974 | AK14: 70.584178 | AL14: 231.92295 | AM14: 23646.72 | AN14: 0.28646851 | AO14: 92.328858 | AP14: 22.907399 | AQ14: 498.00198 | AR14: 1398.239 | AS14: 778.44139 | AT14: 1533.8929 | AU14: 2049.5465 | AV14: 109.24146 | AW14: 72.262706 | AX14: 316.3958 | AY14: 242.84433 | AZ14: 222.72734 | BA14: 101.04183 | BB14: 41.136455 | BC14: 20.623376 | BD14: 35.98606 | BE14: 893.45071 | BF14: 23.826026 | BG14: 7.4897438 | BH14: 8.6205345 | BI14: 7.1919717 | BJ14: 32.442825 | BK14: 11.42499 | BL14: 20.031091 | BM14: 41.485522 | BN14: 7.7093016 | BO14: 25.61705 | BP14: 1359.0607 | BQ14: 329.54374 | BR14: 199.72104 | BS14: 0.69971063 | BT14: 219.27005 | BU14: 10.399118 | BV14: 13.300209 | BW14: 1.9745504 | BX14: 104.97488 | BY14: 38.718728 | BZ14: 17.279709 | CA14: 2.0503282 | CB14: 34.812515 | CC14: 5.0135764 | CD14: 0.79036234 | CE14: 49.513584 | CF14: 1.2211404 | CG14: 438.12504 | CH14: 884.12681 | CI14: 5.4382919 | CJ14: 2.6303668 | CK14: 4.4660448 | CL14: 4.5197122 | CM14: 2.07703 | CN14: 1.9339227 | CO14: 5019.976 | CP14: 0.00066899757 | CQ14: 12.973149 | CR14: 1.9143683 | CS14: 78.050173 | CT14: 95.541118 | CU14: 68.139056 | CV14: 118.1542 | CW14: 276.63998 | CX14: 13.170551 | CY14: 6.5286129 | CZ14: 109.59524 | DA14: 50.329916 | DB14: 42.792421 | DC14: 4.6318643 | DD14: 1.4250472 | DE14: 1.6759654 | DF14: 1.65526 | DG14: 28.703784 | DH14: 10427.412 | DI14: 84.393385 | DJ14: 8824.3183 | DK14: 0 | DL14: 1298.8994 | DM14: 2.217063 | DN14: 1033.4581 | DO14: 0 | DP14: =SUM(D14:DG14) -> 83646.301 | DQ14: =SUM(DH14:DO14) -> 21670.698 | DR14: =DP14+DQ14 -> 105317
A15: EU | B15: Sector | C15: Re-processing of secondary wood material into new wood material | D15: 204.54395 | E15: 105.47208 | F15: 40.056046 | G15: 23.009819 | H15: 51.961684 | I15: 63.781712 | J15: 124.53545 | K15: 354.26046 | L15: 8.4400313 | M15: 109.89879 | N15: 3900.7583 | O15: 2253.6477 | P15: 65.765141 | Q15: 7.9020116 | R15: 275.68985 | S15: 12.022656 | T15: 131.10101 | U15: 43.337618 | V15: 26.20708 | W15: 209.36727 | X15: 38.965028 | Y15: 21.679378 | Z15: 200.87417 | AA15: 33.556714 | AB15: 9.3013539 | AC15: 152.80323 | AD15: 77.063775 | AE15: 1793.9995 | AF15: 3614.7705 | AG15: 65.829287 | AH15: 44.052379 | AI15: 13.086412 | AJ15: 65.26426 | AK15: 24.610402 | AL15: 22.904805 | AM15: 8451.241 | AN15: 0.059242666 | AO15: 34.108725 | AP15: 8.9582682 | AQ15: 182.59749 | AR15: 507.89005 | AS15: 256.10045 | AT15: 740.27321 | AU15: 458.30898 | AV15: 49.660243 | AW15: 12.088397 | AX15: 110.21048 | AY15: 64.794489 | AZ15: 74.976407 | BA15: 31.471748 | BB15: 13.562269 | BC15: 5.0911612 | BD15: 9.1498173 | BE15: 380.94061 | BF15: 6.2210044 | BG15: 1.448438 | BH15: 2.0366288 | BI15: 1.3296304 | BJ15: 8.2916732 | BK15: 3.2591703 | BL15: 6.0741803 | BM15: 12.262175 | BN15: 2.4317991 | BO15: 8.3379596 | BP15: 291.12399 | BQ15: 65.481491 | BR15: 30.671739 | BS15: 0.19852183 | BT15: 56.510476 | BU15: 1.8017896 | BV15: 2.8540624 | BW15: 0.41585097 | BX15: 30.666094 | BY15: 12.858519 | BZ15: 3.9727872 | CA15: 0.41807311 | CB15: 7.8493149 | CC15: 1.3046386 | CD15: 0.16446713 | CE15: 14.930336 | CF15: 0.31336403 | CG15: 123.73708 | CH15: 204.75117 | CI15: 1.209098 | CJ15: 0.81415775 | CK15: 0.73684078 | CL15: 0.78856426 | CM15: 0.72687004 | CN15: 0.47338956 | CO15: 916.71143 | CP15: 0.00022564739 | CQ15: 3.5636092 | CR15: 0.41266439 | CS15: 19.506345 | CT15: 20.736687 | CU15: 17.98941 | CV15: 31.221379 | CW15: 41.0504 | CX15: 4.0235607 | CY15: 2.1802471 | CZ15: 26.88843 | DA15: 11.570458 | DB15: 10.935117 | DC15: 1.1761464 | DD15: 0.3896534 | DE15: 0.5345988 | DF15: 0.41624913 | DG15: 6.9335944 | DH15: 3737.491 | DI15: 31.353547 | DJ15: 3211.0441 | DK15: 0 | DL15: 343.03997 | DM15: 0.49500641 | DN15: 248.47679 | DO15: 0 | DP15: =SUM(D15:DG15) -> 27604.708 | DQ15: =SUM(DH15:DO15) -> 7571.9004 | DR15: =DP15+DQ15 -> 35176.609
... A111: RoW | B111: Sector | C111: Other Services | D111: 6.2820198 | E111: 4.5286756 | F111: 0.45092279 | G111: 0.7842399 | H111: 1.9788993 | I111: 3.1734278 | J111: 18.502115 | K111: 17.863668 | L111: 0.48379502 | M111: 11.205777 | N111: 2.8292769 | O111: 1.2397009 | P111: 0.53508387 | Q111: 1.9584224 | R111: 9.4330265 | S111: 10.45783 | T111: 11.456706 | U111: 4.6145199 | V111: 8.4202916 | W111: 5.3658401 | X111: 0.49477453 | Y111: 0.17923523 | Z111: 2.9959899 | AA111: 2.0198937 | AB111: 0.52382275 | AC111: 245.47755 | AD111: 2.3275403 | AE111: 44.090784 | AF111: 4.5003901 | AG111: 0.64913522 | AH111: 3.5213975 | AI111: 0.63654286 | AJ111: 2.9367524 | AK111: 4.1632369 | AL111: 1.813469 | AM111: 22.534855 | AN111: 0.022845171 | AO111: 3.3026471 | AP111: 0.51064563 | AQ111: 23.628989 | AR111: 37.020674 | AS111: 61.855748 | AT111: 117.73477 | AU111: 71.516147 | AV111: 6.81402 | AW111: 5.1533562 | AX111: 20.48804 | AY111: 9.3884674 | AZ111: 37.043243 | BA111: 4.7929537 | BB111: 2.2566115 | BC111: 0.8693682 | BD111: 1.3091365 | BE111: 211.08673 | BF111: 4342.8038 | BG111: 868.11665 | BH111: 570.42572 | BI111: 643.72028 | BJ111: 4493.3256 | BK111: 1658.6166 | BL111: 1217.5297 | BM111: 4119.9562 | BN111: 394.66018 | BO111: 2929.9925 | BP111: 722.57698 | BQ111: 34.161786 | BR111: 76.055836 | BS111: 9.5809047 | BT111: 2798.3319 | BU111: 1030.4729 | BV111: 146.3456 | BW111: 5.4302855 | BX111: 5162.6091 | BY111: 1815.9052 | BZ111: 356.50702 | CA111: 0.31237768 | CB111: 2318.6939 | CC111: 605.13234 | CD111: 20.108134 | CE111: 5689.3754 | CF111: 138.79827 | CG111: 16503.979 | CH111: 1384.7458 | CI111: 119.69991 | CJ111: 6393.6403 | CK111: 966.46438 | CL111: 500.17976 | CM111: 515.45038 | CN111: 581.46432 | CO111: 12814.769 | CP111: 0.076517194 | CQ111: 1486.7118 | CR111: 100.7535 | CS111: 3314.1739 | CT111: 16946.191 | CU111: 23805.977 | CV111: 43208.089 | CW111: 25686.728 | CX111: 2636.3065 | CY111: 6934.1336 | CZ111: 15555.048 | DA111: 10340.912 | DB111: 28784.353 | DC111: 869.03746 | DD111: 154.68877 | DE111: 1417.4861 | DF111: 534.75365 | DG111: 28646.339 | DH111: 1446.9049 | DI111: 187.11879 | DJ111: 38.851352 | DK111: 0 | DL111: 990690.34 | DM111: 19520.955 | DN111: 8498.4239 | DO111: 0 | DP111: =SUM(D111:DG111) -> 293446.92 | DQ111: =SUM(DH111:DO111) -> 1020382.6 | DR111: =DP111+DQ111 -> 1313829.5
A112: - | B112: Factor of production | C112: Indirect Taxes | D112: 167.11291 | E112: 1893.8717 | F112: 627.50196 | G112: 651.86795 | H112: 347.28212 | I112: 2097.2041 | J112: 11864.694 | K112: 17216.695 | L112: 1353.8296 | M112: 10484.433 | N112: 2217.7244 | O112: 997.08765 | P112: 624.58735 | Q112: 953.98777 | R112: 7494.4807 | S112: 19714.131 | T112: 10928.727 | U112: 1495.7247 | V112: 3186.8874 | W112: 7035.4382 | X112: 578.66615 | Y112: 192.05202 | Z112: 2113.8874 | AA112: 2562.6059 | AB112: 470.05968 | AC112: 5634.9759 | AD112: 2211.7005 | AE112: 49861.544 | AF112: 4401.2113 | AG112: 981.3928 | AH112: 8897.0246 | AI112: 1578.1591 | AJ112: 12287.87 | AK112: 6922.39 | AL112: 4218.1582 | AM112: 36435.651 | AN112: 27.407847 | AO112: 13695.53 | AP112: 2095.3416 | AQ112: 40498.499 | AR112: 50997.786 | AS112: 62426.902 | AT112: 95749.602 | AU112: 92122.696 | AV112: 5560.0842 | AW112: 1491.3652 | AX112: 23892.69 | AY112: 9706.1088 | AZ112: 27186.322 | BA112: 1905.5571 | BB112: 852.08453 | BC112: 541.13923 | BD112: 1103.7113 | BE112: 7801.7046 | BF112: 78815.953 | BG112: 21791.297 | BH112: 14565.756 | BI112: 3398.001 | BJ112: 277923.78 | BK112: 43012.284 | BL112: 44087.544 | BM112: 107576.2 | BN112: 18166.602 | BO112: 95653.297 | BP112: 14765.922 | BQ112: 591.51963 | BR112: 2678.137 | BS112: 250.52841 | BT112: 58237.413 | BU112: 189729.39 | BV112: 9119.7857 | BW112: 196.11725 | BX112: 106519.79 | BY112: 37910.419 | BZ112: 14889.814 | CA112: 71.554098 | CB112: 27131.457 | CC112: 11088.89 | CD112: 95.867876 | CE112: 149146.82 | CF112: 1087.7299 | CG112: 455266.29 | CH112: 42298.441 | CI112: -1790.649 | CJ112: 58907.772 | CK112: 7820.7638 | CL112: 65254.682 | CM112: 10214.065 | CN112: 10861.7 | CO112: 286355.8 | CP112: 4.506481 | CQ112: 90244.515 | CR112: 3010.7014 | CS112: 202027.23 | CT112: 346427.07 | CU112: 245705.69 | CV112: 410871.85 | CW112: 424852.65 | CX112: 28491.477 | CY112: 10499.999 | CZ112: 100165.12 | DA112: 43563.488 | DB112: 103250.76 | DC112: 3209.5717 | DD112: 1185.873 | DE112: 5135.8344 | DF112: 8720.3683 | DG112: 41559.947 | DH112: =SUM(DH4:DH111) -> 6263178.8 | DI112: =SUM(DI4:DI111) -> 2394592.5 | DJ112: =SUM(DJ4:DJ111) -> 2457688.6 | DK112: =SUM(DK4:DK111) -> 0 | DL112: =SUM(DL4:DL111) -> 23707060 | DM112: =SUM(DM4:DM111) -> 6753283.9 | DN112: =SUM(DN4:DN111) -> 11358401 | DO112: 0 | DP112: =SUM(D112:DG112) -> 5010972.5 | DQ112: =SUM(DH112:DO112) -> 52934204 | DR112: =DP112+DQ112 -> 57945177 | DS112: TOTALS
A113: - | B113: Factor of production | C113: Wages | D113: 26508.465 | E113: 13225.81 | F113: 5901.2171 | G113: 2728.5257 | H113: 13992.432 | I113: 11218.883 | J113: 62088.242 | K113: 64802.492 | L113: 3132.8035 | M113: 64192.586 | N113: 19696.287 | O113: 7838.7731 | P113: 2540.6805 | Q113: 4145.4252 | R113: 70328.826 | S113: 10360.115 | T113: 51152.621 | U113: 10575.506 | V113: 9913.4347 | W113: 48346.796 | X113: 4117.7028 | Y113: 2193.3083 | Z113: 18352.83 | AA113: 19050.638 | AB113: 4753.9906 | AC113: 34487.608 | AD113: 13373.589 | AE113: 619606.69 | AF113: 51380.064 | AG113: 6950.5697 | AH113: 23251.84 | AI113: 3714.2303 | AJ113: 14365.663 | AK113: 28573.843 | AL113: 15638.212 | AM113: 375860.95 | AN113: 936.23946 | AO113: 142803.61 | AP113: 7017.4859 | AQ113: 423625.24 | AR113: 398284.8 | AS113: 431779.8 | AT113: 1000519.3 | AU113: 60445.519 | AV113: 17246.778 | AW113: 56602.92 | AX113: 473407.01 | AY113: 441487.81 | AZ113: 563980.31 | BA113: 14606.78 | BB113: 5898.826 | BC113: 3326.2444 | BD113: 8565.5618 | BE113: 194160.9 | BF113: 593030.99 | BG113: 214460.18 | BH113: 74843.503 | BI113: 193059.3 | BJ113: 275571.33 | BK113: 152795.49 | BL113: 115805.51 | BM113: 228675.87 | BN113: 9977.3986 | BO113: 245740.69 | BP113: 39975.038 | BQ113: 4183.1434 | BR113: 5032.9877 | BS113: 2608.9909 | BT113: 236914.91 | BU113: 67196.683 | BV113: 22371.302 | BW113: 1240.3976 | BX113: 172142.32 | BY113: 220330.22 | BZ113: 28124.292 | CA113: 621.71551 | CB113: 70313.689 | CC113: 32663.479 | CD113: 536.1519 | CE113: 204970.65 | CF113: 5512.9676 | CG113: 1686118.8 | CH113: 144512.04 | CI113: 18512.337 | CJ113: 169876.89 | CK113: 20533.4 | CL113: 68296.133 | CM113: 36128.311 | CN113: 24650.093 | CO113: 1429194.6 | CP113: 191.72338 | CQ113: 686823.46 | CR113: 5396.0814 | CS113: 1416672.4 | CT113: 1498257.5 | CU113: 1236975.5 | CV113: 3710335.6 | CW113: 187182.21 | CX113: 72174.946 | CY113: 262596.96 | CZ113: 2636712.4 | DA113: 1065066.6 | DB113: 1046087.5 | DC113: 26334.812 | DD113: 11180.878 | DE113: 66621.5 | DF113: 107857.06 | DG113: 498715.44 | DH113: 0 | DI113: 0 | DJ113: 0 | DK113: 0 | DL113: 0 | DM113: 0 | DN113: 0 | DO113: 0
A114: - | B114: Factor of production | C114: Operating surplus: Consumption of fixed capital | D114: 29494.37 | E114: 19335.339 | F114: 2679.9773 | G114: 1215.0867 | H114: 6331.936 | I114: 5145.5707 | J114: 10971.868 | K114: 21733.822 | L114: 1374.4317 | M114: 11141.49 | N114: 4709.7481 | O114: 1436.6042 | P114: 1057.8811 | Q114: 3039.4333 | R114: 14784.857 | S114: 6024.7979 | T114: 14458.634 | U114: 3779.6194 | V114: 3555.6904 | W114: 10788.918 | X114: 1530.2277 | Y114: 715.99479 | Z114: 4484.6134 | AA114: 5016.551 | AB114: 1243.984 | AC114: 11180.925 | AD114: 5314.2172 | AE114: 115676.57 | AF114: 8508.1811 | AG114: 971.60812 | AH114: 29392.672 | AI114: 16091.753 | AJ114: 38980.202 | AK114: 8218.9752 | AL114: 16397.822 | AM114: 71684.481 | AN114: 76.291424 | AO114: 21781.837 | AP114: 786.40682 | AQ114: 65308.431 | AR114: 97634.871 | AS114: 158761.6 | AT114: 215416.42 | AU114: 408839.65 | AV114: 72683.364 | AW114: 9577.0074 | AX114: 137193.59 | AY114: 51038.764 | AZ114: 69105.981 | BA114: 12818.068 | BB114: 4306.4995 | BC114: 2305.75 | BD114: 4060.1658 | BE114: 15649.425 | BF114: 132455.51 | BG114: 56278.761 | BH114: 7243.4161 | BI114: 10082.201 | BJ114: 225261.85 | BK114: 74991.581 | BL114: 21668.126 | BM114: 51574.832 | BN114: 21878.511 | BO114: 58482.692 | BP114: 8923.607 | BQ114: 616.05382 | BR114: 2223.8227 | BS114: 470.89792 | BT114: 62553.067 | BU114: 71987.253 | BV114: 11708.95 | BW114: 495.87879 | BX114: 121971.6 | BY114: 49333.239 | BZ114: 13180.238 | CA114: 131.43414 | CB114: 23947.023 | CC114: 11955.47 | CD114: 99.806878 | CE114: 126015.63 | CF114: 4698.3948 | CG114: 523689.63 | CH114: 42354.465 | CI114: 6687.735 | CJ114: 151890.97 | CK114: 80658.313 | CL114: 80700.112 | CM114: 33585.033 | CN114: 37066.082 | CO114: 364930.15 | CP114: 28.328943 | CQ114: 125991.31 | CR114: 1194.8218 | CS114: 276783.26 | CT114: 319298.24 | CU114: 344386.95 | CV114: 1028319.8 | CW114: 1072982.8 | CX114: 221119.59 | CY114: 27042.464 | CZ114: 645769.24 | DA114: 140006.37 | DB114: 210450.26 | DC114: 6728.6522 | DD114: 5680.3378 | DE114: 30392.824 | DF114: 50161.537 | DG114: 60035.426 | DH114: 0 | DI114: 0 | DJ114: 0 | DK114: 0 | DL114: 0 | DM114: 0 | DN114: 0 | DO114: 0
A115: - | B115: Factor of production | C115: Operation Surplus | D115: 76213.429 | E115: 29696.069 | F115: 12581.052 | G115: 3006.7475 | H115: 12227.599 | I115: 9602.7735 | J115: 24507.823 | K115: 49340.014 | L115: 4301.9491 | M115: 18126.228 | N115: 7553.6114 | O115: 2990.6524 | P115: 911.70312 | Q115: 2389.5746 | R115: 36187.05 | S115: 10923.687 | T115: 33887.026 | U115: 11696.301 | V115: 14222.848 | W115: 16424.636 | X115: 1972.6208 | Y115: 1062.5718 | Z115: 5326.5564 | AA115: 5906.3252 | AB115: 1356.6816 | AC115: 6311.1096 | AD115: 4263.5828 | AE115: 203521.26 | AF115: 18276.198 | AG115: 3473.4912 | AH115: 27499.964 | AI115: 7889.8693 | AJ115: 36304.948 | AK115: 18276.218 | AL115: 10583.883 | AM115: 158668.31 | AN115: 596.906 | AO115: 37286.628 | AP115: 8320.4082 | AQ115: 213430.82 | AR115: 220560.06 | AS115: 121326.94 | AT115: 471381.58 | AU115: 589690.79 | AV115: 15519.91 | AW115: 1714.8753 | AX115: 6486.2998 | AY115: 18127.043 | AZ115: 126872.9 | BA115: 3801.5573 | BB115: 1741.9935 | BC115: 1257.4064 | BD115: 3195.3845 | BE115: 60655.099 | BF115: 400341.97 | BG115: 110815.27 | BH115: 55138.242 | BI115: 33537.137 | BJ115: 823318.06 | BK115: 131775.01 | BL115: 71728.46 | BM115: 147417.31 | BN115: 23882.853 | BO115: 72971.837 | BP115: 20307.092 | BQ115: 1815.7462 | BR115: 2219.3024 | BS115: 473.02786 | BT115: 98765.406 | BU115: 65696.376 | BV115: 13783.776 | BW115: 648.72968 | BX115: 174171.62 | BY115: 42692.384 | BZ115: 25582.065 | CA115: 175.69035 | CB115: 32177.924 | CC115: 15390.525 | CD115: 144.45142 | CE115: 118647.12 | CF115: 6113.313 | CG115: 474795.95 | CH115: 102183.58 | CI115: 7233.245 | CJ115: 30271.656 | CK115: 15060.303 | CL115: 42778.277 | CM115: 26141.666 | CN115: 34151.031 | CO115: 300523.75 | CP115: 214.25106 | CQ115: 117750.13 | CR115: 6314.1107 | CS115: 841618.22 | CT115: 495757.22 | CU115: 354577.79 | CV115: 1592867.3 | CW115: 1405565.1 | CX115: 61972.067 | CY115: -4034.5726 | CZ115: 30289.197 | DA115: 19119.907 | DB115: 317888.8 | DC115: 795.97588 | DD115: 3095.2802 | DE115: 12940.81 | DF115: 22380.34 | DG115: 83060.24 | DH115: 0 | DI115: 0 | DJ115: 0 | DK115: 0 | DL115: 0 | DM115: 0 | DN115: 0 | DO115: 0
A116: - | B116: Satellite account | C116: Employment male | D116: 3859.7959 | E116: 1959.0231 | F116: 459.49175 | G116: 329.54227 | H116: 394.86057 | I116: 210.78452 | J116: 1070.7769 | K116: 1204.8749 | L116: 43.28983 | M116: 752.87106 | N116: 632.92192 | O116: 205.70232 | P116: 79.669407 | Q116: 88.590899 | R116: 919.63896 | S116: 150.67812 | T116: 465.72641 | U116: 102.02828 | V116: 733.39733 | W116: 813.75008 | X116: 98.286444 | Y116: 45.676682 | Z116: 399.37631 | AA116: 417.31368 | AB116: 97.616557 | AC116: 686.71429 | AD116: 285.96469 | AE116: 9274.8112 | AF116: 1581.7302 | AG116: 120.53974 | AH116: 346.73714 | AI116: 50.228543 | AJ116: 207.61687 | AK116: 354.3887 | AL116: 345.61002 | AM116: 12284.375 | AN116: 25.358248 | AO116: 2414.9755 | AP116: 310.88233 | AQ116: 11148.577 | AR116: 5343.0177 | AS116: 7025.7317 | AT116: 14754.498 | AU116: 742.4641 | AV116: 236.86691 | AW116: 1259.5908 | AX116: 6968.7934 | AY116: 3712.3199 | AZ116: 4215.8312 | BA116: 332.32612 | BB116: 140.53689 | BC116: 100.31921 | BD116: 247.71083 | BE116: 1849.0871 | BF116: 405324.25 | BG116: 142460.47 | BH116: 30204.521 | BI116: 115955.33 | BJ116: 39489.97 | BK116: 24512.643 | BL116: 10245.513 | BM116: 17635.71 | BN116: 617.67083 | BO116: 24070.247 | BP116: 5483.8821 | BQ116: 253.8083 | BR116: 714.73575 | BS116: 40.896225 | BT116: 18179.531 | BU116: 8982.1011 | BV116: 2334.6206 | BW116: 14.349961 | BX116: 14534.095 | BY116: 27775.54 | BZ116: 3185.0394 | CA116: 26.039081 | CB116: 9760.3054 | CC116: 4008.2343 | CD116: 10.284082 | CE116: 31146.902 | CF116: 182.57404 | CG116: 160413.53 | CH116: 17542.191 | CI116: 1913.9737 | CJ116: 12001.797 | CK116: 2027.3202 | CL116: 4833.8985 | CM116: 4576.6802 | CN116: 3586.1478 | CO116: 144921.63 | CP116: 6.6050119 | CQ116: 26253.23 | CR116: 473.43064 | CS116: 107519.53 | CT116: 61118.974 | CU116: 96020.53 | CV116: 96869.636 | CW116: 5613.3689 | CX116: 1702.7436 | CY116: 13304.911 | CZ116: 91696.796 | DA116: 42727.146 | DB116: 29662.423 | DC116: 545.55874 | DD116: 260.06191 | DE116: 9146.1617 | DF116: 2550.7026 | DG116: 24122.577
A117: - | B117: Satellite account | C117: Employment female | D117: 2350.5542 | E117: 1214.8819 | F117: 254.87158 | G117: 180.21738 | H117: 53.073461 | I117: 29.392453 | J117: 949.6976 | K117: 961.48373 | L117: 38.242087 | M117: 1804.3246 | N117: 155.83102 | O117: 46.926085 | P117: 39.773869 | Q117: 29.168212 | R117: 562.63991 | S117: 57.687061 | T117: 182.55644 | U117: 44.492826 | V117: 405.13503 | W117: 353.80176 | X117: 33.947001 | Y117: 14.608885 | Z117: 121.82804 | AA117: 132.98106 | AB117: 23.718565 | AC117: 115.25561 | AD117: 39.497704 | AE117: 2799.1839 | AF117: 779.21708 | AG117: 48.690658 | AH117: 98.967012 | AI117: 13.873315 | AJ117: 59.893164 | AK117: 100.78999 | AL117: 90.643974 | AM117: 1201.8108 | AN117: 2.9884279 | AO117: 2316.9179 | AP117: 296.4421 | AQ117: 11123.624 | AR117: 6233.6133 | AS117: 1997.3593 | AT117: 13256.915 | AU117: 778.14454 | AV117: 260.28644 | AW117: 1144.4953 | AX117: 5838.5696 | AY117: 9143.3981 | AZ117: 14982.541 | BA117: 79.762599 | BB117: 35.083425 | BC117: 26.494477 | BD117: 62.808729 | BE117: 5670.3319 | BF117: 212254.76 | BG117: 73141.389 | BH117: 16568.124 | BI117: 48225.694 | BJ117: 12971.112 | BK117: 9004.6431 | BL117: 5573.9843 | BM117: 9409.5354 | BN117: 1217.5899 | BO117: 19309.399 | BP117: 1062.8771 | BQ117: 38.70306 | BR117: 212.51209 | BS117: 11.155566 | BT117: 6909.7022 | BU117: 860.40343 | BV117: 803.73124 | BW117: 3.2263363 | BX117: 3717.9482 | BY117: 11236.523 | BZ117: 793.5511 | CA117: 3.8140326 | CB117: 2223.8304 | CC117: 812.67236 | CD117: 2.6025736 | CE117: 2644.9007 | CF117: 21.678803 | CG117: 52477.461 | CH117: 5203.4352 | CI117: 861.69077 | CJ117: 2169.3035 | CK117: 389.79987 | CL117: 729.28051 | CM117: 662.82283 | CN117: 577.63089 | CO117: 16368.574 | CP117: 0.82113012 | CQ117: 21982.177 | CR117: 404.84888 | CS117: 91690.75 | CT117: 57261.131 | CU117: 16128.063 | CV117: 57073.737 | CW117: 3610.1416 | CX117: 1168.7997 | CY117: 8162.6652 | CZ117: 45567.445 | DA117: 49405.535 | DB117: 52148.923 | DC117: 120.73051 | DD117: 60.543093 | DE117: 696.70258 | DF117: 778.89687 | DG117: 28526.741
A118: - | B118: Satellite account | C118: Employment hours male | D118: 7706.1312 | E118: 3924.123 | F118: 934.72469 | G118: 648.46808 | H118: 810.30463 | I118: 417.38779 | J118: 1909.9304 | K118: 2261.4594 | L118: 78.451709 | M118: 1479.3911 | N118: 1220.0339 | O118: 394.234 | P118: 141.41544 | Q118: 166.48806 | R118: 1720.2873 | S118: 296.11662 | T118: 791.75035 | U118: 192.68851 | V118: 1415.8444 | W118: 1418.7734 | X118: 184.84795 | Y118: 85.758933 | Z118: 756.74397 | AA118: 796.80184 | AB118: 186.70125 | AC118: 1252.4948 | AD118: 536.80271 | AE118: 16718.502 | AF118: 2850.4089 | AG118: 213.3054 | AH118: 663.90228 | AI118: 96.587365 | AJ118: 390.34306 | AK118: 642.0143 | AL118: 673.17968 | AM118: 24033.177 | AN118: 46.40849 | AO118: 4435.7362 | AP118: 544.45644 | AQ118: 19891.003 | AR118: 9011.1595 | AS118: 13436.851 | AT118: 25111.653 | AU118: 1187.4622 | AV118: 384.62776 | AW118: 2343.4546 | AX118: 12048.419 | AY118: 5551.3977 | AZ118: 6765.4206 | BA118: 582.80672 | BB118: 254.70129 | BC118: 192.21118 | BD118: 482.95605 | BE118: 3203.4145 | BF118: 833389.93 | BG118: 294575.39 | BH118: 59859.332 | BI118: 228564.33 | BJ118: 91566.796 | BK118: 56489.054 | BL118: 23368.977 | BM118: 40671.264 | BN118: 1408.6286 | BO118: 57709.37 | BP118: 12482.463 | BQ118: 565.937 | BR118: 1566.5651 | BS118: 86.024364 | BT118: 42137.166 | BU118: 21312.385 | BV118: 5074.5262 | BW118: 30.580778 | BX118: 33832.638 | BY118: 65429.795 | BZ118: 7561.1275 | CA118: 57.766421 | CB118: 23192.678 | CC118: 9427.0927 | CD118: 22.089164 | CE118: 73566.191 | CF118: 420.19974 | CG118: 371063.91 | CH118: 39759.97 | CI118: 4592.9921 | CJ118: 26643.091 | CK118: 4605.6498 | CL118: 10645.537 | CM118: 10260.001 | CN118: 8182.7798 | CO118: 335260.41 | CP118: 13.769841 | CQ118: 62128.739 | CR118: 1116.5785 | CS118: 243372.16 | CT118: 141283.47 | CU118: 220411.46 | CV118: 213948.89 | CW118: 11263.447 | CX118: 3686.1548 | CY118: 28202.978 | CZ118: 208439.47 | DA118: 90745.444 | DB118: 65938.426 | DC118: 1164.4275 | DD118: 530.72709 | DE118: 21875.27 | DF118: 5283.9733 | DG118: 53938.22
A119: - | B119: Satellite account | C119: Employment hours female | D119: 4590.4282 | E119: 2375.7317 | F119: 498.68252 | G119: 338.14047 | H119: 108.6348 | I119: 58.040785 | J119: 1670.0977 | K119: 1800.3281 | L119: 70.347392 | M119: 3654.2643 | N119: 302.27044 | O119: 89.640211 | P119: 73.708498 | Q119: 55.601455 | R119: 1046.1697 | S119: 116.05035 | T119: 311.8811 | U119: 85.157466 | V119: 784.45068 | W119: 625.27675 | X119: 64.003046 | Y119: 27.43403 | Z119: 229.42923 | AA119: 255.3013 | AB119: 44.543745 | AC119: 211.50597 | AD119: 72.906216 | AE119: 5125.9674 | AF119: 1415.4429 | AG119: 89.552372 | AH119: 188.05429 | AI119: 26.32797 | AJ119: 111.5923 | AK119: 179.51101 | AL119: 177.05284 | AM119: 2289.5 | AN119: 5.3523885 | AO119: 4229.6114 | AP119: 516.97262 | AQ119: 19797.855 | AR119: 10678.238 | AS119: 3735.5167 | AT119: 22391.341 | AU119: 1241.1815 | AV119: 424.14729 | AW119: 2140.5925 | AX119: 9955.3063 | AY119: 13979.126 | AZ119: 24064.454 | BA119: 139.20185 | BB119: 63.503427 | BC119: 51.196043 | BD119: 123.01343 | BE119: 8775.6015 | BF119: 429546.41 | BG119: 148915.1 | BH119: 32345.353 | BI119: 99528.729 | BJ119: 29907.085 | BK119: 20815.547 | BL119: 12578.615 | BM119: 21443.501 | BN119: 2822.3692 | BO119: 45568.186 | BP119: 2403.6869 | BQ119: 86.280826 | BR119: 474.03124 | BS119: 23.774431 | BT119: 15741.938 | BU119: 1978.4687 | BV119: 1750.55 | BW119: 6.8835183 | BX119: 8394.3409 | BY119: 26440.626 | BZ119: 1878.4371 | CA119: 8.3355683 | CB119: 5267.6541 | CC119: 1881.429 | CD119: 5.6008027 | CE119: 6153.164 | CF119: 50.030116 | CG119: 121816.44 | CH119: 11447.347 | CI119: 2014.9181 | CJ119: 4666.2808 | CK119: 872.44577 | CL119: 1532.6757 | CM119: 1435.1495 | CN119: 1286.5853 | CO119: 38116.695 | CP119: 1.7118527 | CQ119: 51139.751 | CR119: 926.39756 | CS119: 204206.86 | CT119: 127619.48 | CU119: 36165.488 | CV119: 121083.31 | CW119: 6768.4162 | CX119: 2447.178 | CY119: 16824.625 | CZ119: 100984.57 | DA119: 95678.122 | DB119: 108668.4 | DC119: 253.73639 | DD119: 121.15389 | DE119: 1632.2017 | DF119: 1598.7556 | DG119: 58693.841
A120: - | B120: Satellite account | C120: Employment: Vulnerable employment | D120: 4570.8276 | E120: 2432.1644 | F120: 470.45481 | G120: 337.80722 | H120: 7.1953954 | I120: 10.721605 | J120: 134.35847 | K120: 180.97654 | L120: 6.7275619 | M120: 220.22636 | N120: 83.43176 | O120: 24.706173 | P120: 4.4206007 | Q120: 10.14655 | R120: 129.65832 | S120: 15.882063 | T120: 27.118267 | U120: 8.6399464 | V120: 87.302503 | W120: 49.046959 | X120: 9.9392352 | Y120: 5.0844968 | Z120: 44.742432 | AA120: 40.2956 | AB120: 12.073883 | AC120: 41.321132 | AD120: 25.223994 | AE120: 769.12406 | AF120: 216.28125 | AG120: 15.329844 | AH120: 7.150341 | AI120: 1.2871638 | AJ120: 3.5689502 | AK120: 7.5396888 | AL120: 12.53004 | AM120: 3318.7266 | AN120: 6.4023945 | AO120: 1041.6747 | AP120: 133.72182 | AQ120: 4258.8095 | AR120: 2394.719 | AS120: 1026.478 | AT120: 4487.0803 | AU120: 296.61542 | AV120: 93.358584 | AW120: 723.66374 | AX120: 38.4 | AY120: 568.383 | AZ120: 1674.882 | BA120: 15.824206 | BB120: 6.9702323 | BC120: 5.5583183 | BD120: 13.86006 | BE120: 1385.019 | BF120: 440225.33 | BG120: 145491.8 | BH120: 42010.552 | BI120: 133243.86 | BJ120: 16985.883 | BK120: 10826.215 | BL120: 4925.3428 | BM120: 9416.9396 | BN120: 681.13268 | BO120: 21222.873 | BP120: 1937.0521 | BQ120: 51.913475 | BR120: 173.37224 | BS120: 4.7299758 | BT120: 8166.3551 | BU120: 5403.0833 | BV120: 704.20915 | BW120: 1.9727872 | BX120: 10564.425 | BY120: 14951.03 | BZ120: 1717.7273 | CA120: 5.0888596 | CB120: 5651.8729 | CC120: 2240.2953 | CD120: 1.0480789 | CE120: 15834.965 | CF120: 32.47202 | CG120: 77026.713 | CH120: 9612.7535 | CI120: 1288.2042 | CJ120: 3741.6015 | CK120: 618.69821 | CL120: 1437.2792 | CM120: 1474.4381 | CN120: 1256.8383 | CO120: 79680.283 | CP120: 2.9223401 | CQ120: 23402.637 | CR120: 455.10818 | CS120: 86555.358 | CT120: 58461 | CU120: 49520.044 | CV120: 43525.97 | CW120: 2820.9906 | CX120: 719.86935 | CY120: 5185.9602 | CZ120: 47641.378 | DA120: 24451.654 | DB120: 23042.094 | DC120: 114.02283 | DD120: 55.213863 | DE120: 8174.5758 | DF120: 278.85579 | DG120: 18207.604
A121: - | B121: Satellite account | C121: Employment hours: Vulnerable employment | D121: 15062.089 | E121: 8170.367 | F121: 2428.885 | G121: 946.6357 | H121: 16.6054 | I121: 40.8956 | J121: 383.01614 | K121: 596.31817 | L121: 23.028201 | M121: 797.61592 | N121: 236.15103 | O121: 80.77553 | P121: 16.459512 | Q121: 49.810592 | R121: 395.93794 | S121: 62.334938 | T121: 82.063817 | U121: 39.655524 | V121: 288.72231 | W121: 158.55923 | X121: 29.013935 | Y121: 16.620763 | Z121: 135.76914 | AA121: 130.1209 | AB121: 34.719555 | AC121: 144.66422 | AD121: 94.343301 | AE121: 2511.3316 | AF121: 695.02572 | AG121: 43.115997 | AH121: 21.761357 | AI121: 4.3242033 | AJ121: 11.840048 | AK121: 28.391006 | AL121: 30.706613 | AM121: 10519.531 | AN121: 16.580135 | AO121: 3026.1402 | AP121: 389.16709 | AQ121: 14843.598 | AR121: 7936.8087 | AS121: 3400.5864 | AT121: 12662.724 | AU121: 802.30483 | AV121: 266.07533 | AW121: 2647.6152 | AX121: 127.12044 | AY121: 1285.9122 | AZ121: 4601.7133 | BA121: 51.122804 | BB121: 19.050121 | BC121: 18.940491 | BD121: 47.468837 | BE121: 3965.0918 | BF121: 1877993.6 | BG121: 699374.93 | BH121: 107774.25 | BI121: 329698.17 | BJ121: 55384.642 | BK121: 105544.2 | BL121: 40845.692 | BM121: 42582.481 | BN121: 3099.7012 | BO121: 109999.92 | BP121: 8863.654 | BQ121: 349.52856 | BR121: 588.15882 | BS121: 126.68086 | BT121: 37864.393 | BU121: 27435.79 | BV121: 2470.1232 | BW121: 892.21801 | BX121: 51097.162 | BY121: 58186.722 | BZ121: 8349.4376 | CA121: 57.007128 | CB121: 26844.348 | CC121: 9942.9093 | CD121: 459.16445 | CE121: 67102.501 | CF121: 5920.1502 | CG121: 346417.5 | CH121: 45983.664 | CI121: 5957.1843 | CJ121: 12648.568 | CK121: 1943.9567 | CL121: 4456.572 | CM121: 4713.2097 | CN121: 3158.7134 | CO121: 384325.3 | CP121: 87.229173 | CQ121: 123497.45 | CR121: 3730.157 | CS121: 409111.04 | CT121: 291393.85 | CU121: 232390.87 | CV121: 204867.88 | CW121: 11292.339 | CX121: 3545.6146 | CY121: 21928.766 | CZ121: 219947.18 | DA121: 120594.33 | DB121: 104821.09 | DC121: 650.10586 | DD121: 311.57658 | DE121: 40852.798 | DF121: 1460.9132 | DG121: 82398.79
A122: - | B122: Satellite account | C122: Energy Carrier Supply: Total | D122: 38305 | E122: 0 | F122: 480236 | G122: 0 | H122: 13075442 | I122: 0 | J122: 0 | K122: 2301625 | L122: 0 | M122: 0 | N122: 769 | O122: 232624 | P122: 214393 | Q122: 213561 | R122: 0 | S122: 36225098 | T122: 675345 | U122: 0 | V122: 519387 | W122: 0 | X122: 0 | Y122: 0 | Z122: 0 | AA122: 0 | AB122: 0 | AC122: 502061 | AD122: 0 | AE122: 0 | AF122: 0 | AG122: 0 | AH122: 5783588 | AI122: 1994502 | AJ122: 0 | AK122: 463886 | AL122: 4000717 | AM122: 0 | AN122: 0 | AO122: 0 | AP122: 0 | AQ122: 0 | AR122: 0 | AS122: 0 | AT122: 0 | AU122: 0 | AV122: 0 | AW122: 0 | AX122: 0 | AY122: 0 | AZ122: 0 | BA122: 876592 | BB122: 0 | BC122: 0 | BD122: 0 | BE122: 0 | BF122: 11563223 | BG122: 0 | BH122: 3813178 | BI122: 0 | BJ122: 474937835 | BK122: 0 | BL122: 0 | BM122: 25758253 | BN122: 0 | BO122: 0 | BP122: 1383 | BQ122: 506038 | BR122: 813039 | BS122: 451789 | BT122: 0 | BU122: 195206994 | BV122: 753827 | BW122: 0 | BX122: 3878157 | BY122: 0 | BZ122: 0 | CA122: 0 | CB122: 0 | CC122: 0 | CD122: 0 | CE122: 5521662 | CF122: 0 | CG122: 0 | CH122: 0 | CI122: 0 | CJ122: 48618384 | CK122: 12968765 | CL122: 0 | CM122: 2003217 | CN122: 10922938 | CO122: 0 | CP122: 0 | CQ122: 0 | CR122: 0 | CS122: 0 | CT122: 0 | CU122: 0 | CV122: 0 | CW122: 0 | CX122: 0 | CY122: 0 | CZ122: 0 | DA122: 0 | DB122: 0 | DC122: 1459422 | DD122: 0 | DE122: 0 | DF122: 0 | DG122: 0
A123: - | B123: Satellite account | C123: Energy Carrier Use: Total | D123: 667023 | E123: 604595 | F123: 183071 | G123: 57549 | H123: 1695730 | I123: 318877 | J123: 408534 | K123: 690840 | L123: 69989 | M123: 214563 | N123: 304433 | O123: 72331 | P123: 230305 | Q123: 199453 | R123: 1086254 | S123: 39203883 | T123: 4308659 | U123: 577421 | V123: 1119431 | W123: 165056 | X123: 162165 | Y123: 85173 | Z123: 741094 | AA123: 611307 | AB123: 189406 | AC123: 1164081 | AD123: 701450 | AE123: 1523793 | AF123: 333701 | AG123: 517742 | AH123: 16675553 | AI123: 1310334 | AJ123: 314646 | AK123: 1865826 | AL123: 6645669 | AM123: 440030 | AN123: 124872 | AO123: 172494 | AP123: 30781 | AQ123: 309165 | AR123: 842916 | AS123: 6839283 | AT123: 1443991 | AU123: 425407 | AV123: 88839 | AW123: 78221 | AX123: 638462 | AY123: 494710 | AZ123: 934608 | BA123: 284411 | BB123: 28097 | BC123: 17701 | BD123: 21145 | BE123: 420472 | BF123: 6710342 | BG123: 3006487 | BH123: 1850914 | BI123: 269705 | BJ123: 27230702 | BK123: 6086781 | BL123: 3590166 | BM123: 4667175 | BN123: 1963522 | BO123: 6679343 | BP123: 2628992 | BQ123: 217543 | BR123: 732516 | BS123: 410987 | BT123: 6484156 | BU123: 215593421 | BV123: 18352095 | BW123: 4624585 | BX123: 21536024 | BY123: 2596905 | BZ123: 1453667 | CA123: 356659 | CB123: 7358853 | CC123: 6595962 | CD123: 875044 | CE123: 21971222 | CF123: 5298791 | CG123: 12991577 | CH123: 3651056 | CI123: 1505124 | CJ123: 138229577 | CK123: 6666043 | CL123: 633431 | CM123: 16423937 | CN123: 19845289 | CO123: 4665985 | CP123: 687740 | CQ123: 295640 | CR123: 351026 | CS123: 1486574 | CT123: 2358373 | CU123: 26020743 | CV123: 5880874 | CW123: 2851663 | CX123: 435843 | CY123: 777898 | CZ123: 6465562 | DA123: 2152340 | DB123: 3437629 | DC123: 814759 | DD123: 69107 | DE123: 326296 | DF123: 896150 | DG123: 1630756
A124: - | B124: Satellite account | C124: Domestic Extraction Used | D124: 617889.13 | E124: 718291.33 | F124: 262136.62 | G124: 5034.583 | H124: 661236.42 | I124: 2896815.6 | J124: 2012.4984 | K124: 1608.7355 | L124: 1.5561634 | M124: 90.775047 | N124: 2248.8815 | O124: 466.1361 | P124: 154.04536 | Q124: 31.261078 | R124: 619.02651 | S124: 1960.9989 | T124: 34474.454 | U124: 10461.935 | V124: 6808.3152 | W124: 358.71267 | X124: 24370.616 | Y124: 10259.018 | Z124: 77475.297 | AA124: 86070.051 | AB124: 16585.993 | AC124: 14251.762 | AD124: 4806.9436 | AE124: 13283.473 | AF124: 2390.4387 | AG124: 5275.7032 | AH124: 33511.619 | AI124: 1435.3868 | AJ124: 33116.152 | AK124: 25211.651 | AL124: 40548.853 | AM124: 70732.37 | AN124: 192.44991 | AO124: 26.931221 | AP124: 10.585546 | AQ124: 33734.039 | AR124: 921.74013 | AS124: 32125.127 | AT124: 2881.8193 | AU124: 923.25606 | AV124: 503.57458 | AW124: 202.77184 | AX124: 3950.5779 | AY124: 117.26462 | AZ124: 56.07383 | BA124: 333.00834 | BB124: 443.64855 | BC124: 373.54142 | BD124: 1004.3608 | BE124: 394.86046 | BF124: 7713523.9 | BG124: 10257269 | BH124: 2167887.9 | BI124: 94211.86 | BJ124: 13145528 | BK124: 38531752 | BL124: 58332.052 | BM124: 201273.98 | BN124: 77.757519 | BO124: 4785.8611 | BP124: 4370.3997 | BQ124: 449.9754 | BR124: 1441.364 | BS124: 0.012584901 | BT124: 4918.6862 | BU124: 16638.827 | BV124: 4346.524 | BW124: 6.2860443 | BX124: 49677.788 | BY124: 3280.7245 | BZ124: 6340.2473 | CA124: 206.19858 | CB124: 26541.087 | CC124: 32143.488 | CD124: 188.85408 | CE124: 22561.964 | CF124: 2420.5518 | CG124: 21222.848 | CH124: 4786.4708 | CI124: 2343.289 | CJ124: 12804.053 | CK124: 5452.6145 | CL124: 8182.4409 | CM124: 4492.9145 | CN124: 3143.2462 | CO124: 109957.06 | CP124: 0.63283166 | CQ124: 9023.9913 | CR124: 4175.4208 | CS124: 55073.02 | CT124: 4048.4644 | CU124: 63130.887 | CV124: 1601.0028 | CW124: 196.22597 | CX124: 610.71328 | CY124: 2437.6442 | CZ124: 14467.354 | DA124: 1340.4779 | DB124: 870.15079 | DC124: 181.85586 | DD124: 446.40994 | DE124: 28.062282 | DF124: 11131.604 | DG124: 3485.0737
A125: - | B125: Satellite account | C125: Unused Domestic Extraction | D125: 405692.64 | E125: 214220.66 | F125: 47466.936 | G125: 1108.5619 | H125: 3652173.1 | I125: 548668.35 | J125: 413.39352 | K125: 291.6425 | L125: 0.6652723 | M125: 28.613907 | N125: 311.4131 | O125: 54.282143 | P125: 23.925449 | Q125: 4.9201451 | R125: 200.18333 | S125: 171.09751 | T125: 6260.9709 | U125: 1642.9235 | V125: 921.45921 | W125: 76.701119 | X125: 3245.6328 | Y125: 1481.6394 | Z125: 11216.281 | AA125: 11670.577 | AB125: 2432.2688 | AC125: 1880.7586 | AD125: 265.69082 | AE125: 2247.3275 | AF125: 301.088 | AG125: 499.67489 | AH125: 1448.2251 | AI125: 79.826069 | AJ125: 1313.931 | AK125: 951.372 | AL125: 1934.4423 | AM125: 10752.757 | AN125: 44.581609 | AO125: 1.8297061 | AP125: 0.59639786 | AQ125: 6638.4101 | AR125: 182.47447 | AS125: 3711.732 | AT125: 250.39413 | AU125: 1487.1898 | AV125: 12.277751 | AW125: 11.577925 | AX125: 577.16489 | AY125: 18.183804 | AZ125: 9.164098 | BA125: 83.924434 | BB125: 82.206431 | BC125: 65.844957 | BD125: 205.9271 | BE125: 77.751214 | BF125: 4088911.7 | BG125: 384395.64 | BH125: 323873.43 | BI125: 20361.674 | BJ125: 28008630 | BK125: 9607203.5 | BL125: 18536.569 | BM125: 54318.609 | BN125: 25.874053 | BO125: 634.86393 | BP125: 1869.5426 | BQ125: 67.49631 | BR125: 420.86679 | BS125: 0.0017840156 | BT125: 1048.3256 | BU125: 5724.3858 | BV125: 2201.4912 | BW125: 1.5387022 | BX125: 9647.1452 | BY125: 1564.3695 | BZ125: 2722.7305 | CA125: 25.243323 | CB125: 8325.9365 | CC125: 5225.6537 | CD125: 36.469511 | CE125: 26131.721 | CF125: 7197.1042 | CG125: 15196.375 | CH125: 2770.2312 | CI125: 1540.9319 | CJ125: 9721.6892 | CK125: 3146.045 | CL125: 5553.9945 | CM125: 3512.4489 | CN125: 1967.6085 | CO125: 9152.5998 | CP125: 0.006310162 | CQ125: 5178.1744 | CR125: 1551.4997 | CS125: 72955.098 | CT125: 1363.4751 | CU125: 42112.207 | CV125: 995.99189 | CW125: 83.922659 | CX125: 537.21254 | CY125: 1755.7471 | CZ125: 12281.733 | DA125: 1086.5703 | DB125: 510.22767 | DC125: 28.947453 | DD125: 35.797862 | DE125: 21.687069 | DF125: 8258.9947 | DG125: 1630.1447
C127: GO | D127: 218887.74 | E127: 163951.02 | F127: 40586.44 | G127: 14507.49 | H127: 61198.15 | I127: 61245.842 | J127: 376131.61 | K127: 498580.81 | L127: 20139.983 | M127: 273001.1 | N127: 105317 | O127: 35176.609 | P127: 17167 | Q127: 34060.893 | R127: 335172.73 | S127: 336920.99 | T127: 256142.53 | U127: 65576.017 | V127: 127696.28 | W127: 254363.7 | X127: 24056.565 | Y127: 9127.7481 | Z127: 76632.453 | AA127: 95846.67 | AB127: 24357.201 | AC127: 273867.32 | AD127: 110830.72 | AE127: 2678132.3 | AF127: 185338.62 | AG127: 34354.311 | AH127: 220995.49 | AI127: 48109.694 | AJ127: 239550.05 | AK127: 153623.3 | AL127: 98167.471 | AM127: 1595104 | AN127: 1932.6736 | AO127: 286671.14 | AP127: 32057.96 | AQ127: 1059252 | AR127: 1117643 | AS127: 1532830.3 | AT127: 3334041.5 | AU127: 1458481.6 | AV127: 194342.36 | AW127: 132872.94 | AX127: 953974.14 | AY127: 639826.36 | AZ127: 1082605.8 | BA127: 71360.147 | BB127: 27665.631 | BC127: 15789.355 | BD127: 34537.706 | BE127: 396222.42 | BF127: 1877848.3 | BG127: 949837.42 | BH127: 219031.67 | BI127: 300118.59 | BJ127: 2436140.7 | BK127: 814746.77 | BL127: 1294328.7 | BM127: 2002503.5 | BN127: 150424.52 | BO127: 1626895.9 | BP127: 280650.16 | BQ127: 16853.694 | BR127: 47744.405 | BS127: 9105.8011 | BT127: 1224017.5 | BU127: 1797937.4 | BV127: 264315.5 | BW127: 6485.4585 | BX127: 2377557.3 | BY127: 1122528.7 | BZ127: 268472.75 | CA127: 2131.4785 | CB127: 499645.36 | CC127: 227501.75 | CD127: 3438.6573 | CE127: 2471482.5 | CF127: 61732.193 | CG127: 10210114 | CH127: 858984.07 | CI127: 73368.447 | CJ127: 922405.43 | CK127: 182990.21 | CL127: 689026.04 | CM127: 244688.97 | CN127: 193812.92 | CO127: 6042963.6 | CP127: 471.30356 | CQ127: 1204309.9 | CR127: 32091.621 | CS127: 3432603.4 | CT127: 3890335.8 | CU127: 4103364.4 | CV127: 11482504 | CW127: 4234690.9 | CX127: 707994.3 | CY127: 562378.29 | CZ127: 5547963 | DA127: 1760247.8 | DB127: 3586022.4 | DC127: 84878.948 | DD127: 45775.276 | DE127: 197794.78 | DF127: 286083.51 | DG127: 1313829.5
DO128: =SUM(DO4:DO111) -> 0
C129: Material extraction coeff | D129: =SUM(D124:D125)/D127 -> 4.6762863 | E129: =SUM(E124:E125)/E127 -> 5.6877473 | F129: =SUM(F124:F125)/F127 -> 7.628251 | G129: =SUM(G124:G125)/G127 -> 0.42344645 | H129: =SUM(H124:H125)/H127 -> 70.482678 | I129: =SUM(I124:I125)/I127 -> 56.256618 | J129: =SUM(J124:J125)/J127 -> 0.0064495827 | K129: =SUM(K124:K125)/K127 -> 0.0038115747 | ... DG129: =SUM(DG124:DG125)/DG127 -> 0.0038933654
C130: Energy use coeff | D130: =D123/D127 -> 3.0473291 | E130: =E123/E127 -> 3.6876562 | F130: =F123/F127 -> 4.5106444 | G130: =G123/G127 -> 3.9668476 | H130: =H123/H127 -> 27.708844 | I130: =I123/I127 -> 5.2065086 | J130: =J123/J127 -> 1.0861464 | K130: =K123/K127 -> 1.3856129 | ... DG130: =DG123/DG127 -> 1.2412234
C131: Male employment share | D131: =D116/SUM(D$116:D$117) -> 0.6215102 | E131: =E116/SUM(E$116:E$117) -> 0.61722802 | F131: =F116/SUM(F$116:F$117) -> 0.64321855 | G131: =G116/SUM(G$116:G$117) -> 0.64646598 | H131: =H116/SUM(H$116:H$117) -> 0.88151501 | I131: =I116/SUM(I$116:I$117) -> 0.87762169 | J131: =J116/SUM(J$116:J$117) -> 0.52996309 | K131: =K116/SUM(K$116:K$117) -> 0.55617517 | ... DG131: =DG116/SUM(DG$116:DG$117) -> 0.45817453
C132: Female employment share | D132: =D117/SUM(D$116:D$117) -> 0.3784898 | E132: =E117/SUM(E$116:E$117) -> 0.38277198 | F132: =F117/SUM(F$116:F$117) -> 0.35678145 | G132: =G117/SUM(G$116:G$117) -> 0.35353402 | H132: =H117/SUM(H$116:H$117) -> 0.11848499 | I132: =I117/SUM(I$116:I$117) -> 0.12237831 | J132: =J117/SUM(J$116:J$117) -> 0.47003691 | K132: =K117/SUM(K$116:K$117) -> 0.44382483 | ... DG132: =DG117/SUM(DG$116:DG$117) -> 0.54182547
C133: Wage rate | D133: =D113/SUM(D116:D117) -> 4.2684333 | E133: =E113/SUM(E116:E117) -> 4.1670465 | F133: =F113/SUM(F116:F117) -> 8.2608064 | G133: =G113/SUM(G116:G117) -> 5.3525729 | H133: =H113/SUM(H116:H117) -> 31.237707 | I133: =I113/SUM(I116:I117) -> 46.710901 | J133: =J113/SUM(J116:J117) -> 30.729534 | K133: =K113/SUM(K116:K117) -> 29.913096 | ... DG133: =DG113/SUM(DG116:DG117) -> 9.4724007
D134: =D133/1000 -> 0.0042684333 | E134: =E133/1000 -> 0.0041670465 | F134: =F133/1000 -> 0.0082608064 | G134: =G133/1000 -> 0.0053525729 | H134: =H133/1000 -> 0.031237707 | I134: =I133/1000 -> 0.046710901 | J134: =J133/1000 -> 0.030729534 | K134: =K133/1000 -> 0.029913096 | ... DG134: =DG133/1000 -> 0.0094724007
C135: Productivity | D135: =D127/SUM(D116:D117)/1000 -> 0.035245637 | E135: =E127/SUM(E116:E117)/1000 -> 0.051655934 | F135: =F127/SUM(F116:F117)/1000 -> 0.056814843 | G135: =G127/SUM(G116:G117)/1000 -> 0.02845947 | H135: =H127/SUM(H116:H117)/1000 -> 0.13662313 | I135: =I127/SUM(I116:I117)/1000 -> 0.25500297 | J135: =J127/SUM(J116:J117)/1000 -> 0.18616003 | K135: =K127/SUM(K116:K117)/1000 -> 0.23014694 | ... DG135: =DG127/SUM(DG116:DG117)/1000 -> 0.02495435

Sheet MRIO.coefficients
D1: EU | E1: EU | F1: EU | G1: EU | H1: EU | I1: EU | J1: EU | K1: EU | L1: EU | M1: EU | N1: EU | O1: EU | P1: EU | Q1: EU | R1: EU | S1: EU | T1: EU | U1: EU | V1: EU | W1: EU | X1: EU | Y1: EU | Z1: EU | AA1: EU | AB1: EU | AC1: EU | AD1: EU | AE1: EU | AF1: EU | AG1: EU | AH1: EU | AI1: EU | AJ1: EU | AK1: EU | AL1: EU | AM1: EU | AN1: EU | AO1: EU | AP1: EU | AQ1: EU | AR1: EU | AS1: EU | AT1: EU | AU1: EU | AV1: EU | AW1: EU | AX1: EU | AY1: EU | AZ1: EU | BA1: EU | BB1: EU | BC1: EU | BD1: EU | BE1: EU | BF1: RoW | BG1: RoW | BH1: RoW | BI1: RoW | BJ1: RoW | BK1: RoW | BL1: RoW | BM1: RoW | BN1: RoW | BO1: RoW | BP1: RoW | BQ1: RoW | BR1: RoW | BS1: RoW | BT1: RoW | BU1: RoW | BV1: RoW | BW1: RoW | BX1: RoW | BY1: RoW | BZ1: RoW | CA1: RoW | CB1: RoW | CC1: RoW | CD1: RoW | CE1: RoW | CF1: RoW | CG1: RoW | CH1: RoW | CI1: RoW | CJ1: RoW | CK1: RoW | CL1: RoW | CM1: RoW | CN1: RoW | CO1: RoW | CP1: RoW | CQ1: RoW | CR1: RoW | CS1: RoW | CT1: RoW | CU1: RoW | CV1: RoW | CW1: RoW | CX1: RoW | CY1: RoW | CZ1: RoW | DA1: RoW | DB1: RoW | DC1: RoW | DD1: RoW | DE1: RoW | DF1: RoW | DG1: RoW | DH1: EU | DI1: EU | DJ1: EU | DK1: EU | DL1: RoW | DM1: RoW | DN1: RoW | DO1: RoW | DP1: INTERMEDIATE DEMAND (ID) | DQ1: FINAL DEMAND (FD) | DR1: AGGREGATE DEMAND (D = ID + FD)
D2: Sector | E2: Sector | F2: Sector | G2: Sector | H2: Sector | I2: Sector | J2: Sector | K2: Sector | L2: Sector | M2: Sector | N2: Sector | O2: Sector | P2: Sector | Q2: Sector | R2: Sector | S2: Sector | T2: Sector | U2: Sector | V2: Sector | W2: Sector | X2: Sector | Y2: Sector | Z2: Sector | AA2: Sector | AB2: Sector | AC2: Sector | AD2: Sector | AE2: Sector | AF2: Sector | AG2: Sector | AH2: Sector | AI2: Sector | AJ2: Sector | AK2: Sector | AL2: Sector | AM2: Sector | AN2: Sector | AO2: Sector | AP2: Sector | AQ2: Sector | AR2: Sector | AS2: Sector | AT2: Sector | AU2: Sector | AV2: Sector | AW2: Sector | AX2: Sector | AY2: Sector | AZ2: Sector | BA2: Sector | BB2: Sector | BC2: Sector | BD2: Sector | BE2: Sector | BF2: Sector | BG2: Sector | BH2: Sector | BI2: Sector | BJ2: Sector | BK2: Sector | BL2: Sector | BM2: Sector | BN2: Sector | BO2: Sector | BP2: Sector | BQ2: Sector | BR2: Sector | BS2: Sector | BT2: Sector | BU2: Sector | BV2: Sector | BW2: Sector | BX2: Sector | BY2: Sector | BZ2: Sector | CA2: Sector | CB2: Sector | CC2: Sector | CD2: Sector | CE2: Sector | CF2: Sector | CG2: Sector | CH2: Sector | CI2: Sector | CJ2: Sector | CK2: Sector | CL2: Sector | CM2: Sector | CN2: Sector | CO2: Sector | CP2: Sector | CQ2: Sector | CR2: Sector | CS2: Sector | CT2: Sector | CU2: Sector | CV2: Sector | CW2: Sector | CX2: Sector | CY2: Sector | CZ2: Sector | DA2: Sector | DB2: Sector | DC2: Sector | DD2: Sector | DE2: Sector | DF2: Sector | DG2: Sector | DH2: Consumption category | DI2: Consumption category | DJ2: Consumption category | DK2: Consumption category | DL2: Consumption category | DM2: Consumption category | DN2: Consumption category | DO2: Consumption category
D3: Agriculture | E3: Animal Farming | F3: Forestry, logging and related service activities (02) | G3: Fishing, operating of fish hatcheries and fish farms; service activities incidental to fishing (05) | H3: Extraction of Fossil-Fuels | I3: Mining & Quarrying of raw materials | J3: Processing of meat | K3: Processing of other food&beverage | L3: Manufacture of tobacco products (16) | M3: Manufacture of textiles | N3: Manufacture of wood and of products of wood and cork, except furniture; manufacture of articles of straw and plaiting materials (20) | O3: Re-processing of secondary wood material into new wood material | P3: Pulp | Q3: Re-processing of secondary paper into new pulp | R3: Paper | S3: Processing of Fossil Fuels | T3: Plastics, basic | U3: Re-processing of secondary plastic into new plastic | V3: Manufacture of Chemicals | W3: Manufacture of rubber and plastic products (25) | X3: Manufacture of glass and glass products | Y3: Re-processing of secondary glass into new glass | Z3: Manufacture of other non-metallic mineral products | AA3: Manufacture of cement, lime and plaster | AB3: Re-processing of ash into clinker | AC3: Manufacture of Metals | AD3: Re-processing of Metals | AE3: Manufacture of durable goods | AF3: Manufacture of furniture; manufacturing n.e.c. (36) | AG3: Recycling | AH3: Production of electricity by fossil fuels | AI3: Production of electricity by renewable energy | AJ3: Transmission & Distribution | AK3: Manufacture of gas; distribution of gaseous fuels through mains | AL3: Water | AM3: Construction (45) | AN3: Re-processing of secondary construction material into aggregates | AO3: Sale, maintenance, repair of motor vehicles, motor vehicles parts, motorcycles, motor cycles parts and accessoiries | AP3: Retail sale of automotive fuel | AQ3: Retail & Wholesale trade | AR3: Leisure Services | AS3: Transport | AT3: KIBS | AU3: Real estate activities (70) | AV3: Renting of machinery and equipment without operator and of personal and household goods (71) | AW3: Research and development (73) | AX3: Public administration and defence; compulsory social security (75) | AY3: Education (80) | AZ3: Health and social work (85) | BA3: Incineration of Waste | BB3: Biogas & Composting | BC3: Waste water | BD3: Landfill of Waste | BE3: Other Services | BF3: Agriculture | BG3: Animal Farming | BH3: Forestry, logging and related service activities (02) | BI3: Fishing, operating of fish hatcheries and fish farms; service activities incidental to fishing (05) | BJ3: Extraction of Fossil-Fuels | BK3: Mining & Quarrying of raw materials | BL3: Processing of meat | BM3: Processing of other food&beverage | BN3: Manufacture of tobacco products (16) | BO3: Manufacture of textiles | BP3: Manufacture of wood and of products of wood and cork, except furniture; manufacture of articles of straw and plaiting materials (20) | BQ3: Re-processing of secondary wood material into new wood material | BR3: Pulp | BS3: Re-processing of secondary paper into new pulp | BT3: Paper | BU3: Processing of Fossil Fuels | BV3: Plastics, basic | BW3: Re-processing of secondary plastic into new plastic | BX3: Manufacture of Chemicals | BY3: Manufacture of rubber and plastic products (25) | BZ3: Manufacture of glass and glass products | CA3: Re-processing of secondary glass into new glass | CB3: Manufacture of other non-metallic mineral products | CC3: Manufacture of cement, lime and plaster | CD3: Re-processing of ash into clinker | CE3: Manufacture of Metals | CF3: Re-processing of Metals | CG3: Manufacture of durable goods | CH3: Manufacture of furniture; manufacturing n.e.c. (36) | CI3: Recycling | CJ3: Production of electricity by fossil fuels | CK3: Production of electricity by renewable energy | CL3: Transmission & Distribution | CM3: Manufacture of gas; distribution of gaseous fuels through mains | CN3: Water | CO3: Construction (45) | CP3: Re-processing of secondary construction material into aggregates | CQ3: Sale, maintenance, repair of motor vehicles, motor vehicles parts, motorcycles, motor cycles parts and accessoiries | CR3: Retail sale of automotive fuel | CS3: Retail & Wholesale trade | CT3: Leisure Services | CU3: Transport | CV3: KIBS | CW3: Real estate activities (70) | CX3: Renting of machinery and equipment without operator and of personal and household goods (71) | CY3: Research and development (73) | CZ3: Public administration and defence; compulsory social security (75) | DA3: Education (80) | DB3: Health and social work (85) | DC3: Incineration of Waste | DD3: Biogas & Composting | DE3: Waste water | DF3: Landfill of Waste | DG3: Other Services | DH3: Consumption | DI3: Final consumption expenditure by government | DJ3: GFCF | DK3: Exports: Total (fob) | DL3: Consumption | DM3: Final consumption expenditure by government | DN3: GFCF | DO3: Exports: Total (fob)
A4: EU | B4: Sector | C4: Agriculture | D4: =MRIO.flows!D4/MRIO.flows!D$127 -> 0.040220156 | E4: =MRIO.flows!E4/MRIO.flows!E$127 -> 0.09905557 | F4: =MRIO.flows!F4/MRIO.flows!F$127 -> 0.0088905906 | G4: =MRIO.flows!G4/MRIO.flows!G$127 -> 0.0017446989 | H4: =MRIO.flows!H4/MRIO.flows!H$127 -> 0.00021454789 | I4: =MRIO.flows!I4/MRIO.flows!I$127 -> 0.00033375483 | J4: =MRIO.flows!J4/MRIO.flows!J$127 -> 0.02990604 | K4: =MRIO.flows!K4/MRIO.flows!K$127 -> 0.10068127 | ... DG4: =MRIO.flows!DG4/MRIO.flows!DG$127 -> 0.00017756765 | DH4: =MRIO.flows!DH4/MRIO.flows!DH$112 -> 0.013844114 | DI4: =MRIO.flows!DI4/MRIO.flows!DI$112 -> 0.00032242838 | DJ4: =MRIO.flows!DJ4/MRIO.flows!DJ$112 -> 0.0016420411 | DL4: =MRIO.flows!DL4/MRIO.flows!DL$112 -> 0.00047120683 | DM4: =MRIO.flows!DM4/MRIO.flows!DM$112 -> 5.8883741e-07 | DN4: =MRIO.flows!DN4/MRIO.flows!DN$112 -> 1.8104929e-05 | DP4: =MRIO.flows!DP4/MRIO.flows!DP$112 -> 0.023147467 | DQ4: =MRIO.flows!DQ4/MRIO.flows!DQ$112 -> 0.001943855 | DR4: =MRIO.flows!DR4/MRIO.flows!DR$112 -> 0.0037774972
A5: EU | B5: Sector | C5: Animal Farming | D5: =MRIO.flows!D5/MRIO.flows!D$127 -> 9.8298293e-05 | E5: =MRIO.flows!E5/MRIO.flows!E$127 -> 0.0086007575 | F5: =MRIO.flows!F5/MRIO.flows!F$127 -> 0.00015511801 | G5: =MRIO.flows!G5/MRIO.flows!G$127 -> 0.00015922693 | H5: =MRIO.flows!H5/MRIO.flows!H$127 -> 0.00021091683 | I5: =MRIO.flows!I5/MRIO.flows!I$127 -> 0.00010636645 | J5: =MRIO.flows!J5/MRIO.flows!J$127 -> 0.22150298 | K5: =MRIO.flows!K5/MRIO.flows!K$127 -> 0.059257922 | ... DG5: =MRIO.flows!DG5/MRIO.flows!DG$127 -> 3.7049851e-05 | DH5: =MRIO.flows!DH5/MRIO.flows!DH$112 -> 0.0049606998 | DI5: =MRIO.flows!DI5/MRIO.flows!DI$112 -> 0.0001413008 | DJ5: =MRIO.flows!DJ5/MRIO.flows!DJ$112 -> 0.0041551413 | DL5: =MRIO.flows!DL5/MRIO.flows!DL$112 -> 3.123948e-05 | DM5: =MRIO.flows!DM5/MRIO.flows!DM$112 -> 5.0746262e-06 | DN5: =MRIO.flows!DN5/MRIO.flows!DN$112 -> 5.6350374e-05 | DP5: =MRIO.flows!DP5/MRIO.flows!DP$112 -> 0.024130237 | DQ5: =MRIO.flows!DQ5/MRIO.flows!DQ$112 -> 0.00081299168 | DR5: =MRIO.flows!DR5/MRIO.flows!DR$112 -> 0.0028294162
A6: EU | B6: Sector | C6: Forestry, logging and related service activities (02) | D6: =MRIO.flows!D6/MRIO.flows!D$127 -> 0.00040925073 | E6: =MRIO.flows!E6/MRIO.flows!E$127 -> 0.0017671034 | F6: =MRIO.flows!F6/MRIO.flows!F$127 -> 0.21730829 | G6: =MRIO.flows!G6/MRIO.flows!G$127 -> 0.00030649516 | H6: =MRIO.flows!H6/MRIO.flows!H$127 -> 0.0009142111 | I6: =MRIO.flows!I6/MRIO.flows!I$127 -> 0.000766745 | J6: =MRIO.flows!J6/MRIO.flows!J$127 -> 0.00018376385 | K6: =MRIO.flows!K6/MRIO.flows!K$127 -> 0.00064722645 | ... DG6: =MRIO.flows!DG6/MRIO.flows!DG$127 -> 1.2285126e-06 | DH6: =MRIO.flows!DH6/MRIO.flows!DH$112 -> 0.0010452624 | DI6: =MRIO.flows!DI6/MRIO.flows!DI$112 -> 0.00014439418 | DJ6: =MRIO.flows!DJ6/MRIO.flows!DJ$112 -> 0.0018845891 | DL6: =MRIO.flows!DL6/MRIO.flows!DL$112 -> 1.3568424e-05 | DM6: =MRIO.flows!DM6/MRIO.flows!DM$112 -> 5.1433722e-07 | DN6: =MRIO.flows!DN6/MRIO.flows!DN$112 -> 3.1549326e-06 | DP6: =MRIO.flows!DP6/MRIO.flows!DP$112 -> 0.0057276906 | DQ6: =MRIO.flows!DQ6/MRIO.flows!DQ$112 -> 0.00022452665 | DR6: =MRIO.flows!DR6/MRIO.flows!DR$112 -> 0.00070042827
A7: EU | B7: Sector | C7: Fishing, operating of fish hatcheries and fish farms; service activities incidental to fishing (05) | D7: =MRIO.flows!D7/MRIO.flows!D$127 -> 5.4525929e-06 | E7: =MRIO.flows!E7/MRIO.flows!E$127 -> 0.00038631281 | F7: =MRIO.flows!F7/MRIO.flows!F$127 -> 0.00038098777 | G7: =MRIO.flows!G7/MRIO.flows!G$127 -> 0.030494783 | H7: =MRIO.flows!H7/MRIO.flows!H$127 -> 4.8163126e-06 | I7: =MRIO.flows!I7/MRIO.flows!I$127 -> 4.9920519e-06 | J7: =MRIO.flows!J7/MRIO.flows!J$127 -> 0.0021191534 | K7: =MRIO.flows!K7/MRIO.flows!K$127 -> 0.0022837874 | ... DG7: =MRIO.flows!DG7/MRIO.flows!DG$127 -> 2.7079187e-06 | DH7: =MRIO.flows!DH7/MRIO.flows!DH$112 -> 0.0014849907 | DI7: =MRIO.flows!DI7/MRIO.flows!DI$112 -> 2.7833211e-06 | DJ7: =MRIO.flows!DJ7/MRIO.flows!DJ$112 -> 3.892269e-05 | DL7: =MRIO.flows!DL7/MRIO.flows!DL$112 -> 1.9011147e-05 | DM7: =MRIO.flows!DM7/MRIO.flows!DM$112 -> 1.8396017e-08 | DN7: =MRIO.flows!DN7/MRIO.flows!DN$112 -> 3.4257989e-07 | DP7: =MRIO.flows!DP7/MRIO.flows!DP$112 -> 0.00092790148 | DQ7: =MRIO.flows!DQ7/MRIO.flows!DQ$112 -> 0.00018622743 | DR7: =MRIO.flows!DR7/MRIO.flows!DR$112 -> 0.00025036578
A8: EU | B8: Sector | C8: Extraction of Fossil-Fuels | D8: =MRIO.flows!D8/MRIO.flows!D$127 -> 0.00097568171 | E8: =MRIO.flows!E8/MRIO.flows!E$127 -> 0.00093357268 | F8: =MRIO.flows!F8/MRIO.flows!F$127 -> 0.00050609551 | G8: =MRIO.flows!G8/MRIO.flows!G$127 -> 0.00023870404 | H8: =MRIO.flows!H8/MRIO.flows!H$127 -> 0.03008272 | I8: =MRIO.flows!I8/MRIO.flows!I$127 -> 0.0026977009 | J8: =MRIO.flows!J8/MRIO.flows!J$127 -> 0.00047192112 | K8: =MRIO.flows!K8/MRIO.flows!K$127 -> 0.00049905769 | ... DG8: =MRIO.flows!DG8/MRIO.flows!DG$127 -> 5.2735496e-06 | DH8: =MRIO.flows!DH8/MRIO.flows!DH$112 -> 0.00083468405 | DI8: =MRIO.flows!DI8/MRIO.flows!DI$112 -> 0.00018601191 | DJ8: =MRIO.flows!DJ8/MRIO.flows!DJ$112 -> 0.00242247 | DL8: =MRIO.flows!DL8/MRIO.flows!DL$112 -> 5.9700871e-06 | DM8: =MRIO.flows!DM8/MRIO.flows!DM$112 -> 1.0571433e-06 | DN8: =MRIO.flows!DN8/MRIO.flows!DN$112 -> 7.7247363e-06 | DP8: =MRIO.flows!DP8/MRIO.flows!DP$112 -> 0.0098453666 | DQ8: =MRIO.flows!DQ8/MRIO.flows!DQ$112 -> 0.00022411384 | DR8: =MRIO.flows!DR8/MRIO.flows!DR$112 -> 0.0010561388
A9: EU | B9: Sector | C9: Mining & Quarrying of raw materials | D9: =MRIO.flows!D9/MRIO.flows!D$127 -> 0.0011436994 | E9: =MRIO.flows!E9/MRIO.flows!E$127 -> 0.0010978336 | F9: =MRIO.flows!F9/MRIO.flows!F$127 -> 0.00038518073 | G9: =MRIO.flows!G9/MRIO.flows!G$127 -> 0.0040482738 | H9: =MRIO.flows!H9/MRIO.flows!H$127 -> 0.0008150672 | I9: =MRIO.flows!I9/MRIO.flows!I$127 -> 0.060972898 | J9: =MRIO.flows!J9/MRIO.flows!J$127 -> 0.00054454051 | K9: =MRIO.flows!K9/MRIO.flows!K$127 -> 0.0012641715 | ... DG9: =MRIO.flows!DG9/MRIO.flows!DG$127 -> 1.6449113e-05 | DH9: =MRIO.flows!DH9/MRIO.flows!DH$112 -> 0.00025337025 | DI9: =MRIO.flows!DI9/MRIO.flows!DI$112 -> 4.7836374e-05 | DJ9: =MRIO.flows!DJ9/MRIO.flows!DJ$112 -> 0.0013498272 | DL9: =MRIO.flows!DL9/MRIO.flows!DL$112 -> 1.0062816e-05 | DM9: =MRIO.flows!DM9/MRIO.flows!DM$112 -> 7.9705137e-07 | DN9: =MRIO.flows!DN9/MRIO.flows!DN$112 -> 2.391616e-05 | DP9: =MRIO.flows!DP9/MRIO.flows!DP$112 -> 0.01111787 | DQ9: =MRIO.flows!DQ9/MRIO.flows!DQ$112 -> 0.0001045543 | DR9: =MRIO.flows!DR9/MRIO.flows!DR$112 -> 0.0010569619
A10: EU | B10: Sector | C10: Processing of meat | D10: =MRIO.flows!D10/MRIO.flows!D$127 -> 0.00026865809 | E10: =MRIO.flows!E10/MRIO.flows!E$127 -> 0.060667221 | F10: =MRIO.flows!F10/MRIO.flows!F$127 -> 0.00071028017 | G10: =MRIO.flows!G10/MRIO.flows!G$127 -> 0.011688455 | H10: =MRIO.flows!H10/MRIO.flows!H$127 -> 0.00036901023 | I10: =MRIO.flows!I10/MRIO.flows!I$127 -> 0.0016640255 | J10: =MRIO.flows!J10/MRIO.flows!J$127 -> 0.068980294 | K10: =MRIO.flows!K10/MRIO.flows!K$127 -> 0.050294548 | ... DG10: =MRIO.flows!DG10/MRIO.flows!DG$127 -> 5.3100845e-05 | DH10: =MRIO.flows!DH10/MRIO.flows!DH$112 -> 0.037024813 | DI10: =MRIO.flows!DI10/MRIO.flows!DI$112 -> 0.0003465478 | DJ10: =MRIO.flows!DJ10/MRIO.flows!DJ$112 -> 0.0011072806 | DL10: =MRIO.flows!DL10/MRIO.flows!DL$112 -> 0.0010405254 | DM10: =MRIO.flows!DM10/MRIO.flows!DM$112 -> 4.0992221e-06 | DN10: =MRIO.flows!DN10/MRIO.flows!DN$112 -> 1.5799734e-05 | DP10: =MRIO.flows!DP10/MRIO.flows!DP$112 -> 0.023111771 | DQ10: =MRIO.flows!DQ10/MRIO.flows!DQ$112 -> 0.0049177873 | DR10: =MRIO.flows!DR10/MRIO.flows!DR$112 -> 0.0064911633
A11: EU | B11: Sector | C11: Processing of other food&beverage | D11: =MRIO.flows!D11/MRIO.flows!D$127 -> 0.00016031951 | E11: =MRIO.flows!E11/MRIO.flows!E$127 -> 0.13313782 | F11: =MRIO.flows!F11/MRIO.flows!F$127 -> 0.0011454115 | G11: =MRIO.flows!G11/MRIO.flows!G$127 -> 0.013178364 | H11: =MRIO.flows!H11/MRIO.flows!H$127 -> 0.00044747178 | I11: =MRIO.flows!I11/MRIO.flows!I$127 -> 0.0018684348 | J11: =MRIO.flows!J11/MRIO.flows!J$127 -> 0.056344983 | K11: =MRIO.flows!K11/MRIO.flows!K$127 -> 0.075054825 | ... DG11: =MRIO.flows!DG11/MRIO.flows!DG$127 -> 6.4226618e-05 | DH11: =MRIO.flows!DH11/MRIO.flows!DH$112 -> 0.048241995 | DI11: =MRIO.flows!DI11/MRIO.flows!DI$112 -> 0.0003252714 | DJ11: =MRIO.flows!DJ11/MRIO.flows!DJ$112 -> 0.0015491581 | DL11: =MRIO.flows!DL11/MRIO.flows!DL$112 -> 0.0017562226 | DM11: =MRIO.flows!DM11/MRIO.flows!DM$112 -> 1.167032e-05 | DN11: =MRIO.flows!DN11/MRIO.flows!DN$112 -> 2.3536972e-05 | DP11: =MRIO.flows!DP11/MRIO.flows!DP$112 -> 0.029907427 | DQ11: =MRIO.flows!DQ11/MRIO.flows!DQ$112 -> 0.0065877161 | DR11: =MRIO.flows!DR11/MRIO.flows!DR$112 -> 0.0086043539
